Workbook

Sheet Dashboard
A1: Johnny's Edge — Lifetime Finance Command Centre
A3: Controlled mirror · Expected salary is never treated as banked cash · Budget, Net Worth, Wealth Plan, Goals and the AI Advisor all recalculate from the Inputs and Recent Ledger sheets
A5: CURRENT POSITION | J5: Month | K5: Income | L5: Costs
A6: Liquid cash | B6: ='Inputs'!B14 -> 6105.64 | C6: Rent protected | D6: ='Inputs'!B31 -> 5990.45 | E6: Emergency fund | F6: ='Inputs'!B32 -> 7.67 | G6: Protection shortfall | H6: 705.76 | J6: Aug | K6: =B19 -> 2906 | L6: =C19 -> 843.28
A7: Actual | C7: Actual | E7: Actual | G7: Before salary | J7: Sep | K7: =B20 -> 7914.88 | L7: =C20 -> 3655.11
A8: Rent cheque | B8: ='Inputs'!B30 -> 11750 | C8: Projected rent money | D8: ='Monthly Plan'!D23 -> 10222.8 | E8: Current projected gap | F8: ='Monthly Plan'!D24 -> 1527.2 | G8: Actual rent gap | H8: 5759.55 | J8: Oct 1–22 | K8: =B21 -> 0 | L8: =C21 -> 13955.33
A9: Actual | C9: Before closure actions | E9: Before closure actions | G9: AED 11,750 less protected rent | J9: Rent cheque | K9: 0 | L9: 11750
A11: RENT CLOSURE ACTIONS
A12: Action | B12: Amount | C12: Deadline | D12: Evidence | E12: Action | F12: Amount | G12: Deadline | H12: Evidence
A13: Salary estimate reduction | B13: ='Rent Closure'!B8 -> 24 | C13: 46265 | D13: AED 2,906 expected; verify credit | E13: Additional income required | F13: ='Rent Closure'!B9 -> 1527.2 | G13: 46295 | H13: Banked cash only
A14: Earn additional income | B14: ='Rent Closure'!B10 -> 0 | C14: 46316 | D14: Banked cash only | E14: Survival spending cap | F14: ='Rent Closure'!B12 -> 285 | G14: 46316 | H14: AED 5/day; AED 35/week
A15: Final conditional rent gap | B15: ='Rent Closure'!B11 -> 0 | C15: 46316 | D15: Must equal zero | E15: Rent cheque | F15: ='Inputs'!B30 -> 11750 | G15: 46317 | H15: Fund by 21 Oct
A17: MONTHLY CASH FLOW TO RENT
A18: Period | B18: Income | C18: Costs before rent | D18: Rent available
A19: Aug 2026 | B19: =SUM('Monthly Plan'!B9:B10) -> 2906 | C19: ='Monthly Plan'!B21 -> 843.28 | D19: ='Monthly Plan'!B22 -> 8168.36
A20: Sep 2026 | B20: ='Monthly Plan'!C11 -> 7914.88 | C20: ='Monthly Plan'!C21 -> 3655.11 | D20: ='Monthly Plan'!C22 -> 12428.13
A21: Oct 1–22 | B21: =0 -> 0 | C21: ='Monthly Plan'!D21 -> 13955.33 | D21: ='Monthly Plan'!D23 -> 10222.8
A22: Total available for rent | D22: ='Monthly Plan'!D23 -> 10222.8
A24: CONTROL STATUS
A25: PAYDAY DAMAGE CONTROL · AED 2,906 EXPECTED
A26: Allocate: DEWA AED 713.03 from salary + AED 100.25 already above rent · Tabby AED 1,314.50 · Survival AED 160 · du/Etisalat AED 718.47. Telecom remains AED 196.46 short from salary, reduced to AED 189.19 after current loose cash.
A27: September SIP AED 462 is not funded. Total extra cash needed: AED 651.19. If unavailable, pause SIP before borrowing. Keep AED 5,990.45 rent untouched and Tabby frozen.
A29: WEALTH POSITION
A30: Metric | B30: Value | C30: Metric | D30: Value | E30: Metric | F30: Value | G30: Metric | H30: Value | J30: Metric | K30: Value
A31: Net worth | B31: ='Net Worth'!F28 -> 16053.319 | C31: Total assets | D31: ='Net Worth'!F25 -> 18740.679 | E31: Total liabilities | F31: ='Net Worth'!F27 -> 2687.36 | G31: Investments (AED) | H31: ='Net Worth'!F21 -> 12635.039 | J31: Health score | K31: ='AI Advisor'!C13 -> 35.858565
A32: Free net worth after commitments | B32: ='Net Worth'!F36 -> 9642.1787 | C32: Free cash today | D32: ='Inputs'!B43 -> 107.52 | E32: Emergency cover (months) | F32: ='Net Worth'!B46 -> 0.0011900926 | G32: Debt to assets | H32: ='Net Worth'!B42 -> 0.14339715 | J32: Grade | K32: ='AI Advisor'!E13 -> D
A33: Monthly plan surplus | B33: =Budget!B39 -> -881.89667 | C33: Savings rate achieved | D33: =Budget!B42 -> 0.083690467 | E33: Lifestyle run rate | F33: =Budget!D27 -> 3849.363 | G33: Daily burn | H33: ='Spend Analysis'!B39 -> 95.762609 | J33: Checks passing | K33: =Checks!B41 -> 30
A34: Capital at 20-year horizon | B34: ='Wealth Plan'!F38 -> 775778.83 | C34: In today's money | D34: ='Wealth Plan'!G38 -> 473435.28 | E34: Independence target | F34: ='Wealth Plan'!B54 -> 1933463 | G34: Years to independence | H34: ='Wealth Plan'!B55 -> beyond horizon | J34: Checks expected | K34: =Checks!C41 -> 30
A36: WHAT TO DO NEXT — TOP ACTIONS FROM THE AI ADVISOR
A37: ='AI Advisor'!A47 -> Health score 36 out of 100, grade D. Net worth is AED 16,053.32, of which AED 12,635.04 actually compounds. The balance sheet is not the problem — the calendar is. AED 5,759.55 of rent still has to be found before 21 Oct, AED 651.59 before 15 Sep, and free cash outside rent and emergency stands at AED 107.52. Do four things in order: hold the rent ring-fence, close the September gap by earning or by pausing the SIP, let the Tabby minimums run to zero by 3 Nov without ever paying a fee, and start accruing rent monthly so October 2027 is a transfer instead of a crisis. Then, and only then, raise the SIP.
A39: This dashboard now mirrors two things at once: the ninety-day survival plan above, and the long-term wealth position below. Read the top half when deciding what to do this week, and the bottom half when deciding whether the week mattered.

Sheet AI Advisor
A1: AI Advisor — Live Recommendations
A3: Every recommendation below is wired to a live condition in this workbook. Change a balance on Inputs or add a line to the ledger and the status column re-decides itself — an item closes when the data says it is closed, not when someone ticks it off. Impact is the dirham value of acting, stated per month unless the note says otherwise.
A5: HEALTH SCORE
A6: # | B6: Component | C6: Score | D6: Weight | E6: Weighted | H6: How it is measured
A7: 1 | B7: Liquidity — free cash against one month of essentials | C7: =MIN(100,MAX(0,IF(Budget!B17=0,0,'Inputs'!B43/Budget!B17)*100)) -> 1.6683019 | D7: 0.2 | E7: =C7*D7 -> 0.33366038 | H7: Free cash outside rent and emergency, divided by monthly essentials, capped at 100.
A8: 2 | B8: Emergency cover — months held against the six-month target | C8: =MIN(100,MAX(0,IF(Budget!B17=0,0,'Inputs'!B32/(Budget!B17*'FX & Assumptions'!B33))*100)) -> 0.019834877 | D8: 0.2 | E8: =C8*D8 -> 0.0039669753 | H8: Emergency fund against six months of essentials.
A9: 3 | B9: Debt — exposure against total assets | C9: =MIN(100,MAX(0,(1-IF('Net Worth'!F25=0,1,'Net Worth'!F27/'Net Worth'!F25))*100)) -> 85.660285 | D9: 0.15 | E9: =C9*D9 -> 12.849043 | H9: One hundred means debt free.
A10: 4 | B10: Savings rate — achieved against target | C10: =MIN(100,MAX(0,IF('FX & Assumptions'!B30=0,0,Budget!B42/'FX & Assumptions'!B30)*100)) -> 41.845233 | D10: 0.2 | E10: =C10*D10 -> 8.3690467 | H10: Investing and emergency top-ups against the target savings rate.
A11: 5 | B11: Budget balance — does the plan fit the salary | C11: =IF(Budget!B39>=0,100,MAX(0,100+Budget!B39/MAX(1,Budget!B8)*100)) -> 88.857738 | D11: 0.15 | E11: =C11*D11 -> 13.328661 | H11: One hundred when the plan balances; falls as the deficit widens.
A12: 6 | B12: Spending discipline — run rate against plan | C12: =MIN(100,MAX(0,IF(Budget!D27=0,100,Budget!B27/Budget!D27*100))) -> 9.7418716 | D12: 0.1 | E12: =C12*D12 -> 0.97418716 | H12: Planned lifestyle spending divided by the actual lifestyle run rate.
B13: FINANCIAL HEALTH SCORE | C13: =SUM(E7:E12) -> 35.858565 | D13: =SUM(D7:D12) -> 1 | E13: =IF(C13>=80,"A",IF(C13>=65,"B",IF(C13>=50,"C",IF(C13>=35,"D","E")))) -> D | H13: Weights are levers — adjust them if you disagree with the emphasis. The grade in column E is the honest headline: an E or a D means the next ninety days are about survival, not strategy.
A15: URGENT — DO THIS WEEK
A16: # | B16: Recommendation | C16: Status | D16: Effort | E16: Impact (AED) | F16: Priority | G16: By when | H16: Why this, and why now
A17: 1 | B17: Bank the AED 189.19 bills-and-survival gap before 15 Sep | C17: =IF('Inputs'!B51>0.01,"OPEN","CLOSED") -> OPEN | D17: High | E17: ='Inputs'!B51 -> 189.19 | F17: =IF(E17>=500,"1 — Critical",IF(E17>=100,"2 — High",IF(E17>=25,"3 — Useful","4 — Housekeeping"))) -> 2 — High | G17: 46280 | H17: Confirmed bills plus the survival allowance exceed loose cash plus the expected payday. This is the one number that decides whether September is calm or improvised. Earn it, or pause the SIP — in that order.
A18: 2 | B18: Do not touch the protected rent in FAB 4002 | C18: =IF('Inputs'!B31>0,"IN FORCE","Released") -> IN FORCE | D18: None | E18: ='Inputs'!B31 -> 5990.45 | F18: =IF(E18>=500,"1 — Critical",IF(E18>=100,"2 — High",IF(E18>=25,"3 — Useful","4 — Housekeeping"))) -> 1 — Critical | G18: 46316 | H18: FAB 4002 shows AED 6,090.70 but only AED 100.25 of it is yours to spend. Treating the account balance as available is the single most likely way this plan fails.
A19: 3 | B19: Let the AED 1,314.50 Tabby autopay run on 3 Sep — do not pay the full statement | C19: =IF('Inputs'!B36>0,"SCHEDULED","Done") -> SCHEDULED | D19: None | E19: ='Inputs'!B37-'Inputs'!B36 -> 657.53 | F19: =IF(E19>=500,"1 — Critical",IF(E19>=100,"2 — High",IF(E19>=25,"3 — Useful","4 — Housekeeping"))) -> 1 — Critical | G19: 46268 | H19: Paying the full August statement costs AED 657.53 more in the month you can least afford it, and saves no fee at all. The Debt Plan proves it.
A20: 4 | B20: Confirm the AED 2,906 salary actually credits on 26 Aug | C20: =IF('Inputs'!C22="Estimated","UNCONFIRMED","Confirmed") -> UNCONFIRMED | D20: Low | E20: ='Inputs'!B22 -> 2906 | F20: =IF(E20>=500,"1 — Critical",IF(E20>=100,"2 — High",IF(E20>=25,"3 — Useful","4 — Housekeeping"))) -> 1 — Critical | G20: 46260 | H20: Every downstream number in this workbook assumes it arrives. Until it is on a statement it is a hope, and the model deliberately refuses to call it cash.
A22: SPENDING — WHERE THE MONEY IS LEAKING
A23: # | B23: Recommendation | C23: Status | D23: Effort | E23: Impact (AED) | F23: Priority | G23: By when | H23: Why this, and why now
A24: 1 | B24: Bring dining back to the plan | C24: =IF(Budget!D21>Budget!B21,"OVER PLAN","OK") -> OVER PLAN | D24: Medium | E24: =MAX(0,Budget!D21-Budget!B21) -> 839.30101 | F24: =IF(E24>=500,"1 — Critical",IF(E24>=100,"2 — High",IF(E24>=25,"3 — Useful","4 — Housekeeping"))) -> 1 — Critical | G24: 46295 | H24: Dining is the largest genuinely controllable category in the ledger. The impact column is the monthly saving from simply hitting the number already written in the Budget.
A25: 2 | B25: Cancel one of the two telecom lines | C25: =IF(AND('Inputs'!B34>0,'Inputs'!B35>0),"TWO LINES ACTIVE","Consolidated") -> TWO LINES ACTIVE | D25: Low | E25: =MIN('Inputs'!B34,'Inputs'!B35) -> 323.95 | F25: =IF(E25>=500,"1 — Critical",IF(E25>=100,"2 — High",IF(E25>=25,"3 — Useful","4 — Housekeeping"))) -> 2 — High | G25: 46295 | H25: du and Etisalat are both being paid every month for one person. Cancelling the smaller line is a permanent saving that requires no willpower at all — the best kind.
A26: 3 | B26: Bring the daily burn under the damage-control cap | C26: =IF('Spend Analysis'!B31>'Spend Analysis'!C31,"ABOVE CAP","WITHIN CAP") -> ABOVE CAP | D26: High | E26: =MAX(0,('Spend Analysis'!B39-'Spend Analysis'!C39)*30.44) -> 2762.8138 | F26: =IF(E26>=500,"1 — Critical",IF(E26>=100,"2 — High",IF(E26>=25,"3 — Useful","4 — Housekeeping"))) -> 1 — Critical | G26: 46290 | H26: The plan caps living costs at AED 5 a day. The confirmed ledger shows day-to-day living running at a large multiple of that. This gap, compounded over eight weeks, is roughly the size of the rent shortfall.
A27: 4 | B27: Kill the Netflix retry | C27: =IF('Obligations'!C18>0,"OPEN","Closed") -> OPEN | D27: None | E27: ='Obligations'!C18 -> 35 | F27: =IF(E27>=500,"1 — Critical",IF(E27>=100,"2 — High",IF(E27>=25,"3 — Useful","4 — Housekeeping"))) -> 3 — Useful | G27: 46266 | H27: The charge was declined, not paid. Cancel it properly rather than leaving it to retry against an account that is holding rent money.
A28: 5 | B28: Stop paying transfer fees | C28: =IF(Budget!D25>0,"LEAKING","Clean") -> LEAKING | D28: Low | E28: =Budget!D25 -> 0.64850435 | F28: =IF(E28>=500,"1 — Critical",IF(E28>=100,"2 — High",IF(E28>=25,"3 — Useful","4 — Housekeeping"))) -> 4 — Housekeeping | G28: 46295 | H28: Small, but it is pure leakage: a fee buys nothing. Batch transfers instead of moving money several times a week.
A29: 6 | B29: Give the AED 14 unreconciled movement a name | C29: =IF(COUNTIFS('Recent Ledger'!$I$6:$I$101,"Unreconciled")>0,"OPEN","Clean") -> OPEN | D29: Low | E29: =SUMIFS('Recent Ledger'!$D$6:$D$101,'Recent Ledger'!$I$6:$I$101,"Unreconciled") -> 64 | F29: =IF(E29>=500,"1 — Critical",IF(E29>=100,"2 — High",IF(E29>=25,"3 — Useful","4 — Housekeeping"))) -> 3 — Useful | G29: 46272 | H29: A control item rather than a money item. A ledger where every dirham has a merchant is a ledger you can trust when it matters.
A31: STRUCTURE — STOP THE CRISIS REPEATING
A32: # | B32: Recommendation | C32: Status | D32: Effort | E32: Impact (AED) | F32: Priority | G32: By when | H32: Why this, and why now
A33: 1 | B33: Start a monthly rent accrual | C33: =IF('Net Worth'!F34>0.01,"NOT STARTED","Funded") -> NOT STARTED | D33: Medium | E33: ='FX & Assumptions'!B29 -> 3916.6667 | F33: =IF(E33>=500,"1 — Critical",IF(E33>=100,"2 — High",IF(E33>=25,"3 — Useful","4 — Housekeeping"))) -> 1 — Critical | G33: 46327 | H33: The rent cheque is not an emergency, it is a subscription that arrives on a known date. Moving the monthly accrual into FAB 4002 on payday converts every future cheque from a crisis into a transfer. This is the highest-value structural change in the workbook.
A34: 2 | B34: Confirm how many rent cheques the lease actually requires | C34: =IF('FX & Assumptions'!B27=4,"ASSUMED — CONFIRM","Confirmed") -> ASSUMED — CONFIRM | D34: None | E34: ='FX & Assumptions'!B28 -> 47000 | F34: =IF(E34>=500,"1 — Critical",IF(E34>=100,"2 — High",IF(E34>=25,"3 — Useful","4 — Housekeeping"))) -> 1 — Critical | G34: 46272 | H34: The whole rent accrual, the Budget essentials ratio and the emergency-fund target all rest on four cheques a year. It is an assumption, not a fact, and it is one phone call to settle.
A35: 3 | B35: Get the emergency fund to AED 1,000 | C35: =IF('Inputs'!B32<1000,"UNFUNDED","Milestone reached") -> UNFUNDED | D35: Medium | E35: =MAX(0,1000-'Inputs'!B32) -> 992.33 | F35: =IF(E35>=500,"1 — Critical",IF(E35>=100,"2 — High",IF(E35>=25,"3 — Useful","4 — Housekeeping"))) -> 1 — Critical | G35: 46477 | H35: AED 7.67 is not a buffer. Until there is a real one, every unexpected cost lands on the card or on the rent money.
A36: 4 | B36: Move to a single spending account with a weekly allowance | C36: ="RECOMMENDED" -> RECOMMENDED | D36: Low | E36: =0 -> 0 | F36: =IF(E36>=500,"1 — Critical",IF(E36>=100,"2 — High",IF(E36>=25,"3 — Useful","4 — Housekeeping"))) -> 4 — Housekeeping | G36: 46296 | H36: The ledger shows constant small transfers from 4002 into 4001. Each one is a decision, and each one erodes the ring-fence. One weekly transfer, then spend only what landed.
A38: INVESTING — THE PART THAT COMPOUNDS
A39: # | B39: Recommendation | C39: Status | D39: Effort | E39: Impact (AED) | F39: Priority | G39: By when | H39: Why this, and why now
A40: 1 | B40: Sweep the idle rupee cash into the next SIP | C40: =IF('Net Worth'!F19>1,"IDLE","Swept") -> IDLE | D40: None | E40: ='Net Worth'!F19 -> 14.970572 | F40: =IF(E40>=500,"1 — Critical",IF(E40>=100,"2 — High",IF(E40>=25,"3 — Useful","4 — Housekeeping"))) -> 4 — Housekeeping | G40: 46275 | H40: Settlement cash sitting in the broker account earns nothing. It is small, but sweeping it costs nothing and is the only free money in the file.
A41: 2 | B41: Reduce single-fund-house concentration | C41: =IF('Investments'!B16>0.8,"CONCENTRATED","Diversified") -> CONCENTRATED | D41: Medium | E41: =MAX(0,('Investments'!B16-0.8)*'Investments'!E12*'FX & Assumptions'!B7) -> 1456.9714 | F41: =IF(E41>=500,"1 — Critical",IF(E41>=100,"2 — High",IF(E41>=25,"3 — Useful","4 — Housekeeping"))) -> 1 — Critical | G41: 46477 | H41: Almost the entire mutual-fund portfolio sits with one fund house. That is an operational risk as much as a market one. Direct future SIP instalments elsewhere rather than selling — no exit load, no capital gains event.
A42: 3 | B42: Do not pause the SIP unless the September gap is still open on 8 Sep | C42: =IF('Inputs'!B51>0.01,"CONDITIONAL","Safe to continue") -> CONDITIONAL | D42: None | E42: ='Inputs'!B39 -> 462.4 | F42: =IF(E42>=500,"1 — Critical",IF(E42>=100,"2 — High",IF(E42>=25,"3 — Useful","4 — Housekeeping"))) -> 2 — High | G42: 46273 | H42: A paused SIP is cheap to restart; a missed rent cheque is not. But pausing early, when the gap might still be closed by earning, gives up compounding for nothing. Decide on 8 Sep with real balances, not on 26 Aug with estimates.
A43: 4 | B43: Review the 41 open Amana positions | C43: =IF('Investments'!B25<0,"FLOATING LOSS","In profit") -> FLOATING LOSS | D43: Medium | E43: =('Investments'!B26+'Investments'!B27)*-1*'FX & Assumptions'!B9 -> 75.176075 | F43: =IF(E43>=500,"1 — Critical",IF(E43>=100,"2 — High",IF(E43>=25,"3 — Useful","4 — Housekeeping"))) -> 3 — Useful | G43: 46295 | H43: Forty-one open positions on an account worth under AED 3,200 is a lot of moving parts, and the statement shows floating and overnight fees quietly working against you. Fewer, larger, longer-held positions would cost less to carry.
A44: 5 | B44: Raise the SIP by 10% every year, automatically | C44: =IF('FX & Assumptions'!B32>0,"IN PLAN","Not set") -> IN PLAN | D44: None | E44: ='Wealth Plan'!H45 -> 394157.35 | F44: =IF(E44>=500,"1 — Critical",IF(E44>=100,"2 — High",IF(E44>=25,"3 — Useful","4 — Housekeeping"))) -> 1 — Critical | G44: 46388 | H44: The impact column is what the step-up is worth at the twenty-year horizon compared with a flat contribution. It costs nothing today because the increase comes out of next year's raise.
A46: THE ONE-PARAGRAPH VERDICT
A47: ="Health score "&TEXT(C13,"0")&" out of 100, grade "&E13&". Net worth is AED "&TEXT('Net Worth'!F28,"#,##0.00")&", of which AED "&TEXT('Net Worth'!F21,"#,##0.00")&" actually compounds. The balance sheet is not the problem — the calendar is. AED "&TEXT('Net Worth'!F34,"#,##0.00")&" of rent still has to be found before 21 Oct, AED "&TEXT('Inputs'!B53,"#,##0.00")&" before 15 Sep, and free cash outside rent and emergency stands at AED "&TEXT('Inputs'!B43,"#,##0.00")&". Do four things in order: hold the rent ring-fence, close the September gap by earning or by pausing the SIP, let the Tabby minimums run to zero by 3 Nov without ever paying a fee, and start accruing rent monthly so October 2027 is a transfer instead of a crisis. Then, and only then, raise the SIP." -> Health score 36 out of 100, grade D. Net worth is AED 16,053.32, of which AED 12,635.04 actually compounds. The balance sheet is not the problem — the calendar is. AED 5,759.55 of rent still has to be found before 21 Oct, AED 651.59 before 15 Sep, and free cash outside rent and emergency stands at AED 107.52. Do four things in order: hold the rent ring-fence, close the September gap by earning or by pausing the SIP, let the Tabby minimums run to zero by 3 Nov without ever paying a fee, and start accruing rent monthly so October 2027 is a transfer instead of a crisis. Then, and only then, raise the SIP.

Sheet Inputs
A1: Johnny's Edge — Authoritative Inputs
A3: As of 25 Aug 2026 · Confirmed balances are separated from estimates. Salary AED 2,906 is expected, not banked.
A5: CURRENT LIQUID BALANCES — CONFIRMED ACTUAL
A6: Item | B6: Amount | C6: Currency | D6: Status | E6: As of | F6: Audit note
A7: FAB 4001 | B7: 3.45 | C7: AED | D7: Actual | E7: 46259.275 | F7: Confirmed FAB app/SMS balance after AED 13.50 ENOC purchase
A8: FAB 4002 | B8: 6090.7 | C8: AED | D8: Actual | E8: 46257.901 | F8: Confirmed FAB app/SMS balance; contains AED 5,990.45 rent plus only AED 100.25 toward DEWA
A9: FAB emergency | B9: 7.67 | C9: AED | D9: Actual | E9: 46259.482 | F9: Confirmed FAB app emergency-fund balance; do not spend
A10: NBD current | B10: 0.2 | C10: AED | D10: Actual | E10: 46251.635 | F10: Confirmed NBD card-linked balance after AED 2 SRN Supermarket purchase
A11: NBD Plus Saver | B11: 2.73 | C11: AED | D11: Last reported | E11: 46248 | F11: NBD Plus Saver last reported; refresh required if changed
A12: Tabby Cash | B12: 0.89 | C12: AED | D12: Last reported | E12: 46248 | F12: Tabby Cash wallet; separate from Tabby Card borrowing
A13: Cash/Wio | B13: 0 | C13: AED | D13: Actual | E13: 46259 | F13: No other cash balance reported
A14: TOTAL LIQUID CASH | B14: =SUM(B7:B13) -> 6105.64 | C14: AED | D14: Formula | E14: 46246 | F14: Formula check: AED 6,105.64 = FAB 6,101.82 + NBD 2.93 + Tabby Cash 0.89
A16: INCOME, REFUNDS AND TIMING
A17: Driver | B17: Amount | C17: Status | D17: Expected date | E17: Treatment | F17: Audit note
A18: Normal monthly salary | B18: 7914.88 | C18: Actual baseline | D18: 46260 | E18: Salary | F18: July salary baseline
A19: Two-ticket salary recovery | B19: 3740 | C19: Actual | D19: 46241 | E19: Already in cash | F19: Two × AED 1,870 deducted from salary; principal portion of AED 4,000 received
A20: Two-ticket profit | B20: 260 | C20: Actual | D20: 46241 | E20: Already in cash | F20: AED 4,000 received less AED 3,740 salary deduction
A21: Third-ticket salary recovery | B21: 1540 | C21: Actual | D21: 46246 | E21: Already in cash | F21: AED 1,540 salary advance received on 12 Aug; removed from 26 Aug receivables
A22: Remaining payday cash | B22: 2906 | C22: Estimated | D22: 46260 | E22: Expected inflow | F22: AED 2,906 expected 26 Aug; do not count until credited
A23: Separate additional income | B23: 0 | C23: None | D23: 46260 | E23: No separate inflow | F23: AED 8,500 estimate already includes ticket profits
A24: Prior-month salary received | B24: 1430 | C24: Actual | D24: 46246 | E24: Allocate to rent | F24: Separate from the coming AED 8,500 salary cycle
A25: Coming salary-cycle total | B25: 8476 | C25: Estimated target | D25: 46260 | E25: Projection | F25: AED 5,570 already received plus approximately AED 2,906 expected
A26: Third-ticket profit | B26: 30 | C26: Actual | D26: 46246 | E26: Already in cash | F26: AED 30 ticket profit received on 12 Aug; removed from 26 Aug receivables
A27: Current expected salary-cycle income | B27: =SUM(B19:B22)+B26 -> 8476 | C27: Formula | D27: 46260 | E27: Projection | F27: Formula: AED 5,570 already received + AED 2,906 expected = AED 8,476 cycle
A28: OBLIGATIONS AND CONTROL ASSUMPTIONS
A29: Item | B29: Amount | C29: Status | D29: Date / cadence | E29: Rule | F29: Audit note
A30: October rent cheque | B30: 11750 | C30: Actual | D30: 46317 | E30: Must be fully funded by 21 Oct | F30: 26 Oct salary is too late
A31: Rent protected now | B31: 5990.45 | C31: Actual | D31: 46246 | E31: Do not spend | F31: True protected rent after excluding AED 1,020.25 required for bills and living
A32: Emergency fund | B32: 7.67 | C32: Actual | D32: 46245 | E32: Do not spend | F32: Next milestone AED 1,000
A33: DEWA monthly baseline | B33: 813.28 | C33: Actual bill | D33: 46265 | E33: Pay by due date | F33: Actual August DEWA bill supplied 25 Aug; replaces AED 793.42 estimate
A34: du recurring baseline | B34: 590.98 | C34: Estimated | D34: 46268 | E34: Monthly | F34: September estimate; replace with actual du bill when generated
A35: Etisalat recurring baseline | B35: 323.95 | C35: Estimated | D35: 46268 | E35: Monthly | F35: September estimate; replace with actual Etisalat bill when generated
A36: Tabby no-fee minimum | B36: 1314.5 | C36: Actual due | D36: 46268 | E36: Autopay / no-fee minimum | F36: Confirmed August Tabby amount due; card must remain frozen
A37: Tabby full statement | B37: 1972.03 | C37: Actual statement | D37: 46268 | E37: Optional full statement | F37: Do not choose if it compromises rent or essential bills
A38: Tabby outstanding exposure | B38: 2687.36 | C38: Actual confirmed exposure | D38: 46298 | E38: Card frozen | F38: AED 1,972.03 August statement + AED 715.33 September statement
A39: September SIP funding | B39: 462.4 | C39: Estimated | D39: 46275 | E39: Keep active | F39: ₹12,000 at last confirmed transfer rate
A40: ICICI post-Aug SIP cash | B40: 388.51 | C40: Actual | D40: 46244 | E40: INR | F40: August four SIPs completed
A41: Living cap to rent cheque | B41: 285 | C41: Control cap | D41: 46316 | E41: AED 5/day; AED 35/week | F41: AED 5/day or AED 35/week through 21 Oct; AED 160 reserved first through 25 Sep
... A43: Current loose cash outside rent/emergency | B43: 107.52 | C43: Actual | D43: 46259.315 | E43: Protected calculation | F43: AED 6,105.64 liquidity less AED 5,990.45 rent and AED 7.67 emergency
A44: ="Extra cash required before 15 Sep: AED "&TEXT(B53,"#,##0.00")&" — AED "&TEXT(B51,"#,##0.00")&" to close the bills-and-survival gap plus AED "&TEXT(B52,"#,##0.00")&" to fund the 10 Sep Nippon SIP. Bank it as real cash or pause the SIP; never take it from the AED "&TEXT(B31,"#,##0.00")&" protected rent or from the emergency fund." -> Extra cash required before 15 Sep: AED 651.59 — AED 189.19 to close the bills-and-survival gap plus AED 462.40 to fund the 10 Sep Nippon SIP. Bank it as real cash or pause the SIP; never take it from the AED 5,990.45 protected rent or from the emergency fund.
A46: NEAR-TERM FUNDING GAP — CASH NEEDED BEFORE 15 SEP
A47: Item | B47: Amount | C47: Status | D47: Date | E47: Rule | F47: Audit note
A48: Survival allowance to 25 Sep | B48: 160 | C48: Control cap | D48: 46290 | E48: AED 5/day; AED 35/week | F48: Damage-control cap held from 26 Aug to 25 Sep. Editable lever: raising it widens the gap one-for-one.
A49: Near-term bills to 15 Sep | B49: =B33+B36+B34+B35 -> 3042.71 | C49: Formula | D49: 46280 | E49: Essential bills only | F49: DEWA AED 813.28 + Tabby no-fee minimum AED 1,314.50 + du AED 590.98 + Etisalat AED 323.95.
A50: Cash available incl. expected payday | B50: =B43+B22 -> 3013.52 | C50: Formula | D50: 46260 | E50: Only banked cash closes the gap | F50: Loose cash outside rent and emergency (AED 107.52) plus the AED 2,906 expected 26 Aug payday.
A51: Bills + survival funding gap | B51: =MAX(0,B49+B48-B50) -> 189.19 | C51: Formula | D51: 46280 | E51: Close before 15 Sep | F51: Requirement AED 3,202.71 against AED 3,013.52 available.
A52: September SIP funding | B52: =B39 -> 462.4 | C52: Link | D52: 46275 | E52: Pause before borrowing | F52: Mirrors the SIP funding row above so the total below moves when the SIP estimate changes.
A53: EXTRA CASH REQUIRED BEFORE 15 SEP | B53: =B51+B52 -> 651.59 | C53: Formula | D53: 46280 | E53: Bank it or pause the SIP | F53: Gap plus SIP. Note: earlier notes in this file quoted AED 651.19; the correct arithmetic is AED 189.19 + AED 462.40 = AED 651.59.

Sheet FX & Assumptions
A1: Rates, Returns and Planning Assumptions
A3: Every lever the rest of the workbook depends on lives here. Blue figures on a yellow fill are the only cells meant to be edited by hand; black figures are calculated. Change a lever here and Budget, Net Worth, Wealth Plan, Goals and AI Advisor all move together.
A5: CURRENCY
A6: Assumption | B6: Value | C6: Unit | D6: Basis | E6: Type | F6: Note
A7: AED per INR | B7: 0.0385333 | C7: AED / INR | D7: Derived from the last confirmed SIP transfer | E7: Lever | F7: AED 462.40 funded INR 12,000 on 10 Aug 2026, so 462.40 / 12,000 = 0.0385333. Refresh this whenever a new transfer settles at a different rate.
A8: INR per AED | B8: =IF(B7=0,0,1/B7) -> 25.95158 | C8: INR / AED | D8: Reciprocal of the row above | E8: Formula | F8: Roughly INR 25.95 per dirham at the last confirmed transfer rate.
A9: AED per USD | B9: 3.6725 | C9: AED / USD | D9: UAE dirham peg to the US dollar | E9: Lever | F9: The dirham has been pegged at 3.6725 since 1997; treat as fixed unless the peg changes.
A10: USD per AED | B10: =IF(B9=0,0,1/B9) -> 0.27229408 | C10: USD / AED | D10: Reciprocal of the row above | E10: Formula | F10: Used to read the Amana statement back into dirhams.
A12: RETURN, INFLATION AND RISK ASSUMPTIONS
A13: Assumption | B13: Value | C13: Unit | D13: Basis | E13: Type | F13: Note
A14: Indian equity mutual funds — expected return | B14: 0.11 | C14: p.a. nominal | D14: Long-run planning assumption | E14: Lever | F14: Nominal INR return before currency effects. Deliberately below the trailing returns shown on the Investments sheet: a snapshot gain is not a forecast.
A15: Global equity (Amana) — expected return | B15: 0.08 | C15: p.a. nominal | D15: Long-run planning assumption | E15: Lever | F15: Broad developed-market equity assumption in USD.
A16: Cash and savings — expected return | B16: 0.02 | C16: p.a. nominal | D16: UAE savings account range | E16: Lever | F16: FAB and NBD balances earn close to nothing; 2% is generous.
A17: Silver / commodity — expected return | B17: 0.05 | C17: p.a. nominal | D17: Long-run planning assumption | E17: Lever | F17: Applies to the Nippon Silver ETF FoF holding only.
A18: UAE inflation | B18: 0.025 | C18: p.a. | D18: Planning assumption | E18: Lever | F18: Used to restate the Wealth Plan into today's money.
A19: Scenario adjustment to returns | B19: 0 | C19: p.a. | D19: Owner-set stress lever | E19: Lever | F19: Set to 0 for the base case, -0.03 for a bear case, +0.02 for a bull case. Applies to every growth assumption in the Wealth Plan.
A20: Blended portfolio planning return | B20: =IF('Investments'!B50=0,B14,(('Investments'!B43+'Investments'!B44+'Investments'!B45+'Investments'!B46)*B14+'Investments'!B47*B17+'Investments'!B48*B15+'Investments'!B49*B16)/'Investments'!B50)+B19 -> 0.10161181 | C20: p.a. nominal | D20: Weighted by the asset-allocation table on Investments | E20: Formula | F20: Each sleeve is weighted by its present value at its own expected return: Indian equity funds at the equity rate, the silver holding at the commodity rate, Amana at the global rate and idle broker cash at the cash rate. The scenario adjustment is then added.
A21: Real (after-inflation) planning return | B21: =(1+B20)/(1+B18)-1 -> 0.074743227 | C21: p.a. real | D21: Blended return deflated by inflation | E21: Formula | F21: The number that actually matters for buying power.
A23: INCOME, HOUSING AND SAVINGS ASSUMPTIONS
A24: Assumption | B24: Value | C24: Unit | D24: Basis | E24: Type | F24: Note
A25: Net monthly salary | B25: ='Inputs'!B18 -> 7914.88 | C25: AED | D25: Inputs sheet, July salary baseline | E25: Formula | F25: Linked, not typed. Update the baseline on Inputs and every sheet follows.
A26: Annual salary increment | B26: 0.04 | C26: p.a. | D26: Planning assumption | E26: Lever | F26: Applied from the first full plan year onward.
A27: Rent cheques per year | B27: 4 | C27: cheques | D27: ASSUMPTION — CONFIRM AGAINST THE LEASE | E27: Lever | F27: The lease schedule in this file shows one cheque of AED 11,750 due 22 Oct 2026 but not the cadence. Four cheques a year is the common Dubai arrangement and is what the monthly rent accrual on Budget uses. If the real schedule is different, change this one cell.
A28: Annual rent | B28: ='Inputs'!B30*B27 -> 47000 | C28: AED | D28: Cheque value times cheques per year | E28: Formula | F28: Drives the monthly rent accrual used in the Budget.
A29: Monthly rent accrual | B29: =B28/12 -> 3916.6667 | C29: AED | D29: Annual rent spread evenly | E29: Formula | F29: Setting money aside every month is what turns the next cheque from a crisis into a transfer.
A30: Target savings rate | B30: 0.2 | C30: of net income | D30: Wealth-building target | E30: Lever | F30: Everything invested plus emergency-fund top-ups, as a share of net income.
A31: Current monthly SIP | B31: ='Inputs'!B39 -> 462.4 | C31: AED | D31: Inputs sheet | E31: Formula | F31: INR 12,000 at the last confirmed transfer rate.
A32: Annual SIP step-up | B32: 0.1 | C32: p.a. | D32: Wealth-building lever | E32: Lever | F32: Raising the SIP by 10% a year is the single highest-leverage habit in this plan; the Wealth Plan sensitivity block prices it.
A33: Emergency fund target | B33: 6 | C33: months of essential spend | D33: Standard planning rule | E33: Lever | F33: Measured against the essential subtotal on the Budget sheet.
A35: LEDGER WINDOW AND PLAN HORIZON
A36: Assumption | B36: Value | C36: Unit | D36: Basis | E36: Type | F36: Note
A37: Ledger first transaction | B37: =MIN('Recent Ledger'!$A$6:$A$101) -> 46237.472 | C37: date | D37: Recent Ledger | E37: Formula | F37: Earliest confirmed transaction in the ledger.
A38: Ledger last transaction | B38: =MAX('Recent Ledger'!$A$6:$A$101) -> 46259.275 | C38: date | D38: Recent Ledger | E38: Formula | F38: Latest confirmed transaction in the ledger.
A39: Days covered by the ledger | B39: =INT(B38)-INT(B37)+1 -> 23 | C39: days | D39: Inclusive day count | E39: Formula | F39: The ledger is a partial month, so actuals are scaled to a monthly run rate before they are compared with the plan.
A40: Run-rate factor to a full month | B40: =IF(B39=0,0,30.44/B39) -> 1.3234783 | C40: x | D40: Average month length divided by days covered | E40: Formula | F40: Multiply any ledger actual by this to get a monthly run rate.
A41: Plan start | B41: 46266 | C41: date | D41: First full month of the plan | E41: Lever | F41: The Wealth Plan projects forward from this date.
A42: Plan horizon | B42: 20 | C42: years | D42: Owner-set | E42: Lever | F42: Length of the projection on the Wealth Plan sheet.
A44: Assumption discipline: a lever is a number this workbook cannot prove. Every one of them is on this sheet, in blue on yellow, with its basis written next to it. Nothing else in the file hardcodes a rate or a return. The two levers most likely to be wrong are rent cheques per year and the AED/INR rate — confirm both against the lease and the next transfer receipt.

Sheet Budget
A1: Monthly Budget — Plan against Reality
A3: Column B is the plan. Column C is what the confirmed ledger actually shows for 3–25 Aug 2026. Column D scales that partial month to a full-month run rate so the two are comparable. A red variance means the run rate is above plan.
A5: MONTHLY INCOME
A6: Line | B6: Monthly plan | C6: Ledger actual 3–25 Aug | D6: Monthly run rate | E6: Variance vs plan | F6: % of income | G6: Priority | H6: Note
A7: Net salary | B7: ='FX & Assumptions'!B25 -> 7914.88 | C7: 0 | D7: =C7*'FX & Assumptions'!$B$40 -> 0 | E7: =D7-B7 -> -7914.88 | F7: =IF($B$8=0,0,B7/$B$8) -> 1 | G7: Core | H7: July baseline. The AED 2,906 expected on 26 Aug is the remainder of this month's cycle, not an extra month of pay.
A8: TOTAL MONTHLY INCOME | B8: =B7 -> 7914.88 | C8: =C7 -> 0 | D8: =D7 -> 0 | F8: =IF(B8=0,0,B8/B8) -> 1 | G8: Core | H8: Side income from ticket dealing is treated as one-off recovery, not salary, so it never inflates the plan.
A10: ESSENTIAL — THE BILLS THAT KEEP THE LIGHTS ON
A11: Line | B11: Monthly plan | C11: Ledger actual 3–25 Aug | D11: Monthly run rate | E11: Variance vs plan | F11: % of income | G11: Priority | H11: Note
A12: Rent accrual | B12: ='FX & Assumptions'!B29 -> 3916.6667 | C12: 0 | D12: =C12*'FX & Assumptions'!$B$40 -> 0 | E12: =D12-B12 -> -3916.6667 | F12: =IF($B$8=0,0,B12/$B$8) -> 0.49484852 | G12: Critical | H12: The rent cheque is not a surprise, it is a subscription. Accruing it monthly is what removes the October panic permanently. No ledger line exists because nothing has been set aside monthly so far.
A13: Utilities & Telecom | B13: ='Inputs'!B33+'Inputs'!B34+'Inputs'!B35 -> 1728.21 | C13: =SUMIFS('Recent Ledger'!$D$6:$D$101,'Recent Ledger'!$I$6:$I$101,$A13,'Recent Ledger'!$J$6:$J$101,1) -> 914.93 | D13: =C13*'FX & Assumptions'!$B$40 -> 1210.89 | E13: =D13-B13 -> -517.32003 | F13: =IF($B$8=0,0,B13/$B$8) -> 0.21834949 | G13: Critical | H13: DEWA AED 813.28 + du AED 590.98 + Etisalat AED 323.95. Two telecom lines for one person is the most obvious fixed-cost cut available.
A14: Groceries | B14: 450 | C14: =SUMIFS('Recent Ledger'!$D$6:$D$101,'Recent Ledger'!$I$6:$I$101,$A14,'Recent Ledger'!$J$6:$J$101,1) -> 280.53 | D14: =C14*'FX & Assumptions'!$B$40 -> 371.27536 | E14: =D14-B14 -> -78.724643 | F14: =IF($B$8=0,0,B14/$B$8) -> 0.056854937 | G14: Essential | H14: Cooking at home is the cheapest lever that does not require earning more.
A15: Fuel & Transport | B15: 250 | C15: =SUMIFS('Recent Ledger'!$D$6:$D$101,'Recent Ledger'!$I$6:$I$101,$A15,'Recent Ledger'!$J$6:$J$101,1) -> 300.52 | D15: =C15*'FX & Assumptions'!$B$40 -> 397.73169 | E15: =D15-B15 -> 147.73169 | F15: =IF($B$8=0,0,B15/$B$8) -> 0.031586076 | G15: Essential | H15: Fuel and Metro. Work-essential; protect this before cutting anything else.
A16: Family & Support | B16: 100 | C16: =SUMIFS('Recent Ledger'!$D$6:$D$101,'Recent Ledger'!$I$6:$I$101,$A16,'Recent Ledger'!$J$6:$J$101,1) -> 142.97 | D16: =C16*'FX & Assumptions'!$B$40 -> 189.21769 | E16: =D16-B16 -> 89.217687 | F16: =IF($B$8=0,0,B16/$B$8) -> 0.01263443 | G16: Essential | H16: Medical and family support transfers.
A17: SUBTOTAL ESSENTIAL | B17: =SUM(B12:B16) -> 6444.8767 | C17: =SUM(C12:C16) -> 1638.95 | D17: =SUM(D12:D16) -> 2169.1147 | E17: =SUM(E12:E16) -> -4275.762 | F17: =IF($B$8=0,0,B17/$B$8) -> 0.81427345 | G17: Critical | H17: This subtotal is the base of the emergency-fund target on the Goals sheet.
A19: LIFESTYLE — THE PART THAT IS ACTUALLY A CHOICE
A20: Line | B20: Monthly plan | C20: Ledger actual 3–25 Aug | D20: Monthly run rate | E20: Variance vs plan | F20: % of income | G20: Priority | H20: Note
A21: Dining | B21: 200 | C21: =SUMIFS('Recent Ledger'!$D$6:$D$101,'Recent Ledger'!$I$6:$I$101,$A21,'Recent Ledger'!$J$6:$J$101,1) -> 785.28 | D21: =C21*'FX & Assumptions'!$B$40 -> 1039.301 | E21: =D21-B21 -> 839.30101 | F21: =IF($B$8=0,0,B21/$B$8) -> 0.025268861 | G21: Discretionary | H21: The single largest controllable category in the ledger. Restaurant and delivery spending has been running far above any plan that also funds rent.
A22: Lifestyle & Shopping | B22: 100 | C22: =SUMIFS('Recent Ledger'!$D$6:$D$101,'Recent Ledger'!$I$6:$I$101,$A22,'Recent Ledger'!$J$6:$J$101,1) -> 563.75 | D22: =C22*'FX & Assumptions'!$B$40 -> 746.11087 | E22: =D22-B22 -> 646.11087 | F22: =IF($B$8=0,0,B22/$B$8) -> 0.01263443 | G22: Discretionary | H22: Convenience-store and hotel spending. Frozen under the damage-control cap.
A23: Grooming | B23: 65 | C23: =SUMIFS('Recent Ledger'!$D$6:$D$101,'Recent Ledger'!$I$6:$I$101,$A23,'Recent Ledger'!$J$6:$J$101,1) -> 65 | D23: =C23*'FX & Assumptions'!$B$40 -> 86.026087 | E23: =D23-B23 -> 21.026087 | F23: =IF($B$8=0,0,B23/$B$8) -> 0.0082123797 | G23: Discretionary | H23: One barber visit a month.
A24: Travel | B24: 0 | C24: =SUMIFS('Recent Ledger'!$D$6:$D$101,'Recent Ledger'!$I$6:$I$101,$A24,'Recent Ledger'!$J$6:$J$101,1) -> 1430 | D24: =C24*'FX & Assumptions'!$B$40 -> 1892.5739 | E24: =D24-B24 -> 1892.5739 | F24: =IF($B$8=0,0,B24/$B$8) -> 0 | G24: Deferred | H24: The AED 1,430 Emirates ticket sits in the ledger with a refund pending. No further travel spend is planned before the October rent cheque clears.
A25: Bank Fees | B25: 10 | C25: =SUMIFS('Recent Ledger'!$D$6:$D$101,'Recent Ledger'!$I$6:$I$101,$A25,'Recent Ledger'!$J$6:$J$101,1) -> 0.49 | D25: =C25*'FX & Assumptions'!$B$40 -> 0.64850435 | E25: =D25-B25 -> -9.3514957 | F25: =IF($B$8=0,0,B25/$B$8) -> 0.001263443 | G25: Avoidable | H25: Transfer fees. Avoidable with a little batching.
A26: Unreconciled | B26: 0 | C26: =SUMIFS('Recent Ledger'!$D$6:$D$101,'Recent Ledger'!$I$6:$I$101,$A26,'Recent Ledger'!$J$6:$J$101,1) -> 64 | D26: =C26*'FX & Assumptions'!$B$40 -> 84.702609 | E26: =D26-B26 -> 84.702609 | F26: =IF($B$8=0,0,B26/$B$8) -> 0 | G26: Control | H26: Balance-derived movements with no confirmed merchant. Target is zero: every dirham should have a name.
A27: SUBTOTAL LIFESTYLE | B27: =SUM(B21:B26) -> 375 | C27: =SUM(C21:C26) -> 2908.52 | D27: =SUM(D21:D26) -> 3849.363 | E27: =SUM(E21:E26) -> 3474.363 | F27: =IF($B$8=0,0,B27/$B$8) -> 0.047379114 | G27: Discretionary | H27: Every dirham cut here is a dirham that can fund rent, kill Tabby or buy units.
A29: DEBT AND WEALTH — WHAT BUILDS THE FUTURE
A30: Line | B30: Monthly plan | C30: Ledger actual 3–25 Aug | D30: Monthly run rate | E30: Variance vs plan | F30: % of income | G30: Priority | H30: Note
A31: Tabby repayment | B31: ='Inputs'!B36 -> 1314.5 | C31: 0 | D31: =C31*'FX & Assumptions'!$B$40 -> 0 | E31: =D31-B31 -> -1314.5 | F31: =IF($B$8=0,0,B31/$B$8) -> 0.16607959 | G31: Critical | H31: The no-fee minimum due 3 Sep. Paying the full statement is better whenever rent and essential bills stay funded.
A32: Nippon SIP | B32: ='FX & Assumptions'!B31 -> 462.4 | C32: 0 | D32: =C32*'FX & Assumptions'!$B$40 -> 0 | E32: =D32-B32 -> -462.4 | F32: =IF($B$8=0,0,B32/$B$8) -> 0.058421606 | G32: Wealth | H32: INR 12,000 a month. This is the only line in the budget that compounds.
A33: Emergency fund top-up | B33: 200 | C33: 0 | D33: =C33*'FX & Assumptions'!$B$40 -> 0 | E33: =D33-B33 -> -200 | F33: =IF($B$8=0,0,B33/$B$8) -> 0.025268861 | G33: Wealth | H33: The emergency fund holds AED 7.67 against a six-month target. AED 200 a month is the smallest amount that makes the number move.
A34: SUBTOTAL DEBT AND WEALTH | B34: =SUM(B31:B33) -> 1976.9 | C34: =SUM(C31:C33) -> 0 | D34: =SUM(D31:D33) -> 0 | E34: =SUM(E31:E33) -> -1976.9 | F34: =IF($B$8=0,0,B34/$B$8) -> 0.24977005 | G34: Wealth | H34: Debt repayment is defence; the SIP and the emergency fund are offence.
A36: RESULT
A37: Result | B37: Monthly plan | C37: Ledger actual 3–25 Aug | D37: Monthly run rate | E37: Variance vs plan | F37: % of income | G37: Verdict | H37: Note
A38: Total outflow | B38: =B17+B27+B34 -> 8796.7767 | C38: =C17+C27+C34 -> 4547.47 | D38: =D17+D27+D34 -> 6018.4777 | E38: =D38-B38 -> -2778.299 | F38: =IF($B$8=0,0,B38/$B$8) -> 1.1114226 | G38: =IF(B39>=0,"Plan balances","Plan does not balance") -> Plan does not balance | H38: Every planned dirham out, including debt repayment and investing.
A39: Surplus / (deficit) | B39: =B8-B38 -> -881.89667 | C39: =C8-C38 -> -4547.47 | D39: =D8-D38 -> -6018.4777 | E39: =D39-B39 -> -5136.581 | F39: =IF($B$8=0,0,B39/$B$8) -> -0.11142262 | G39: =IF(B39>=0,"OK","ACTION") -> ACTION | H39: Negative means the plan spends more than the salary. The gap has to be closed by cutting lifestyle, cutting a telecom line, or earning more — not by borrowing.
A40: BUDGET HEALTH RATIOS
A41: Ratio | B41: Value | C41: Benchmark | D41: Verdict | H41: Note
A42: Savings rate achieved | B42: =IF(B8=0,0,(B32+B33)/B8) -> 0.083690467 | C42: ='FX & Assumptions'!B30 -> 0.2 | D42: =IF(B42>=C42,"ON TARGET","BELOW TARGET") -> BELOW TARGET | H42: Investing plus emergency-fund top-ups as a share of net income, against the target lever.
A43: Essential ratio | B43: =IF(B8=0,0,B17/B8) -> 0.81427345 | C43: 0.5 | D43: =IF(B43<=C43,"OK","HIGH") -> HIGH | H43: Essentials above half of net income leaves almost no room to build wealth. Rent accrual is the dominant term.
A44: Lifestyle ratio | B44: =IF(B8=0,0,B27/B8) -> 0.047379114 | C44: 0.15 | D44: =IF(B44<=C44,"OK","HIGH") -> OK | H44: Discretionary spending as a share of net income.
A45: Run-rate lifestyle ratio (actual) | B45: =IF(B8=0,0,D27/B8) -> 0.48634509 | C45: 0.15 | D45: =IF(B45<=C45,"OK","HIGH") -> HIGH | H45: The same ratio measured on what the ledger actually shows, not on the plan. This is the honest number.
A47: How to use this sheet: fix column B once a month, then let column C fill itself from the ledger. The only line that must never be cut is the rent accrual — everything else is negotiable, and the Budget only balances once the negotiation actually happens.

Sheet Spend Analysis
A1: Where the Money Actually Went
A3: Built entirely from the confirmed ledger, 3–25 Aug 2026. Transfers between own accounts, salary credits and fully refunded charges are excluded, so nothing is counted twice and nothing is counted that never left.
A5: SPENDING BY CATEGORY
A6: Category | B6: Total | C6: Share | D6: Personal | E6: Household | F6: Per day | G6: Read
A7: Travel | B7: =SUMIFS('Recent Ledger'!$D$6:$D$101,'Recent Ledger'!$I$6:$I$101,$A7,'Recent Ledger'!$J$6:$J$101,1) -> 1430 | C7: =IF($B$17=0,0,B7/$B$17) -> 0.31446057 | D7: =SUMIFS('Recent Ledger'!$D$6:$D$101,'Recent Ledger'!$I$6:$I$101,$A7,'Recent Ledger'!$J$6:$J$101,1,'Recent Ledger'!$K$6:$K$101,"Personal") -> 0 | E7: =SUMIFS('Recent Ledger'!$D$6:$D$101,'Recent Ledger'!$I$6:$I$101,$A7,'Recent Ledger'!$J$6:$J$101,1,'Recent Ledger'!$K$6:$K$101,"Household") -> 1430 | F7: =IF('FX & Assumptions'!$B$39=0,0,B7/'FX & Assumptions'!$B$39) -> 62.173913 | G7: One Emirates ticket with a refund pending. Strip it out and the underlying burn rate is far lower — but the cash still left the account.
A8: Utilities & Telecom | B8: =SUMIFS('Recent Ledger'!$D$6:$D$101,'Recent Ledger'!$I$6:$I$101,$A8,'Recent Ledger'!$J$6:$J$101,1) -> 914.93 | C8: =IF($B$17=0,0,B8/$B$17) -> 0.20119539 | D8: =SUMIFS('Recent Ledger'!$D$6:$D$101,'Recent Ledger'!$I$6:$I$101,$A8,'Recent Ledger'!$J$6:$J$101,1,'Recent Ledger'!$K$6:$K$101,"Personal") -> 0 | E8: =SUMIFS('Recent Ledger'!$D$6:$D$101,'Recent Ledger'!$I$6:$I$101,$A8,'Recent Ledger'!$J$6:$J$101,1,'Recent Ledger'!$K$6:$K$101,"Household") -> 914.93 | F8: =IF('FX & Assumptions'!$B$39=0,0,B8/'FX & Assumptions'!$B$39) -> 39.779565 | G8: A single DubaiPay payment covering du and Etisalat. Two telecom contracts for one person is a standing, cancellable cost.
A9: Dining | B9: =SUMIFS('Recent Ledger'!$D$6:$D$101,'Recent Ledger'!$I$6:$I$101,$A9,'Recent Ledger'!$J$6:$J$101,1) -> 785.28 | C9: =IF($B$17=0,0,B9/$B$17) -> 0.17268503 | D9: =SUMIFS('Recent Ledger'!$D$6:$D$101,'Recent Ledger'!$I$6:$I$101,$A9,'Recent Ledger'!$J$6:$J$101,1,'Recent Ledger'!$K$6:$K$101,"Personal") -> 478.76 | E9: =SUMIFS('Recent Ledger'!$D$6:$D$101,'Recent Ledger'!$I$6:$I$101,$A9,'Recent Ledger'!$J$6:$J$101,1,'Recent Ledger'!$K$6:$K$101,"Household") -> 306.52 | F9: =IF('FX & Assumptions'!$B$39=0,0,B9/'FX & Assumptions'!$B$39) -> 34.142609 | G9: Restaurants, delivery and cafés. The largest genuinely controllable number in the file and the fastest route to closing the September gap.
A10: Lifestyle & Shopping | B10: =SUMIFS('Recent Ledger'!$D$6:$D$101,'Recent Ledger'!$I$6:$I$101,$A10,'Recent Ledger'!$J$6:$J$101,1) -> 563.75 | C10: =IF($B$17=0,0,B10/$B$17) -> 0.12397003 | D10: =SUMIFS('Recent Ledger'!$D$6:$D$101,'Recent Ledger'!$I$6:$I$101,$A10,'Recent Ledger'!$J$6:$J$101,1,'Recent Ledger'!$K$6:$K$101,"Personal") -> 563.75 | E10: =SUMIFS('Recent Ledger'!$D$6:$D$101,'Recent Ledger'!$I$6:$I$101,$A10,'Recent Ledger'!$J$6:$J$101,1,'Recent Ledger'!$K$6:$K$101,"Household") -> 0 | F10: =IF('FX & Assumptions'!$B$39=0,0,B10/'FX & Assumptions'!$B$39) -> 24.51087 | G10: Convenience stores and hotel bills. Small tickets, high frequency.
A11: Fuel & Transport | B11: =SUMIFS('Recent Ledger'!$D$6:$D$101,'Recent Ledger'!$I$6:$I$101,$A11,'Recent Ledger'!$J$6:$J$101,1) -> 300.52 | C11: =IF($B$17=0,0,B11/$B$17) -> 0.066085098 | D11: =SUMIFS('Recent Ledger'!$D$6:$D$101,'Recent Ledger'!$I$6:$I$101,$A11,'Recent Ledger'!$J$6:$J$101,1,'Recent Ledger'!$K$6:$K$101,"Personal") -> 180.52 | E11: =SUMIFS('Recent Ledger'!$D$6:$D$101,'Recent Ledger'!$I$6:$I$101,$A11,'Recent Ledger'!$J$6:$J$101,1,'Recent Ledger'!$K$6:$K$101,"Household") -> 120 | F11: =IF('FX & Assumptions'!$B$39=0,0,B11/'FX & Assumptions'!$B$39) -> 13.066087 | G11: Fuel and Metro. Work-essential; cut this last.
A12: Groceries | B12: =SUMIFS('Recent Ledger'!$D$6:$D$101,'Recent Ledger'!$I$6:$I$101,$A12,'Recent Ledger'!$J$6:$J$101,1) -> 280.53 | C12: =IF($B$17=0,0,B12/$B$17) -> 0.061689247 | D12: =SUMIFS('Recent Ledger'!$D$6:$D$101,'Recent Ledger'!$I$6:$I$101,$A12,'Recent Ledger'!$J$6:$J$101,1,'Recent Ledger'!$K$6:$K$101,"Personal") -> 181.78 | E12: =SUMIFS('Recent Ledger'!$D$6:$D$101,'Recent Ledger'!$I$6:$I$101,$A12,'Recent Ledger'!$J$6:$J$101,1,'Recent Ledger'!$K$6:$K$101,"Household") -> 98.75 | F12: =IF('FX & Assumptions'!$B$39=0,0,B12/'FX & Assumptions'!$B$39) -> 12.196957 | G12: Many small top-up trips rather than one weekly shop, which reliably costs more.
A13: Family & Support | B13: =SUMIFS('Recent Ledger'!$D$6:$D$101,'Recent Ledger'!$I$6:$I$101,$A13,'Recent Ledger'!$J$6:$J$101,1) -> 142.97 | C13: =IF($B$17=0,0,B13/$B$17) -> 0.03143946 | D13: =SUMIFS('Recent Ledger'!$D$6:$D$101,'Recent Ledger'!$I$6:$I$101,$A13,'Recent Ledger'!$J$6:$J$101,1,'Recent Ledger'!$K$6:$K$101,"Personal") -> 0 | E13: =SUMIFS('Recent Ledger'!$D$6:$D$101,'Recent Ledger'!$I$6:$I$101,$A13,'Recent Ledger'!$J$6:$J$101,1,'Recent Ledger'!$K$6:$K$101,"Household") -> 142.97 | F13: =IF('FX & Assumptions'!$B$39=0,0,B13/'FX & Assumptions'!$B$39) -> 6.216087 | G13: Medical support transfer. The duplicate was refunded and is excluded.
A14: Grooming | B14: =SUMIFS('Recent Ledger'!$D$6:$D$101,'Recent Ledger'!$I$6:$I$101,$A14,'Recent Ledger'!$J$6:$J$101,1) -> 65 | C14: =IF($B$17=0,0,B14/$B$17) -> 0.014293662 | D14: =SUMIFS('Recent Ledger'!$D$6:$D$101,'Recent Ledger'!$I$6:$I$101,$A14,'Recent Ledger'!$J$6:$J$101,1,'Recent Ledger'!$K$6:$K$101,"Personal") -> 65 | E14: =SUMIFS('Recent Ledger'!$D$6:$D$101,'Recent Ledger'!$I$6:$I$101,$A14,'Recent Ledger'!$J$6:$J$101,1,'Recent Ledger'!$K$6:$K$101,"Household") -> 0 | F14: =IF('FX & Assumptions'!$B$39=0,0,B14/'FX & Assumptions'!$B$39) -> 2.826087 | G14: One barber visit.
A15: Unreconciled | B15: =SUMIFS('Recent Ledger'!$D$6:$D$101,'Recent Ledger'!$I$6:$I$101,$A15,'Recent Ledger'!$J$6:$J$101,1) -> 64 | C15: =IF($B$17=0,0,B15/$B$17) -> 0.01407376 | D15: =SUMIFS('Recent Ledger'!$D$6:$D$101,'Recent Ledger'!$I$6:$I$101,$A15,'Recent Ledger'!$J$6:$J$101,1,'Recent Ledger'!$K$6:$K$101,"Personal") -> 0 | E15: =SUMIFS('Recent Ledger'!$D$6:$D$101,'Recent Ledger'!$I$6:$I$101,$A15,'Recent Ledger'!$J$6:$J$101,1,'Recent Ledger'!$K$6:$K$101,"Household") -> 64 | F15: =IF('FX & Assumptions'!$B$39=0,0,B15/'FX & Assumptions'!$B$39) -> 2.7826087 | G15: Movements proven by the balance trail but with no confirmed merchant, plus one outbound transfer to an untracked account. Target: zero.
A16: Bank Fees | B16: =SUMIFS('Recent Ledger'!$D$6:$D$101,'Recent Ledger'!$I$6:$I$101,$A16,'Recent Ledger'!$J$6:$J$101,1) -> 0.49 | C16: =IF($B$17=0,0,B16/$B$17) -> 0.0001077522 | D16: =SUMIFS('Recent Ledger'!$D$6:$D$101,'Recent Ledger'!$I$6:$I$101,$A16,'Recent Ledger'!$J$6:$J$101,1,'Recent Ledger'!$K$6:$K$101,"Personal") -> 0.49 | E16: =SUMIFS('Recent Ledger'!$D$6:$D$101,'Recent Ledger'!$I$6:$I$101,$A16,'Recent Ledger'!$J$6:$J$101,1,'Recent Ledger'!$K$6:$K$101,"Household") -> 0 | F16: =IF('FX & Assumptions'!$B$39=0,0,B16/'FX & Assumptions'!$B$39) -> 0.021304348 | G16: Transfer fee. Small, but pure leakage.
A17: TOTAL CONFIRMED SPENDING | B17: =SUM(B7:B16) -> 4547.47 | C17: =IF(B17=0,0,B17/B17) -> 1 | D17: =SUM(D7:D16) -> 1470.3 | E17: =SUM(E7:E16) -> 3077.17 | F17: =IF('FX & Assumptions'!$B$39=0,0,B17/'FX & Assumptions'!$B$39) -> 197.71609 | G17: Cross-check: this total must equal the sum of the 1-flagged rows in the ledger. The Checks sheet proves it.
A19: TOP MERCHANTS BY VALUE
A20: Merchant | B20: Total | C20: Share of spend | D20: Times seen | E20: Average ticket | F20: Per day | G20: Read
A21: Emirates ticket | B21: =SUMIFS('Recent Ledger'!$D$6:$D$101,'Recent Ledger'!$C$6:$C$101,$A21,'Recent Ledger'!$J$6:$J$101,1) -> 1430 | C21: =IF($B$17=0,0,B21/$B$17) -> 0.31446057 | D21: =COUNTIFS('Recent Ledger'!$C$6:$C$101,$A21,'Recent Ledger'!$J$6:$J$101,1) -> 1 | E21: =IF(D21=0,0,B21/D21) -> 1430 | F21: =IF('FX & Assumptions'!$B$39=0,0,B21/'FX & Assumptions'!$B$39) -> 62.173913 | G21: Single largest line in the ledger; refund pending.
A22: du + Etisalat via DubaiPay | B22: =SUMIFS('Recent Ledger'!$D$6:$D$101,'Recent Ledger'!$C$6:$C$101,$A22,'Recent Ledger'!$J$6:$J$101,1) -> 914.93 | C22: =IF($B$17=0,0,B22/$B$17) -> 0.20119539 | D22: =COUNTIFS('Recent Ledger'!$C$6:$C$101,$A22,'Recent Ledger'!$J$6:$J$101,1) -> 1 | E22: =IF(D22=0,0,B22/D22) -> 914.93 | F22: =IF('FX & Assumptions'!$B$39=0,0,B22/'FX & Assumptions'!$B$39) -> 39.779565 | G22: One payment, two contracts. Consolidating to one line is a permanent saving.
A23: RTS Business Bay Hotel | B23: =SUMIFS('Recent Ledger'!$D$6:$D$101,'Recent Ledger'!$C$6:$C$101,$A23,'Recent Ledger'!$J$6:$J$101,1) -> 386.75 | C23: =IF($B$17=0,0,B23/$B$17) -> 0.08504729 | D23: =COUNTIFS('Recent Ledger'!$C$6:$C$101,$A23,'Recent Ledger'!$J$6:$J$101,1) -> 3 | E23: =IF(D23=0,0,B23/D23) -> 128.91667 | F23: =IF('FX & Assumptions'!$B$39=0,0,B23/'FX & Assumptions'!$B$39) -> 16.815217 | G23: Three charges in one day. The kind of spend that only shows up when it is totalled.
A24: Asas Al Madina General | B24: =SUMIFS('Recent Ledger'!$D$6:$D$101,'Recent Ledger'!$C$6:$C$101,$A24,'Recent Ledger'!$J$6:$J$101,1) -> 338.3 | C24: =IF($B$17=0,0,B24/$B$17) -> 0.074393014 | D24: =COUNTIFS('Recent Ledger'!$C$6:$C$101,$A24,'Recent Ledger'!$J$6:$J$101,1) -> 20 | E24: =IF(D24=0,0,B24/D24) -> 16.915 | F24: =IF('FX & Assumptions'!$B$39=0,0,B24/'FX & Assumptions'!$B$39) -> 14.708696 | G24: The most frequent merchant in the file. Small tickets, constant repetition.
A25: 25 Hours F and B | B25: =SUMIFS('Recent Ledger'!$D$6:$D$101,'Recent Ledger'!$C$6:$C$101,$A25,'Recent Ledger'!$J$6:$J$101,1) -> 163.75 | C25: =IF($B$17=0,0,B25/$B$17) -> 0.036009034 | D25: =COUNTIFS('Recent Ledger'!$C$6:$C$101,$A25,'Recent Ledger'!$J$6:$J$101,1) -> 2 | E25: =IF(D25=0,0,B25/D25) -> 81.875 | F25: =IF('FX & Assumptions'!$B$39=0,0,B25/'FX & Assumptions'!$B$39) -> 7.1195652
A26: Emarat 1691 Mutina S | B26: =SUMIFS('Recent Ledger'!$D$6:$D$101,'Recent Ledger'!$C$6:$C$101,$A26,'Recent Ledger'!$J$6:$J$101,1) -> 120.02 | C26: =IF($B$17=0,0,B26/$B$17) -> 0.026392697 | D26: =COUNTIFS('Recent Ledger'!$C$6:$C$101,$A26,'Recent Ledger'!$J$6:$J$101,1) -> 1 | E26: =IF(D26=0,0,B26/D26) -> 120.02 | F26: =IF('FX & Assumptions'!$B$39=0,0,B26/'FX & Assumptions'!$B$39) -> 5.2182609
A27: Salkara / Team Taste | B27: =SUMIFS('Recent Ledger'!$D$6:$D$101,'Recent Ledger'!$C$6:$C$101,$A27,'Recent Ledger'!$J$6:$J$101,1) -> 101.5 | C27: =IF($B$17=0,0,B27/$B$17) -> 0.022320103 | D27: =COUNTIFS('Recent Ledger'!$C$6:$C$101,$A27,'Recent Ledger'!$J$6:$J$101,1) -> 1 | E27: =IF(D27=0,0,B27/D27) -> 101.5 | F27: =IF('FX & Assumptions'!$B$39=0,0,B27/'FX & Assumptions'!$B$39) -> 4.4130435
A28: e& Money medical support | B28: =SUMIFS('Recent Ledger'!$D$6:$D$101,'Recent Ledger'!$C$6:$C$101,$A28,'Recent Ledger'!$J$6:$J$101,1) -> 100 | C28: =IF($B$17=0,0,B28/$B$17) -> 0.021990249 | D28: =COUNTIFS('Recent Ledger'!$C$6:$C$101,$A28,'Recent Ledger'!$J$6:$J$101,1) -> 1 | E28: =IF(D28=0,0,B28/D28) -> 100 | F28: =IF('FX & Assumptions'!$B$39=0,0,B28/'FX & Assumptions'!$B$39) -> 4.3478261
A29: Cielo Kabab Restaurant | B29: =SUMIFS('Recent Ledger'!$D$6:$D$101,'Recent Ledger'!$C$6:$C$101,$A29,'Recent Ledger'!$J$6:$J$101,1) -> 78 | C29: =IF($B$17=0,0,B29/$B$17) -> 0.017152395 | D29: =COUNTIFS('Recent Ledger'!$C$6:$C$101,$A29,'Recent Ledger'!$J$6:$J$101,1) -> 1 | E29: =IF(D29=0,0,B29/D29) -> 78 | F29: =IF('FX & Assumptions'!$B$39=0,0,B29/'FX & Assumptions'!$B$39) -> 3.3913043
A30: Zomato | B30: =SUMIFS('Recent Ledger'!$D$6:$D$101,'Recent Ledger'!$C$6:$C$101,$A30,'Recent Ledger'!$J$6:$J$101,1) -> 66.52 | C30: =IF($B$17=0,0,B30/$B$17) -> 0.014627914 | D30: =COUNTIFS('Recent Ledger'!$C$6:$C$101,$A30,'Recent Ledger'!$J$6:$J$101,1) -> 1 | E30: =IF(D30=0,0,B30/D30) -> 66.52 | F30: =IF('FX & Assumptions'!$B$39=0,0,B30/'FX & Assumptions'!$B$39) -> 2.8921739
A31: ISK Gents Saloon | B31: =SUMIFS('Recent Ledger'!$D$6:$D$101,'Recent Ledger'!$C$6:$C$101,$A31,'Recent Ledger'!$J$6:$J$101,1) -> 65 | C31: =IF($B$17=0,0,B31/$B$17) -> 0.014293662 | D31: =COUNTIFS('Recent Ledger'!$C$6:$C$101,$A31,'Recent Ledger'!$J$6:$J$101,1) -> 1 | E31: =IF(D31=0,0,B31/D31) -> 65 | F31: =IF('FX & Assumptions'!$B$39=0,0,B31/'FX & Assumptions'!$B$39) -> 2.826087
A32: Sahil Zam Zam Mandi | B32: =SUMIFS('Recent Ledger'!$D$6:$D$101,'Recent Ledger'!$C$6:$C$101,$A32,'Recent Ledger'!$J$6:$J$101,1) -> 52 | C32: =IF($B$17=0,0,B32/$B$17) -> 0.01143493 | D32: =COUNTIFS('Recent Ledger'!$C$6:$C$101,$A32,'Recent Ledger'!$J$6:$J$101,1) -> 1 | E32: =IF(D32=0,0,B32/D32) -> 52 | F32: =IF('FX & Assumptions'!$B$39=0,0,B32/'FX & Assumptions'!$B$39) -> 2.2608696
A34: BURN RATE AND CONTROL
A35: Metric | B35: Value | C35: Benchmark | D35: Status | G35: Read
A36: Total spend in the ledger window | B36: =B17 -> 4547.47 | G36: Everything that genuinely left the accounts between 3 and 25 Aug.
A37: Spend excluding the refundable ticket | B37: =B17-B7 -> 3117.47 | G37: The underlying number once the one-off Emirates ticket is set aside.
A38: Spend excluding ticket and utilities | B38: =B17-B7-B8 -> 2202.54 | G38: Day-to-day living cost only: food, fuel, shops, grooming.
A39: Daily burn — day-to-day living | B39: =IF('FX & Assumptions'!$B$39=0,0,(B17-B7-B8)/'FX & Assumptions'!$B$39) -> 95.762609 | C39: ='Inputs'!B41/57 -> 5 | D39: =IF(B39<=C39,"WITHIN CAP","ABOVE CAP") -> ABOVE CAP | G39: This is the headline finding of the whole sheet. The damage-control plan caps living costs at AED 5 a day; the confirmed ledger shows a multiple of that. The cap is not being kept, and that gap is exactly why the rent cheque is at risk.
A40: Personal share of spending | B40: =IF(B17=0,0,D17/B17) -> 0.32332264 | C40: 0.35 | D40: =IF(B40<=C40,"OK","HIGH") -> OK | G40: Personal lifestyle spending against household and work-essential spending.
A41: Household share of spending | B41: =IF(B17=0,0,E17/B17) -> 0.67667736 | C41: 0.65 | G41: The balance of the split.
A42: Discretionary share (dining, lifestyle, grooming) | B42: =IF(B17=0,0,(B9+B10+B14)/B17) -> 0.31094873 | C42: 0.25 | D42: =IF(B42<=C42,"OK","HIGH") -> HIGH | G42: The share of spending that can be cut this week without any structural change.
A43: Monthly run rate at this pace | B43: =B17*'FX & Assumptions'!$B$40 -> 6018.4777 | C43: ='FX & Assumptions'!B25 -> 7914.88 | D43: =IF(B43<=C43,"WITHIN SALARY","ABOVE SALARY") -> WITHIN SALARY | G43: The partial ledger scaled to a full month, against net salary. If this reads ABOVE SALARY, the shortfall is structural, not bad luck.
A45: Read this sheet before the Budget. The Budget says what should happen; this sheet says what did. Where they disagree, this sheet is right.

Sheet Recent Ledger
A1: Recent Confirmed Ledger
A3: Personal and household transactions are separated; transfers and refunds never count as spending. Columns I to K normalise every line into one budget category, a 1/0 spend flag and a personal/household split so the Budget, Spend Analysis and AI Advisor sheets can total it without any manual sorting.
A5: Date/time | B5: Bank | C5: Merchant | D5: Amount | E5: Category | F5: Class | G5: Balance after | H5: Treatment | I5: Budget category | J5: Counts as spend | K5: Split
A6: 46237.472 | B6: FAB | C6: du + Etisalat via DubaiPay | D6: 914.93 | E6: Household utilities | F6: Household | G6: 2535.86 | H6: Expense · paid once | I6: Utilities & Telecom | J6: 1 | K6: Household
A7: 46237.5 | B7: NBD | C7: Asas Al Madina General | D7: 14 | E7: Lifestyle | F7: Personal | G7: 183.92 | H7: Expense | I7: Lifestyle & Shopping | J7: 1 | K7: Personal
A8: 46237.542 | B8: NBD | C8: Yas Home General Trading | D8: 22.97 | E8: Household other | F8: Household | G8: 160.95 | H8: Expense | I8: Family & Support | J8: 1 | K8: Household
A9: 46237.836 | B9: NBD | C9: Spicy Falcon Restaurant | D9: 16 | E9: Food & Dining | F9: Household | G9: 144.95 | H9: Expense | I9: Dining | J9: 1 | K9: Household
A10: 46238.196 | B10: NBD | C10: Emarat Nad Al Hamar | D10: 13.5 | E10: Lifestyle | F10: Personal | G10: 131.45 | H10: Expense | I10: Lifestyle & Shopping | J10: 1 | K10: Personal
A11: 46238.208 | B11: Tabby Cash | C11: Nad Al Hamar Star Grocery | D11: 2 | E11: Lifestyle | F11: Personal | G11: 0.89 | H11: Wallet expense; not Card debt | I11: Lifestyle & Shopping | J11: 1 | K11: Personal
A12: 46238.333 | B12: NBD | C12: Asas Al Madina General | D12: 24.5 | E12: Groceries | F12: Household | G12: 106.95 | H12: Expense | I12: Groceries | J12: 1 | K12: Household
A13: 46239.325 | B13: NBD | C13: Reel Entertainment | D13: 20 | E13: Household other | F13: Household | G13: 86.95 | H13: Expense | I13: Family & Support | J13: 1 | K13: Household
A14: 46239.449 | B14: NBD | C14: HNS Restaurant and Cafe | D14: 10 | E14: Food & Dining | F14: Household | G14: 76.95 | H14: Expense | I14: Dining | J14: 1 | K14: Household
A15: 46239.449 | B15: NBD | C15: Burger King Dubai Mall | D15: 10 | E15: Food & Dining | F15: Household | G15: 66.95 | H15: Expense | I15: Dining | J15: 1 | K15: Household
A16: 46239.45 | B16: NBD | C16: Texas Dubai Mall | D16: 10 | E16: Food & Dining | F16: Household | G16: 56.95 | H16: Expense | I16: Dining | J16: 1 | K16: Household
A17: 46239.64 | B17: NBD | C17: Team Taste Restaurant | D17: 31 | E17: Food & Dining | F17: Household | G17: 25.95 | H17: Expense | I17: Dining | J17: 1 | K17: Household
... A101: 46259.275 | B101: FAB 4001 | C101: ENOC Site 39 | D101: 13.5 | E101: Transport & Fuel | F101: Personal | G101: 3.45 | H101: Expense | I101: Fuel & Transport | J101: 1 | K101: Personal

Sheet Monthly Plan
A1: Cash Flow to the October Rent Cheque
A3: The model excludes the 26 Oct salary because the rent cheque clears on 22 Oct.
A5: Cash flow | B5: Aug 2026E | C5: Sep 2026E | D5: Oct 1–22E | E5: Total | F5: Status | G5: Notes
A6: Opening liquid cash | B6: ='Inputs'!B14 -> 6105.64 | C6: =B22 -> 8168.36 | D6: =C22 -> 12428.13 | E6: =SUM(B6:D6) -> 26702.13 | F6: Actual / last reported | G6: Reconciled 25 Aug from FAB app, NBD SMS and last-reported wallet balances
A7: Rent refund | B7: 0 | C7: 0 | D7: 0 | E7: 0 | F7: Actual received | G7: AED 1,430 is included in opening cash
A8: Pending early salary cash | B8: 0 | C8: 0 | D8: 0 | E8: 0 | F8: Actual received | G8: AED 1,540 is included in opening cash
A9: Remaining Aug payday base | B9: ='Inputs'!B22 -> 2906 | C9: =0 -> 0 | D9: =0 -> 0 | E9: =SUM(B9:D9) -> 2906 | F9: Estimated | G9: Approximately AED 2,906 expected 26 Aug; only credited cash counts
A10: Expected extra income | B10: ='Inputs'!B23 -> 0 | C10: =0 -> 0 | D10: =0 -> 0 | E10: =SUM(B10:D10) -> 0 | F10: Estimated | G10: No additional separate inflow beyond the AED 8,500 estimate
A11: September salary | B11: =0 -> 0 | C11: ='Inputs'!B18 -> 7914.88 | D11: =0 -> 0 | E11: =SUM(B11:D11) -> 7914.88 | F11: Estimated | G11: 26 Sep salary available before rent
A12: Total available | B12: =SUM(B6:B11) -> 9011.64 | C12: =SUM(C6:C11) -> 16083.24 | D12: =SUM(D6:D11) -> 12428.13 | E12: =SUM(B12:D12) -> 37523.01 | F12: Formula | G12: Opening + inflows
A13: DEWA | B13: ='Inputs'!B33 -> 813.28 | C13: ='Inputs'!B33 -> 813.28 | D13: 0 | E13: =SUM(B13:D13) -> 1626.56 | F13: Aug actual / Sep baseline | G13: AED 813.28 actual August bill; September repeats current bill only as a planning baseline
A14: du | B14: =0 -> 0 | C14: ='Inputs'!B34 -> 590.98 | D14: ='Inputs'!B34 -> 590.98 | E14: =SUM(B14:D14) -> 1181.96 | F14: Estimated | G14: Sep and Oct cycles
A15: Etisalat | B15: =0 -> 0 | C15: ='Inputs'!B35 -> 323.95 | D15: ='Inputs'!B35 -> 323.95 | E15: =SUM(B15:D15) -> 647.9 | F15: Estimated | G15: Sep and Oct cycles
A16: Tabby no-fee minimum | B16: =0 -> 0 | C16: ='Inputs'!B36 -> 1314.5 | D16: ='Inputs'!B42 -> 715.33 | E16: =SUM(B16:D16) -> 2029.83 | F16: Sep option / Oct generated | G16: Sep no-fee minimum AED1,314.50; Oct generated statement AED715.33 due 3 Oct
A17: Nippon SIP funding | B17: =0 -> 0 | C17: ='Inputs'!B39 -> 462.4 | D17: ='Inputs'!B39 -> 462.4 | E17: =SUM(B17:D17) -> 924.8 | F17: Estimated | G17: Sep and Oct funding
A18: Living allowance | B18: 30 | C18: 150 | D18: 105 | E18: =SUM(B18:D18) -> 285 | F18: Damage-control cap | G18: AED 160 survival allowance through 25 Sep · AED 5/day or AED 35/week | H18: Zero discretionary spending; any overspend directly increases the rent gap
A19: Rent cheque | B19: =0 -> 0 | C19: =0 -> 0 | D19: ='Inputs'!B30 -> 11750 | E19: =SUM(B19:D19) -> 11750 | F19: Actual | G19: Due 22 Oct
A20: Emergency protected | B20: =0 -> 0 | C20: =0 -> 0 | D20: ='Inputs'!B32 -> 7.67 | E20: =SUM(B20:D20) -> 7.67 | F20: Actual | G20: Protected
A21: Total requirements | B21: =SUM(B13:B20) -> 843.28 | C21: =SUM(C13:C20) -> 3655.11 | D21: =SUM(D13:D20) -> 13955.33 | E21: =SUM(B21:D21) -> 18453.72 | F21: Formula | G21: Costs + protected amounts
A22: Closing cash / gap | B22: =B12-B21 -> 8168.36 | C22: =C12-C21 -> 12428.13 | D22: =D12-D21 -> -1527.2 | E22: =D22 -> -1527.2 | F22: Formula | G22: Negative value is the rent-plan shortfall before additional income
A23: Rent money before cheque | B23: =0 -> 0 | C23: =0 -> 0 | D23: =D12-SUM(D13:D18)-D20 -> 10222.8 | E23: =D23 -> 10222.8 | F23: Formula | G23: Rent remains protected; near-term bills plus survival exceed available loose cash by AED 189.19 before SIP
A24: Rent shortfall | B24: =0 -> 0 | C24: =0 -> 0 | D24: =MAX(0,D19-D23) -> 1527.2 | E24: =D24 -> 1527.2 | F24: SHORTFALL | G24: Additional banked income required by 21 Oct

Sheet Rent Closure
A1: October Rent — Zero-Gap Control Plan
A3: A zero result is a conditional plan, not a claim that pending inflows are already banked.
A5: RECONCILED RENT POSITION
A6: Step | B6: Amount | C6: Running gap | D6: Status | E6: Deadline | F6: Owner action | G6: Evidence rule
A7: Projected shortfall before damage control | B7: ='Monthly Plan'!D24 -> 1527.2 | C7: =B7 -> 1527.2 | D7: Open risk | E7: 46316 | F7: No discretionary spending | G7: Monthly Plan after all confirmed/estimated obligations
A8: Salary adjustment vs previous estimate | B8: 24 | C8: =C7 -> 1527.2 | D8: Included in projection | E8: 46260 | F8: Confirm AED 2,906 when credited | G8: Prior estimate AED 2,930; current expected AED 2,906
A9: Additional income required | B9: =C8 -> 1527.2 | C9: =MAX(0,C8-B9) -> 0 | D9: Required, not received | E9: 46316 | F9: Generate and bank the full amount | G9: Only banked cash counts
A10: Further living-cost reduction | B10: 0 | C10: =MAX(0,C9-B10) -> 0 | D10: No safe reduction assumed | E10: 46316 | F10: Hold survival allowance at AED 160 through 25 Sep | G10: AED 5/day is already the minimum control cap
A11: FINAL CONDITIONAL GAP | B11: =C10 -> 0 | C11: =C10 -> 0 | D11: Must equal zero | E11: 46316 | F11: Complete income action | G11: Conditional on expected salaries and extra income
A12: Revised living cap to 22 Oct | B12: ='Inputs'!B41 -> 285 | C12: 0 | D12: Control | E12: 46316 | F12: AED 5/day; AED 35/week | G12: Essentials only; discretionary spending AED 0
A14: RENT VAULT MILESTONES
A15: Funding step | B15: Amount | C15: Running rent funding | D15: Status | E15: Deadline | F15: Evidence rule | G15: Control note
A16: Base projected rent money | B16: ='Monthly Plan'!D23 -> 10222.8 | C16: =B16 -> 10222.8 | D16: Projected | E16: 46316 | F16: Monthly Plan projection | G16: Before additional income
A17: Salary estimate adjustment | B17: 0 | C17: =C16+B17 -> 10222.8 | D17: Already modelled | E17: 46260 | F17: Confirm actual salary credit | G17: No separate uplift assumed
A18: Additional income required | B18: =B9 -> 1527.2 | C18: =C17+B18 -> 11750 | D18: Required | E18: 46316 | F18: Banked cash only | G18: Required after all obligations and survival allowance
A19: Further living-cost reduction | B19: 0 | C19: =C18+B19 -> 11750 | D19: Not recommended | E19: 46316 | F19: Do not cut below AED 5/day | G19: Current allowance is already survival level
A20: FINAL RENT FUNDING | B20: =C19-'Inputs'!B30 -> 0 | C20: =C19 -> 11750 | D20: Must equal cheque | E20: 46316 | F20: All controls completed | G20: Must reconcile to AED 11,750
A21: Damage control updated 25 Aug: AED 5,990.45 rent remains protected. Expected AED 2,906 payday must cover DEWA, Tabby, du/Etisalat and AED 160 survival spending. Available loose cash is AED 3,013.52 including payday; bills plus survival require AED 3,202.71, leaving AED 189.19 to find. The September SIP adds AED 462, so total additional cash needed is AED 651.19. Pause SIP before borrowing or touching rent.

Sheet Obligations
A1: Bills, Debt and Recurring Commitments
A3: Paid items are shown once. Estimated recurring bills must be replaced when actual bills arrive.
A5: Due date | B5: Item | C5: Amount | D5: Currency | E5: Actual / estimate | F5: Recurrence | G5: Priority | H5: Control note
A6: 46229 | B6: DEWA July paid | C6: 793.42 | D6: AED | E6: Actual paid | F6: Monthly | G6: Essential | H6: Do not deduct again
A7: 46237 | B7: du August paid | C7: 590.98 | D7: AED | E7: Actual paid | F7: Monthly | G7: Essential | H7: Next estimate 03 Sep
A8: 46237 | B8: Etisalat August paid | C8: 323.95 | D8: AED | E8: Actual paid | F8: Monthly | G8: Essential | H8: Next estimate 03 Sep
A9: 46244 | B9: Four Nippon SIPs | C9: 12000 | D9: INR | E9: Actual completed | F9: Monthly | G9: Core investment | H9: Do not retry
A10: 46265 | B10: DEWA August | C10: 813.28 | D10: AED | E10: Actual bill | F10: Monthly | G10: Essential | H10: Actual bill replaces AED 793.42 estimate; pay by due date
A11: 46268 | B11: Tabby no-fee minimum | C11: 1314.5 | D11: AED | E11: Actual due | F11: One-time statement | G11: Critical | H11: Autopay selected; keep card frozen; full statement AED 1,972.03 optional
A12: 46275 | B12: Nippon SIP funding | C12: 462.4 | D12: AED | E12: Estimated | F12: Monthly | G12: Core investment | H12: ₹12,000; continue only while essentials remain funded
A13: 46280 | B13: du | C13: 590.98 | D13: AED | E13: Estimated | F13: Monthly | G13: Essential | H13: September estimate AED 590.98; actual bill required; due around 15 Sep
A14: 46280 | B14: Etisalat | C14: 323.95 | D14: AED | E14: Estimated | F14: Monthly | G14: Essential | H14: September estimate AED 323.95; actual bill required; due around 15 Sep
A15: 46298 | B15: October Tabby payment | C15: 715.33 | D15: AED | E15: Actual generated | F15: Before rent cheque | G15: Critical | H15: September statement generated; amount due AED 715.33
A16: 46317 | B16: Rent cheque | C16: 11750 | D16: AED | E16: Actual | F16: None | G16: Critical | H16: Fully fund by 21 Oct
B17: Tabby outstanding exposure | C17: 2687.36 | D17: AED | E17: Actual confirmed total | F17: Card frozen | G17: Debt control | H17: AED 1,972.03 August statement + AED 715.33 September statement; do not add separately
B18: Netflix retry risk | C18: 35 | D18: AED | E18: Declined / not charged | F18: Subscription | G18: Pause | H18: Cancel or leave unfunded; do not use protected cash for a retry

Sheet Debt Plan
A1: Debt Plan — Getting Tabby to Zero
A3: One debt, two statements, a hard freeze and a dated route to zero. Tabby carries no interest while the no-fee minimum is met on time, which makes punctuality — not size — the whole risk here.
A5: POSITION
A6: Item | B6: Amount | C6: Due | D6: Status | E6: Priority | F6: Rule | G6: Cost of slipping | H6: Note
A7: August statement (full) | B7: ='Inputs'!B37 -> 1972.03 | C7: 46268 | D7: Actual statement | E7: Optional | F7: Pay in full only if rent and bills stay funded | H7: Clearing this on 3 Sep would end the debt a month early, but the September funding gap says the cash is not there.
A8: August no-fee minimum | B8: ='Inputs'!B36 -> 1314.5 | C8: 46268 | D8: Actual due | E8: Critical | F8: Autopay is already selected | G8: =35 -> 35 | H8: The amount that must land on 3 Sep. Missing it converts a free debt into an expensive one.
A9: September statement | B9: ='Inputs'!B42 -> 715.33 | C9: 46298 | D9: Actual generated | E9: Critical | F9: Pay by due date | G9: =35 -> 35 | H9: Already generated and confirmed. It falls due nineteen days before the rent cheque.
A10: Total outstanding exposure | B10: ='Inputs'!B38 -> 2687.36 | D10: Actual confirmed | E10: Debt control | F10: Card frozen until zero | H10: August statement plus September statement. Do not add the two statements to this figure again — it already contains both.
A11: Remaining after the 3 Sep minimum | B11: =B10-B8 -> 1372.86 | D11: Formula | E11: Debt control | F11: Falls to zero on the schedule below | H11: What is still owed once the September minimum clears.
A13: ROUTE TO ZERO — RECOMMENDED (PAY THE NO-FEE MINIMUM, PROTECT RENT)
A14: Payment date | B14: Opening balance | C14: Payment | D14: Closing balance | E14: Fee incurred | F14: Funded from | G14: Cumulative paid | H14: Note
A15: 46268 | B15: ='Inputs'!B38 -> 2687.36 | C15: ='Inputs'!B36 -> 1314.5 | D15: =MAX(0,B15-C15) -> 1372.86 | E15: 0 | F15: 26 Aug salary | G15: =C15 -> 1314.5 | H15: The confirmed no-fee minimum. Autopay already selected.
A16: 46298 | B16: =D15 -> 1372.86 | C16: ='Inputs'!B42 -> 715.33 | D16: =MAX(0,B16-C16) -> 657.53 | E16: 0 | F16: 26 Sep salary | G16: =G15+C16 -> 2029.83 | H16: The generated September statement, due before the rent cheque clears.
A17: 46329 | B17: =D16 -> 657.53 | C17: =D16 -> 657.53 | D17: =MAX(0,B17-C17) -> 0 | E17: 0 | F17: 26 Oct salary | G17: =G16+C17 -> 2687.36 | H17: The tail of the August statement. Paying it here clears the card completely.
A18: DEBT FREE | B18: =D17 -> 0 | D18: =IF(D17<=0.01,"Zero balance","Still outstanding") -> Zero balance | E18: =SUM(E15:E17) -> 0 | F18: Three salary cycles | G18: =G17 -> 2687.36 | H18: Total paid equals total owed, and no fee is ever incurred. That is the whole objective.
A20: ALTERNATIVE — CLEAR THE FULL AUGUST STATEMENT ON 3 SEP
A21: Comparison | B21: Recommended route | C21: Aggressive route | D21: Difference | E21: Verdict | H21: Note
A22: Cash needed on 3 Sep | B22: ='Inputs'!B36 -> 1314.5 | C22: ='Inputs'!B37 -> 1972.03 | D22: =C22-B22 -> 657.53 | E22: =IF(C22>B22,"Aggressive costs more now","") -> Aggressive costs more now | H22: The aggressive route needs this much extra in September, on top of a month that is already short.
A23: Debt free on | B23: =A17 -> 46329 | C23: =A16 -> 46298 | E23: ="One month later" -> One month later | H23: The aggressive route ends the debt in October instead of November.
A24: Fees incurred either way | B24: =E18 -> 0 | C24: 0 | D24: =C24-B24 -> 0 | E24: ="No difference" -> No difference | H24: Neither route incurs a fee, so speed buys nothing but the feeling of speed.
A25: Effect on the October rent cheque | B25: =0 -> 0 | C25: =C22-B22 -> 657.53 | D25: =C25-B25 -> 657.53 | E25: =IF(C25>0,"Aggressive puts rent at risk","") -> Aggressive puts rent at risk | H25: Every dirham sent early to Tabby is a dirham not available for the AED 11,750 cheque.
A27: STANDING DEBT RULES
A28: Rule | B28: Status | H28: Why
A29: Keep the Tabby Card frozen until the balance is zero | B29: =IF('Inputs'!B38>0,"IN FORCE","Released") -> IN FORCE | H29: A frozen card cannot generate a new statement. The balance can then only fall.
A30: Never miss a due date | B30: ="IN FORCE" -> IN FORCE | H30: Tabby is free while the minimum is met on time. Late is the only way this debt becomes expensive.
A31: No new buy-now-pay-later of any kind before the rent cheque clears | B31: =IF(TODAY()<DATE(2026,10,22),"IN FORCE","Review") -> IN FORCE | H31: New instalments would land in exactly the months the rent has to be funded.
A32: Tabby Cash wallet spending is not Card borrowing | B32: ="IN FORCE" -> IN FORCE | H32: Carried over from the original classification rule; spending the wallet never resets the Card streak.
A33: Cancel or leave the Netflix subscription unfunded | B33: =IF('Obligations'!C18>0,"OPEN","Closed") -> OPEN | H33: The AED 35 charge was declined, not paid. Letting it retry against protected cash would be the smallest and most avoidable own goal in the file.
A35: This is a small debt with a big shadow. AED 2,687.36 is not what threatens the rent cheque; the timing is. Two of the three payments fall in the same eight weeks as the cheque, which is why the schedule above funds each one from a different salary.

Sheet Investments
A1: Investment Portfolio
A3: MF Central snapshot dated 10 Aug 2026 after the four ₹3,000 Nippon SIPs.
A5: Fund | B5: Fund house | C5: Units | D5: Cost | E5: Snapshot value | F5: Gain / loss | G5: Return | H5: NAV | I5: SIP status | J5: Evidence | K5: Value (AED) | L5: Weight
A6: Nippon Large Cap | B6: Nippon | C6: 758.192 | D6: 75000 | E6: 78012.04 | F6: =E6-D6 -> 3012.04 | G6: =IF(D6=0,0,F6/D6) -> 0.040160533 | H6: 102.89 | I6: Active | J6: MF Central 10 Aug | K6: =E6*'FX & Assumptions'!$B$7 -> 3006.0613 | L6: =IF($E$12=0,0,E6/$E$12) -> 0.31830326
A7: Nippon Multi Cap | B7: Nippon | C7: 226.127 | D7: 73936.89 | E7: 77061.61 | F7: =E7-D7 -> 3124.72 | G7: =IF(D7=0,0,F7/D7) -> 0.042261989 | H7: 340.7896 | I7: Active | J7: Multi Cap email confirms 8.803 new units | K7: =E7*'FX & Assumptions'!$B$7 -> 2969.4381 | L7: =IF($E$12=0,0,E7/$E$12) -> 0.31442534
A8: Nippon Growth Mid Cap | B8: Nippon | C8: 6.993 | D8: 33000 | E8: 35303.33 | F8: =E8-D8 -> 2303.33 | G8: =IF(D8=0,0,F8/D8) -> 0.069797879 | H8: 5048.38 | I8: Active | J8: MF Central 10 Aug | K8: =E8*'FX & Assumptions'!$B$7 -> 1360.3538 | L8: =IF($E$12=0,0,E8/$E$12) -> 0.14404399
A9: Nippon Small Cap | B9: Nippon | C9: 189.636 | D9: 35968 | E9: 39456.63 | F9: =E9-D9 -> 3488.63 | G9: =IF(D9=0,0,F9/D9) -> 0.096992604 | H9: 208.07 | I9: Active | J9: MF Central 10 Aug | K9: =E9*'FX & Assumptions'!$B$7 -> 1520.3942 | L9: =IF($E$12=0,0,E9/$E$12) -> 0.1609902
A10: Nippon Silver ETF FoF | B10: Nippon | C10: 115.191 | D10: 2971.14 | E10: 4046.82 | F10: =E10-D10 -> 1075.68 | G10: =IF(D10=0,0,F10/D10) -> 0.36204285 | H10: 35.13 | I10: Cancelled | J10: Holding remains; SIP cancelled | K10: =E10*'FX & Assumptions'!$B$7 -> 155.93733 | L10: =IF($E$12=0,0,E10/$E$12) -> 0.016511759
A11: Motilal Oswal Midcap | B11: Motilal Oswal | C11: 93.721 | D11: 11000 | E11: 11206.72 | F11: =E11-D11 -> 206.72 | G11: =IF(D11=0,0,F11/D11) -> 0.018792727 | H11: 119.57534 | I11: Active | J11: MF Central 10 Aug | K11: =E11*'FX & Assumptions'!$B$7 -> 431.8319 | L11: =IF($E$12=0,0,E11/$E$12) -> 0.045725449
A12: TOTAL | D12: =SUM(D6:D11) -> 231876.03 | E12: =SUM(E6:E11) -> 245087.15 | F12: =SUM(F6:F11) -> 13211.12 | G12: =IF(D12=0,0,F12/D12) -> 0.056974928 | J12: Rounded statement total | K12: =E12*'FX & Assumptions'!$B$7 -> 9444.0167 | L12: =IF($E$12=0,0,E12/$E$12) -> 1
A14: PORTFOLIO CONTROLS
A15: Metric | B15: Value | C15: Status | D15: Note
A16: Nippon concentration | B16: =SUM(E6:E10)/E12 -> 0.95427455 | C16: High | D16: Nippon value / total MF value
A17: Motilal concentration | B17: =E11/E12 -> 0.045725449 | C17: Low | D17: Motilal value / total MF value
A18: Next SIP | B18: 12000 | C18: Active | D18: Due 10 Sep; AED 462.40 estimated funding
A20: AMANA STATEMENT CONTROLS
A21: Metric | B21: Value | C21: Status | D21: Evidence
A22: Ending account value | B22: 864.82 | C22: Actual | D22: Amana statement through 10 Aug 2026
A23: Net money in / out | B23: 852.11 | C23: Actual | D23: Statement total
A24: Realized profit | B24: 162.13 | C24: Actual | D24: Statement summary
A25: Floating profit / loss | B25: -130.69 | C25: Actual | D25: Statement summary
A26: Floating fees | B26: -8.45 | C26: Actual | D26: Statement summary
A27: Overnight fees | B27: -12.02 | C27: Actual | D27: Statement summary
A28: Amana Earn | B28: 3.72 | C28: Actual | D28: Statement summary
A29: Open positions | B29: 41 | C29: Actual | D29: PLTR, VOO and Realty Income sold 28 Jul
A31: CONSOLIDATED PORTFOLIO IN DIRHAMS
A32: Holding group | B32: Native value | C32: Currency | D32: Rate to AED | E32: Value (AED) | F32: Share | J32: Note
A33: Indian mutual funds — 6 schemes | B33: =E12 -> 245087.15 | C33: INR | D33: ='FX & Assumptions'!$B$7 -> 0.0385333 | E33: =B33*D33 -> 9444.0167 | F33: =IF($E$36=0,0,E33/$E$36) -> 0.7474466 | J33: Five Nippon schemes plus one Motilal Oswal midcap fund, valued at the 10 Aug MF Central snapshot.
A34: ICICI settlement cash | B34: ='Inputs'!B40 -> 388.51 | C34: INR | D34: ='FX & Assumptions'!$B$7 -> 0.0385333 | E34: =B34*D34 -> 14.970572 | F34: =IF($E$36=0,0,E34/$E$36) -> 0.0011848458 | J34: Rupee cash left idle after the August SIPs.
A35: Amana trading account | B35: =B22 -> 864.82 | C35: USD | D35: ='FX & Assumptions'!$B$9 -> 3.6725 | E35: =B35*D35 -> 3176.0514 | F35: =IF($E$36=0,0,E35/$E$36) -> 0.25136856 | J35: Ending account value across 41 open positions.
A36: TOTAL INVESTED (AED) | E36: =SUM(E33:E35) -> 12635.039 | J36: This is the figure the Net Worth and Wealth Plan sheets grow.
A37: Total cost basis (AED) | E37: =D12*'FX & Assumptions'!$B$7+B23*'FX & Assumptions'!$B$9+'Inputs'!B40*'FX & Assumptions'!$B$7 -> 12079.293 | J37: Mutual-fund cost plus net money paid into Amana plus the idle broker cash. The cash is carried at cost so that holding it never shows up as a gain.
A38: Total gain / (loss) (AED) | E38: =E36-E37 -> 555.74553 | J38: Snapshot gain, not a forecast. The Wealth Plan deliberately assumes less.
A39: Return on cost | E39: =IF(E37=0,0,E38/E37) -> 0.046008116 | J39: Simple return on money in. Not annualised — most of this capital has been invested for less than a full year.
A41: ASSET ALLOCATION — ACTUAL AGAINST TARGET
A42: Asset class | B42: Value (AED) | C42: Actual weight | D42: Target weight | E42: Drift | F42: Action | J42: Note
A43: Indian large cap | B43: =E6*'FX & Assumptions'!$B$7 -> 3006.0613 | C43: =IF($B$50=0,0,B43/$B$50) -> 0.23791469 | D43: 0.3 | E43: =C43-D43 -> -0.062085308 | F43: =IF(ABS(E43)<=0.05,"On target",IF(E43>0,"Overweight","Underweight")) -> Underweight | J43: Nippon Large Cap. The stabiliser of the portfolio.
A44: Indian multi cap | B44: =E7*'FX & Assumptions'!$B$7 -> 2969.4381 | C44: =IF($B$50=0,0,B44/$B$50) -> 0.23501615 | D44: 0.2 | E44: =C44-D44 -> 0.035016149 | F44: =IF(ABS(E44)<=0.05,"On target",IF(E44>0,"Overweight","Underweight")) -> On target | J44: Nippon Multi Cap. Already close to target.
A45: Indian mid cap | B45: =(E8+E11)*'FX & Assumptions'!$B$7 -> 1792.1857 | C45: =IF($B$50=0,0,B45/$B$50) -> 0.14184252 | D45: 0.15 | E45: =C45-D45 -> -0.0081574816 | F45: =IF(ABS(E45)<=0.05,"On target",IF(E45>0,"Overweight","Underweight")) -> On target | J45: Nippon Growth Mid Cap plus Motilal Oswal Midcap. Two funds doing the same job — a candidate for consolidation.
A46: Indian small cap | B46: =E9*'FX & Assumptions'!$B$7 -> 1520.3942 | C46: =IF($B$50=0,0,B46/$B$50) -> 0.12033158 | D46: 0.1 | E46: =C46-D46 -> 0.020331579 | F46: =IF(ABS(E46)<=0.05,"On target",IF(E46>0,"Overweight","Underweight")) -> On target | J46: Nippon Small Cap. The highest-volatility sleeve; keep it small and never sell it in a panic.
A47: Commodity — silver | B47: =E10*'FX & Assumptions'!$B$7 -> 155.93733 | C47: =IF($B$50=0,0,B47/$B$50) -> 0.012341658 | D47: 0.05 | E47: =C47-D47 -> -0.037658342 | F47: =IF(ABS(E47)<=0.05,"On target",IF(E47>0,"Overweight","Underweight")) -> On target | J47: Nippon Silver ETF FoF. The SIP is cancelled but the holding remains; it is the best-performing line in the portfolio and worth keeping as a diversifier.
A48: Global equity | B48: =B22*'FX & Assumptions'!$B$9 -> 3176.0514 | C48: =IF($B$50=0,0,B48/$B$50) -> 0.25136856 | D48: 0.15 | E48: =C48-D48 -> 0.10136856 | F48: =IF(ABS(E48)<=0.05,"On target",IF(E48>0,"Overweight","Underweight")) -> Overweight | J48: Amana account. The only non-rupee investment exposure in the file.
A49: Broker cash | B49: ='Inputs'!B40*'FX & Assumptions'!$B$7 -> 14.970572 | C49: =IF($B$50=0,0,B49/$B$50) -> 0.0011848458 | D49: 0.05 | E49: =C49-D49 -> -0.048815154 | F49: =IF(ABS(E49)<=0.05,"On target",IF(E49>0,"Overweight","Underweight")) -> On target | J49: Idle settlement cash. Target is really zero; 5% is the practical tolerance.
A50: TOTAL | B50: =SUM(B43:B49) -> 12635.039 | C50: =IF(B50=0,0,SUM(B43:B49)/B50) -> 1 | D50: =SUM(D43:D49) -> 1 | E50: =C50-D50 -> 0 | F50: =IF(ABS(D50-1)<0.0001,"Targets valid","TARGETS DO NOT SUM TO 100%") -> Targets valid | J50: Rebalance by directing new SIP instalments, never by selling. Selling triggers exit loads and capital gains; redirecting costs nothing.
A52: RISK CONTROLS
A53: Control | B53: Value | C53: Limit | D53: Status | J53: Read
A54: Single fund house — Nippon | B54: =B16 -> 0.95427455 | C54: 0.8 | D54: =IF(B54<=C54,"Within limit","BREACH") -> BREACH | J54: Five of six mutual-fund holdings sit with one asset management company. Market risk is diversified; operational and manager risk is not.
A55: Largest single fund | B55: =MAX(L6:L11) -> 0.31830326 | C55: 0.35 | D55: =IF(B55<=C55,"Within limit","BREACH") -> Within limit | J55: No single fund should dominate. Concentration here is what turns one bad manager into a bad portfolio.
A56: Small and mid cap combined | B56: =IF(B50=0,0,(B45+B46)/B50) -> 0.2621741 | C56: 0.3 | D56: =IF(B56<=C56,"Within limit","BREACH") -> Within limit | J56: The volatile end. Fine at this size for a long horizon; painful if it has to be sold early.
A57: Commodity sleeve | B57: =IF(B50=0,0,B47/B50) -> 0.012341658 | C57: 0.15 | D57: =IF(B57<=C57,"Within limit","BREACH") -> Within limit | J57: Silver diversifies equity but produces no income. A modest allocation is the right size.
A58: Rupee currency exposure | B58: =IF(B50=0,0,(B43+B44+B45+B46+B47+B49)/B50) -> 0.74863144 | C58: 0.85 | D58: =IF(B58<=C58,"Within limit","BREACH") -> Within limit | J58: Almost the entire portfolio is denominated in rupees while every liability is in dirhams. The dirham is pegged to the dollar, so this is a genuine, unhedged currency mismatch.
A59: Dollar currency exposure | B59: =IF(B50=0,0,B48/B50) -> 0.25136856 | C59: 0.5 | D59: =IF(B59<=C59,"Within limit","BREACH") -> Within limit | J59: Effectively dirham-linked because of the peg, which makes it the natural home for money that will be spent in the UAE.
A60: Amana open positions | B60: =B29 -> 41 | C60: 15 | D60: =IF(B60<=C60,"Within limit","BREACH") -> BREACH | J60: Forty-one open positions on an account worth under AED 3,200 means the carrying costs on the statement — floating and overnight fees — do real damage relative to the capital at work.
A61: Portfolio as a share of net worth | B61: =IF('Net Worth'!F28=0,0,E36/'Net Worth'!F28) -> 0.78706708 | C61: 0.6 | D61: =IF(B61<=C61,"Within limit","BREACH") -> BREACH | J61: How much of your net worth is actually compounding rather than sitting in a current account.
A63: The portfolio is doing its job — every scheme is in profit at the snapshot date and the SIP has been running without interruption. The two things worth fixing are structural rather than performance-related: one fund house holds nearly everything, and nearly everything is denominated in a currency you do not spend. Both are fixed with future contributions, not by selling anything.

Sheet Net Worth
A1: Net Worth — Everything You Own, Everything You Owe
A3: One number, in dirhams, built from confirmed balances only. Indian rupee and US dollar holdings are converted at the rates on the FX & Assumptions sheet. Expected salary is never counted as an asset.
A5: ASSETS — LIQUID CASH
A6: Asset | B6: Held at | C6: Native amount | D6: Currency | E6: Rate to AED | F6: Value (AED) | G6: Note
A7: FAB 4001 — spending account | B7: First Abu Dhabi Bank | C7: ='Inputs'!B7 -> 3.45 | D7: AED | E7: 1 | F7: =C7*E7 -> 3.45 | G7: The day-to-day card account. Confirmed 25 Aug after the ENOC purchase.
A8: FAB 4002 — rent account | B8: First Abu Dhabi Bank | C8: ='Inputs'!B8 -> 6090.7 | D8: AED | E8: 1 | F8: =C8*E8 -> 6090.7 | G8: Holds AED 5,990.45 of protected rent plus AED 100.25 towards DEWA. Spendable balance is the AED 100.25, not the AED 6,090.70.
A9: FAB emergency fund | B9: First Abu Dhabi Bank | C9: ='Inputs'!B9 -> 7.67 | D9: AED | E9: 1 | F9: =C9*E9 -> 7.67 | G9: Ring-fenced. Counts as an asset but must never be counted as available cash.
A10: NBD current | B10: Emirates NBD | C10: ='Inputs'!B10 -> 0.2 | D10: AED | E10: 1 | F10: =C10*E10 -> 0.2 | G10: Card-linked; effectively empty.
A11: NBD Plus Saver | B11: Emirates NBD | C11: ='Inputs'!B11 -> 2.73 | D11: AED | E11: 1 | F11: =C11*E11 -> 2.73 | G11: Last reported 14 Aug. Refresh if it has moved.
A12: Tabby Cash wallet | B12: Tabby | C12: ='Inputs'!B12 -> 0.89 | D12: AED | E12: 1 | F12: =C12*E12 -> 0.89 | G12: The wallet, not the Card. Spending it never touches Card debt.
A13: Cash on hand / Wio | B13: Cash | C13: ='Inputs'!B13 -> 0 | D13: AED | E13: 1 | F13: =C13*E13 -> 0 | G13: No other cash balance reported.
A14: TOTAL LIQUID CASH | B14: Sum of confirmed balances | F14: =SUM(F7:F13) -> 6105.64 | G14: Ties to the confirmed liquidity total on Inputs. The Checks sheet proves it.
A16: ASSETS — INVESTMENTS
A17: Asset | B17: Held at | C17: Native amount | D17: Currency | E17: Rate to AED | F17: Value (AED) | G17: Note
A18: Indian mutual funds — 6 schemes | B18: Nippon India / Motilal Oswal | C18: ='Investments'!E12 -> 245087.15 | D18: INR | E18: ='FX & Assumptions'!B7 -> 0.0385333 | F18: =C18*E18 -> 9444.0167 | G18: Snapshot value from MF Central, 10 Aug 2026. Five Nippon schemes plus one Motilal Oswal midcap fund.
A19: ICICI settlement cash | B19: ICICI | C19: ='Inputs'!B40 -> 388.51 | D19: INR | E19: ='FX & Assumptions'!B7 -> 0.0385333 | F19: =C19*E19 -> 14.970572 | G19: Idle rupee cash left after the August SIPs. Earning nothing; sweep it into the next SIP.
A20: Amana trading account | B20: Amana Capital | C20: ='Investments'!B22 -> 864.82 | D20: USD | E20: ='FX & Assumptions'!B9 -> 3.6725 | F20: =C20*E20 -> 3176.0514 | G20: Ending account value on the statement through 10 Aug 2026, across 41 open positions.
A21: TOTAL INVESTMENTS | B21: Sum of converted values | F21: =SUM(F18:F20) -> 12635.039 | G21: Everything that is capable of compounding. This is the number the Wealth Plan grows.
A23: BALANCE SHEET
A24: Item | B24: Basis | C24: Native amount | D24: Currency | E24: Rate to AED | F24: Value (AED) | G24: Note
A25: TOTAL ASSETS | B25: Cash + investments | F25: =F14+F21 -> 18740.679 | G25: Liquid cash plus investments.
A26: Tabby outstanding exposure | B26: Tabby Card | C26: ='Inputs'!B38 -> 2687.36 | D26: AED | E26: 1 | F26: =C26*E26 -> 2687.36 | G26: AED 1,972.03 August statement plus AED 715.33 September statement. The card is frozen, so this balance can only fall from here.
A27: TOTAL LIABILITIES | B27: Sum of debts | F27: =F26 -> 2687.36 | G27: The only interest-bearing-style obligation in the file. Everything else is a bill, not a debt.
A28: NET WORTH | B28: Assets less liabilities | F28: =F25-F27 -> 16053.319 | G28: The single number to watch month over month. It should rise even in a month where the bank balance falls, because units bought are worth more than cash spent.
A30: COMMITTED OBLIGATIONS BEFORE 22 OCTOBER
A31: Item | B31: Basis | C31: Native amount | D31: Currency | E31: Rate to AED | F31: Value (AED) | G31: Note
A32: October rent cheque | B32: Lease schedule | C32: ='Inputs'!B30 -> 11750 | D32: AED | E32: 1 | F32: =C32*E32 -> 11750 | G32: Clears 22 Oct. The 26 Oct salary is four days too late to fund it.
A33: Rent already protected | B33: FAB 4002 | C33: ='Inputs'!B31 -> 5990.45 | D33: AED | E33: 1 | F33: =C33*E33 -> 5990.45 | G33: Already banked and ring-fenced.
A34: RENT STILL TO FUND | B34: Cheque less protected | F34: =MAX(0,F32-F33) -> 5759.55 | G34: What has to be found before 21 Oct. Not a liability on the balance sheet, but a claim on every dirham earned between now and then.
A35: Extra cash required before 15 Sep | B35: Inputs funding build-up | C35: ='Inputs'!B53 -> 651.59 | D35: AED | E35: 1 | F35: =C35*E35 -> 651.59 | G35: Bills-and-survival gap plus the September SIP.
A36: FREE NET WORTH AFTER COMMITMENTS | B36: Net worth less commitments | F36: =F28-F34-F35 -> 9642.1787 | G36: Net worth with the next two months' hard commitments already subtracted. This is the honest picture of how much room actually exists.
A38: COMPOSITION AND SOLVENCY
A39: Metric | B39: Value | C39: Benchmark | D39: Status | G39: Read
A40: Cash as a share of assets | B40: =IF(F25=0,0,F14/F25) -> 0.3257961 | C40: 0.3 | D40: =IF(B40<=C40,"OK","CASH HEAVY") -> CASH HEAVY | G40: Most of the cash here is spoken for by rent, so the real free-cash share is far lower than this figure suggests.
A41: Investments as a share of assets | B41: =IF(F25=0,0,F21/F25) -> 0.6742039 | C41: 0.6 | D41: =IF(B41>=C41,"OK","LOW") -> OK | G41: The share of the balance sheet that compounds.
A42: Debt to assets | B42: =IF(F25=0,0,F27/F25) -> 0.14339715 | C42: 0.2 | D42: =IF(B42<=C42,"OK","HIGH") -> OK | G42: Tabby against total assets. Manageable in size, but it is the most expensive money in the file if a fee is ever triggered.
A43: Free cash outside rent and emergency | B43: ='Inputs'!B43 -> 107.52 | C43: 1000 | D43: =IF(B43>=C43,"OK","THIN") -> THIN | G43: The genuinely spendable balance today. Everything else is protected.
A44: Emergency fund held | B44: ='Inputs'!B32 -> 7.67 | C44: =B45 -> 38669.26 | D44: =IF(B44>=B45,"FUNDED","UNFUNDED") -> UNFUNDED | G44: Against the six-month target below. This is the largest single gap on the balance sheet.
A45: Emergency fund target | B45: =Budget!B17*'FX & Assumptions'!B33 -> 38669.26 | G45: Six months of essential spending, taken from the Budget essentials subtotal.
A46: Emergency cover held | B46: =IF(Budget!B17=0,0,'Inputs'!B32/Budget!B17) -> 0.0011900926 | C46: 6 | D46: =IF(B46>=C46,"OK","CRITICAL") -> CRITICAL | G46: Months of essential spending the emergency fund would actually cover. Units are months.
A47: Liquidity ratio (free cash to monthly essentials) | B47: =IF(Budget!B17=0,0,'Inputs'!B43/Budget!B17) -> 0.016683019 | C47: 1 | D47: =IF(B47>=C47,"OK","CRITICAL") -> CRITICAL | G47: How much of one month of essentials today's free cash would cover. Units are months.
A49: Net worth is the scoreboard; the Budget is the game. A month where spending was disciplined and the SIP was funded shows up here as a higher number even if the current account looks empty. Update the confirmed balances on Inputs, and this sheet updates itself.

Sheet Wealth Plan
A1: Wealth Plan — Turning a Salary into Capital
A3: A projection, not a promise. Contributions are added at each year end and grown at the blended planning return from the FX & Assumptions sheet. Change one lever there and the whole table moves. Today's-money column strips out inflation so the numbers mean something.
A5: STARTING POSITION AND ENGINE
A6: Input | B6: Value | C6: Source | I6: Note
A7: Investable assets today | B7: ='Net Worth'!F21 -> 12635.039 | C7: Net Worth sheet | I7: Mutual funds, broker cash and the Amana account. Bank balances are excluded: they are working capital, not capital.
A8: Monthly SIP today | B8: =Budget!B32 -> 462.4 | C8: Budget sheet | I8: The recurring investment that already exists.
A9: Extra monthly investment | B9: 0 | C9: LEVER — set this yourself | I9: Anything you redirect on top of the SIP once the plan balances. Set it to 300 and watch the horizon value below; that is what one restaurant week a month is worth over twenty years.
A10: Total monthly contribution | B10: =B8+B9 -> 462.4 | C10: Formula | I10: What actually goes in every month.
A11: Year-one contribution | B11: =B10*12 -> 5548.8 | C11: Formula | I11: First full plan year.
A12: Annual step-up | B12: ='FX & Assumptions'!B32 -> 0.1 | C12: FX & Assumptions | I12: Raising the contribution each year is what separates a savings account from a wealth plan.
A13: Blended planning return | B13: ='FX & Assumptions'!B20 -> 0.10161181 | C13: FX & Assumptions | I13: Weighted by the current investment mix, plus the scenario adjustment.
A14: Inflation | B14: ='FX & Assumptions'!B18 -> 0.025 | C14: FX & Assumptions | I14: Used for the today's-money column.
A15: Horizon | B15: ='FX & Assumptions'!B42 -> 20 | C15: FX & Assumptions | I15: Years projected below.
A17: YEAR-BY-YEAR PROJECTION
A18: Plan year | B18: Calendar year | C18: Opening capital | D18: Contributions | E18: Investment growth | F18: Closing capital | G18: Closing in today's money | H18: Cumulative contributions | I18: Milestone
A19: 1 | B19: =YEAR('FX & Assumptions'!$B$41)+A19-1 -> 2026 | C19: =$B$7 -> 12635.039 | D19: =$B$11 -> 5548.8 | E19: =C19*$B$13 -> 1283.8691 | F19: =C19+D19+E19 -> 19467.708 | G19: =F19/(1+$B$14)^A19 -> 18992.886 | H19: =D19 -> 5548.8 | I19: =IF(AND(F19>=1000000,C19<1000000),"AED 1,000,000 crossed",IF(AND(F19>=500000,C19<500000),"AED 500,000 crossed",IF(AND(F19>=250000,C19<250000),"AED 250,000 crossed",IF(AND(F19>=100000,C19<100000),"AED 100,000 crossed",IF(AND(F19>=50000,C19<50000),"AED 50,000 crossed","")))))
A20: 2 | B20: =YEAR('FX & Assumptions'!$B$41)+A20-1 -> 2027 | C20: =F19 -> 19467.708 | D20: =D19*(1+$B$12) -> 6103.68 | E20: =C20*$B$13 -> 1978.149 | F20: =C20+D20+E20 -> 27549.537 | G20: =F20/(1+$B$14)^A20 -> 26222.046 | H20: =H19+D20 -> 11652.48 | I20: =IF(AND(F20>=1000000,C20<1000000),"AED 1,000,000 crossed",IF(AND(F20>=500000,C20<500000),"AED 500,000 crossed",IF(AND(F20>=250000,C20<250000),"AED 250,000 crossed",IF(AND(F20>=100000,C20<100000),"AED 100,000 crossed",IF(AND(F20>=50000,C20<50000),"AED 50,000 crossed","")))))
A21: 3 | B21: =YEAR('FX & Assumptions'!$B$41)+A21-1 -> 2028 | C21: =F20 -> 27549.537 | D21: =D20*(1+$B$12) -> 6714.048 | E21: =C21*$B$13 -> 2799.3582 | F21: =C21+D21+E21 -> 37062.943 | G21: =F21/(1+$B$14)^A21 -> 34416.627 | H21: =H20+D21 -> 18366.528 | I21: =IF(AND(F21>=1000000,C21<1000000),"AED 1,000,000 crossed",IF(AND(F21>=500000,C21<500000),"AED 500,000 crossed",IF(AND(F21>=250000,C21<250000),"AED 250,000 crossed",IF(AND(F21>=100000,C21<100000),"AED 100,000 crossed",IF(AND(F21>=50000,C21<50000),"AED 50,000 crossed","")))))
A22: 4 | B22: =YEAR('FX & Assumptions'!$B$41)+A22-1 -> 2029 | C22: =F21 -> 37062.943 | D22: =D21*(1+$B$12) -> 7385.4528 | E22: =C22*$B$13 -> 3766.0326 | F22: =C22+D22+E22 -> 48214.428 | G22: =F22/(1+$B$14)^A22 -> 43679.893 | H22: =H21+D22 -> 25751.981 | I22: =IF(AND(F22>=1000000,C22<1000000),"AED 1,000,000 crossed",IF(AND(F22>=500000,C22<500000),"AED 500,000 crossed",IF(AND(F22>=250000,C22<250000),"AED 250,000 crossed",IF(AND(F22>=100000,C22<100000),"AED 100,000 crossed",IF(AND(F22>=50000,C22<50000),"AED 50,000 crossed","")))))
A23: 5 | B23: =YEAR('FX & Assumptions'!$B$41)+A23-1 -> 2030 | C23: =F22 -> 48214.428 | D23: =D22*(1+$B$12) -> 8123.9981 | E23: =C23*$B$13 -> 4899.1552 | F23: =C23+D23+E23 -> 61237.582 | G23: =F23/(1+$B$14)^A23 -> 54125.099 | H23: =H22+D23 -> 33875.979 | I23: =IF(AND(F23>=1000000,C23<1000000),"AED 1,000,000 crossed",IF(AND(F23>=500000,C23<500000),"AED 500,000 crossed",IF(AND(F23>=250000,C23<250000),"AED 250,000 crossed",IF(AND(F23>=100000,C23<100000),"AED 100,000 crossed",IF(AND(F23>=50000,C23<50000),"AED 50,000 crossed",""))))) -> AED 50,000 crossed
A24: 6 | B24: =YEAR('FX & Assumptions'!$B$41)+A24-1 -> 2031 | C24: =F23 -> 61237.582 | D24: =D23*(1+$B$12) -> 8936.3979 | E24: =C24*$B$13 -> 6222.4614 | F24: =C24+D24+E24 -> 76396.441 | G24: =F24/(1+$B$14)^A24 -> 65876.412 | H24: =H23+D24 -> 42812.377 | I24: =IF(AND(F24>=1000000,C24<1000000),"AED 1,000,000 crossed",IF(AND(F24>=500000,C24<500000),"AED 500,000 crossed",IF(AND(F24>=250000,C24<250000),"AED 250,000 crossed",IF(AND(F24>=100000,C24<100000),"AED 100,000 crossed",IF(AND(F24>=50000,C24<50000),"AED 50,000 crossed","")))))
A25: 7 | B25: =YEAR('FX & Assumptions'!$B$41)+A25-1 -> 2032 | C25: =F24 -> 76396.441 | D25: =D24*(1+$B$12) -> 9830.0377 | E25: =C25*$B$13 -> 7762.7805 | F25: =C25+D25+E25 -> 93989.259 | G25: =F25/(1+$B$14)^A25 -> 79069.896 | H25: =H24+D25 -> 52642.414 | I25: =IF(AND(F25>=1000000,C25<1000000),"AED 1,000,000 crossed",IF(AND(F25>=500000,C25<500000),"AED 500,000 crossed",IF(AND(F25>=250000,C25<250000),"AED 250,000 crossed",IF(AND(F25>=100000,C25<100000),"AED 100,000 crossed",IF(AND(F25>=50000,C25<50000),"AED 50,000 crossed","")))))
A26: 8 | B26: =YEAR('FX & Assumptions'!$B$41)+A26-1 -> 2033 | C26: =F25 -> 93989.259 | D26: =D25*(1+$B$12) -> 10813.041 | E26: =C26*$B$13 -> 9550.4185 | F26: =C26+D26+E26 -> 114352.72 | G26: =F26/(1+$B$14)^A26 -> 93854.602 | H26: =H25+D26 -> 63455.456 | I26: =IF(AND(F26>=1000000,C26<1000000),"AED 1,000,000 crossed",IF(AND(F26>=500000,C26<500000),"AED 500,000 crossed",IF(AND(F26>=250000,C26<250000),"AED 250,000 crossed",IF(AND(F26>=100000,C26<100000),"AED 100,000 crossed",IF(AND(F26>=50000,C26<50000),"AED 50,000 crossed",""))))) -> AED 100,000 crossed
A27: 9 | B27: =YEAR('FX & Assumptions'!$B$41)+A27-1 -> 2034 | C27: =F26 -> 114352.72 | D27: =D26*(1+$B$12) -> 11894.346 | E27: =C27*$B$13 -> 11619.587 | F27: =C27+D27+E27 -> 137866.65 | G27: =F27/(1+$B$14)^A27 -> 110393.74 | H27: =H26+D27 -> 75349.801 | I27: =IF(AND(F27>=1000000,C27<1000000),"AED 1,000,000 crossed",IF(AND(F27>=500000,C27<500000),"AED 500,000 crossed",IF(AND(F27>=250000,C27<250000),"AED 250,000 crossed",IF(AND(F27>=100000,C27<100000),"AED 100,000 crossed",IF(AND(F27>=50000,C27<50000),"AED 50,000 crossed","")))))
A28: 10 | B28: =YEAR('FX & Assumptions'!$B$41)+A28-1 -> 2035 | C28: =F27 -> 137866.65 | D28: =D27*(1+$B$12) -> 13083.78 | E28: =C28*$B$13 -> 14008.88 | F28: =C28+D28+E28 -> 164959.31 | G28: =F28/(1+$B$14)^A28 -> 128865.95 | H28: =H27+D28 -> 88433.582 | I28: =IF(AND(F28>=1000000,C28<1000000),"AED 1,000,000 crossed",IF(AND(F28>=500000,C28<500000),"AED 500,000 crossed",IF(AND(F28>=250000,C28<250000),"AED 250,000 crossed",IF(AND(F28>=100000,C28<100000),"AED 100,000 crossed",IF(AND(F28>=50000,C28<50000),"AED 50,000 crossed","")))))
A29: 11 | B29: =YEAR('FX & Assumptions'!$B$41)+A29-1 -> 2036 | C29: =F28 -> 164959.31 | D29: =D28*(1+$B$12) -> 14392.158 | E29: =C29*$B$13 -> 16761.814 | F29: =C29+D29+E29 -> 196113.28 | G29: =F29/(1+$B$14)^A29 -> 149466.72 | H29: =H28+D29 -> 102825.74 | I29: =IF(AND(F29>=1000000,C29<1000000),"AED 1,000,000 crossed",IF(AND(F29>=500000,C29<500000),"AED 500,000 crossed",IF(AND(F29>=250000,C29<250000),"AED 250,000 crossed",IF(AND(F29>=100000,C29<100000),"AED 100,000 crossed",IF(AND(F29>=50000,C29<50000),"AED 50,000 crossed","")))))
A30: 12 | B30: =YEAR('FX & Assumptions'!$B$41)+A30-1 -> 2037 | C30: =F29 -> 196113.28 | D30: =D29*(1+$B$12) -> 15831.374 | E30: =C30*$B$13 -> 19927.425 | F30: =C30+D30+E30 -> 231872.08 | G30: =F30/(1+$B$14)^A30 -> 172409.85 | H30: =H29+D30 -> 118657.11 | I30: =IF(AND(F30>=1000000,C30<1000000),"AED 1,000,000 crossed",IF(AND(F30>=500000,C30<500000),"AED 500,000 crossed",IF(AND(F30>=250000,C30<250000),"AED 250,000 crossed",IF(AND(F30>=100000,C30<100000),"AED 100,000 crossed",IF(AND(F30>=50000,C30<50000),"AED 50,000 crossed","")))))
A31: 13 | B31: =YEAR('FX & Assumptions'!$B$41)+A31-1 -> 2038 | C31: =F30 -> 231872.08 | D31: =D30*(1+$B$12) -> 17414.511 | E31: =C31*$B$13 -> 23560.941 | F31: =C31+D31+E31 -> 272847.54 | G31: =F31/(1+$B$14)^A31 -> 197929.16 | H31: =H30+D31 -> 136071.63 | I31: =IF(AND(F31>=1000000,C31<1000000),"AED 1,000,000 crossed",IF(AND(F31>=500000,C31<500000),"AED 500,000 crossed",IF(AND(F31>=250000,C31<250000),"AED 250,000 crossed",IF(AND(F31>=100000,C31<100000),"AED 100,000 crossed",IF(AND(F31>=50000,C31<50000),"AED 50,000 crossed",""))))) -> AED 250,000 crossed
... A38: 20 | B38: =YEAR('FX & Assumptions'!$B$41)+A38-1 -> 2045 | C38: =F37 -> 673415.87 | D38: =D37*(1+$B$12) -> 33935.956 | E38: =C38*$B$13 -> 68427.004 | F38: =C38+D38+E38 -> 775778.83 | G38: =F38/(1+$B$14)^A38 -> 473435.28 | H38: =H37+D38 -> 317807.52 | I38: =IF(AND(F38>=1000000,C38<1000000),"AED 1,000,000 crossed",IF(AND(F38>=500000,C38<500000),"AED 500,000 crossed",IF(AND(F38>=250000,C38<250000),"AED 250,000 crossed",IF(AND(F38>=100000,C38<100000),"AED 100,000 crossed",IF(AND(F38>=50000,C38<50000),"AED 50,000 crossed","")))))
A39: HORIZON TOTAL | D39: =SUM(D19:D38) -> 317807.52 | E39: =SUM(E19:E38) -> 445336.27 | F39: =F38 -> 775778.83 | G39: =G38 -> 473435.28 | H39: =H38 -> 317807.52 | I39: Growth above contributions is the part the market pays you. If it is smaller than contributions, time is the missing ingredient, not returns.
A41: WHAT EACH LEVER IS ACTUALLY WORTH
A42: Scenario | B42: Monthly contribution | C42: Step-up | D42: Return | E42: Horizon | F42: Capital at horizon | G42: In today's money | H42: Difference vs base | I42: Read
A43: Base — today's SIP, 10% step-up | B43: =$B$10 -> 462.4 | C43: =$B$12 -> 0.1 | D43: =$B$13 -> 0.10161181 | E43: =$B$15 -> 20 | F43: =$B$7*(1+D43)^E43+IF(ABS(D43-C43)<0.0001,B43*12*E43*(1+D43)^(E43-1),B43*12*((1+D43)^E43-(1+C43)^E43)/(D43-C43)) -> 775778.83 | G43: =F43/(1+$B$14)^E43 -> 473435.28 | H43: =F43-F$43 -> 0 | I43: Exactly the table above.
A44: Add AED 300 a month | B44: =$B$10+300 -> 762.4 | C44: =$B$12 -> 0.1 | D44: =$B$13 -> 0.10161181 | E44: =$B$15 -> 20 | F44: =$B$7*(1+D44)^E44+IF(ABS(D44-C44)<0.0001,B44*12*E44*(1+D44)^(E44-1),B44*12*((1+D44)^E44-(1+C44)^E44)/(D44-C44)) -> 1222308.2 | G44: =F44/(1+$B$14)^E44 -> 745939.17 | H44: =F44-F$43 -> 446529.36 | I44: Roughly one week of restaurant spending redirected. Compare the difference column with the sacrifice; this is the cheapest wealth in the file.
A45: Step-up 15% instead of 10% | B45: =$B$10 -> 462.4 | C45: =0.15 -> 0.15 | D45: =$B$13 -> 0.10161181 | E45: =$B$15 -> 20 | F45: =$B$7*(1+D45)^E45+IF(ABS(D45-C45)<0.0001,B45*12*E45*(1+D45)^(E45-1),B45*12*((1+D45)^E45-(1+C45)^E45)/(D45-C45)) -> 1169936.2 | G45: =F45/(1+$B$14)^E45 -> 713978.06 | H45: =F45-F$43 -> 394157.35 | I45: Costs nothing today. Every raise partly goes to the SIP instead of to lifestyle.
A46: No step-up at all | B46: =$B$10 -> 462.4 | C46: =0 -> 0 | D46: =$B$13 -> 0.10161181 | E46: =$B$15 -> 20 | F46: =$B$7*(1+D46)^E46+IF(ABS(D46-C46)<0.0001,B46*12*E46*(1+D46)^(E46-1),B46*12*((1+D46)^E46-(1+C46)^E46)/(D46-C46)) -> 411211.88 | G46: =F46/(1+$B$14)^E46 -> 250950.66 | H46: =F46-F$43 -> -364566.95 | I46: The same contribution forever. Inflation quietly shrinks it every year.
A47: Returns 3 points lower | B47: =$B$10 -> 462.4 | C47: =$B$12 -> 0.1 | D47: =$B$13-0.03 -> 0.071611808 | E47: =$B$15 -> 20 | F47: =$B$7*(1+D47)^E47+IF(ABS(D47-C47)<0.0001,B47*12*E47*(1+D47)^(E47-1),B47*12*((1+D47)^E47-(1+C47)^E47)/(D47-C47)) -> 585864.41 | G47: =F47/(1+$B$14)^E47 -> 357536.02 | H47: =F47-F$43 -> -189914.42 | I47: The stress case. Note how much less it costs you than skipping contributions does — the contribution lever is under your control, the return lever is not.
A48: Pause the SIP for one year, then resume | B48: =$B$10 -> 462.4 | C48: =$B$12 -> 0.1 | D48: =$B$13 -> 0.10161181 | E48: =($B$15-1) -> 19 | F48: =$B$7*(1+D48)^E48+IF(ABS(D48-C48)<0.0001,B48*12*E48*(1+D48)^(E48-1),B48*12*((1+D48)^E48-(1+C48)^E48)/(D48-C48)) -> 673415.87 | G48: =F48/(1+$B$14)^E48 -> 421240.29 | H48: =F48-F$43 -> -102362.96 | I48: Modelled as one year less of compounding on the whole horizon. A pause is never free.
A50: FINANCIAL INDEPENDENCE
A51: Metric | B51: Value | C51: Basis | I51: Read
A52: Annual essential spending today | B52: =Budget!B17*12 -> 77338.52 | C52: Budget essentials x 12 | I52: Rent accrual, utilities, groceries, fuel and family support. Not lifestyle.
A53: Safe withdrawal rate | B53: 0.04 | C53: LEVER — standard planning rule | I53: The share of capital you could draw each year without running it down. Conservative.
A54: Capital needed for independence | B54: =IF(B53=0,0,B52/B53) -> 1933463 | C54: Essential spending divided by the withdrawal rate | I54: The number at which essential living costs are paid by capital rather than by work.
A55: Years to reach it at the base plan | B55: =IF(COUNTIF(G19:G38,"<"&B54)>=20,"beyond horizon",COUNTIF(G19:G38,"<"&B54)+1) -> beyond horizon | C55: First year the today's-money column clears the target | I55: Counted in today's money, so the answer is honest. If it reads beyond horizon, the fix is the contribution lever, not a better fund.
A56: Capital at horizon in today's money | B56: =G38 -> 473435.28 | C56: Year-by-year projection | I56: Where the base plan actually lands.
A57: Shortfall against independence | B57: =MAX(0,B54-B56) -> 1460027.7 | C57: Target less projected | I57: Zero means the base plan gets there within the horizon.
A59: The uncomfortable arithmetic: the plan below only runs if the Budget balances first. Rent accrual, then the emergency fund, then debt, then the SIP — in that order. A wealth plan funded by a frozen credit card is not a wealth plan.

Sheet Goals
A1: Goals — From Surviving the Month to Owning the Decade
A3: Ordered the only way that works: protect the roof, close the gap, kill the debt, build the buffer, then compound. Progress is calculated live from the rest of the workbook — nothing here is typed in by hand except the targets.
A5: STAGE 1 — SURVIVE THE NEXT NINETY DAYS
A6: Goal | B6: Target | C6: Where you are | D6: Gap | E6: Progress | F6: Deadline | G6: Per month needed | H6: Note
A7: Close the September funding gap | B7: ='Inputs'!B53 -> 651.59 | C7: ='Inputs'!B43 -> 107.52 | D7: =MAX(0,B7-C7) -> 544.07 | E7: =IF(B7=0,1,MIN(1,C7/B7)) -> 0.16501174 | F7: 46280 | G7: =IF(1=0,D7,D7/1) -> 544.07 | H7: Bills, survival spending and the SIP through 15 Sep, against the loose cash that exists today. This is the nearest cliff edge in the file.
A8: Fully fund the October rent cheque | B8: ='Inputs'!B30 -> 11750 | C8: ='Inputs'!B31 -> 5990.45 | D8: =MAX(0,B8-C8) -> 5759.55 | E8: =IF(B8=0,1,MIN(1,C8/B8)) -> 0.50982553 | F8: 46316 | G8: =IF(2=0,D8,D8/2) -> 2879.775 | H8: The cheque clears 22 Oct and the 26 Oct salary is four days too late. Two salary cycles to find the balance.
A9: Clear the Tabby card to zero | B9: ='Inputs'!B38 -> 2687.36 | C9: 0 | D9: =MAX(0,B9-C9) -> 2687.36 | E9: =IF(B9=0,1,MIN(1,C9/B9)) -> 0 | F9: 46329 | G9: =IF(3=0,D9,D9/3) -> 895.78667 | H9: Progress reads 0% until the balance falls — that is deliberate. Follow the Debt Plan schedule and this closes on 3 Nov with no fees.
A11: STAGE 2 — BUILD THE BUFFER
A12: Goal | B12: Target | C12: Where you are | D12: Gap | E12: Progress | F12: Deadline | G12: Per month needed | H12: Note
A13: Emergency fund — first milestone | B13: 1000 | C13: ='Inputs'!B32 -> 7.67 | D13: =MAX(0,B13-C13) -> 992.33 | E13: =IF(B13=0,1,MIN(1,C13/B13)) -> 0.00767 | F13: 46477 | G13: =IF(6=0,D13,D13/6) -> 165.38833 | H13: AED 1,000 is the milestone the original plan already named. At AED 200 a month from the Budget it takes five months, and it ends the era where one flat tyre becomes a crisis.
A14: Emergency fund — three months of essentials | B14: =Budget!B17*3 -> 19334.63 | C14: ='Inputs'!B32 -> 7.67 | D14: =MAX(0,B14-C14) -> 19326.96 | E14: =IF(B14=0,1,MIN(1,C14/B14)) -> 0.0003966975 | F14: 46752 | G14: =IF(16=0,D14,D14/16) -> 1207.935 | H14: Three months of the Budget essentials subtotal. The point at which a lost job stops being an emergency and becomes an inconvenience.
A15: Emergency fund — six months of essentials | B15: =Budget!B17*'FX & Assumptions'!B33 -> 38669.26 | C15: ='Inputs'!B32 -> 7.67 | D15: =MAX(0,B15-C15) -> 38661.59 | E15: =IF(B15=0,1,MIN(1,C15/B15)) -> 0.0001983488 | F15: 47299 | G15: =IF(34=0,D15,D15/34) -> 1137.1056 | H15: Full target. Reach it and the SIP never has to be paused again for a bad month.
A16: Rent vault — one full year of rent | B16: ='FX & Assumptions'!B28 -> 47000 | C16: ='Inputs'!B31 -> 5990.45 | D16: =MAX(0,B16-C16) -> 41009.55 | E16: =IF(B16=0,1,MIN(1,C16/B16)) -> 0.12745638 | F16: 47047 | G16: =IF(26=0,D16,D16/26) -> 1577.2904 | H16: A year of rent held in advance. This is the goal that permanently ends the October panic, because the cheque stops competing with the salary.
A18: STAGE 3 — COMPOUND
A19: Goal | B19: Target | C19: Where you are | D19: Gap | E19: Progress | F19: Deadline | G19: Per month needed | H19: Note
A20: Investments reach AED 25,000 | B20: 25000 | C20: ='Net Worth'!F21 -> 12635.039 | D20: =MAX(0,B20-C20) -> 12364.961 | E20: =IF(B20=0,1,MIN(1,C20/B20)) -> 0.50540155 | F20: 47362 | G20: =IF(36=0,D20,D20/36) -> 343.47115 | H20: Roughly two and a half times the current portfolio, on the current SIP alone.
A21: Net worth reaches AED 100,000 | B21: 100000 | C21: ='Net Worth'!F28 -> 16053.319 | D21: =MAX(0,B21-C21) -> 83946.681 | E21: =IF(B21=0,1,MIN(1,C21/B21)) -> 0.16053319 | F21: 48458 | G21: =IF(72=0,D21,D21/72) -> 1165.9261 | H21: The first genuinely life-changing threshold: a year of net salary held as capital.
A22: Net worth reaches AED 250,000 | B22: 250000 | C22: ='Net Worth'!F28 -> 16053.319 | D22: =MAX(0,B22-C22) -> 233946.68 | E22: =IF(B22=0,1,MIN(1,C22/B22)) -> 0.064213275 | F22: 49919 | G22: =IF(120=0,D22,D22/120) -> 1949.5557 | H22: At this point investment growth in a normal year starts to rival what saving adds.
A23: Capital covers essential living costs | B23: ='Wealth Plan'!B54 -> 1933463 | C23: ='Net Worth'!F21 -> 12635.039 | D23: =MAX(0,B23-C23) -> 1920828 | E23: =IF(B23=0,1,MIN(1,C23/B23)) -> 0.0065349266 | F23: 53571 | G23: =IF(240=0,D23,D23/240) -> 8003.4498 | H23: Financial independence as defined on the Wealth Plan: essential spending paid by capital rather than by work.
A25: GOAL SCOREBOARD
A26: Metric | B26: Value | H26: Read
A27: Goals fully funded | B27: =COUNTIF(E7:E9,">=1")+COUNTIF(E13:E16,">=1")+COUNTIF(E20:E23,">=1") -> 0 | H27: Goals already at 100%.
A28: Goals under 25% funded | B28: =COUNTIF(E7:E9,"<0.25")+COUNTIF(E13:E16,"<0.25")+COUNTIF(E20:E23,"<0.25") -> 9 | H28: Goals that have barely started. Expected to be high today; the point is to watch it fall.
A29: Total still to fund across every goal | B29: =SUM(D7:D9)+SUM(D13:D16)+SUM(D20:D23) -> 2360067.7 | H29: The full distance from here to the last goal. Large numbers are fine — they are supposed to take years.
A30: Nearest deadline | B30: =MIN(F7:F9) -> 46280 | H30: The date that decides what you do this week.
A31: Stage 1 average progress | B31: =AVERAGE(E7:E9) -> 0.22494576 | H31: Survive-the-quarter progress. Nothing in stage 2 or 3 matters until this is at 100%.
A33: Sequence matters more than ambition. Funding the SIP while the rent cheque is short is not investing, it is borrowing from the landlord. Work down this sheet in order and every later goal gets easier, because each stage removes a claim on the salary.

Sheet Checks
A1: Model Integrity Checks
A3: Core cash, income and rent projections reconcile. Do not treat the model as fully cleared until the AED 14 balance movement is identified.
A5: Check | B5: Actual | C5: Expected | D5: Difference | E5: Tolerance | F5: Status | G5: Fix / note
A6: Liquid cash ties | B6: ='Inputs'!B14 -> 6105.64 | C6: 6105.64 | D6: =B6-C6 -> 0 | E6: =0.01 -> 0.01 | F6: =IF(ABS(D6)<=E6,"OK","REVIEW") -> OK | G6: FAB app actuals + NBD current/saver + Tabby Cash last reported
A7: FAB components tie | B7: =SUM('Inputs'!B7:B9) -> 6101.82 | C7: 6101.82 | D7: =B7-C7 -> 0 | E7: =0.01 -> 0.01 | F7: =IF(ABS(D7)<=E7,"OK","REVIEW") -> OK | G7: AED 3.45 + AED 6,090.70 + AED 7.67
A8: NBD components tie | B8: =SUM('Inputs'!B10:B11) -> 2.93 | C8: 2.93 | D8: =B8-C8 -> 0 | E8: =0.01 -> 0.01 | F8: =IF(ABS(D8)<=E8,"OK","CHECK") -> OK | G8: NBD current AED 0.20 + saver AED 2.73 last reported
A9: August salary timing ties | B9: ='Inputs'!B25 -> 8476 | C9: =SUM('Inputs'!B19:B22)+'Inputs'!B26 -> 8476 | D9: =B9-C9 -> 0 | E9: =0.01 -> 0.01 | F9: =IF(ABS(D9)<=E9,"OK","CHECK") -> OK | G9: AED 5,570 received + AED 2,906 expected = AED 8,476
A10: Mutual-fund totals tie | B10: ='Investments'!E12 -> 245087.15 | C10: ='Investments'!E12 -> 245087.15 | D10: =B10-C10 -> 0 | E10: =0.10 -> 0.1 | F10: =IF(ABS(D10)<=E10,"OK","CHECK") -> OK | G10: Statement rounding tolerance
A11: Rent closure reaches zero | B11: ='Rent Closure'!C11 -> 0 | C11: =0 -> 0 | D11: =B11-C11 -> 0 | E11: =0.01 -> 0.01 | F11: =IF(ABS(D11)<=E11,"OK","CHECK") -> OK | G11: Conditional zero-gap plan
A12: Survival spending cap ties | B12: ='Inputs'!B41 -> 285 | C12: 285 | D12: 0 | E12: 0.01 | F12: OK | G12: AED 5/day or AED 35/week through 21 Oct
A13: Unclassified balance-derived spending | B13: 0 | C13: 0 | D13: 0 | E13: 0 | F13: OK | G13: All adjacent FAB balances reconcile; AED 70 was a Canva refund (not a transfer); AED 0.49 is a balance-derived fee
A14: Tabby statements counted once | B14: =SUMPRODUCT(('Obligations'!B6:B17="Tabby no-fee minimum")*1)+SUMPRODUCT(('Obligations'!B6:B17="October Tabby payment")*1) -> 2 | C14: 2 | D14: =B14-C14 -> 0 | E14: =0 -> 0 | F14: =IF(ABS(D14)<=E14,"OK","CHECK") -> OK | G14: Exactly two dated Tabby obligations: 3 Sep and 3 Oct
A15: Final rent funding equals cheque | B15: ='Rent Closure'!C20 -> 11750 | C15: ='Inputs'!B30 -> 11750 | D15: =B15-C15 -> 0 | E15: =0.01 -> 0.01 | F15: =IF(ABS(D15)<=E15,"OK","CHECK") -> OK | G15: Closure milestones reconcile
A16: Amana ending value ties | B16: ='Investments'!B22 -> 864.82 | C16: =864.82 -> 864.82 | D16: =B16-C16 -> 0 | E16: =0.01 -> 0.01 | F16: =IF(ABS(D16)<=E16,"OK","CHECK") -> OK | G16: Amana statement through 10 Aug
A17: Bills + survival funding gap | B17: ='Inputs'!B51 -> 189.19 | C17: 189.19 | D17: =B17-C17 -> 0 | E17: 0.01 | F17: =IF(ABS(D17)<=E17,"OK","CHECK") -> OK | G17: Available AED 3,013.52 vs AED 3,202.71 required
A18: ="Total extra cash including the September SIP: AED "&TEXT('Inputs'!B53,"#,##0.00")&" — the AED "&TEXT('Inputs'!B51,"#,##0.00")&" bills-and-survival gap plus AED "&TEXT('Inputs'!B39,"#,##0.00")&" of SIP funding. Earlier notes in this workbook quoted AED 651.19; the correct arithmetic is AED 651.59, and this cell now computes it rather than repeating it." -> Total extra cash including the September SIP: AED 651.59 — the AED 189.19 bills-and-survival gap plus AED 462.40 of SIP funding. Earlier notes in this workbook quoted AED 651.19; the correct arithmetic is AED 651.59, and this cell now computes it rather than repeating it.
A21: EXTENDED INTEGRITY CHECKS — WEALTH, BUDGET, DEBT AND ADVISOR SHEETS
A22: Check | B22: Actual | C22: Expected | D22: Difference | E22: Tolerance | F22: Status | G22: Fix / note
A23: Net Worth cash ties to Inputs liquidity | B23: ='Net Worth'!F14 -> 6105.64 | C23: ='Inputs'!B14 -> 6105.64 | D23: =B23-C23 -> 0 | E23: 0.01 | F23: =IF(ABS(D23)<=E23,"OK","CHECK") -> OK | G23: Both must read the same confirmed balances.
A24: Balance sheet identity holds | B24: ='Net Worth'!F28 -> 16053.319 | C24: ='Net Worth'!F25-'Net Worth'!F27 -> 16053.319 | D24: =B24-C24 -> 0 | E24: 0.01 | F24: =IF(ABS(D24)<=E24,"OK","CHECK") -> OK | G24: Net worth must equal assets less liabilities.
A25: Spend Analysis total ties to the ledger | B25: ='Spend Analysis'!B17 -> 4547.47 | C25: =SUMIFS('Recent Ledger'!$D$6:$D$101,'Recent Ledger'!$J$6:$J$101,1) -> 4547.47 | D25: =B25-C25 -> 0 | E25: 0.01 | F25: =IF(ABS(D25)<=E25,"OK","CHECK") -> OK | G25: Category totals must account for every flagged spend line and nothing else.
A26: Every ledger line is classified | B26: =COUNTIF('Recent Ledger'!$I$6:$I$101,"<>") -> 96 | C26: 96 | D26: =B26-C26 -> 0 | E26: 0 | F26: =IF(ABS(D26)<=E26,"OK","CHECK") -> OK | G26: All 96 ledger rows carry a budget category, including the deliberately excluded ones.
A27: No spend line left uncategorised | B27: =COUNTIFS('Recent Ledger'!$J$6:$J$101,1,'Recent Ledger'!$I$6:$I$101,"Excluded") -> 0 | C27: 0 | D27: =B27-C27 -> 0 | E27: 0 | F27: =IF(ABS(D27)<=E27,"OK","CHECK") -> OK | G27: A row cannot count as spending and be excluded at the same time.
A28: Budget actuals tie to Spend Analysis | B28: =SUM(Budget!C13:C16)+SUM(Budget!C21:C26) -> 4547.47 | C28: ='Spend Analysis'!B17 -> 4547.47 | D28: =B28-C28 -> 0 | E28: 0.01 | F28: =IF(ABS(D28)<=E28,"OK","CHECK") -> OK | G28: The Budget pulls the same ledger totals the Spend Analysis sheet reports.
A29: Budget income identity holds | B29: =Budget!B38+Budget!B39 -> 7914.88 | C29: =Budget!B8 -> 7914.88 | D29: =B29-C29 -> 0 | E29: 0.01 | F29: =IF(ABS(D29)<=E29,"OK","CHECK") -> OK | G29: Outflow plus surplus must equal income.
A30: Allocation targets sum to 100% | B30: ='Investments'!D50 -> 1 | C30: 1 | D30: =B30-C30 -> 0 | E30: 0.0001 | F30: =IF(ABS(D30)<=E30,"OK","CHECK") -> OK | G30: Otherwise every drift figure on the allocation table is meaningless.
A31: Investments AED total ties to Net Worth | B31: ='Investments'!E36 -> 12635.039 | C31: ='Net Worth'!F21 -> 12635.039 | D31: =B31-C31 -> 0 | E31: 0.01 | F31: =IF(ABS(D31)<=E31,"OK","CHECK") -> OK | G31: Same holdings, same rates, two sheets.
A32: Allocation total ties to invested total | B32: ='Investments'!B50 -> 12635.039 | C32: ='Investments'!E36 -> 12635.039 | D32: =B32-C32 -> 0 | E32: 0.01 | F32: =IF(ABS(D32)<=E32,"OK","CHECK") -> OK | G32: Every dirham of the portfolio is allocated to exactly one asset class.
A33: Debt schedule clears to zero | B33: ='Debt Plan'!D17 -> 0 | C33: 0 | D33: =B33-C33 -> 0 | E33: 0.01 | F33: =IF(ABS(D33)<=E33,"OK","CHECK") -> OK | G33: The recommended route must actually end the debt.
A34: Debt payments equal the exposure | B34: ='Debt Plan'!G17 -> 2687.36 | C34: ='Inputs'!B38 -> 2687.36 | D34: =B34-C34 -> 0 | E34: 0.01 | F34: =IF(ABS(D34)<=E34,"OK","CHECK") -> OK | G34: Total paid must equal total owed — no more, no less.
A35: Wealth Plan closed form matches the table | B35: ='Wealth Plan'!F43 -> 775778.83 | C35: ='Wealth Plan'!F38 -> 775778.83 | D35: =B35-C35 -> -7.76e-08 | E35: 0.01 | F35: =IF(ABS(D35)<=E35,"OK","CHECK") -> OK | G35: The sensitivity block and the year-by-year projection use different maths; they must agree on the base case.
A36: Advisor score weights sum to 100% | B36: ='AI Advisor'!D13 -> 1 | C36: 1 | D36: =B36-C36 -> 0 | E36: 0.0001 | F36: =IF(ABS(D36)<=E36,"OK","CHECK") -> OK | G36: Otherwise the health score is not out of 100.
A37: Extra cash before 15 Sep computes correctly | B37: ='Inputs'!B53 -> 651.59 | C37: 651.59 | D37: =B37-C37 -> 0 | E37: 0.01 | F37: =IF(ABS(D37)<=E37,"OK","CHECK") -> OK | G37: AED 189.19 gap plus AED 462.40 SIP. Corrects the AED 651.19 quoted in earlier notes.
A38: FX rates are reciprocal | B38: ='FX & Assumptions'!B7*'FX & Assumptions'!B8 -> 1 | C38: 1 | D38: =B38-C38 -> 0 | E38: 0.0001 | F38: =IF(ABS(D38)<=E38,"OK","CHECK") -> OK | G38: Guards against someone editing one rate and not the other.
A39: Rent goal gap ties to Net Worth | B39: =Goals!D8 -> 5759.55 | C39: ='Net Worth'!F34 -> 5759.55 | D39: =B39-C39 -> 0 | E39: 0.01 | F39: =IF(ABS(D39)<=E39,"OK","CHECK") -> OK | G39: The Goals sheet and the balance sheet must agree on what is still owed on the cheque.
A40: Ledger balance trail ends at the confirmed balance | B40: ='Recent Ledger'!G101 -> 3.45 | C40: ='Inputs'!B7 -> 3.45 | D40: =B40-C40 -> 0 | E40: 0.01 | F40: =IF(ABS(D40)<=E40,"OK","CHECK") -> OK | G40: The last balance in the ledger must equal the confirmed FAB 4001 balance on Inputs. This is the strongest single proof that the ledger is complete.
A41: CHECKS PASSING | B41: =COUNTIF(F6:F17,"OK")+COUNTIF(F23:F40,"OK") -> 30 | C41: =12+18 -> 30 | D41: =B41-C41 -> 0 | E41: 0 | F41: =IF(B41=C41,"ALL OK","REVIEW") -> ALL OK | G41: If this reads REVIEW, find the CHECK rows above before trusting any number in this workbook.

Sheet Sources & Audit
A1: Sources, Assumptions and Change Log
A3: This workbook is a controlled mirror of Johnny's Edge, not a bank connection.
A5: ID | B5: Item | C5: Value / scope | D5: Status | E5: As of | F5: Source | G5: Notes
A6: S1 | B6: Cash balances | C6: AED 7,224.19 | D6: Actual | E6: 46246 | F6: 12 Aug FAB SMS screenshot | G6: FAB, NBD and Tabby Cash components; latest confirmed balances
A7: S2 | B7: Rent cheque | C7: AED 11,750 | D7: Actual | E7: 46245 | F7: Johnny's lease schedule | G7: Due 22 Oct 2026
A8: S3 | B8: Prior-month salary | C8: AED 1,430 | D8: Actual received / rent allocated | E8: 46246 | F8: AED 3,000 inward-remittance SMS | G8: Separate from coming salary cycle
A9: S4 | B9: Third-ticket cash | C9: AED 1,570 | D9: Actual received | E9: 46246 | F9: AED 3,000 inward-remittance SMS | G9: AED 1,540 salary recovery + AED 30 profit
A10: S5 | B10: DEWA baseline | C10: AED 793.42 | D10: Estimated | E10: 46229 | F10: Last confirmed DEWA payment | G10: Replace after actual August bill
A11: S6 | B11: du + Etisalat | C11: AED 914.93 | D11: Actual paid / recurring estimate | E11: 46237 | F11: DubaiPay card record | G11: du 590.98 + Etisalat 323.95
A12: S7 | B12: Tabby September | C12: AED 1,314.50 | D12: Actual statement option | E12: 46238 | F12: Tabby screenshots | G12: No-fee minimum due 03 Sep
A13: S8 | B13: Nippon SIP | C13: ₹12,000 completed | D13: Actual | E13: 46244 | F13: MF Central + Nippon confirmation email | G13: Four ₹3,000 SIPs
A14: S9 | B14: Mutual funds | C14: ₹245,087.15 snapshot | D14: Actual with rounding | E14: 46244 | F14: MF Central screenshots | G14: Unit rounding may create minor differences
A15: S10 | B15: Website | C15: Version 70 | D15: Controlled mirror | E15: 46245 | F15: Johnny's Edge | G15: Amana statement reconciled
A16: S11 | B16: Amana statement | C16: US$864.82 ending value | D16: Actual | E16: 46244 | F16: Amana PDF statement | G16: 41 open positions; PLTR, VOO and Realty Income sold 28 Jul
A17: C1 | B17: Classification rule | C17: Tabby Cash ≠ Tabby Card | D17: Control | E17: 46245 | F17: Owner instruction | G17: Wallet spending never resets Card streak
... A44: S44 | B44: Survival allowance | C44: AED 160 | D44: Management cap | E44: 46259.531 | F44: Johnny’s Edge damage-control plan | G44: AED 5/day or AED 35/week; no discretionary spending
