Workbook

Sheet Start Here
B1: JOHNNY'S EDGE
B2: Personal Finance Operating System
B3: ="Built 11 Aug 2026 · Last structural update "&TEXT(TODAY(),"dd mmm yyyy") -> Built 11 Aug 2026 · Last structural update 26 Aug 2026
B5: Every number on every sheet is a live formula. Update a balance on Accounts, add a row on Transactions, or change an assumption on Settings — everything downstream recalculates. Nothing here is typed twice.
B8: Sheet | C8: What it's for
B9: Command Center | C9: Open this first, every day. Cash position, this month, what you may spend, the gap, upcoming bills, live alerts.
B10: Today's Brief | C10: The same picture in plain English — read it out loud to yourself in 30 seconds.
B11: Cash Calendar | C11: Week by week to the rent cheque. Shows exactly which week gets tight.
B12: Goals & Future Planning | C12: NEW — UNTOLD Dubai, the couple's trip, and the January rent renewal, with savings targets that never outrank the rent gap.
B13: Weekly Check-In | C13: NEW — spending shown by the week and month, not the day. On-track/over/watch status, plus a rolling 12-week history.
B14: Family & Future Security | C14: NEW — a staged plan for a possible pregnancy, a family-sized emergency fund, and a home, with researched real costs and an honest reality check on timing.
B15: Settings | C15: Every assumption lives here — salary, rent, buffers, thresholds. Change nothing anywhere else.
B16: Accounts | C16: Every account, current balance, what's reserved, what's genuinely spendable.
B17: Account History | C17: NEW — a running log of every account's balance over time, with a trend chart.
B18: Transactions | C18: The master ledger. Add a row here for every expense or income — everything else derives from it.
B19: Bills & Commitments | C19: Every bill and expected inflow, sorted by due date, with real billing-cycle rules.
... B29: Archive - Original | C29: Your original workbook, exactly as uploaded, untouched.
A31: DAILY ROUTINE · under two minutes
B33: 1. | C33: Open Command Center. Check the status colour and read the alerts.
B34: 2. | C34: Update any account balance that's changed on the Accounts sheet.
B35: 3. | C35: Add today's spending to Transactions — five fields, everything else fills itself.
B36: 4. | C36: Once a week: open Cash Calendar and check nothing has gone red.

Sheet MASTER PLAN
B1: THE MASTER PLAN
B2: ="Everything in one place · "&TEXT(TODAY(),"dd mmmm yyyy") -> Everything in one place · 26 August 2026
B3: Cash, rent, debt, investments, family and goals — sequenced. Nothing below jumps the queue.
A5: WHERE YOU STAND TODAY
B6: Measure | C6: Value | F6: Note
B7: Liquid cash (all AED accounts) | C7: =Settings!$B$60 -> 6105.17 | F7: Every account you can touch
B8: Protected (rent vault + emergency) | C8: =Settings!$B$61 -> 5948.37 | F8: Committed — not spending money
B9: Genuinely spendable | C9: =Settings!$B$62 -> 156.8 | F9: What has to last to 26 August
B10: Investments (MF + Amana + Binance) | C10: =Settings!$B$114 -> 12805.332 | F10: Not liquid, not for the rent gap
B11: TOTAL ASSETS | C11: =Settings!$B$115 -> 18910.502 | D11: Net worth after Tabby | E11: =Settings!$B$118 -> 16223.142 | F11: Everything you own, tracked. This line does not net off what you owe.
B12: Status | C12: =Settings!$B$109 -> CRITICAL | F12: Driven by the rent gap, not by net worth
A14: STAGE 1 · NOW → 21 OCTOBER · close the rent gap. Nothing else matters until this is done.
B15: Item | C15: Value | D15: Deadline | F15: How
B16: Rent cheque due | C16: =Settings!$B$19 -> 11750 | D16: 46317 | F16: Cheque clears — must be funded by the 21st
B17: Already vaulted | C17: ='Rent Vault'!$B$11 -> 5940.7 | F17: FAB 4002
B18: Still to fund | C18: ='Rent Vault'!$B$12 -> 5809.3 | D18: 46316 | F18: What the vault still needs
B19: SHORTFALL after all income and bills | C19: =Settings!$B$81 -> 3091.03 | D19: 46316 | F19: The real number — income must cover this
B20: Earn per week | C20: =Settings!$B$83 -> 386.37875 | F20: Every week from now. Log it as it lands.
B21: Daily spending cap to 26 Aug | C21: =Settings!$B$62/14 -> 11.2 | F21: What's left divided by days to payday
B22: Survival floor | C22: =Settings!$B$15 -> 15 | F22: Your cap sits BELOW this — the gap closes through income, not cuts
A24: STAGE 2 · OCT → MID 2027 · rebuild the floor beneath you
B25: Item | C25: Target | D25: Now | E25: Gap | F25: Why it comes first
B26: Safety buffer | C26: =Settings!$B$14 -> 250 | D26: =MIN(Settings!$B$62,Settings!$B$14) -> 156.8 | E26: =MAX($C26-$D26,0) -> 93.2 | F26: One month of breathing room
B27: Emergency fund | C27: ='Family & Future Security'!$B$18 -> 21966 | D27: =Accounts!$D$9 -> 7.67 | E27: =MAX($C27-$D27,0) -> 21958.33 | F27: Six months of essentials. Single income, family coming — this is the real insurance.
B28: Tabby cleared | C28: =Settings!$B$32 -> 2687.36 | D28: =0 -> 0 | E28: =MAX($C28-$D28,0) -> 2687.36 | F28: Once paid, AED 1,314.50/month returns to you permanently
A30: STAGE 3 · FAMILY · start the insurance check now, the saving after Stage 2
B31: Item | C31: Amount | D31: When | F31: Note
B32: Maternity provision | C32: ='Family & Future Security'!$B$32 -> 11000 | F32: Her EBP covers most of it — this is the gap plus newborn essentials
B33: → contingency for scans and extras | C33: ='Family & Future Security'!$B$30 -> 3000 | F33: Editable on the Family sheet
B34: → newborn first year | C34: =Settings!$B$149 -> 8000 | F34: Crib, car seat, paediatrician — insurance covers none of it
B35: CONFIRM WITH HR | C35: — | F35: Five-minute call: is maternity excluded on the Basic tier? Do this regardless of timing.
A37: STAGE 4 · INVESTMENTS · already running — protect it, then accelerate
B38: Path | C38: Timeline to ₹1 crore | D38: Monthly cost | F38: Trade-off
B39: Keep SIP flat (₹12,000/mo) | C39: 13.4 years | D39: ₹12,000 | F39: No change. Slowest, but survivable today.
B40: 10% annual step-up | C40: 11.8 years | D40: Grows to ₹28,297 by yr 10 | F40: Costs more every year. Needs real income growth.
B41: Step-up + restart Motilal ₹6k for 5 yrs | C41: 10.75 years | D41: Peaks ~₹34,000/mo in yr 5 | F41: Fastest realistic path. Motilal is your best performer at 23.81%.
B42: Step-up + Motilal forever | C42: 10.4 years | D42: Same, ongoing | F42: Only 4 months faster than stopping at 5 years — not worth the extra commitment.
B43: 7 years is not achievable | C43: — | F43: Would need ~₹55,000/month, roughly 4.5× your salary. The lever that moves this is income growth, not fund selection.
B44: Current portfolio | C44: =Settings!$B$114 -> 12805.332 | F44: MF ₹245,086 + Amana AED 3,176 + Binance AED 192. Nippon is 95% of the MF side — concentrated in one fund house.
A46: STAGE 5 · GOALS & HOME · funded only after Stages 1–3
B47: Goal | C47: Amount | D47: When | E47: Per week | F47: Reality
B48: UNTOLD Dubai · 1 ticket | C48: =Settings!$B$135 -> 350 | D48: 46331 | E48: ='Goals & Future Planning'!$B$19 -> 31.818182 | F48: Fundable once the rent gap closes — not before
B49: Couple's trip · 4–5 days | C49: =Settings!$B$136 -> 4000 | D49: — | E49: — | F49: No date set. Set one on Settings to activate the countdown.
B50: January rent cheque | C50: =Settings!$B$128 -> 11750 | D50: 46409 | E50: — | F50: Quarterly. Assumed flat — confirm with the landlord.
B51: Home · Dubai | C51: =1000000 -> 1000000 | D51: — | E51: — | F51: Needs ~AED 270–280k cash at closing and AED 15,000/mo salary. Not eligible on current income — multi-year, income-led.
B52: Home · India | C52: =0 -> 0 | D52: — | E52: — | F52: No city set. Tell me where and I'll research real numbers.
A55: IF YOU REMEMBER ONE THING
B56: ="Earn AED "&TEXT(Settings!$B$83,"#,##0.00")&" a week and don't spend it. That single number closes the rent gap. Everything else on this sheet — the emergency fund, the maternity provision, UNTOLD, the trip, the ₹1 crore timeline, the home — waits behind it and becomes possible once it's done." -> Earn AED 386.38 a week and don't spend it. That single number closes the rent gap. Everything else on this sheet — the emergency fund, the maternity provision, UNTOLD, the trip, the ₹1 crore timeline, the home — waits behind it and becomes possible once it's done.

Sheet Command Center
A1: JOHNNY'S EDGE
A2: ="Financial Command Center · "&TEXT(Settings!$B$9,"dddd, dd mmmm yyyy")&" · "&Settings!$B$66&" days until income" -> Financial Command Center · Wednesday, 26 August 2026 · 31 days until income
A4: =Settings!$B$109&" · HEALTH SCORE "&TEXT(Settings!$B$108,"0")&"/100"&CHAR(10)&IF(Settings!$B$72<0,"After protecting rent and every confirmed commitment you are short by AED "&TEXT(Settings!$B$81,"#,##0.00")&" to reach 21 October. Nothing is safe to spend beyond AED "&TEXT(Settings!$B$75,"#,##0.00")&" a day.","After protecting rent and every confirmed commitment you have AED "&TEXT(Settings!$B$72,"#,##0.00")&" for "&Settings!$B$73&" days — about AED "&TEXT(Settings!$B$75,"#,##0.00")&" a day.") -> CRITICAL · HEALTH SCORE 18/100 After protecting rent and every confirmed commitment you are short by AED 3,091.03 to reach 21 October. Nothing is safe to spend beyond AED 0.00 a day.
A7: CASH POSITION
A8: TOTAL LIQUID CASH | D8: PROTECTED / RESERVED | G8: TRUE SPENDABLE CASH | J8: TOTAL ACCESSIBLE ASSETS
A9: =Settings!$B$60 -> 6105.17 | D9: =Settings!$B$61 -> 5948.37 | G9: =Settings!$B$62 -> 156.8 | J9: =Settings!$B$115 -> 18910.502
A10: All AED accounts | D10: Rent vault + emergency | G10: Before upcoming bills | J10: Cash + investments
A11: EMERGENCY FUND | D11: INVESTMENTS (AED) | G11: BNPL EXPOSURE | J11: RENT FUNDED
A12: =Settings!$B$98 -> 7.67 | D12: =Settings!$B$96+Settings!$B$110+Settings!$B$113 -> 12805.332 | G12: =Settings!$B$101 -> 2687.36 | J12: =Settings!$B$100 -> 0.50559149
A13: ="Target AED "&TEXT(Settings!$B$23,"#,##0")&" · "&TEXT(Settings!$B$99,"0.0%") -> Target AED 1,000 · 0.8% | D13: ="MF "&TEXT(Settings!$B$96,"#,##0")&" + Amana "&TEXT(Settings!$B$110,"#,##0")&" + Binance "&TEXT(Settings!$B$113,"#,##0") -> MF 9,437 + Amana 3,176 + Binance 192 | G13: Tabby — card frozen | J13: ="AED "&TEXT(Settings!$B$70,"#,##0.00")&" still to fund" -> AED 5,809.30 still to fund
A15: THIS MONTH
A16: INCOME RECEIVED | D16: SPENT THIS MONTH | G16: HOUSEHOLD | J16: PERSONAL / LIFESTYLE
A17: =Settings!$B$85 -> 11466.7 | D17: =Settings!$B$86 -> 7587.65 | G17: =Settings!$B$87 -> 6028.4 | J17: =Settings!$B$88 -> 1559.25
A18: Banked only | D18: ="Avg AED "&TEXT(Settings!$B$90,"#,##0.00")&"/day" -> Avg AED 119.99/day | G18: Essential home costs | J18: Discretionary
A19: REMAINING OBLIGATIONS | D19: EXPECTED INFLOWS | G19: PROJECTED MONTH-END CASH | J19: DAYS UNTIL INCOME
A20: =Settings!$B$92 -> 0 | D20: =Settings!$B$93 -> 0 | G20: =Settings!$B$94 -> -443.15962 | J20: =Settings!$B$66 -> 31
A21: Bills left this month | D21: Not yet banked | G21: At current burn rate | J21: ="Payday "&TEXT(Settings!$B$12,"dd mmm") -> Payday 26 Sep
A23: WHAT YOU MAY ACTUALLY SPEND
A24: SURVIVAL / WEEK | D24: SAFE / WEEK | G24: COMFORTABLE / WEEK | J24: WEEKEND ALLOWANCE
A25: =Settings!$B$76*7 -> -332.05516 | D25: =Settings!$B$75*7 -> 0 | G25: =Settings!$B$77*7 -> 0 | J25: =Settings!$B$78 -> 0
A26: ="AED "&TEXT(Settings!$B$76,"#,##0.00")&"/day" -> AED -47.44/day | D26: ="AED "&TEXT(Settings!$B$75,"#,##0.00")&"/day · the binding limit" -> AED 0.00/day · the binding limit | G26: Zero unless finances allow | J26: Safe daily x weekend length
A28: THE GAP
A29: FINANCIAL GAP | D29: GAP WITHOUT BUFFER | G29: EXTRA INCOME / DAY | J29: EXTRA INCOME / WEEK
A30: =Settings!$B$81 -> 3091.03 | D30: =Settings!$B$80 -> 2841.03 | G30: =Settings!$B$82 -> 55.196964 | J30: =Settings!$B$83 -> 386.37875
A31: To 21 Oct, buffer intact | D31: If you sacrifice the buffer | G31: To close the gap | J31: Weekly earning target
A33: UPCOMING OBLIGATIONS · next payments, soonest first
A34: Payment | D34: Due date | F34: Amount | G34: Pay from | I34: Certainty | J34: Status | L34: Days left
A35: =IF(SMALL('Bills & Commitments'!$S$7:$S$80,1)>=99999,"",IFERROR(INDEX('Bills & Commitments'!$B$7:$B$80,MATCH(SMALL('Bills & Commitments'!$S$7:$S$80,1),'Bills & Commitments'!$S$7:$S$80,0)),"")) -> Nippon SIP — September | D35: =IF(SMALL('Bills & Commitments'!$S$7:$S$80,1)>=99999,"",IFERROR(INDEX('Bills & Commitments'!$A$7:$A$80,MATCH(SMALL('Bills & Commitments'!$S$7:$S$80,1),'Bills & Commitments'!$S$7:$S$80,0)),"")) -> 46275 | F35: =IF(SMALL('Bills & Commitments'!$S$7:$S$80,1)>=99999,"",IFERROR(INDEX('Bills & Commitments'!$G$7:$G$80,MATCH(SMALL('Bills & Commitments'!$S$7:$S$80,1),'Bills & Commitments'!$S$7:$S$80,0)),"")) -> 462.4 | G35: =IF(SMALL('Bills & Commitments'!$S$7:$S$80,1)>=99999,"",IFERROR(INDEX('Bills & Commitments'!$K$7:$K$80,MATCH(SMALL('Bills & Commitments'!$S$7:$S$80,1),'Bills & Commitments'!$S$7:$S$80,0)),"")) -> ICICI (INR) | I35: =IF(SMALL('Bills & Commitments'!$S$7:$S$80,1)>=99999,"",IFERROR(INDEX('Bills & Commitments'!$O$7:$O$80,MATCH(SMALL('Bills & Commitments'!$S$7:$S$80,1),'Bills & Commitments'!$S$7:$S$80,0)),"")) -> Estimated | J35: =IF(SMALL('Bills & Commitments'!$S$7:$S$80,1)>=99999,"",IFERROR(INDEX('Bills & Commitments'!$Q$7:$Q$80,MATCH(SMALL('Bills & Commitments'!$S$7:$S$80,1),'Bills & Commitments'!$S$7:$S$80,0)),"")) -> Scheduled | L35: =IF(SMALL('Bills & Commitments'!$S$7:$S$80,1)>=99999,"",IFERROR(INDEX('Bills & Commitments'!$P$7:$P$80,MATCH(SMALL('Bills & Commitments'!$S$7:$S$80,1),'Bills & Commitments'!$S$7:$S$80,0)),"")) -> 15
A36: =IF(SMALL('Bills & Commitments'!$S$7:$S$80,2)>=99999,"",IFERROR(INDEX('Bills & Commitments'!$B$7:$B$80,MATCH(SMALL('Bills & Commitments'!$S$7:$S$80,2),'Bills & Commitments'!$S$7:$S$80,0)),"")) -> du — September | D36: =IF(SMALL('Bills & Commitments'!$S$7:$S$80,2)>=99999,"",IFERROR(INDEX('Bills & Commitments'!$A$7:$A$80,MATCH(SMALL('Bills & Commitments'!$S$7:$S$80,2),'Bills & Commitments'!$S$7:$S$80,0)),"")) -> 46280 | F36: =IF(SMALL('Bills & Commitments'!$S$7:$S$80,2)>=99999,"",IFERROR(INDEX('Bills & Commitments'!$G$7:$G$80,MATCH(SMALL('Bills & Commitments'!$S$7:$S$80,2),'Bills & Commitments'!$S$7:$S$80,0)),"")) -> 590.98 | G36: =IF(SMALL('Bills & Commitments'!$S$7:$S$80,2)>=99999,"",IFERROR(INDEX('Bills & Commitments'!$K$7:$K$80,MATCH(SMALL('Bills & Commitments'!$S$7:$S$80,2),'Bills & Commitments'!$S$7:$S$80,0)),"")) -> FAB 4001 Current | I36: =IF(SMALL('Bills & Commitments'!$S$7:$S$80,2)>=99999,"",IFERROR(INDEX('Bills & Commitments'!$O$7:$O$80,MATCH(SMALL('Bills & Commitments'!$S$7:$S$80,2),'Bills & Commitments'!$S$7:$S$80,0)),"")) -> Estimated | J36: =IF(SMALL('Bills & Commitments'!$S$7:$S$80,2)>=99999,"",IFERROR(INDEX('Bills & Commitments'!$Q$7:$Q$80,MATCH(SMALL('Bills & Commitments'!$S$7:$S$80,2),'Bills & Commitments'!$S$7:$S$80,0)),"")) -> Scheduled | L36: =IF(SMALL('Bills & Commitments'!$S$7:$S$80,2)>=99999,"",IFERROR(INDEX('Bills & Commitments'!$P$7:$P$80,MATCH(SMALL('Bills & Commitments'!$S$7:$S$80,2),'Bills & Commitments'!$S$7:$S$80,0)),"")) -> 20
A37: =IF(SMALL('Bills & Commitments'!$S$7:$S$80,3)>=99999,"",IFERROR(INDEX('Bills & Commitments'!$B$7:$B$80,MATCH(SMALL('Bills & Commitments'!$S$7:$S$80,3),'Bills & Commitments'!$S$7:$S$80,0)),"")) -> Etisalat — September | D37: =IF(SMALL('Bills & Commitments'!$S$7:$S$80,3)>=99999,"",IFERROR(INDEX('Bills & Commitments'!$A$7:$A$80,MATCH(SMALL('Bills & Commitments'!$S$7:$S$80,3),'Bills & Commitments'!$S$7:$S$80,0)),"")) -> 46280 | F37: =IF(SMALL('Bills & Commitments'!$S$7:$S$80,3)>=99999,"",IFERROR(INDEX('Bills & Commitments'!$G$7:$G$80,MATCH(SMALL('Bills & Commitments'!$S$7:$S$80,3),'Bills & Commitments'!$S$7:$S$80,0)),"")) -> 323.95 | G37: =IF(SMALL('Bills & Commitments'!$S$7:$S$80,3)>=99999,"",IFERROR(INDEX('Bills & Commitments'!$K$7:$K$80,MATCH(SMALL('Bills & Commitments'!$S$7:$S$80,3),'Bills & Commitments'!$S$7:$S$80,0)),"")) -> FAB 4001 Current | I37: =IF(SMALL('Bills & Commitments'!$S$7:$S$80,3)>=99999,"",IFERROR(INDEX('Bills & Commitments'!$O$7:$O$80,MATCH(SMALL('Bills & Commitments'!$S$7:$S$80,3),'Bills & Commitments'!$S$7:$S$80,0)),"")) -> Estimated | J37: =IF(SMALL('Bills & Commitments'!$S$7:$S$80,3)>=99999,"",IFERROR(INDEX('Bills & Commitments'!$Q$7:$Q$80,MATCH(SMALL('Bills & Commitments'!$S$7:$S$80,3),'Bills & Commitments'!$S$7:$S$80,0)),"")) -> Scheduled | L37: =IF(SMALL('Bills & Commitments'!$S$7:$S$80,3)>=99999,"",IFERROR(INDEX('Bills & Commitments'!$P$7:$P$80,MATCH(SMALL('Bills & Commitments'!$S$7:$S$80,3),'Bills & Commitments'!$S$7:$S$80,0)),"")) -> 20
A38: =IF(SMALL('Bills & Commitments'!$S$7:$S$80,4)>=99999,"",IFERROR(INDEX('Bills & Commitments'!$B$7:$B$80,MATCH(SMALL('Bills & Commitments'!$S$7:$S$80,4),'Bills & Commitments'!$S$7:$S$80,0)),"")) -> DEWA — September | D38: =IF(SMALL('Bills & Commitments'!$S$7:$S$80,4)>=99999,"",IFERROR(INDEX('Bills & Commitments'!$A$7:$A$80,MATCH(SMALL('Bills & Commitments'!$S$7:$S$80,4),'Bills & Commitments'!$S$7:$S$80,0)),"")) -> 46295 | F38: =IF(SMALL('Bills & Commitments'!$S$7:$S$80,4)>=99999,"",IFERROR(INDEX('Bills & Commitments'!$G$7:$G$80,MATCH(SMALL('Bills & Commitments'!$S$7:$S$80,4),'Bills & Commitments'!$S$7:$S$80,0)),"")) -> 793.42 | G38: =IF(SMALL('Bills & Commitments'!$S$7:$S$80,4)>=99999,"",IFERROR(INDEX('Bills & Commitments'!$K$7:$K$80,MATCH(SMALL('Bills & Commitments'!$S$7:$S$80,4),'Bills & Commitments'!$S$7:$S$80,0)),"")) -> FAB 4001 Current | I38: =IF(SMALL('Bills & Commitments'!$S$7:$S$80,4)>=99999,"",IFERROR(INDEX('Bills & Commitments'!$O$7:$O$80,MATCH(SMALL('Bills & Commitments'!$S$7:$S$80,4),'Bills & Commitments'!$S$7:$S$80,0)),"")) -> Estimated | J38: =IF(SMALL('Bills & Commitments'!$S$7:$S$80,4)>=99999,"",IFERROR(INDEX('Bills & Commitments'!$Q$7:$Q$80,MATCH(SMALL('Bills & Commitments'!$S$7:$S$80,4),'Bills & Commitments'!$S$7:$S$80,0)),"")) -> Scheduled | L38: =IF(SMALL('Bills & Commitments'!$S$7:$S$80,4)>=99999,"",IFERROR(INDEX('Bills & Commitments'!$P$7:$P$80,MATCH(SMALL('Bills & Commitments'!$S$7:$S$80,4),'Bills & Commitments'!$S$7:$S$80,0)),"")) -> 35
A39: =IF(SMALL('Bills & Commitments'!$S$7:$S$80,5)>=99999,"",IFERROR(INDEX('Bills & Commitments'!$B$7:$B$80,MATCH(SMALL('Bills & Commitments'!$S$7:$S$80,5),'Bills & Commitments'!$S$7:$S$80,0)),"")) -> Tabby — September statement | D39: =IF(SMALL('Bills & Commitments'!$S$7:$S$80,5)>=99999,"",IFERROR(INDEX('Bills & Commitments'!$A$7:$A$80,MATCH(SMALL('Bills & Commitments'!$S$7:$S$80,5),'Bills & Commitments'!$S$7:$S$80,0)),"")) -> 46298 | F39: =IF(SMALL('Bills & Commitments'!$S$7:$S$80,5)>=99999,"",IFERROR(INDEX('Bills & Commitments'!$G$7:$G$80,MATCH(SMALL('Bills & Commitments'!$S$7:$S$80,5),'Bills & Commitments'!$S$7:$S$80,0)),"")) -> 715.33 | G39: =IF(SMALL('Bills & Commitments'!$S$7:$S$80,5)>=99999,"",IFERROR(INDEX('Bills & Commitments'!$K$7:$K$80,MATCH(SMALL('Bills & Commitments'!$S$7:$S$80,5),'Bills & Commitments'!$S$7:$S$80,0)),"")) -> FAB 4001 Current | I39: =IF(SMALL('Bills & Commitments'!$S$7:$S$80,5)>=99999,"",IFERROR(INDEX('Bills & Commitments'!$O$7:$O$80,MATCH(SMALL('Bills & Commitments'!$S$7:$S$80,5),'Bills & Commitments'!$S$7:$S$80,0)),"")) -> Actual | J39: =IF(SMALL('Bills & Commitments'!$S$7:$S$80,5)>=99999,"",IFERROR(INDEX('Bills & Commitments'!$Q$7:$Q$80,MATCH(SMALL('Bills & Commitments'!$S$7:$S$80,5),'Bills & Commitments'!$S$7:$S$80,0)),"")) -> Scheduled | L39: =IF(SMALL('Bills & Commitments'!$S$7:$S$80,5)>=99999,"",IFERROR(INDEX('Bills & Commitments'!$P$7:$P$80,MATCH(SMALL('Bills & Commitments'!$S$7:$S$80,5),'Bills & Commitments'!$S$7:$S$80,0)),"")) -> 38
A40: =IF(SMALL('Bills & Commitments'!$S$7:$S$80,6)>=99999,"",IFERROR(INDEX('Bills & Commitments'!$B$7:$B$80,MATCH(SMALL('Bills & Commitments'!$S$7:$S$80,6),'Bills & Commitments'!$S$7:$S$80,0)),"")) -> Nippon SIP — October | D40: =IF(SMALL('Bills & Commitments'!$S$7:$S$80,6)>=99999,"",IFERROR(INDEX('Bills & Commitments'!$A$7:$A$80,MATCH(SMALL('Bills & Commitments'!$S$7:$S$80,6),'Bills & Commitments'!$S$7:$S$80,0)),"")) -> 46305 | F40: =IF(SMALL('Bills & Commitments'!$S$7:$S$80,6)>=99999,"",IFERROR(INDEX('Bills & Commitments'!$G$7:$G$80,MATCH(SMALL('Bills & Commitments'!$S$7:$S$80,6),'Bills & Commitments'!$S$7:$S$80,0)),"")) -> 462.4 | G40: =IF(SMALL('Bills & Commitments'!$S$7:$S$80,6)>=99999,"",IFERROR(INDEX('Bills & Commitments'!$K$7:$K$80,MATCH(SMALL('Bills & Commitments'!$S$7:$S$80,6),'Bills & Commitments'!$S$7:$S$80,0)),"")) -> ICICI (INR) | I40: =IF(SMALL('Bills & Commitments'!$S$7:$S$80,6)>=99999,"",IFERROR(INDEX('Bills & Commitments'!$O$7:$O$80,MATCH(SMALL('Bills & Commitments'!$S$7:$S$80,6),'Bills & Commitments'!$S$7:$S$80,0)),"")) -> Estimated | J40: =IF(SMALL('Bills & Commitments'!$S$7:$S$80,6)>=99999,"",IFERROR(INDEX('Bills & Commitments'!$Q$7:$Q$80,MATCH(SMALL('Bills & Commitments'!$S$7:$S$80,6),'Bills & Commitments'!$S$7:$S$80,0)),"")) -> Scheduled | L40: =IF(SMALL('Bills & Commitments'!$S$7:$S$80,6)>=99999,"",IFERROR(INDEX('Bills & Commitments'!$P$7:$P$80,MATCH(SMALL('Bills & Commitments'!$S$7:$S$80,6),'Bills & Commitments'!$S$7:$S$80,0)),"")) -> 45
A41: =IF(SMALL('Bills & Commitments'!$S$7:$S$80,7)>=99999,"",IFERROR(INDEX('Bills & Commitments'!$B$7:$B$80,MATCH(SMALL('Bills & Commitments'!$S$7:$S$80,7),'Bills & Commitments'!$S$7:$S$80,0)),"")) -> du — October | D41: =IF(SMALL('Bills & Commitments'!$S$7:$S$80,7)>=99999,"",IFERROR(INDEX('Bills & Commitments'!$A$7:$A$80,MATCH(SMALL('Bills & Commitments'!$S$7:$S$80,7),'Bills & Commitments'!$S$7:$S$80,0)),"")) -> 46310 | F41: =IF(SMALL('Bills & Commitments'!$S$7:$S$80,7)>=99999,"",IFERROR(INDEX('Bills & Commitments'!$G$7:$G$80,MATCH(SMALL('Bills & Commitments'!$S$7:$S$80,7),'Bills & Commitments'!$S$7:$S$80,0)),"")) -> 590.98 | G41: =IF(SMALL('Bills & Commitments'!$S$7:$S$80,7)>=99999,"",IFERROR(INDEX('Bills & Commitments'!$K$7:$K$80,MATCH(SMALL('Bills & Commitments'!$S$7:$S$80,7),'Bills & Commitments'!$S$7:$S$80,0)),"")) -> FAB 4001 Current | I41: =IF(SMALL('Bills & Commitments'!$S$7:$S$80,7)>=99999,"",IFERROR(INDEX('Bills & Commitments'!$O$7:$O$80,MATCH(SMALL('Bills & Commitments'!$S$7:$S$80,7),'Bills & Commitments'!$S$7:$S$80,0)),"")) -> Estimated | J41: =IF(SMALL('Bills & Commitments'!$S$7:$S$80,7)>=99999,"",IFERROR(INDEX('Bills & Commitments'!$Q$7:$Q$80,MATCH(SMALL('Bills & Commitments'!$S$7:$S$80,7),'Bills & Commitments'!$S$7:$S$80,0)),"")) -> Scheduled | L41: =IF(SMALL('Bills & Commitments'!$S$7:$S$80,7)>=99999,"",IFERROR(INDEX('Bills & Commitments'!$P$7:$P$80,MATCH(SMALL('Bills & Commitments'!$S$7:$S$80,7),'Bills & Commitments'!$S$7:$S$80,0)),"")) -> 50
A42: =IF(SMALL('Bills & Commitments'!$S$7:$S$80,8)>=99999,"",IFERROR(INDEX('Bills & Commitments'!$B$7:$B$80,MATCH(SMALL('Bills & Commitments'!$S$7:$S$80,8),'Bills & Commitments'!$S$7:$S$80,0)),"")) -> Etisalat — October | D42: =IF(SMALL('Bills & Commitments'!$S$7:$S$80,8)>=99999,"",IFERROR(INDEX('Bills & Commitments'!$A$7:$A$80,MATCH(SMALL('Bills & Commitments'!$S$7:$S$80,8),'Bills & Commitments'!$S$7:$S$80,0)),"")) -> 46310 | F42: =IF(SMALL('Bills & Commitments'!$S$7:$S$80,8)>=99999,"",IFERROR(INDEX('Bills & Commitments'!$G$7:$G$80,MATCH(SMALL('Bills & Commitments'!$S$7:$S$80,8),'Bills & Commitments'!$S$7:$S$80,0)),"")) -> 323.95 | G42: =IF(SMALL('Bills & Commitments'!$S$7:$S$80,8)>=99999,"",IFERROR(INDEX('Bills & Commitments'!$K$7:$K$80,MATCH(SMALL('Bills & Commitments'!$S$7:$S$80,8),'Bills & Commitments'!$S$7:$S$80,0)),"")) -> FAB 4001 Current | I42: =IF(SMALL('Bills & Commitments'!$S$7:$S$80,8)>=99999,"",IFERROR(INDEX('Bills & Commitments'!$O$7:$O$80,MATCH(SMALL('Bills & Commitments'!$S$7:$S$80,8),'Bills & Commitments'!$S$7:$S$80,0)),"")) -> Estimated | J42: =IF(SMALL('Bills & Commitments'!$S$7:$S$80,8)>=99999,"",IFERROR(INDEX('Bills & Commitments'!$Q$7:$Q$80,MATCH(SMALL('Bills & Commitments'!$S$7:$S$80,8),'Bills & Commitments'!$S$7:$S$80,0)),"")) -> Scheduled | L42: =IF(SMALL('Bills & Commitments'!$S$7:$S$80,8)>=99999,"",IFERROR(INDEX('Bills & Commitments'!$P$7:$P$80,MATCH(SMALL('Bills & Commitments'!$S$7:$S$80,8),'Bills & Commitments'!$S$7:$S$80,0)),"")) -> 50
A44: ALERTS
A45: =IF(Settings!$B$72<0,"● CRITICAL — projected rent funding is short by AED "&TEXT(Settings!$B$81,"#,##0.00")&". Living budget to 21 Oct is effectively zero without new income.","") -> ● CRITICAL — projected rent funding is short by AED 3,091.03. Living budget to 21 Oct is effectively zero without new income.
A46: =IF(COUNTIFS('Bills & Commitments'!$Q$7:$Q$80,"OVERDUE")>0,"● A bill is OVERDUE — see the obligations table above.","")
A47: =IF(Settings!$B$94<0,"● Projected month-end cash is negative at the current burn rate.","") -> ● Projected month-end cash is negative at the current burn rate.
A48: =IF(Settings!$B$90>Settings!$B$75,"● Spending is running above the safe pace: AED "&TEXT(Settings!$B$90,"#,##0.00")&"/day actual vs AED "&TEXT(Settings!$B$75,"#,##0.00")&"/day allowed.","") -> ● Spending is running above the safe pace: AED 119.99/day actual vs AED 0.00/day allowed.
A49: =IF(Settings!$B$99<0.25,"● Emergency fund is at "&TEXT(Settings!$B$99,"0.0%")&" of target — there is no shock absorber.","") -> ● Emergency fund is at 0.8% of target — there is no shock absorber.
A50: =IF(Settings!$B$101>Settings!$B$60*0.5,"● BNPL exposure is "&TEXT(Settings!$B$101/Settings!$B$60,"0%")&" of liquid cash.","")
A51: =IF(COUNTIFS(Reconciliation!$H$9:$H$16,"RECONCILIATION REQUIRED")>0,"● "&COUNTIFS(Reconciliation!$H$9:$H$16,"RECONCILIATION REQUIRED")&" account(s) do not reconcile — transactions are missing.","")
A52: =IF(COUNTIFS('Checks & Audit'!$F$8:$F$26,"CHECK")>0,"● Integrity checks are failing — open the Checks & Audit sheet.","● All integrity checks pass.") -> ● All integrity checks pass.

Sheet Today's Brief
B1: TODAY'S CFO BRIEF
B2: ="Prepared for "&Settings!$B$7&" · "&TEXT(Settings!$B$9,"dddd, dd mmmm yyyy") -> Prepared for Johnny · Wednesday, 26 August 2026
B5: ="Today you hold AED "&TEXT(Settings!$B$60,"#,##0.00")&" in total liquid cash across every account." -> Today you hold AED 6,105.17 in total liquid cash across every account.
B8: ="Of that, AED "&TEXT(Settings!$B$61,"#,##0.00")&" is protected — the rent vault and the emergency fund. Your true usable balance is AED "&TEXT(Settings!$B$62,"#,##0.00")&"." -> Of that, AED 5,948.37 is protected — the rent vault and the emergency fund. Your true usable balance is AED 156.80.
B11: ="There are "&Settings!$B$66&" days until your next income on "&TEXT(Settings!$B$12,"dd mmmm")&", and "&Settings!$B$73&" days until the rent cheque must be fully funded on "&TEXT(Settings!$B$21,"dd mmmm")&"." -> There are 31 days until your next income on 26 September, and 56 days until the rent cheque must be fully funded on 21 October.
B14: ="Recommended spending ceiling THIS WEEK: AED "&TEXT(Settings!$B$75*7,"#,##0.00")&". Survival week: AED "&TEXT(Settings!$B$76*7,"#,##0.00")&". Comfortable week: "&IF(Settings!$B$77=0,"not available yet.","AED "&TEXT(Settings!$B$77*7,"#,##0.00")&".") -> Recommended spending ceiling THIS WEEK: AED 0.00. Survival week: AED -332.06. Comfortable week: not available yet.
B17: ="Recommended ceiling for the whole weekend: AED "&TEXT(Settings!$B$78,"#,##0.00")&"." -> Recommended ceiling for the whole weekend: AED 0.00.
B20: ="Next payment: "&Settings!$B$103&" — AED "&TEXT(Settings!$B$102,"#,##0.00")&" on "&TEXT(Settings!$B$104,"dd mmmm")&"." -> Next payment: Nippon SIP — September — AED 462.40 on 10 September.
B23: ="Largest payment before the rent deadline: "&Settings!$B$106&" — AED "&TEXT(Settings!$B$105,"#,##0.00")&" on "&TEXT(Settings!$B$107,"dd mmmm")&"." -> Largest payment before the rent deadline: DEWA — September — AED 793.42 on 30 September.
B26: ="At your current burn rate of AED "&TEXT(Settings!$B$90,"#,##0.00")&" a day, projected month-end cash is AED "&TEXT(Settings!$B$94,"#,##0.00")&"." -> At your current burn rate of AED 119.99 a day, projected month-end cash is AED -443.16.
B29: ="MAIN RISK: "&IF(Settings!$B$72<0,"the October rent cheque. After every confirmed commitment you are AED "&TEXT(Settings!$B$81,"#,##0.00")&" short of funding it, and that assumes the AED 1,430 refund and AED 1,540 pending salary both land. If both fail, add AED 2,970.",IF(Settings!$B$99<0.25,"you have almost no emergency cover. One unexpected bill becomes debt.","spending drift above the safe daily pace.")) -> MAIN RISK: the October rent cheque. After every confirmed commitment you are AED 3,091.03 short of funding it, and that assumes the AED 1,430 refund and AED 1,540 pending salary both land. If both fail, add AED 2,970.
B32: ="ACTION TODAY: "&IF(Settings!$B$72<0,"earn or recover AED "&TEXT(Settings!$B$82,"#,##0.00")&" today (AED "&TEXT(Settings!$B$83,"#,##0.00")&" this week), and hold spending at or below AED "&TEXT(Settings!$B$76,"#,##0.00")&". Do not release a dirham against money that has not landed.","hold spending at or below AED "&TEXT(Settings!$B$75,"#,##0.00")&" and move any surplus into the rent vault.") -> ACTION TODAY: earn or recover AED 55.20 today (AED 386.38 this week), and hold spending at or below AED -47.44. Do not release a dirham against money that has not landed.
B35: Every figure above is a live formula. Nothing here is typed by hand — change a balance on the Accounts sheet or add a transaction and this brief rewrites itself.
B38: HOW TO KEEP THIS ALIVE · under one minute a day
B39: 1. Add the day's spending to the Transactions sheet — Date, Account, Type, Category, Merchant, Amount. Everything else is a dropdown or fills itself.
B40: 2. Update the Current Balance column on the Accounts sheet whenever you check your bank. That single column drives the whole dashboard.
B41: 3. When a bill is paid, put the real figure in the Actual column on Bills & Commitments and set Settled to Yes. Never delete the row.
B42: 4. Once a month, open Reconciliation. If an account says RECONCILIATION REQUIRED, a transaction is missing — find it before you trust any projection.
B43: 5. Change assumptions only on the Settings sheet. Nothing is hardcoded anywhere else.

Sheet Settings
A1: Control Panel
A2: Every assumption in the workbook lives here. Edit only the blue text on yellow fill — nothing else is hardcoded elsewhere.
A5: CORE ASSUMPTIONS · edit yellow cells only
A6: Setting | B6: Value | C6: Unit | D6: Note / source
A7: Owner | B7: Johnny | C7: – | D7: Workbook owner
A8: Base currency | B8: AED | C8: – | D8: All dashboard figures are AED unless labelled
A9: As-of date (automatic) | B9: =TODAY() -> 46260 | C9: date | D9: Recalculates every time the file is opened
A10: Monthly salary — base | B10: 7914.88 | C10: AED | D10: July 2026 salary baseline
A11: Salary day of month | B11: 26 | C11: day | D11: Credit day
A12: Next income date | B12: =IF(DAY($B$9)<$B$11,DATE(YEAR($B$9),MONTH($B$9),$B$11),DATE(YEAR($B$9),MONTH($B$9)+1,$B$11)) -> 46291 | C12: date | D12: Derived from the salary day. On payday itself the salary has landed, so the count rolls to next month — with <= it returned zero days, which drove the safe daily limit to zero on the one day of the month you are paid.
A13: Days until next income | B13: =MAX($B$12-$B$9,0) -> 31 | C13: days | D13: Derived
A14: Minimum cash safety buffer | B14: 250 | C14: AED | D14: Cash you refuse to go below
A15: Minimum living need per day | B15: 15 | C15: AED/day | D15: Floor for food/transport — the control cap basis
A16: Comfortable-mode multiplier | B16: 1.35 | C16: x | D16: Only displayed if finances support it
A17: Survival-mode multiplier | B17: 0.65 | C17: x | D17: Emergency compression
A18: Weekend length | B18: 2 | C18: days | D18: Used for the weekend allowance
A19: Rent cheque amount | B19: 11750 | C19: AED | D19: Lease schedule
A20: Rent cheque date | B20: 46317 | C20: date | D20: Cheque clears this day
A21: Rent must be fully funded by | B21: =$B$20-1 -> 46316 | C21: date | D21: One day before clearing — the 26 Oct salary is too late
A22: Days until rent funding deadline | B22: =MAX($B$21-$B$9,0) -> 56 | C22: days | D22: Derived — the binding constraint
A23: Emergency fund target | B23: 1000 | C23: AED | D23: Next milestone
A24: DEWA monthly baseline | B24: 793.42 | C24: AED | D24: Last confirmed bill — replace when actual arrives
A25: du monthly baseline | B25: 590.98 | C25: AED | D25: Paid 03 Aug
A26: Etisalat monthly baseline | B26: 323.95 | C26: AED | D26: Paid 03 Aug
A27: Monthly SIP | B27: 12000 | C27: INR | D27: Four Nippon SIPs
A28: INR to AED rate | B28: 0.0385333 | C28: rate | D28: Implied by AED 462.40 = INR 12,000
A29: Monthly SIP (AED equivalent) | B29: =ROUND($B$27*$B$28,2) -> 462.4 | C29: AED | D29: Derived
A30: Tabby no-fee minimum | B30: 1314.5 | C30: AED | D30: September statement option
A31: Tabby full statement | B31: 1972.03 | C31: AED | D31: Optional full clearance
A32: Tabby total outstanding exposure | B32: 2687.36 | C32: AED | D32: Resolves as: 1,314.50 (Aug stmt, 3 Sep) + 715.33 (Sep stmt, 3 Oct) + 657.53 (Oct stmt, ~3 Nov, not yet generated). CONFIRMED via Tabby chat 15 Aug.
A34: USD to AED rate (fixed peg) | B34: 3.6725 | D34: AED's fixed dirham peg — has not moved since 1997
A35: Amana ending value (USD) | B35: 864.82 | D35: Statement ending 10 Aug 2026 | F35: Categories | G35: Classes | H35: Transaction types | I35: Accounts | J35: Essential? | K35: Fixed / Variable | L35: Yes / No | M35: Certainty
F36: Salary | G36: Household | H36: Income | I36: FAB 4001 Current | J36: Essential | K36: Fixed | L36: Yes | M36: Actual
F37: Side Income | G37: Personal | H37: Expense | I37: FAB 4002 Home Expenditure | J37: Non-Essential | K37: Variable | L37: No | M37: Estimated
F38: Refund / Reimbursement | G38: Financial | H38: Transfer In | I38: FAB 4003 Emergency Fund | M38: Possible
F39: Groceries | G39: Income | H39: Transfer Out | I39: NBD Current
F40: Food & Dining | G40: Internal | I40: NBD Plus Saver
F41: Utilities | G41: Business | I41: Tabby Cash
F42: Telecom | I42: Cash / Wio
F43: Transport | I43: ICICI (INR)
F44: Travel & Airfare
F45: Household Other
F46: Family Support
F47: Lifestyle
F48: Shopping
F49: Entertainment
F50: Health
F51: Rent
F52: BNPL
F53: Investments
F54: Savings
F55: Internal Transfer
F56: Other
A57: Binance total value (AED) | B57: 191.8 | D57: App overview, 11 Aug 2026 — 'Est. Total Value'
A58: DERIVED ENGINE · do not edit · every dashboard figure traces to a row here
A59: # | B59: Metric | C59: Value | D59: Basis
A60: E1 · Total AED liquid cash | B60: =Accounts!$D$15 -> 6105.17 | D60: All AED accounts flagged as liquid
A61: E2 · Reserved / protected | B61: =Accounts!$E$15 -> 5948.37 | D61: Rent vault + emergency fund
A62: E3 · Spendable cash now | B62: =$B$60-$B$61 -> 156.8 | D62: Liquid less reserved
A63: E4 · Bills due before next income | B63: =SUMIFS('Bills & Commitments'!$G$7:$G$80,'Bills & Commitments'!$D$7:$D$80,"Outflow",'Bills & Commitments'!$I$7:$I$80,"No",'Bills & Commitments'!$H$7:$H$80,"AED",'Bills & Commitments'!$C$7:$C$80,"<>Rent",'Bills & Commitments'!$A$7:$A$80,">="&$B$9,'Bills & Commitments'!$A$7:$A$80,"<="&$B$12) -> 1377.33 | D63: Unsettled AED outflows between today and payday, rent cheque excluded
A64: E5 · Safety buffer | B64: =$B$14 -> 250 | D64: Control panel
A65: E6 · Short-horizon pool — to next salary | B65: =$B$62-$B$63-$B$64 -> -1470.53 | D65: Spendable − bills − buffer
A66: E7 · Days until next income | B66: =$B$13 -> 31 | D66: Live
A67: E8 · Daily limit — to next salary | B67: =IF($B$66<=0,0,$B$65/$B$66) -> -47.436452 | D67: Liquidity view only; ignores the rent wall
A68: E9 · Expected inflows before rent deadline | B68: =SUMIFS('Bills & Commitments'!$G$7:$G$80,'Bills & Commitments'!$D$7:$D$80,"Inflow",'Bills & Commitments'!$I$7:$I$80,"No",'Bills & Commitments'!$H$7:$H$80,"AED",'Bills & Commitments'!$A$7:$A$80,"<="&$B$21) -> 7914.88 | D68: Unsettled AED inflows on or before 21 Oct
A69: E10 · Committed outflows before rent deadline | B69: =SUMIFS('Bills & Commitments'!$G$7:$G$80,'Bills & Commitments'!$D$7:$D$80,"Outflow",'Bills & Commitments'!$I$7:$I$80,"No",'Bills & Commitments'!$H$7:$H$80,"AED",'Bills & Commitments'!$C$7:$C$80,"<>Rent",'Bills & Commitments'!$A$7:$A$80,"<="&$B$21) -> 4263.41 | D69: Bills excluding the rent cheque itself
A70: E11 · Rent still to fund | B70: =MAX($B$19-SUMIFS(Accounts!$E$7:$E$14,Accounts!$H$7:$H$14,"Rent vault"),0) -> 5809.3 | D70: Cheque less whatever sits in an account whose Purpose reads 'Rent vault'
A71: E12 · Cash available for the rent cheque | B71: =$B$62+$B$68-$B$69-($B$73*$B$15)+SUMIFS(Accounts!$E$7:$E$14,Accounts!$H$7:$H$14,"Rent vault") -> 8908.97 | D71: Spendable + inflows − commitments − minimum living + vault
A72: E13 · Living pool to rent deadline (after buffer) | B72: =$B$62+$B$68-$B$69-$B$70-$B$64 -> -2251.03 | D72: What is left for living once rent is fully funded
A73: E14 · Days until rent deadline | B73: =$B$22 -> 56 | D73: Live
A74: E15 · Daily limit — to rent deadline | B74: =IF($B$73<=0,0,$B$72/$B$73) -> -40.196964 | D74: The binding constraint
A75: E16 · SAFE DAILY LIMIT (binding) | B75: =MAX(MIN($B$67,$B$74),0) -> 0 | D75: The lower of the two horizons — never negative
A76: E17 · Survival daily limit | B76: =MIN($B$67,$B$15) -> -47.436452 | D76: The absolute floor you must live on. It is inside the rent plan — but only fundable if the gap is closed.
A77: E18 · Comfortable daily limit | B77: =IF($B$74<$B$15,0,$B$75*$B$16) -> 0 | D77: Shown as zero unless the finances genuinely support it
A78: E19 · Weekend allowance | B78: =MAX($B$75,$B$76)*$B$18 -> 0 | D78: Safe daily where positive, otherwise the survival floor, times weekend length
A79: E20 · Minimum living need to rent deadline | B79: =$B$73*$B$15 -> 840 | D79: Days × minimum daily need
A80: E21 · FINANCIAL GAP — before safety buffer | B80: =MAX($B$79-($B$72+$B$64),0) -> 2841.03 | D80: Shortfall if the buffer is sacrificed
A81: E22 · FINANCIAL GAP — including safety buffer | B81: =MAX($B$79-$B$72,0) -> 3091.03 | D81: The honest headline number
A82: E23 · Extra income needed per day | B82: =IF($B$73<=0,0,$B$81/$B$73) -> 55.196964 | D82: Gap spread over remaining days
A83: E24 · Extra income needed per week | B83: =$B$82*7 -> 386.37875 | D83: Weekly earning target
A84: E25 · Current month key | B84: =TEXT($B$9,"YYYY-MM") -> 2026-08 | D84: Drives all month-to-date figures
A85: E26 · Income received this month | B85: =SUMIFS(Transactions!$O$7:$O$520,Transactions!$F$7:$F$520,"Income",Transactions!$P$7:$P$520,"AED",Transactions!$C$7:$C$520,$B$84) -> 11466.7 | D85: Banked income only
A86: E27 · Spending this month (own money) | B86: =SUMIFS(Transactions!$O$7:$O$520,Transactions!$F$7:$F$520,"Expense",Transactions!$P$7:$P$520,"AED",Transactions!$C$7:$C$520,$B$84)-SUMIFS(Transactions!$O$7:$O$520,Transactions!$F$7:$F$520,"Expense",Transactions!$P$7:$P$520,"AED",Transactions!$C$7:$C$520,$B$84,Transactions!$J$7:$J$520,"Business") -> 7587.65 | D86: Household + personal only. Reimbursable business outflows (the ticket bookings) are excluded — that money was never yours to spend.
A87: E28 · Household spending this month | B87: =SUMIFS(Transactions!$O$7:$O$520,Transactions!$F$7:$F$520,"Expense",Transactions!$P$7:$P$520,"AED",Transactions!$C$7:$C$520,$B$84,Transactions!$J$7:$J$520,"Household") -> 6028.4
A88: E29 · Personal / lifestyle spending this month | B88: =SUMIFS(Transactions!$O$7:$O$520,Transactions!$F$7:$F$520,"Expense",Transactions!$P$7:$P$520,"AED",Transactions!$C$7:$C$520,$B$84,Transactions!$J$7:$J$520,"Personal") -> 1559.25
A89: E30 · Days elapsed this month | B89: =DAY($B$9) -> 26
A90: E31 · Average daily spend — recurring | B90: =IF($B$89=0,0,($B$86-SUMIFS(Transactions!$O$7:$O$520,Transactions!$F$7:$F$520,"Expense",Transactions!$P$7:$P$520,"AED",Transactions!$C$7:$C$520,$B$84,Transactions!$O$7:$O$520,">=500",Transactions!$J$7:$J$520,"<>Business"))/$B$89) -> 119.99192 | D90: Day-to-day burn rate. Excludes reimbursable business outflows and single transactions of AED 500 or more (this month: the AED 1,430 airfare and the AED 914.93 utilities run). Threshold hardcoded at AED 500.
A91: E32 · Days left in this month | B91: =DAY(EOMONTH($B$9,0))-DAY($B$9) -> 5
A92: E33 · Remaining obligations this month | B92: =SUMIFS('Bills & Commitments'!$G$7:$G$80,'Bills & Commitments'!$D$7:$D$80,"Outflow",'Bills & Commitments'!$I$7:$I$80,"No",'Bills & Commitments'!$H$7:$H$80,"AED",'Bills & Commitments'!$A$7:$A$80,">="&$B$9,'Bills & Commitments'!$A$7:$A$80,"<="&EOMONTH($B$9,0)) -> 0
A93: E34 · Expected inflows remaining this month | B93: =SUMIFS('Bills & Commitments'!$G$7:$G$80,'Bills & Commitments'!$D$7:$D$80,"Inflow",'Bills & Commitments'!$I$7:$I$80,"No",'Bills & Commitments'!$H$7:$H$80,"AED",'Bills & Commitments'!$A$7:$A$80,">="&$B$9,'Bills & Commitments'!$A$7:$A$80,"<="&EOMONTH($B$9,0)) -> 0
A94: E35 · Projected month-end cash | B94: =$B$62+$B$93-$B$92-($B$90*$B$91) -> -443.15962 | D94: At the current burn rate
A95: E36 · Investments value (INR) | B95: =Investments!$F$12 -> 244917.52 | D95: MF Central snapshot
A96: E37 · Investments value (AED equivalent) | B96: =$B$95*$B$28 -> 9437.4803 | D96: At the Settings rate
A97: E38 · Total accessible assets (AED) | B97: =$B$115 -> 18910.502 | D97: Superseded by E56 — kept for backward formula compatibility
A98: E39 · Emergency fund balance | B98: =Accounts!$D$9 -> 7.67
A99: E40 · Emergency fund progress | B99: =IF($B$23=0,0,$B$98/$B$23) -> 0.00767
A100: E41 · Rent funding progress | B100: =IF($B$19=0,0,SUMIFS(Accounts!$E$7:$E$14,Accounts!$H$7:$H$14,"Rent vault")/$B$19) -> 0.50559149
A101: E42 · BNPL exposure | B101: =$B$32 -> 2687.36
A102: E43 · Next payment — amount | B102: =IFERROR(INDEX('Bills & Commitments'!$G$7:$G$80,MATCH(MIN('Bills & Commitments'!$S$7:$S$80),'Bills & Commitments'!$S$7:$S$80,0)),0) -> 462.4
A103: E44 · Next payment — name | B103: =IFERROR(INDEX('Bills & Commitments'!$B$7:$B$80,MATCH(MIN('Bills & Commitments'!$S$7:$S$80),'Bills & Commitments'!$S$7:$S$80,0)),"None") -> Nippon SIP — September
...

Sheet Accounts
A1: Accounts & Cash Control
A2: Money that exists · money already committed · money genuinely available. These three are never mixed.
A5: ACCOUNT REGISTER
A6: Account | B6: Type | C6: Currency | D6: Current Balance | E6: Reserved / Committed | F6: Available to Spend | G6: Counts as AED liquid cash? | H6: Purpose | I6: Last Updated | J6: Notes
A7: FAB 4001 Current | B7: Bank | C7: AED | D7: 14.95 | E7: 0 | F7: =D7-E7 -> 14.95 | G7: Yes | H7: Day-to-day spending | I7: 46260 | J7: Card XXXX1599. Emarat fuel (13.50), 18:20.
A8: FAB 4002 Home Expenditure | B8: Bank | C8: AED | D8: 5940.7 | E8: 5940.7 | F8: =D8-E8 -> 0 | G8: Yes | H8: Rent vault | I8: 46259 | J8: Rent vault. AED 150 moved out for home expenditure, per owner. 50.6% funded.
A9: FAB 4003 Emergency Fund | B9: Savings | C9: AED | D9: 7.67 | E9: =D9 -> 7.67 | F9: =D9-E9 -> 0 | G9: Yes | H9: Emergency fund | I9: 46245 | J9: Next milestone AED 1,000
A10: NBD Current | B10: Bank | C10: AED | D10: 138.23 | E10: 0 | F10: =D10-E10 -> 138.23 | G10: Yes | H10: Secondary current | I10: 46260 | J10: Card 3695. Cielo Kabab, Emarat 6192, Netflix (actual 36.09, not the ~35.00 shown) all cleared today.
A11: NBD Plus Saver | B11: Savings | C11: AED | D11: 2.73 | E11: 0 | F11: =D11-E11 -> 2.73 | G11: Yes | H11: Savings sub-account | I11: 46239 | J11: Includes AED 1.64 interest credit
A12: Tabby Cash | B12: Wallet | C12: AED | D12: 0.89 | E12: 0 | F12: =D12-E12 -> 0.89 | G12: Yes | H12: Funded wallet | I12: 46238 | J12: Wallet money — NOT Tabby Card borrowing
A13: Cash / Wio | B13: Cash | C13: AED | D13: 0 | E13: 0 | F13: =D13-E13 -> 0 | G13: Yes | H13: Physical cash | I13: 46245 | J13: No balance reported
A14: ICICI (INR) | B14: Bank | C14: INR | D14: 12388.51 | E14: 0 | F14: =D14-E14 -> 12388.51 | G14: No | H14: SIP funding account | I14: 46260 | J14: CONFIRMED via ICICI app screenshot, personal India account. Fresh remittance (INR 12,000 from today's SIP transfer) just landed. Monthly SIP auto-debit will pull ~12,000 from here, returning balance to ~388.51 until next month's remittance. Personal, not part of AED household calculations.
A15: TOTAL — AED liquid | D15: =SUMIFS(D7:D14,C7:C14,"AED",G7:G14,"Yes") -> 6105.17 | E15: =SUMIFS(E7:E14,C7:C14,"AED",G7:G14,"Yes") -> 5948.37 | F15: =D15-E15 -> 156.8 | H15: ="Ties to AED "&TEXT($D$15,"#,##0.00")&" — recomputed, never typed" -> Ties to AED 6,105.17 — recomputed, never typed
H16: FAB 4002 is now flagged as the rent vault, so its full balance is treated as committed. If any part of it is really a utilities float, lower the Reserved figure and the dashboard re-rates instantly.
A17: WHAT THE THREE COLUMNS MEAN
A18: Current Balance | B18: Money that exists in the account right now.
A19: Reserved / Committed | B19: Money physically present but already spoken for — rent vault and emergency fund. Spending it breaks a commitment.
A20: Available to Spend | B20: Balance minus reserved. This is the only number that may fund discretionary spending, and it is still reduced by upcoming bills on the dashboard.

Sheet Account History
A1: Account Balance History
A2: Every balance you've ever recorded, per account, over time. Add a new row each time you check a balance — the trend chart and per-account summary update automatically.
A5: BALANCE LOG · add a row per account per check-in | G5: LATEST BALANCE PER ACCOUNT · pulls the most recent dated entry for each
A6: Date | B6: Account | C6: Balance | D6: Change vs last entry | E6: Note | G6: Account | H6: Latest balance | I6: As of | J6: Entries logged
A7: 46229 | B7: FAB 4001 Current | D7: =IF($C7="","",IFERROR($C7-LOOKUP(2,1/(($B$7:$B6=$B7)*($A$7:$A6<$A7)),$C$7:$C6),"")) | E7: Approx. — DEWA July paid this date · Balance not recorded for this date; left blank so the latest-balance lookup skips it rather than returning text. | G7: FAB 4001 Current | H7: =IFERROR(LOOKUP(2,1/(($B$7:$B$100=$G7)*($C$7:$C$100<>"")),$C$7:$C$100),"No data") -> 14.95 | I7: =IFERROR(LOOKUP(2,1/(($B$7:$B$100=$G7)*($C$7:$C$100<>"")),$A$7:$A$100),"") -> 46260 | J7: =COUNTIF($B$7:$B$100,$G7) -> 4
A8: 46237 | B8: FAB 4001 Current | D8: =IF($C8="","",IFERROR($C8-LOOKUP(2,1/(($B$7:$B7=$B8)*($A$7:$A7<$A8)),$C$7:$C7),"")) | E8: du + Etisalat paid via DubaiPay · Balance not recorded for this date; left blank so the latest-balance lookup skips it rather than returning text. | G8: FAB 4002 Home Expenditure | H8: =IFERROR(LOOKUP(2,1/(($B$7:$B$100=$G8)*($C$7:$C$100<>"")),$C$7:$C$100),"No data") -> 5940.7 | I8: =IFERROR(LOOKUP(2,1/(($B$7:$B$100=$G8)*($C$7:$C$100<>"")),$A$7:$A$100),"") -> 46259 | J8: =COUNTIF($B$7:$B$100,$G8) -> 2
A9: 46238 | B9: NBD Plus Saver | C9: 2.73 | D9: =IF($C9="","",IFERROR($C9-LOOKUP(2,1/(($B$7:$B8=$B9)*($A$7:$A8<$A9)),$C$7:$C8),"")) | E9: Includes AED 1.64 interest credit | G9: FAB 4003 Emergency Fund | H9: =IFERROR(LOOKUP(2,1/(($B$7:$B$100=$G9)*($C$7:$C$100<>"")),$C$7:$C$100),"No data") -> 7.67 | I9: =IFERROR(LOOKUP(2,1/(($B$7:$B$100=$G9)*($C$7:$C$100<>"")),$A$7:$A$100),"") -> 46245 | J9: =COUNTIF($B$7:$B$100,$G9) -> 1
A10: 46238 | B10: Tabby Cash | C10: 0.89 | D10: =IF($C10="","",IFERROR($C10-LOOKUP(2,1/(($B$7:$B9=$B10)*($A$7:$A9<$A10)),$C$7:$C9),"")) | E10: Funded wallet | G10: NBD Current | H10: =IFERROR(LOOKUP(2,1/(($B$7:$B$100=$G10)*($C$7:$C$100<>"")),$C$7:$C$100),"No data") -> 138.23 | I10: =IFERROR(LOOKUP(2,1/(($B$7:$B$100=$G10)*($C$7:$C$100<>"")),$A$7:$A$100),"") -> 46260 | J10: =COUNTIF($B$7:$B$100,$G10) -> 4
A11: 46239 | B11: NBD Current | C11: 15.7 | D11: =IF($C11="","",IFERROR($C11-LOOKUP(2,1/(($B$7:$B10=$B11)*($A$7:$A10<$A11)),$C$7:$C10),"")) | E11: Last point before the unidentified AED 13.50 spend | G11: NBD Plus Saver | H11: =IFERROR(LOOKUP(2,1/(($B$7:$B$100=$G11)*($C$7:$C$100<>"")),$C$7:$C$100),"No data") -> 2.73 | I11: =IFERROR(LOOKUP(2,1/(($B$7:$B$100=$G11)*($C$7:$C$100<>"")),$A$7:$A$100),"") -> 46238 | J11: =COUNTIF($B$7:$B$100,$G11) -> 1
A12: 46240 | B12: NBD Current | C12: 2.2 | D12: =IF($C12="","",IFERROR($C12-LOOKUP(2,1/(($B$7:$B11=$B12)*($A$7:$A11<$A12)),$C$7:$C11),"")) -> -13.5 | E12: Last reported before the workbook was built | G12: Tabby Cash | H12: =IFERROR(LOOKUP(2,1/(($B$7:$B$100=$G12)*($C$7:$C$100<>"")),$C$7:$C$100),"No data") -> 0.89 | I12: =IFERROR(LOOKUP(2,1/(($B$7:$B$100=$G12)*($C$7:$C$100<>"")),$A$7:$A$100),"") -> 46238 | J12: =COUNTIF($B$7:$B$100,$G12) -> 1
A13: 46244 | B13: ICICI (INR) | C13: 388.51 | D13: =IF($C13="","",IFERROR($C13-LOOKUP(2,1/(($B$7:$B12=$B13)*($A$7:$A12<$A13)),$C$7:$C12),"")) | E13: After four Nippon SIPs completed | G13: Cash / Wio | H13: =IFERROR(LOOKUP(2,1/(($B$7:$B$100=$G13)*($C$7:$C$100<>"")),$C$7:$C$100),"No data") -> 0 | I13: =IFERROR(LOOKUP(2,1/(($B$7:$B$100=$G13)*($C$7:$C$100<>"")),$A$7:$A$100),"") -> 46245 | J13: =COUNTIF($B$7:$B$100,$G13) -> 1
A14: 46245 | B14: FAB 4001 Current | C14: 245.09 | D14: =IF($C14="","",IFERROR($C14-LOOKUP(2,1/(($B$7:$B13=$B14)*($A$7:$A13<$A14)),$C$7:$C13),"")) -> 245.09 | E14: Confirmed by the FAB app — card XXXX1599 | G14: ICICI (INR) | H14: =IFERROR(LOOKUP(2,1/(($B$7:$B$100=$G14)*($C$7:$C$100<>"")),$C$7:$C$100),"No data") -> 12388.51 | I14: =IFERROR(LOOKUP(2,1/(($B$7:$B$100=$G14)*($C$7:$C$100<>"")),$A$7:$A$100),"") -> 46260 | J14: =COUNTIF($B$7:$B$100,$G14) -> 2
A15: 46245 | B15: FAB 4002 Home Expenditure | C15: 4004.61 | D15: =IF($C15="","",IFERROR($C15-LOOKUP(2,1/(($B$7:$B14=$B15)*($A$7:$A14<$A15)),$C$7:$C14),"")) | E15: Confirmed by the FAB app — designated rent vault
A16: 46245 | B16: FAB 4003 Emergency Fund | C16: 7.67 | D16: =IF($C16="","",IFERROR($C16-LOOKUP(2,1/(($B$7:$B15=$B16)*($A$7:$A15<$A16)),$C$7:$C15),"")) | E16: Confirmed by the FAB app
A17: 46245 | B17: NBD Current | C17: 2.2 | D17: =IF($C17="","",IFERROR($C17-LOOKUP(2,1/(($B$7:$B16=$B17)*($A$7:$A16<$A17)),$C$7:$C16),"")) -> 0 | E17: Confirmed
A18: 46245 | B18: Cash / Wio | C18: 0 | D18: =IF($C18="","",IFERROR($C18-LOOKUP(2,1/(($B$7:$B17=$B18)*($A$7:$A17<$A18)),$C$7:$C17),"")) | E18: No balance reported
A19: 46259 | B19: FAB 4002 Home Expenditure | C19: 5940.7 | D19: =IF($C19="","",IFERROR($C19-LOOKUP(2,1/(($B$7:$B18=$B19)*($A$7:$A18<$A19)),$C$7:$C18),"")) -> 1936.09 | E19: Confirmed on the Accounts sheet. AED 150 moved out for home expenditure.
A20: 46260 | B20: FAB 4001 Current | C20: 14.95 | D20: =IF($C20="","",IFERROR($C20-LOOKUP(2,1/(($B$7:$B19=$B20)*($A$7:$A19<$A20)),$C$7:$C19),"")) -> -230.14 | E20: Confirmed on the Accounts sheet. Card XXXX1599, Emarat fuel 13.50 at 18:20.
A21: 46260 | B21: NBD Current | C21: 138.23 | D21: =IF($C21="","",IFERROR($C21-LOOKUP(2,1/(($B$7:$B20=$B21)*($A$7:$A20<$A21)),$C$7:$C20),"")) -> 136.03 | E21: Confirmed on the Accounts sheet. Cielo Kabab, Emarat 6192 and Netflix 36.09 cleared.
A22: 46260 | B22: ICICI (INR) | C22: 12388.51 | D22: =IF($C22="","",IFERROR($C22-LOOKUP(2,1/(($B$7:$B21=$B22)*($A$7:$A21<$A22)),$C$7:$C21),"")) -> 12000 | E22: Confirmed via the ICICI app. Fresh INR 12,000 remittance landed for the SIP.
D23: =IF($C23="","",IFERROR($C23-LOOKUP(2,1/(($B$7:$B22=$B23)*($A$7:$A22<$A23)),$C$7:$C22),""))
A24: The latest-balance summary now sits to the right, at column G — it had to move out of columns A–E because it was reading the very range it lives in. Rows below here are free for new log entries.
D25: =IF($C25="","",IFERROR($C25-LOOKUP(2,1/(($B$7:$B24=$B25)*($A$7:$A24<$A25)),$C$7:$C24),""))
D26: =IF($C26="","",IFERROR($C26-LOOKUP(2,1/(($B$7:$B25=$B26)*($A$7:$A25<$A26)),$C$7:$C25),""))
D27: =IF($C27="","",IFERROR($C27-LOOKUP(2,1/(($B$7:$B26=$B27)*($A$7:$A26<$A27)),$C$7:$C26),""))
D28: =IF($C28="","",IFERROR($C28-LOOKUP(2,1/(($B$7:$B27=$B28)*($A$7:$A27<$A28)),$C$7:$C27),""))
D29: =IF($C29="","",IFERROR($C29-LOOKUP(2,1/(($B$7:$B28=$B29)*($A$7:$A28<$A29)),$C$7:$C28),""))
D30: =IF($C30="","",IFERROR($C30-LOOKUP(2,1/(($B$7:$B29=$B30)*($A$7:$A29<$A30)),$C$7:$C29),""))
D31: =IF($C31="","",IFERROR($C31-LOOKUP(2,1/(($B$7:$B30=$B31)*($A$7:$A30<$A31)),$C$7:$C30),""))
D32: =IF($C32="","",IFERROR($C32-LOOKUP(2,1/(($B$7:$B31=$B32)*($A$7:$A31<$A32)),$C$7:$C31),""))
D33: =IF($C33="","",IFERROR($C33-LOOKUP(2,1/(($B$7:$B32=$B33)*($A$7:$A32<$A33)),$C$7:$C32),""))
D34: =IF($C34="","",IFERROR($C34-LOOKUP(2,1/(($B$7:$B33=$B34)*($A$7:$A33<$A34)),$C$7:$C33),""))
D35: =IF($C35="","",IFERROR($C35-LOOKUP(2,1/(($B$7:$B34=$B35)*($A$7:$A34<$A35)),$C$7:$C34),""))
D36: =IF($C36="","",IFERROR($C36-LOOKUP(2,1/(($B$7:$B35=$B36)*($A$7:$A35<$A36)),$C$7:$C35),""))
... D100: =IF($C100="","",IFERROR($C100-LOOKUP(2,1/(($B$7:$B99=$B100)*($A$7:$A99<$A100)),$C$7:$C99),""))

Sheet Transactions
A1: Master Transaction Database
A2: One row per movement of money. Type your entry in the first empty row — grey columns fill themselves. Transfers never count as spending.
A4: QUICK ADD → you only need to fill: Date · Account · Type · Category · Merchant · Amount. Everything else is optional or automatic.
A6: ID | B6: Date | C6: Month | D6: Year | E6: Account | F6: Type | G6: Category | H6: Subcategory | I6: Merchant / Payee | J6: Class | K6: Fixed / Var | L6: Essential? | M6: Payment Method | N6: Recurring? | O6: Amount | P6: Currency | Q6: Cash Impact (AED) | R6: Related Bill | S6: Verified? | T6: Notes | U6: Original timestamp
A7: =IF($B7="","","T"&TEXT(ROW()-6,"0000")) -> T1.00 | B7: 46237 | C7: =IF($B7="","",TEXT($B7,"YYYY-MM")) -> 2026-08 | D7: =IF($B7="","",YEAR($B7)) -> 2026 | E7: FAB 4001 Current | F7: Expense | G7: Utilities | H7: du + Etisalat | I7: du + Etisalat via DubaiPay | J7: Household | K7: Fixed | L7: Essential | M7: Card | N7: Yes | O7: 914.93 | P7: AED | Q7: =IF($B7="","",IF($P7<>"AED",0,IF($F7="Income",$O7,IF($F7="Expense",-$O7,0)))) -> -914.93 | R7: du August | S7: Yes | T7: Paid once — du 590.98 + Etisalat 323.95 | U7: 2026-08-03 11:20
A8: =IF($B8="","","T"&TEXT(ROW()-6,"0000")) -> T2.00 | B8: 46237 | C8: =IF($B8="","",TEXT($B8,"YYYY-MM")) -> 2026-08 | D8: =IF($B8="","",YEAR($B8)) -> 2026 | E8: NBD Current | F8: Expense | G8: Lifestyle | H8: Convenience store | I8: Asas Al Madina General | J8: Personal | K8: Variable | L8: Non-Essential | M8: Card | N8: No | O8: 14 | P8: AED | Q8: =IF($B8="","",IF($P8<>"AED",0,IF($F8="Income",$O8,IF($F8="Expense",-$O8,0)))) -> -14 | S8: Yes | U8: 2026-08-03 12:00
A9: =IF($B9="","","T"&TEXT(ROW()-6,"0000")) -> T3.00 | B9: 46237 | C9: =IF($B9="","",TEXT($B9,"YYYY-MM")) -> 2026-08 | D9: =IF($B9="","",YEAR($B9)) -> 2026 | E9: NBD Current | F9: Expense | G9: Household Other | H9: Home supplies | I9: Yas Home General Trading | J9: Household | K9: Variable | L9: Essential | M9: Card | N9: No | O9: 22.97 | P9: AED | Q9: =IF($B9="","",IF($P9<>"AED",0,IF($F9="Income",$O9,IF($F9="Expense",-$O9,0)))) -> -22.97 | S9: Yes | U9: 2026-08-03 13:00
A10: =IF($B10="","","T"&TEXT(ROW()-6,"0000")) -> T4.00 | B10: 46237 | C10: =IF($B10="","",TEXT($B10,"YYYY-MM")) -> 2026-08 | D10: =IF($B10="","",YEAR($B10)) -> 2026 | E10: NBD Current | F10: Expense | G10: Food & Dining | H10: Restaurant | I10: Spicy Falcon Restaurant | J10: Household | K10: Variable | L10: Non-Essential | M10: Card | N10: No | O10: 16 | P10: AED | Q10: =IF($B10="","",IF($P10<>"AED",0,IF($F10="Income",$O10,IF($F10="Expense",-$O10,0)))) -> -16 | S10: Yes | U10: 2026-08-03 20:04
A11: =IF($B11="","","T"&TEXT(ROW()-6,"0000")) -> T5.00 | B11: 46238 | C11: =IF($B11="","",TEXT($B11,"YYYY-MM")) -> 2026-08 | D11: =IF($B11="","",YEAR($B11)) -> 2026 | E11: NBD Current | F11: Expense | G11: Lifestyle | H11: Fuel / convenience | I11: Emarat Nad Al Hamar | J11: Personal | K11: Variable | L11: Non-Essential | M11: Card | N11: No | O11: 13.5 | P11: AED | Q11: =IF($B11="","",IF($P11<>"AED",0,IF($F11="Income",$O11,IF($F11="Expense",-$O11,0)))) -> -13.5 | S11: Yes | U11: 2026-08-04 04:42
A12: =IF($B12="","","T"&TEXT(ROW()-6,"0000")) -> T6.00 | B12: 46238 | C12: =IF($B12="","",TEXT($B12,"YYYY-MM")) -> 2026-08 | D12: =IF($B12="","",YEAR($B12)) -> 2026 | E12: Tabby Cash | F12: Expense | G12: Lifestyle | H12: Convenience store | I12: Nad Al Hamar Star Grocery | J12: Personal | K12: Variable | L12: Non-Essential | M12: Wallet | N12: No | O12: 2 | P12: AED | Q12: =IF($B12="","",IF($P12<>"AED",0,IF($F12="Income",$O12,IF($F12="Expense",-$O12,0)))) -> -2 | S12: Yes | T12: Tabby Cash wallet — never Tabby Card debt | U12: 2026-08-04 05:00
A13: =IF($B13="","","T"&TEXT(ROW()-6,"0000")) -> T7.00 | B13: 46238 | C13: =IF($B13="","",TEXT($B13,"YYYY-MM")) -> 2026-08 | D13: =IF($B13="","",YEAR($B13)) -> 2026 | E13: NBD Current | F13: Expense | G13: Groceries | H13: Grocery | I13: Asas Al Madina General | J13: Household | K13: Variable | L13: Essential | M13: Card | N13: No | O13: 24.5 | P13: AED | Q13: =IF($B13="","",IF($P13<>"AED",0,IF($F13="Income",$O13,IF($F13="Expense",-$O13,0)))) -> -24.5 | S13: Yes | U13: 2026-08-04 08:00
A14: =IF($B14="","","T"&TEXT(ROW()-6,"0000")) -> T8.00 | B14: 46239 | C14: =IF($B14="","",TEXT($B14,"YYYY-MM")) -> 2026-08 | D14: =IF($B14="","",YEAR($B14)) -> 2026 | E14: NBD Current | F14: Expense | G14: Entertainment | H14: Cinema | I14: Reel Entertainment | J14: Personal | K14: Variable | L14: Non-Essential | M14: Card | N14: No | O14: 20 | P14: AED | Q14: =IF($B14="","",IF($P14<>"AED",0,IF($F14="Income",$O14,IF($F14="Expense",-$O14,0)))) -> -20 | S14: Yes | T14: Reclassified from Household Other — this is discretionary | U14: 2026-08-05 07:48
A15: =IF($B15="","","T"&TEXT(ROW()-6,"0000")) -> T9.00 | B15: 46239 | C15: =IF($B15="","",TEXT($B15,"YYYY-MM")) -> 2026-08 | D15: =IF($B15="","",YEAR($B15)) -> 2026 | E15: NBD Current | F15: Expense | G15: Food & Dining | H15: Cafe | I15: HNS Restaurant and Cafe | J15: Household | K15: Variable | L15: Non-Essential | M15: Card | N15: No | O15: 10 | P15: AED | Q15: =IF($B15="","",IF($P15<>"AED",0,IF($F15="Income",$O15,IF($F15="Expense",-$O15,0)))) -> -10 | S15: Yes | U15: 2026-08-05 10:46
A16: =IF($B16="","","T"&TEXT(ROW()-6,"0000")) -> T10.00 | B16: 46239 | C16: =IF($B16="","",TEXT($B16,"YYYY-MM")) -> 2026-08 | D16: =IF($B16="","",YEAR($B16)) -> 2026 | E16: NBD Current | F16: Expense | G16: Food & Dining | H16: Fast food | I16: Burger King Dubai Mall | J16: Household | K16: Variable | L16: Non-Essential | M16: Card | N16: No | O16: 10 | P16: AED | Q16: =IF($B16="","",IF($P16<>"AED",0,IF($F16="Income",$O16,IF($F16="Expense",-$O16,0)))) -> -10 | S16: Yes | U16: 2026-08-05 10:47
A17: =IF($B17="","","T"&TEXT(ROW()-6,"0000")) -> T11.00 | B17: 46239 | C17: =IF($B17="","",TEXT($B17,"YYYY-MM")) -> 2026-08 | D17: =IF($B17="","",YEAR($B17)) -> 2026 | E17: NBD Current | F17: Expense | G17: Food & Dining | H17: Fast food | I17: Texas Dubai Mall | J17: Household | K17: Variable | L17: Non-Essential | M17: Card | N17: No | O17: 10 | P17: AED | Q17: =IF($B17="","",IF($P17<>"AED",0,IF($F17="Income",$O17,IF($F17="Expense",-$O17,0)))) -> -10 | S17: Yes | U17: 2026-08-05 10:48
A18: =IF($B18="","","T"&TEXT(ROW()-6,"0000")) -> T12.00 | B18: 46239 | C18: =IF($B18="","",TEXT($B18,"YYYY-MM")) -> 2026-08 | D18: =IF($B18="","",YEAR($B18)) -> 2026 | E18: NBD Current | F18: Expense | G18: Food & Dining | H18: Restaurant | I18: Team Taste Restaurant | J18: Household | K18: Variable | L18: Non-Essential | M18: Card | N18: No | O18: 31 | P18: AED | Q18: =IF($B18="","",IF($P18<>"AED",0,IF($F18="Income",$O18,IF($F18="Expense",-$O18,0)))) -> -31 | S18: Yes | U18: 2026-08-05 15:22
A19: =IF($B19="","","T"&TEXT(ROW()-6,"0000")) -> T13.00 | B19: 46239 | C19: =IF($B19="","",TEXT($B19,"YYYY-MM")) -> 2026-08 | D19: =IF($B19="","",YEAR($B19)) -> 2026 | E19: NBD Current | F19: Expense | G19: Groceries | H19: Supermarket | I19: Raya Al Talal Supermarket | J19: Household | K19: Variable | L19: Essential | M19: Card | N19: No | O19: 10.25 | P19: AED | Q19: =IF($B19="","",IF($P19<>"AED",0,IF($F19="Income",$O19,IF($F19="Expense",-$O19,0)))) -> -10.25 | S19: Yes | U19: 2026-08-05 15:23
A20: =IF($B20="","","T"&TEXT(ROW()-6,"0000")) -> T14.00 | B20: 46239 | C20: =IF($B20="","",TEXT($B20,"YYYY-MM")) -> 2026-08 | D20: =IF($B20="","",YEAR($B20)) -> 2026 | E20: FAB 4001 Current | F20: Expense | G20: Lifestyle | H20: Convenience store | I20: Asas Al Madina General | J20: Personal | K20: Variable | L20: Non-Essential | M20: Card | N20: No | O20: 14 | P20: AED | Q20: =IF($B20="","",IF($P20<>"AED",0,IF($F20="Income",$O20,IF($F20="Expense",-$O20,0)))) -> -14 | S20: Yes | U20: 2026-08-05 15:49
A21: =IF($B21="","","T"&TEXT(ROW()-6,"0000")) -> T15.00 | B21: 46240 | C21: =IF($B21="","",TEXT($B21,"YYYY-MM")) -> 2026-08 | D21: =IF($B21="","",YEAR($B21)) -> 2026 | E21: FAB 4001 Current | F21: Expense | G21: Groceries | H21: Grocery | I21: Asas Al Madina General | J21: Household | K21: Variable | L21: Essential | M21: Card | N21: No | O21: 20 | P21: AED | Q21: =IF($B21="","",IF($P21<>"AED",0,IF($F21="Income",$O21,IF($F21="Expense",-$O21,0)))) -> -20 | S21: Yes | U21: 2026-08-06 16:43
A22: =IF($B22="","","T"&TEXT(ROW()-6,"0000")) -> T16.00 | B22: 46240 | C22: =IF($B22="","",TEXT($B22,"YYYY-MM")) -> 2026-08 | D22: =IF($B22="","",YEAR($B22)) -> 2026 | E22: FAB 4002 Home Expenditure | F22: Income | G22: Salary | H22: Advance | I22: Advance salary + ticket refund profit | J22: Income | K22: Fixed | L22: Essential | M22: Bank credit | N22: Yes | O22: 4000 | P22: AED | Q22: =IF($B22="","",IF($P22<>"AED",0,IF($F22="Income",$O22,IF($F22="Expense",-$O22,0)))) -> 4000 | R22: Remaining August payday | S22: Yes | T22: AED 3,740 early salary + AED 260 profit from the ticket refund = AED 4,000, landing in FAB 4002 (the rent vault), not 4001. Counts against the 26 Aug payday. | U22: 2026-08-06 20:56
A23: =IF($B23="","","T"&TEXT(ROW()-6,"0000")) | C23: =IF($B23="","",TEXT($B23,"YYYY-MM")) | D23: =IF($B23="","",YEAR($B23)) | Q23: =IF($B23="","",IF($P23<>"AED",0,IF($F23="Income",$O23,IF($F23="Expense",-$O23,0)))) | S23: No
A24: =IF($B24="","","T"&TEXT(ROW()-6,"0000")) -> T18.00 | B24: 46241 | C24: =IF($B24="","",TEXT($B24,"YYYY-MM")) -> 2026-08 | D24: =IF($B24="","",YEAR($B24)) -> 2026 | E24: FAB 4001 Current | F24: Expense | G24: Family Support | H24: Medical support | I24: e& Money medical support | J24: Household | K24: Variable | L24: Essential | M24: Transfer | N24: No | O24: 100 | P24: AED | Q24: =IF($B24="","",IF($P24<>"AED",0,IF($F24="Income",$O24,IF($F24="Expense",-$O24,0)))) -> -100 | S24: Yes | U24: 2026-08-07 06:00
A25: =IF($B25="","","T"&TEXT(ROW()-6,"0000")) -> T19.00 | B25: 46241 | C25: =IF($B25="","",TEXT($B25,"YYYY-MM")) -> 2026-08 | D25: =IF($B25="","",YEAR($B25)) -> 2026 | E25: FAB 4001 Current | F25: Transfer Out | G25: Internal Transfer | H25: Duplicate transfer | I25: Duplicate e& Money transfer | J25: Internal | K25: Variable | L25: Essential | M25: Transfer | N25: No | O25: 100 | P25: AED | Q25: =IF($B25="","",IF($P25<>"AED",0,IF($F25="Income",$O25,IF($F25="Expense",-$O25,0)))) -> 0 | S25: Yes | T25: Receivable — refunded 11 Aug. Never an expense | U25: 2026-08-07 06:01
A26: =IF($B26="","","T"&TEXT(ROW()-6,"0000")) -> T20.00 | B26: 46245 | C26: =IF($B26="","",TEXT($B26,"YYYY-MM")) -> 2026-08 | D26: =IF($B26="","",YEAR($B26)) -> 2026 | E26: NBD Current | F26: Expense | G26: Lifestyle | H26: Unidentified card spend | I26: NBD card — merchant not identified | J26: Personal | K26: Variable | L26: Non-Essential | M26: Card | N26: No | O26: 13.5 | P26: AED | Q26: =IF($B26="","",IF($P26<>"AED",0,IF($F26="Income",$O26,IF($F26="Expense",-$O26,0)))) -> -13.5 | S26: No | T26: Identified from the NBD balance trail (15.70 recorded vs 2.20 actual). Confirm the merchant. | U26: 2026-08-11 (from balance trail)
A27: =IF($B27="","","T"&TEXT(ROW()-6,"0000")) -> T21.00 | B27: 46241 | C27: =IF($B27="","",TEXT($B27,"YYYY-MM")) -> 2026-08 | D27: =IF($B27="","",YEAR($B27)) -> 2026 | E27: FAB 4001 Current | F27: Expense | G27: Travel & Airfare | H27: Airfare | I27: Emirates ticket | J27: Household | K27: Variable | L27: Essential | M27: Card | N27: No | O27: 1430 | P27: AED | Q27: =IF($B27="","",IF($P27<>"AED",0,IF($F27="Income",$O27,IF($F27="Expense",-$O27,0)))) -> -1430 | R27: Rent refund | S27: Yes | T27: Refund of AED 1,430 expected — treated as a future inflow, not netted here | U27: 2026-08-07 15:54
A28: =IF($B28="","","T"&TEXT(ROW()-6,"0000")) -> T22.00 | B28: 46242 | C28: =IF($B28="","",TEXT($B28,"YYYY-MM")) -> 2026-08 | D28: =IF($B28="","",YEAR($B28)) -> 2026 | E28: FAB 4001 Current | F28: Expense | G28: Lifestyle | H28: Convenience store | I28: Asas Al Madina General | J28: Personal | K28: Variable | L28: Non-Essential | M28: Card | N28: No | O28: 14 | P28: AED | Q28: =IF($B28="","",IF($P28<>"AED",0,IF($F28="Income",$O28,IF($F28="Expense",-$O28,0)))) -> -14 | S28: Yes | U28: 2026-08-08 07:36
A29: =IF($B29="","","T"&TEXT(ROW()-6,"0000")) -> T23.00 | B29: 46242 | C29: =IF($B29="","",TEXT($B29,"YYYY-MM")) -> 2026-08 | D29: =IF($B29="","",YEAR($B29)) -> 2026 | E29: FAB 4001 Current | F29: Expense | G29: Lifestyle | H29: Hotel / leisure | I29: RTS Business Bay Hotel | J29: Personal | K29: Variable | L29: Non-Essential | M29: Card | N29: No | O29: 65 | P29: AED | Q29: =IF($B29="","",IF($P29<>"AED",0,IF($F29="Income",$O29,IF($F29="Expense",-$O29,0)))) -> -65 | S29: Yes | U29: 2026-08-08 15:45
A30: =IF($B30="","","T"&TEXT(ROW()-6,"0000")) -> T24.00 | B30: 46242 | C30: =IF($B30="","",TEXT($B30,"YYYY-MM")) -> 2026-08 | D30: =IF($B30="","",YEAR($B30)) -> 2026 | E30: FAB 4001 Current | F30: Expense | G30: Lifestyle | H30: Hotel / leisure | I30: RTS Business Bay Hotel | J30: Personal | K30: Variable | L30: Non-Essential | M30: Card | N30: No | O30: 47.25 | P30: AED | Q30: =IF($B30="","",IF($P30<>"AED",0,IF($F30="Income",$O30,IF($F30="Expense",-$O30,0)))) -> -47.25 | S30: Yes | U30: 2026-08-08 17:24
A31: =IF($B31="","","T"&TEXT(ROW()-6,"0000")) -> T25.00 | B31: 46242 | C31: =IF($B31="","",TEXT($B31,"YYYY-MM")) -> 2026-08 | D31: =IF($B31="","",YEAR($B31)) -> 2026 | E31: FAB 4001 Current | F31: Expense | G31: Lifestyle | H31: Hotel / leisure | I31: RTS Business Bay Hotel | J31: Personal | K31: Variable | L31: Non-Essential | M31: Card | N31: No | O31: 274.5 | P31: AED | Q31: =IF($B31="","",IF($P31<>"AED",0,IF($F31="Income",$O31,IF($F31="Expense",-$O31,0)))) -> -274.5 | S31: Yes | T31: Third charge same venue same day — AED 386.75 total on 08 Aug | U31: 2026-08-08 17:42
A32: =IF($B32="","","T"&TEXT(ROW()-6,"0000")) -> T26.00 | B32: 46242 | C32: =IF($B32="","",TEXT($B32,"YYYY-MM")) -> 2026-08 | D32: =IF($B32="","",YEAR($B32)) -> 2026 | E32: FAB 4001 Current | F32: Expense | G32: Lifestyle | H32: Convenience store | I32: Asas Al Madina General | J32: Personal | K32: Variable | L32: Non-Essential | M32: Card | N32: No | O32: 20.5 | P32: AED | Q32: =IF($B32="","",IF($P32<>"AED",0,IF($F32="Income",$O32,IF($F32="Expense",-$O32,0)))) -> -20.5 | S32: Yes | U32: 2026-08-08 20:03
A33: =IF($B33="","","T"&TEXT(ROW()-6,"0000")) -> T27.00 | B33: 46243 | C33: =IF($B33="","",TEXT($B33,"YYYY-MM")) -> 2026-08 | D33: =IF($B33="","",YEAR($B33)) -> 2026 | E33: FAB 4001 Current | F33: Expense | G33: Food & Dining | H33: Restaurant | I33: Salkara / Team Taste | J33: Household | K33: Variable | L33: Non-Essential | M33: Card | N33: No | O33: 101.5 | P33: AED | Q33: =IF($B33="","",IF($P33<>"AED",0,IF($F33="Income",$O33,IF($F33="Expense",-$O33,0)))) -> -101.5 | S33: Yes | U33: 2026-08-09 09:43
A34: =IF($B34="","","T"&TEXT(ROW()-6,"0000")) -> T28.00 | B34: 46243 | C34: =IF($B34="","",TEXT($B34,"YYYY-MM")) -> 2026-08 | D34: =IF($B34="","",YEAR($B34)) -> 2026 | E34: FAB 4001 Current | F34: Expense | G34: Lifestyle | H34: Convenience store | I34: Shams Al Qusais Grocery | J34: Personal | K34: Variable | L34: Non-Essential | M34: Card | N34: No | O34: 10 | P34: AED | Q34: =IF($B34="","",IF($P34<>"AED",0,IF($F34="Income",$O34,IF($F34="Expense",-$O34,0)))) -> -10 | S34: Yes | U34: 2026-08-09 15:37
A35: =IF($B35="","","T"&TEXT(ROW()-6,"0000")) -> T29.00 | B35: 46243 | C35: =IF($B35="","",TEXT($B35,"YYYY-MM")) -> 2026-08 | D35: =IF($B35="","",YEAR($B35)) -> 2026 | E35: FAB 4001 Current | F35: Expense | G35: Transport | H35: Fuel | I35: ENOC Site 1006 | J35: Household | K35: Variable | L35: Essential | M35: Card | N35: No | O35: 50 | P35: AED | Q35: =IF($B35="","",IF($P35<>"AED",0,IF($F35="Income",$O35,IF($F35="Expense",-$O35,0)))) -> -50 | S35: Yes | U35: 2026-08-09 15:49
A36: =IF($B36="","","T"&TEXT(ROW()-6,"0000")) -> T30.00 | B36: 46244 | C36: =IF($B36="","",TEXT($B36,"YYYY-MM")) -> 2026-08 | D36: =IF($B36="","",YEAR($B36)) -> 2026 | E36: FAB 4001 Current | F36: Expense | G36: Lifestyle | H36: Fuel / convenience | I36: Emarat Nad Al Hamar | J36: Personal | K36: Variable | L36: Non-Essential | M36: Card | N36: No | O36: 13.5 | P36: AED | Q36: =IF($B36="","",IF($P36<>"AED",0,IF($F36="Income",$O36,IF($F36="Expense",-$O36,0)))) -> -13.5 | S36: Yes | U36: 2026-08-10 07:49
A37: =IF($B37="","","T"&TEXT(ROW()-6,"0000")) -> T31.00 | B37: 46244 | C37: =IF($B37="","",TEXT($B37,"YYYY-MM")) -> 2026-08 | D37: =IF($B37="","",YEAR($B37)) -> 2026 | E37: FAB 4001 Current | F37: Expense | G37: Food & Dining | H37: Restaurant | I37: Jamahir Al Khair Restaurant | J37: Household | K37: Variable | L37: Non-Essential | M37: Card | N37: No | O37: 27 | P37: AED | Q37: =IF($B37="","",IF($P37<>"AED",0,IF($F37="Income",$O37,IF($F37="Expense",-$O37,0)))) -> -27 | S37: Yes | U37: 2026-08-10 10:37
A38: =IF($B38="","","T"&TEXT(ROW()-6,"0000")) -> T32.00 | B38: 46244 | C38: =IF($B38="","",TEXT($B38,"YYYY-MM")) -> 2026-08 | D38: =IF($B38="","",YEAR($B38)) -> 2026 | E38: FAB 4001 Current | F38: Expense | G38: Groceries | H38: Grocery | I38: Asas Al Madina General | J38: Household | K38: Variable | L38: Essential | M38: Card | N38: No | O38: 23 | P38: AED | Q38: =IF($B38="","",IF($P38<>"AED",0,IF($F38="Income",$O38,IF($F38="Expense",-$O38,0)))) -> -23 | S38: Yes | U38: 2026-08-10 13:29
A39: =IF($B39="","","T"&TEXT(ROW()-6,"0000")) -> T33.00 | B39: 46244 | C39: =IF($B39="","",TEXT($B39,"YYYY-MM")) -> 2026-08 | D39: =IF($B39="","",YEAR($B39)) -> 2026 | E39: FAB 4001 Current | F39: Expense | G39: Food & Dining | H39: Delivery | I39: Zomato | J39: Household | K39: Variable | L39: Non-Essential | M39: Card | N39: No | O39: 66.52 | P39: AED | Q39: =IF($B39="","",IF($P39<>"AED",0,IF($F39="Income",$O39,IF($F39="Expense",-$O39,0)))) -> -66.52 | S39: Yes | U39: 2026-08-10 15:51
A40: =IF($B40="","","T"&TEXT(ROW()-6,"0000")) -> T34.00 | B40: 46244 | C40: =IF($B40="","",TEXT($B40,"YYYY-MM")) -> 2026-08 | D40: =IF($B40="","",YEAR($B40)) -> 2026 | E40: ICICI (INR) | F40: Expense | G40: Investments | H40: Nippon SIP | I40: Four Nippon SIPs INR 12,000 | J40: Financial | K40: Fixed | L40: Essential | M40: Auto-debit | N40: Yes | O40: 12000 | P40: INR | Q40: =IF($B40="","",IF($P40<>"AED",0,IF($F40="Income",$O40,IF($F40="Expense",-$O40,0)))) -> 0 | R40: Nippon SIP Aug | S40: Yes | T40: INR — excluded from AED cash impact by design | U40: 2026-08-10
A41: =IF($B41="","","T"&TEXT(ROW()-6,"0000")) -> T35.00 | B41: 46245 | C41: =IF($B41="","",TEXT($B41,"YYYY-MM")) -> 2026-08 | D41: =IF($B41="","",YEAR($B41)) -> 2026 | E41: FAB 4001 Current | F41: Transfer In | G41: Internal Transfer | H41: Refund of duplicate | I41: Duplicate e& Money transfer refund | J41: Internal | K41: Variable | L41: Essential | M41: Transfer | N41: No | O41: 100 | P41: AED | Q41: =IF($B41="","",IF($P41<>"AED",0,IF($F41="Income",$O41,IF($F41="Expense",-$O41,0)))) -> 0 | S41: Yes | T41: Refund — never income | U41: 2026-08-11 08:00
A42: =IF($B42="","","T"&TEXT(ROW()-6,"0000")) -> T36.00 | B42: 46245 | C42: =IF($B42="","",TEXT($B42,"YYYY-MM")) -> 2026-08 | D42: =IF($B42="","",YEAR($B42)) -> 2026 | E42: FAB 4001 Current | F42: Expense | G42: Lifestyle | H42: Convenience store | I42: Asas Al Madina General | J42: Personal | K42: Variable | L42: Non-Essential | M42: Card | N42: No | O42: 14 | P42: AED | Q42: =IF($B42="","",IF($P42<>"AED",0,IF($F42="Income",$O42,IF($F42="Expense",-$O42,0)))) -> -14 | S42: Yes | T42: Card XXXX1599 · balance after AED 245.09 — confirms FAB 4001 is the spending account | U42: 2026-08-11 10:02
A43: =IF($B43="","","T"&TEXT(ROW()-6,"0000")) -> T37.00 | B43: 46246 | C43: =IF($B43="","",TEXT($B43,"YYYY-MM")) -> 2026-08 | D43: =IF($B43="","",YEAR($B43)) -> 2026 | E43: FAB 4001 Current | F43: Income | G43: Refund / Reimbursement | H43: Combined remittance | I43: Rent refund (1,430) + advance salary 2nd portion (1,540) | J43: Income | K43: Variable | L43: Essential | M43: Bank credit | N43: No | O43: 3000 | P43: AED | Q43: =IF($B43="","",IF($P43<>"AED",0,IF($F43="Income",$O43,IF($F43="Expense",-$O43,0)))) -> 3000 | S43: No | T43: Bank notification: inward remittance AED 3,000, 12 Aug, balance after AED 3,206.09. Expected 1,430+1,540=2,970 — AED 30 surplus unexplained. Balance also implies ~AED 39 of unlogged spending between 11-12 Aug — REQUIRES VERIFICATION. | U43: 2026-08-12 (bank notification)
A44: =IF($B44="","","T"&TEXT(ROW()-6,"0000")) -> T38.00 | B44: 46245 | C44: =IF($B44="","",TEXT($B44,"YYYY-MM")) -> 2026-08 | D44: =IF($B44="","",YEAR($B44)) -> 2026 | E44: FAB 4001 Current | F44: Expense | G44: Lifestyle | H44: Convenience store | I44: Asas Al Madina General | J44: Personal | K44: Variable | L44: Non-Essential | M44: Card | N44: No | O44: 19 | P44: AED | Q44: =IF($B44="","",IF($P44<>"AED",0,IF($F44="Income",$O44,IF($F44="Expense",-$O44,0)))) -> -19 | S44: Yes | T44: Card XXXX1599 — confirms the AED 39 balance gap: this + RTA Metro below | U44: 2026-08-11 21:30
A45: =IF($B45="","","T"&TEXT(ROW()-6,"0000")) -> T39.00 | B45: 46246 | C45: =IF($B45="","",TEXT($B45,"YYYY-MM")) -> 2026-08 | D45: =IF($B45="","",YEAR($B45)) -> 2026 | E45: FAB 4001 Current | F45: Expense | G45: Transport | H45: Nol card top-up | I45: RTA Dubai Metro TVM | J45: Household | K45: Variable | L45: Essential | M45: Card | N45: No | O45: 20 | P45: AED | Q45: =IF($B45="","",IF($P45<>"AED",0,IF($F45="Income",$O45,IF($F45="Expense",-$O45,0)))) -> -20 | S45: Yes | T45: Card XXXX1599, Nol card top-up | U45: 2026-08-12 06:28
A46: =IF($B46="","","T"&TEXT(ROW()-6,"0000")) -> T40.00 | B46: 46246 | C46: =IF($B46="","",TEXT($B46,"YYYY-MM")) -> 2026-08 | D46: =IF($B46="","",YEAR($B46)) -> 2026 | E46: FAB 4001 Current | F46: Transfer Out | G46: Internal Transfer | H46: Rent vault funding | I46: Transfer to FAB 4002 rent vault | J46: Internal | K46: Variable | L46: Essential | M46: Transfer | N46: No | O46: 1430 | P46: AED | Q46: =IF($B46="","",IF($P46<>"AED",0,IF($F46="Income",$O46,IF($F46="Expense",-$O46,0)))) -> 0 | S46: Yes | T46: Protecting the refund for rent, per plan | U46: 2026-08-12
A47: =IF($B47="","","T"&TEXT(ROW()-6,"0000")) -> T41.00 | B47: 46246 | C47: =IF($B47="","",TEXT($B47,"YYYY-MM")) -> 2026-08 | D47: =IF($B47="","",YEAR($B47)) -> 2026 | E47: FAB 4002 Home Expenditure | F47: Transfer In | G47: Internal Transfer | H47: Rent vault funding | I47: Transfer from FAB 4001 | J47: Internal | K47: Variable | L47: Essential | M47: Transfer | N47: No | O47: 1430 | P47: AED | Q47: =IF($B47="","",IF($P47<>"AED",0,IF($F47="Income",$O47,IF($F47="Expense",-$O47,0)))) -> 0 | S47: Yes | U47: 2026-08-12
A48: =IF($B48="","","T"&TEXT(ROW()-6,"0000")) -> T42.00 | B48: 46246 | C48: =IF($B48="","",TEXT($B48,"YYYY-MM")) -> 2026-08 | D48: =IF($B48="","",YEAR($B48)) -> 2026 | E48: FAB 4001 Current | F48: Transfer Out | G48: Internal Transfer | H48: Rent vault funding | I48: Transfer to FAB 4002 | J48: Internal | K48: Variable | L48: Essential | M48: Transfer | N48: No | O48: 1576.09 | P48: AED | Q48: =IF($B48="","",IF($P48<>"AED",0,IF($F48="Income",$O48,IF($F48="Expense",-$O48,0)))) -> 0 | S48: Yes | U48: 2026-08-12 16:48
A49: =IF($B49="","","T"&TEXT(ROW()-6,"0000")) -> T43.00 | B49: 46246 | C49: =IF($B49="","",TEXT($B49,"YYYY-MM")) -> 2026-08 | D49: =IF($B49="","",YEAR($B49)) -> 2026 | E49: FAB 4002 Home Expenditure | F49: Transfer In | G49: Internal Transfer | H49: Rent vault funding | I49: Transfer from FAB 4001 | J49: Internal | K49: Variable | L49: Essential | M49: Transfer | N49: No | O49: 1576.09 | P49: AED | Q49: =IF($B49="","",IF($P49<>"AED",0,IF($F49="Income",$O49,IF($F49="Expense",-$O49,0)))) -> 0 | S49: Yes | U49: 2026-08-12 16:48
A50: =IF($B50="","","T"&TEXT(ROW()-6,"0000")) -> T44.00 | B50: 46246 | C50: =IF($B50="","",TEXT($B50,"YYYY-MM")) -> 2026-08 | D50: =IF($B50="","",YEAR($B50)) -> 2026 | E50: FAB 4001 Current | F50: Expense | G50: Food & Dining | H50: Fast food | I50: KFC Sharjah | J50: Household | K50: Variable | L50: Non-Essential | M50: Card | N50: No | O50: 33 | P50: AED | Q50: =IF($B50="","",IF($P50<>"AED",0,IF($F50="Income",$O50,IF($F50="Expense",-$O50,0)))) -> -33 | S50: Yes | U50: 2026-08-12 19:30
A51: =IF($B51="","","T"&TEXT(ROW()-6,"0000")) -> T45.00 | B51: 46246 | C51: =IF($B51="","",TEXT($B51,"YYYY-MM")) -> 2026-08 | D51: =IF($B51="","",YEAR($B51)) -> 2026 | E51: FAB 4001 Current | F51: Expense | G51: Food & Dining | H51: Fast food | I51: KFC Nad Al Hamar | J51: Household | K51: Variable | L51: Non-Essential | M51: Card | N51: No | O51: 1.5 | P51: AED | Q51: =IF($B51="","",IF($P51<>"AED",0,IF($F51="Income",$O51,IF($F51="Expense",-$O51,0)))) -> -1.5 | S51: Yes | U51: 2026-08-12 19:43
A52: =IF($B52="","","T"&TEXT(ROW()-6,"0000")) -> T46.00 | B52: 46246 | C52: =IF($B52="","",TEXT($B52,"YYYY-MM")) -> 2026-08 | D52: =IF($B52="","",YEAR($B52)) -> 2026 | E52: FAB 4001 Current | F52: Expense | G52: Lifestyle | H52: Convenience store | I52: Asas Al Madina General | J52: Personal | K52: Variable | L52: Non-Essential | M52: Card | N52: No | O52: 15 | P52: AED | Q52: =IF($B52="","",IF($P52<>"AED",0,IF($F52="Income",$O52,IF($F52="Expense",-$O52,0)))) -> -15 | S52: Yes | U52: 2026-08-12 21:19
A53: =IF($B53="","","T"&TEXT(ROW()-6,"0000")) -> T47.00 | B53: 46247 | C53: =IF($B53="","",TEXT($B53,"YYYY-MM")) -> 2026-08 | D53: =IF($B53="","",YEAR($B53)) -> 2026 | E53: FAB 4001 Current | F53: Expense | G53: Food & Dining | H53: Bakery | I53: Nad Al Hamar Bakery | J53: Household | K53: Variable | L53: Non-Essential | M53: Card | N53: No | O53: 10 | P53: AED | Q53: =IF($B53="","",IF($P53<>"AED",0,IF($F53="Income",$O53,IF($F53="Expense",-$O53,0)))) -> -10 | S53: Yes | U53: 2026-08-13 20:01
A54: =IF($B54="","","T"&TEXT(ROW()-6,"0000")) -> T48.00 | B54: 46247 | C54: =IF($B54="","",TEXT($B54,"YYYY-MM")) -> 2026-08 | D54: =IF($B54="","",YEAR($B54)) -> 2026 | E54: FAB 4001 Current | F54: Expense | G54: Lifestyle | H54: Convenience store | I54: Asas Al Madina General | J54: Personal | K54: Variable | L54: Non-Essential | M54: Card | N54: No | O54: 14 | P54: AED | Q54: =IF($B54="","",IF($P54<>"AED",0,IF($F54="Income",$O54,IF($F54="Expense",-$O54,0)))) -> -14 | S54: Yes | U54: 2026-08-13 20:59
A55: =IF($B55="","","T"&TEXT(ROW()-6,"0000")) -> T49.00 | B55: 46248 | C55: =IF($B55="","",TEXT($B55,"YYYY-MM")) -> 2026-08 | D55: =IF($B55="","",YEAR($B55)) -> 2026 | E55: FAB 4001 Current | F55: Expense | G55: Lifestyle | H55: Convenience store | I55: Emarat Nad Al Hamar | J55: Personal | K55: Variable | L55: Non-Essential | M55: Card | N55: No | O55: 13.5 | P55: AED | Q55: =IF($B55="","",IF($P55<>"AED",0,IF($F55="Income",$O55,IF($F55="Expense",-$O55,0)))) -> -13.5 | S55: Yes | U55: 2026-08-14 18:08
A56: =IF($B56="","","T"&TEXT(ROW()-6,"0000")) -> T50.00 | B56: 46248 | C56: =IF($B56="","",TEXT($B56,"YYYY-MM")) -> 2026-08 | D56: =IF($B56="","",YEAR($B56)) -> 2026 | E56: FAB 4001 Current | F56: Expense | G56: Transport | H56: Fuel | I56: Emarat 6192 Nad Al Hamar | J56: Household | K56: Variable | L56: Essential | M56: Card | N56: No | O56: 50 | P56: AED | Q56: =IF($B56="","",IF($P56<>"AED",0,IF($F56="Income",$O56,IF($F56="Expense",-$O56,0)))) -> -50 | S56: Yes | U56: 2026-08-14 18:11
A57: =IF($B57="","","T"&TEXT(ROW()-6,"0000")) -> T51.00 | B57: 46249 | C57: =IF($B57="","",TEXT($B57,"YYYY-MM")) -> 2026-08 | D57: =IF($B57="","",YEAR($B57)) -> 2026 | E57: FAB 4001 Current | F57: Expense | G57: Lifestyle | H57: Small purchase | I57: Jackson Trading Co LLC | J57: Personal | K57: Variable | L57: Non-Essential | M57: Card | N57: No | O57: 2 | P57: AED | Q57: =IF($B57="","",IF($P57<>"AED",0,IF($F57="Income",$O57,IF($F57="Expense",-$O57,0)))) -> -2 | S57: Yes | U57: 2026-08-15 02:31
A58: =IF($B58="","","T"&TEXT(ROW()-6,"0000")) -> T52.00 | B58: 46249 | C58: =IF($B58="","",TEXT($B58,"YYYY-MM")) -> 2026-08 | D58: =IF($B58="","",YEAR($B58)) -> 2026 | E58: FAB 4001 Current | F58: Expense | G58: Lifestyle | H58: Small purchase | I58: Jackson Trading Co LLC | J58: Personal | K58: Variable | L58: Non-Essential | M58: Card | N58: No | O58: 3 | P58: AED | Q58: =IF($B58="","",IF($P58<>"AED",0,IF($F58="Income",$O58,IF($F58="Expense",-$O58,0)))) -> -3 | S58: Yes | U58: 2026-08-15 02:33
... A71: =IF($B71="","","T"&TEXT(ROW()-6,"0000")) -> T65.00 | B71: 46251 | C71: =IF($B71="","",TEXT($B71,"YYYY-MM")) -> 2026-08 | D71: =IF($B71="","",YEAR($B71)) -> 2026 | E71: FAB 4001 Current | F71: Expense | G71: Lifestyle | H71: Convenience store | I71: Asas Al Madina General | J71: Personal | K71: Variable | L71: Non-Essential | M71: Card | N71: No | O71: 14 | P71: AED | Q71: =IF($B71="","",IF($P71<>"AED",0,IF($F71="Income",$O71,IF($F71="Expense",-$O71,0)))) -> -14 | S71: Yes | U71: 2026-08-17 15:08
A72: =IF($B72="","","T"&TEXT(ROW()-6,"0000")) -> T66.00 | B72: 46251 | C72: =IF($B72="","",TEXT($B72,"YYYY-MM")) -> 2026-08 | D72: =IF($B72="","",YEAR($B72)) -> 2026 | E72: FAB 4001 Current | F72: Income | G72: Refund / Reimbursement | H72: Canva refund | I72: Canva (Sydney AU) — refund | J72: Personal | K72: Variable | L72: Essential | M72: Unknown | N72: No | O72: 70 | P72: AED | Q72: =IF($B72="","",IF($P72<>"AED",0,IF($F72="Income",$O72,IF($F72="Expense",-$O72,0)))) -> 70 | S72: Yes | T72: Amount matches the 15 Aug Canva charge exactly (70.00). No explicit refund SMS seen, but the exact match is strong evidence — flagged as inferred, not directly confirmed. | U72: 2026-08-17 ~16:00
A73: =IF($B73="","","T"&TEXT(ROW()-6,"0000")) -> T67.00 | B73: 46251 | C73: =IF($B73="","",TEXT($B73,"YYYY-MM")) -> 2026-08 | D73: =IF($B73="","",YEAR($B73)) -> 2026 | E73: FAB 4001 Current | F73: Expense | G73: Food & Dining | H73: Restaurant | I73: Spicy Falcon Restaurant | J73: Household | K73: Variable | L73: Non-Essential | M73: Card | N73: No | O73: 22 | P73: AED | Q73: =IF($B73="","",IF($P73<>"AED",0,IF($F73="Income",$O73,IF($F73="Expense",-$O73,0)))) -> -22 | S73: Yes | U73: 2026-08-17 18:01
A74: =IF($B74="","","T"&TEXT(ROW()-6,"0000")) -> T68.00 | B74: 46252 | C74: =IF($B74="","",TEXT($B74,"YYYY-MM")) -> 2026-08 | D74: =IF($B74="","",YEAR($B74)) -> 2026 | E74: FAB 4001 Current | F74: Expense | G74: Other | H74: Duty free | I74: Dubai Duty Free | J74: Personal | K74: Variable | L74: Non-Essential | M74: Card | N74: No | O74: 13 | P74: AED | Q74: =IF($B74="","",IF($P74<>"AED",0,IF($F74="Income",$O74,IF($F74="Expense",-$O74,0)))) -> -13 | S74: Yes | U74: 2026-08-18 06:45
A75: =IF($B75="","","T"&TEXT(ROW()-6,"0000")) -> T69.00 | B75: 46252 | C75: =IF($B75="","",TEXT($B75,"YYYY-MM")) -> 2026-08 | D75: =IF($B75="","",YEAR($B75)) -> 2026 | E75: FAB 4001 Current | F75: Expense | G75: Lifestyle | H75: Small purchase | I75: Jackson Trading Co | J75: Personal | K75: Variable | L75: Non-Essential | M75: Card | N75: No | O75: 3 | P75: AED | Q75: =IF($B75="","",IF($P75<>"AED",0,IF($F75="Income",$O75,IF($F75="Expense",-$O75,0)))) -> -3 | S75: Yes | U75: 2026-08-18 07:27
A76: =IF($B76="","","T"&TEXT(ROW()-6,"0000")) -> T70.00 | B76: 46252 | C76: =IF($B76="","",TEXT($B76,"YYYY-MM")) -> 2026-08 | D76: =IF($B76="","",YEAR($B76)) -> 2026 | E76: FAB 4001 Current | F76: Expense | G76: Lifestyle | H76: Small purchase | I76: Jackson Trading Co | J76: Personal | K76: Variable | L76: Non-Essential | M76: Card | N76: No | O76: 2 | P76: AED | Q76: =IF($B76="","",IF($P76<>"AED",0,IF($F76="Income",$O76,IF($F76="Expense",-$O76,0)))) -> -2 | S76: Yes | U76: 2026-08-18 07:28
A77: =IF($B77="","","T"&TEXT(ROW()-6,"0000")) -> T71.00 | B77: 46252 | C77: =IF($B77="","",TEXT($B77,"YYYY-MM")) -> 2026-08 | D77: =IF($B77="","",YEAR($B77)) -> 2026 | E77: FAB 4001 Current | F77: Transfer Out | G77: Food & Dining | H77: Food/lifestyle at work | I77: External remittance to XXXX7801 — food/lifestyle | J77: Personal | K77: Variable | L77: Non-Essential | M77: Transfer | N77: No | O77: 50.49 | P77: AED | Q77: =IF($B77="","",IF($P77<>"AED",0,IF($F77="Income",$O77,IF($F77="Expense",-$O77,0)))) -> 0 | S77: Yes | T77: CONFIRMED by owner — personal food/lifestyle spending at work. | U77: 2026-08-18 07:50
A78: =IF($B78="","","T"&TEXT(ROW()-6,"0000")) -> T72.00 | B78: 46252 | C78: =IF($B78="","",TEXT($B78,"YYYY-MM")) -> 2026-08 | D78: =IF($B78="","",YEAR($B78)) -> 2026 | E78: FAB 4001 Current | F78: Expense | G78: Food & Dining | H78: Restaurant | I78: Malek Altikka Restaurant | J78: Household | K78: Variable | L78: Non-Essential | M78: Card | N78: No | O78: 30 | P78: AED | Q78: =IF($B78="","",IF($P78<>"AED",0,IF($F78="Income",$O78,IF($F78="Expense",-$O78,0)))) -> -30 | S78: Yes | U78: 2026-08-18 21:34
A79: =IF($B79="","","T"&TEXT(ROW()-6,"0000")) -> T73.00 | B79: 46253 | C79: =IF($B79="","",TEXT($B79,"YYYY-MM")) -> 2026-08 | D79: =IF($B79="","",YEAR($B79)) -> 2026 | E79: FAB 4001 Current | F79: Expense | G79: Transport | H79: Fuel | I79: ENOC Site 39 | J79: Household | K79: Variable | L79: Essential | M79: Card | N79: No | O79: 13.5 | P79: AED | Q79: =IF($B79="","",IF($P79<>"AED",0,IF($F79="Income",$O79,IF($F79="Expense",-$O79,0)))) -> -13.5 | S79: Yes | U79: 2026-08-19 06:27
A80: =IF($B80="","","T"&TEXT(ROW()-6,"0000")) -> T74.00 | B80: 46253 | C80: =IF($B80="","",TEXT($B80,"YYYY-MM")) -> 2026-08 | D80: =IF($B80="","",YEAR($B80)) -> 2026 | E80: FAB 4001 Current | F80: Income | G80: Internal Transfer | H80: Vault transfer in | I80: From FAB 4002 | J80: Internal | K80: Variable | L80: Essential | M80: Transfer | N80: No | O80: 60 | P80: AED | Q80: =IF($B80="","",IF($P80<>"AED",0,IF($F80="Income",$O80,IF($F80="Expense",-$O80,0)))) -> 60 | S80: Yes | U80: 2026-08-19 19:24
A81: =IF($B81="","","T"&TEXT(ROW()-6,"0000")) -> T75.00 | B81: 46253 | C81: =IF($B81="","",TEXT($B81,"YYYY-MM")) -> 2026-08 | D81: =IF($B81="","",YEAR($B81)) -> 2026 | E81: FAB 4001 Current | F81: Expense | G81: Transport | H81: Nol card top-up | I81: RTA Dubai Metro | J81: Household | K81: Variable | L81: Essential | M81: Card | N81: No | O81: 20 | P81: AED | Q81: =IF($B81="","",IF($P81<>"AED",0,IF($F81="Income",$O81,IF($F81="Expense",-$O81,0)))) -> -20 | S81: Yes | U81: 2026-08-19 19:24
A82: =IF($B82="","","T"&TEXT(ROW()-6,"0000")) -> T76.00 | B82: 46253 | C82: =IF($B82="","",TEXT($B82,"YYYY-MM")) -> 2026-08 | D82: =IF($B82="","",YEAR($B82)) -> 2026 | E82: FAB 4001 Current | F82: Expense | G82: Lifestyle | H82: Convenience store | I82: Asas Al Madina General | J82: Personal | K82: Variable | L82: Non-Essential | M82: Card | N82: No | O82: 4 | P82: AED | Q82: =IF($B82="","",IF($P82<>"AED",0,IF($F82="Income",$O82,IF($F82="Expense",-$O82,0)))) -> -4 | S82: Yes | U82: 2026-08-19 23:15
A83: =IF($B83="","","T"&TEXT(ROW()-6,"0000")) -> T77.00 | B83: 46254 | C83: =IF($B83="","",TEXT($B83,"YYYY-MM")) -> 2026-08 | D83: =IF($B83="","",YEAR($B83)) -> 2026 | E83: FAB 4001 Current | F83: Expense | G83: Lifestyle | H83: Convenience store | I83: Asas Al Madina General | J83: Personal | K83: Variable | L83: Non-Essential | M83: Card | N83: No | O83: 14 | P83: AED | Q83: =IF($B83="","",IF($P83<>"AED",0,IF($F83="Income",$O83,IF($F83="Expense",-$O83,0)))) -> -14 | S83: Yes | U83: 2026-08-20 17:54
A84: =IF($B84="","","T"&TEXT(ROW()-6,"0000")) -> T78.00 | B84: 46254 | C84: =IF($B84="","",TEXT($B84,"YYYY-MM")) -> 2026-08 | D84: =IF($B84="","",YEAR($B84)) -> 2026 | E84: FAB 4001 Current | F84: Expense | G84: Food & Dining | H84: Restaurant | I84: Eat and Drink Restaurant | J84: Household | K84: Variable | L84: Non-Essential | M84: Card | N84: No | O84: 12 | P84: AED | Q84: =IF($B84="","",IF($P84<>"AED",0,IF($F84="Income",$O84,IF($F84="Expense",-$O84,0)))) -> -12 | S84: Yes | U84: 2026-08-20 18:26
A85: =IF($B85="","","T"&TEXT(ROW()-6,"0000")) -> T79.00 | B85: 46255 | C85: =IF($B85="","",TEXT($B85,"YYYY-MM")) -> 2026-08 | D85: =IF($B85="","",YEAR($B85)) -> 2026 | E85: FAB 4001 Current | F85: Expense | G85: Groceries | H85: Grocery | I85: S R N Supermarket | J85: Household | K85: Variable | L85: Essential | M85: Card | N85: No | O85: 2.99 | P85: AED | Q85: =IF($B85="","",IF($P85<>"AED",0,IF($F85="Income",$O85,IF($F85="Expense",-$O85,0)))) -> -2.99 | S85: Yes | U85: 2026-08-21 08:57
A86: =IF($B86="","","T"&TEXT(ROW()-6,"0000")) -> T80.00 | B86: 46255 | C86: =IF($B86="","",TEXT($B86,"YYYY-MM")) -> 2026-08 | D86: =IF($B86="","",YEAR($B86)) -> 2026 | E86: FAB 4001 Current | F86: Expense | G86: Groceries | H86: Grocery | I86: S R N Supermarket (2nd purchase) | J86: Household | K86: Variable | L86: Essential | M86: Unknown | N86: No | O86: 2.99 | P86: AED | Q86: =IF($B86="","",IF($P86<>"AED",0,IF($F86="Income",$O86,IF($F86="Expense",-$O86,0)))) -> -2.99 | S86: Yes | T86: CONFIRMED via SMS — second purchase, same store, 09:31, 34 min after the first. | U86: 2026-08-21 09:31
A87: =IF($B87="","","T"&TEXT(ROW()-6,"0000")) -> T81.00 | B87: 46255 | C87: =IF($B87="","",TEXT($B87,"YYYY-MM")) -> 2026-08 | D87: =IF($B87="","",YEAR($B87)) -> 2026 | E87: FAB 4001 Current | F87: Expense | G87: Lifestyle | H87: Convenience store | I87: Asas Al Madina General | J87: Personal | K87: Variable | L87: Non-Essential | M87: Card | N87: No | O87: 13.5 | P87: AED | Q87: =IF($B87="","",IF($P87<>"AED",0,IF($F87="Income",$O87,IF($F87="Expense",-$O87,0)))) -> -13.5 | S87: Yes | U87: 2026-08-21 12:11
A88: =IF($B88="","","T"&TEXT(ROW()-6,"0000")) -> T82.00 | B88: 46256 | C88: =IF($B88="","",TEXT($B88,"YYYY-MM")) -> 2026-08 | D88: =IF($B88="","",YEAR($B88)) -> 2026 | E88: FAB 4001 Current | F88: Income | G88: Internal Transfer | H88: Vault transfer in | I88: From FAB 4002 | J88: Internal | K88: Variable | L88: Essential | M88: Unknown | N88: No | O88: 100 | P88: AED | Q88: =IF($B88="","",IF($P88<>"AED",0,IF($F88="Income",$O88,IF($F88="Expense",-$O88,0)))) -> 100 | S88: Yes | T88: CONFIRMED via SMS, 21:31 | U88: 2026-08-21 21:31
A89: =IF($B89="","","T"&TEXT(ROW()-6,"0000")) -> T83.00 | B89: 46256 | C89: =IF($B89="","",TEXT($B89,"YYYY-MM")) -> 2026-08 | D89: =IF($B89="","",YEAR($B89)) -> 2026 | E89: FAB 4001 Current | F89: Expense | G89: Lifestyle | H89: Convenience store | I89: Asas Al Madina General | J89: Personal | K89: Variable | L89: Non-Essential | M89: Card | N89: No | O89: 14 | P89: AED | Q89: =IF($B89="","",IF($P89<>"AED",0,IF($F89="Income",$O89,IF($F89="Expense",-$O89,0)))) -> -14 | S89: Yes | U89: 2026-08-22 11:53
A90: =IF($B90="","","T"&TEXT(ROW()-6,"0000")) -> T84.00 | B90: 46256 | C90: =IF($B90="","",TEXT($B90,"YYYY-MM")) -> 2026-08 | D90: =IF($B90="","",YEAR($B90)) -> 2026 | E90: FAB 4001 Current | F90: Income | G90: Internal Transfer | H90: Vault transfer in | I90: From FAB 4002 | J90: Internal | K90: Variable | L90: Essential | M90: Transfer | N90: No | O90: 200 | P90: AED | Q90: =IF($B90="","",IF($P90<>"AED",0,IF($F90="Income",$O90,IF($F90="Expense",-$O90,0)))) -> 200 | S90: Yes | U90: 2026-08-22 15:25
A91: =IF($B91="","","T"&TEXT(ROW()-6,"0000")) -> T85.00 | B91: 46256 | C91: =IF($B91="","",TEXT($B91,"YYYY-MM")) -> 2026-08 | D91: =IF($B91="","",YEAR($B91)) -> 2026 | E91: FAB 4001 Current | F91: Expense | G91: Food & Dining | H91: Restaurant | I91: 25 Hours F and B | J91: Household | K91: Variable | L91: Non-Essential | M91: Card | N91: No | O91: 63.75 | P91: AED | Q91: =IF($B91="","",IF($P91<>"AED",0,IF($F91="Income",$O91,IF($F91="Expense",-$O91,0)))) -> -63.75 | S91: Yes | U91: 2026-08-22 15:31
A92: =IF($B92="","","T"&TEXT(ROW()-6,"0000")) -> T86.00 | B92: 46256 | C92: =IF($B92="","",TEXT($B92,"YYYY-MM")) -> 2026-08 | D92: =IF($B92="","",YEAR($B92)) -> 2026 | E92: FAB 4001 Current | F92: Expense | G92: Food & Dining | H92: Restaurant | I92: 25 Hours F and B | J92: Household | K92: Variable | L92: Non-Essential | M92: Card | N92: No | O92: 100 | P92: AED | Q92: =IF($B92="","",IF($P92<>"AED",0,IF($F92="Income",$O92,IF($F92="Expense",-$O92,0)))) -> -100 | S92: Yes | U92: 2026-08-22 15:40
A93: =IF($B93="","","T"&TEXT(ROW()-6,"0000")) -> T87.00 | B93: 46256 | C93: =IF($B93="","",TEXT($B93,"YYYY-MM")) -> 2026-08 | D93: =IF($B93="","",YEAR($B93)) -> 2026 | E93: FAB 4001 Current | F93: Income | G93: Internal Transfer | H93: Vault transfer in | I93: From FAB 4002 | J93: Internal | K93: Variable | L93: Essential | M93: Transfer | N93: No | O93: 500 | P93: AED | Q93: =IF($B93="","",IF($P93<>"AED",0,IF($F93="Income",$O93,IF($F93="Expense",-$O93,0)))) -> 500 | S93: Yes | U93: 2026-08-22 17:18
A94: =IF($B94="","","T"&TEXT(ROW()-6,"0000")) -> T88.00 | B94: 46256 | C94: =IF($B94="","",TEXT($B94,"YYYY-MM")) -> 2026-08 | D94: =IF($B94="","",YEAR($B94)) -> 2026 | E94: FAB 4001 Current | F94: Expense | G94: Food & Dining | H94: Hotel dining | I94: Sofitel Dubai Downtown | J94: Personal | K94: Variable | L94: Non-Essential | M94: Card | N94: No | O94: 10 | P94: AED | Q94: =IF($B94="","",IF($P94<>"AED",0,IF($F94="Income",$O94,IF($F94="Expense",-$O94,0)))) -> -10 | S94: Yes | U94: 2026-08-22 17:40
A95: =IF($B95="","","T"&TEXT(ROW()-6,"0000")) -> T89.00 | B95: 46256 | C95: =IF($B95="","",TEXT($B95,"YYYY-MM")) -> 2026-08 | D95: =IF($B95="","",YEAR($B95)) -> 2026 | E95: FAB 4001 Current | F95: Expense | G95: Food & Dining | H95: Restaurant | I95: Curry Chatti (Sharjah) | J95: Household | K95: Variable | L95: Non-Essential | M95: Card | N95: No | O95: 4 | P95: AED | Q95: =IF($B95="","",IF($P95<>"AED",0,IF($F95="Income",$O95,IF($F95="Expense",-$O95,0)))) -> -4 | S95: Yes | U95: 2026-08-22 19:04
A96: =IF($B96="","","T"&TEXT(ROW()-6,"0000")) -> T90.00 | B96: 46257 | C96: =IF($B96="","",TEXT($B96,"YYYY-MM")) -> 2026-08 | D96: =IF($B96="","",YEAR($B96)) -> 2026 | E96: FAB 4001 Current | F96: Expense | G96: Lifestyle | H96: Convenience store | I96: Asas Al Madina General | J96: Personal | K96: Variable | L96: Non-Essential | M96: Card | N96: No | O96: 39 | P96: AED | Q96: =IF($B96="","",IF($P96<>"AED",0,IF($F96="Income",$O96,IF($F96="Expense",-$O96,0)))) -> -39 | S96: Yes | U96: 2026-08-23 00:12
A97: =IF($B97="","","T"&TEXT(ROW()-6,"0000")) -> T91.00 | B97: 46257 | C97: =IF($B97="","",TEXT($B97,"YYYY-MM")) -> 2026-08 | D97: =IF($B97="","",YEAR($B97)) -> 2026 | E97: FAB 4001 Current | F97: Expense | G97: Lifestyle | H97: Convenience store | I97: Asas Al Madina General | J97: Personal | K97: Variable | L97: Non-Essential | M97: Card | N97: No | O97: 20 | P97: AED | Q97: =IF($B97="","",IF($P97<>"AED",0,IF($F97="Income",$O97,IF($F97="Expense",-$O97,0)))) -> -20 | S97: Yes | U97: 2026-08-23 12:08
A98: =IF($B98="","","T"&TEXT(ROW()-6,"0000")) -> T92.00 | B98: 46257 | C98: =IF($B98="","",TEXT($B98,"YYYY-MM")) -> 2026-08 | D98: =IF($B98="","",YEAR($B98)) -> 2026 | E98: FAB 4001 Current | F98: Expense | G98: Food & Dining | H98: Restaurant | I98: Cielo Kabab Restaurant | J98: Household | K98: Variable | L98: Non-Essential | M98: Card | N98: No | O98: 78 | P98: AED | Q98: =IF($B98="","",IF($P98<>"AED",0,IF($F98="Income",$O98,IF($F98="Expense",-$O98,0)))) -> -78 | S98: Yes | U98: 2026-08-23 19:03
A99: =IF($B99="","","T"&TEXT(ROW()-6,"0000")) -> T93.00 | B99: 46257 | C99: =IF($B99="","",TEXT($B99,"YYYY-MM")) -> 2026-08 | D99: =IF($B99="","",YEAR($B99)) -> 2026 | E99: FAB 4001 Current | F99: Expense | G99: Groceries | H99: Grocery | I99: Nad Al Hamar Star Grocery | J99: Household | K99: Variable | L99: Essential | M99: Card | N99: No | O99: 10 | P99: AED | Q99: =IF($B99="","",IF($P99<>"AED",0,IF($F99="Income",$O99,IF($F99="Expense",-$O99,0)))) -> -10 | S99: Yes | U99: 2026-08-23 19:06
A100: =IF($B100="","","T"&TEXT(ROW()-6,"0000")) -> T94.00 | B100: 46257 | C100: =IF($B100="","",TEXT($B100,"YYYY-MM")) -> 2026-08 | D100: =IF($B100="","",YEAR($B100)) -> 2026 | E100: FAB 4001 Current | F100: Transfer Out | G100: Internal Transfer | H100: Vault funding | I100: To FAB 4002 | J100: Internal | K100: Variable | L100: Essential | M100: Transfer | N100: No | O100: 420 | P100: AED | Q100: =IF($B100="","",IF($P100<>"AED",0,IF($F100="Income",$O100,IF($F100="Expense",-$O100,0)))) -> 0 | S100: Yes | U100: 2026-08-23 21:37
... A108: =IF($B108="","","T"&TEXT(ROW()-6,"0000")) -> T102.00 | B108: 46256 | C108: =IF($B108="","",TEXT($B108,"YYYY-MM")) -> 2026-08 | D108: =IF($B108="","",YEAR($B108)) -> 2026 | E108: FAB 4002 Home Expenditure | F108: Transfer Out | G108: Internal Transfer | H108: Vault transfer out | I108: To FAB 4001 | J108: Internal | K108: Variable | L108: Essential | M108: Transfer | N108: No | O108: 500 | P108: AED | Q108: =IF($B108="","",IF($P108<>"AED",0,IF($F108="Income",$O108,IF($F108="Expense",-$O108,0)))) -> 0 | S108: Yes | U108: 2026-08-22 17:18
A109: =IF($B109="","","T"&TEXT(ROW()-6,"0000")) -> T103.00 | B109: 46256 | C109: =IF($B109="","",TEXT($B109,"YYYY-MM")) -> 2026-08 | D109: =IF($B109="","",YEAR($B109)) -> 2026 | E109: FAB 4002 Home Expenditure | F109: Expense | G109: Other | H109: REQUIRES VERIFICATION | I109: Unexplained outflow (shrunk from 180) | J109: Household | K109: Variable | L109: Essential | M109: Unknown | N109: No | O109: 100 | P109: AED | Q109: =IF($B109="","",IF($P109<>"AED",0,IF($F109="Income",$O109,IF($F109="Expense",-$O109,0)))) -> -100 | S109: Yes | T109: Was 180 — now 100 after confirming the 80 transfer separately (new row). Genuine remaining gap. | U109: 2026-08-22 ~19-23 Aug
A110: =IF($B110="","","T"&TEXT(ROW()-6,"0000")) -> T104.00 | B110: 46257 | C110: =IF($B110="","",TEXT($B110,"YYYY-MM")) -> 2026-08 | D110: =IF($B110="","",YEAR($B110)) -> 2026 | E110: FAB 4002 Home Expenditure | F110: Transfer In | G110: Internal Transfer | H110: Vault funding | I110: From FAB 4001 | J110: Internal | K110: Variable | L110: Essential | M110: Transfer | N110: No | O110: 420 | P110: AED | Q110: =IF($B110="","",IF($P110<>"AED",0,IF($F110="Income",$O110,IF($F110="Expense",-$O110,0)))) -> 0 | S110: Yes | U110: 2026-08-23 21:37
A111: =IF($B111="","","T"&TEXT(ROW()-6,"0000")) -> T105.00 | B111: 46251 | C111: =IF($B111="","",TEXT($B111,"YYYY-MM")) -> 2026-08 | D111: =IF($B111="","",YEAR($B111)) -> 2026 | E111: NBD Current | F111: Expense | G111: Groceries | H111: Grocery | I111: S R N Supermarket | J111: Household | K111: Variable | L111: Essential | M111: Card | N111: No | O111: 2 | P111: AED | Q111: =IF($B111="","",IF($P111<>"AED",0,IF($F111="Income",$O111,IF($F111="Expense",-$O111,0)))) -> -2 | S111: Yes | U111: 2026-08-17 15:14
A112: =IF($B112="","","T"&TEXT(ROW()-6,"0000")) -> T106.00 | B112: 46255 | C112: =IF($B112="","",TEXT($B112,"YYYY-MM")) -> 2026-08 | D112: =IF($B112="","",YEAR($B112)) -> 2026 | E112: FAB 4001 Current | F112: Expense | G112: Food & Dining | H112: Restaurant | I112: Spicy Falcon Restaurant | J112: Household | K112: Variable | L112: Non-Essential | M112: Card | N112: No | O112: 26.5 | P112: AED | Q112: =IF($B112="","",IF($P112<>"AED",0,IF($F112="Income",$O112,IF($F112="Expense",-$O112,0)))) -> -26.5 | S112: Yes | T112: CONFIRMED via SMS | U112: 2026-08-21 22:03
A113: =IF($B113="","","T"&TEXT(ROW()-6,"0000")) -> T107.00 | B113: 46256 | C113: =IF($B113="","",TEXT($B113,"YYYY-MM")) -> 2026-08 | D113: =IF($B113="","",YEAR($B113)) -> 2026 | E113: FAB 4001 Current | F113: Expense | G113: Health | H113: Grooming | I113: ISK Gents Saloon | J113: Personal | K113: Variable | L113: Non-Essential | M113: Card | N113: No | O113: 65 | P113: AED | Q113: =IF($B113="","",IF($P113<>"AED",0,IF($F113="Income",$O113,IF($F113="Expense",-$O113,0)))) -> -65 | S113: Yes | T113: CONFIRMED via SMS, 11:46. Was flagged as an unexplained 15 inflow — the real story is this 65 expense plus an 80 transfer (added as a new row). | U113: 2026-08-22 11:46
A114: =IF($B114="","","T"&TEXT(ROW()-6,"0000")) -> T108.00 | B114: 46256 | C114: =IF($B114="","",TEXT($B114,"YYYY-MM")) -> 2026-08 | D114: =IF($B114="","",YEAR($B114)) -> 2026 | E114: FAB 4001 Current | F114: Income | G114: Internal Transfer | H114: Vault transfer in | I114: From FAB 4002 | J114: Internal | K114: Variable | L114: Essential | M114: Transfer | N114: No | O114: 80 | P114: AED | Q114: =IF($B114="","",IF($P114<>"AED",0,IF($F114="Income",$O114,IF($F114="Expense",-$O114,0)))) -> 80 | S114: Yes | T114: CONFIRMED via SMS, 11:51 | U114: 2026-08-22 11:51
A115: =IF($B115="","","T"&TEXT(ROW()-6,"0000")) -> T109.00 | B115: 46256 | C115: =IF($B115="","",TEXT($B115,"YYYY-MM")) -> 2026-08 | D115: =IF($B115="","",YEAR($B115)) -> 2026 | E115: FAB 4002 Home Expenditure | F115: Transfer Out | G115: Internal Transfer | H115: Vault transfer out | I115: To FAB 4001 | J115: Internal | K115: Variable | L115: Essential | M115: Transfer | N115: No | O115: 80 | P115: AED | Q115: =IF($B115="","",IF($P115<>"AED",0,IF($F115="Income",$O115,IF($F115="Expense",-$O115,0)))) -> 0 | S115: Yes | T115: CONFIRMED via SMS, 11:51 | U115: 2026-08-22 11:51
A116: =IF($B116="","","T"&TEXT(ROW()-6,"0000")) -> T110.00 | B116: 46260 | C116: =IF($B116="","",TEXT($B116,"YYYY-MM")) -> 2026-08 | D116: =IF($B116="","",YEAR($B116)) -> 2026 | E116: NBD Current | F116: Income | G116: Salary | H116: August payday | I116: Salary credit | J116: Household | K116: Fixed | L116: Essential | M116: Bank credit | N116: No | O116: 2906.7 | P116: AED | Q116: =IF($B116="","",IF($P116<>"AED",0,IF($F116="Income",$O116,IF($F116="Expense",-$O116,0)))) -> 2906.7 | S116: Yes | T116: CONFIRMED via SMS — landed in NBD, not FAB as in prior months. | U116: 2026-08-26
A117: =IF($B117="","","T"&TEXT(ROW()-6,"0000")) -> T111.00 | B117: 46260 | C117: =IF($B117="","",TEXT($B117,"YYYY-MM")) -> 2026-08 | D117: =IF($B117="","",YEAR($B117)) -> 2026 | E117: NBD Current | F117: Expense | G117: BNPL | H117: Tabby monthly card fee | I117: Tabby | J117: Household | K117: Fixed | L117: Essential | M117: Card | N117: No | O117: 49 | P117: AED | Q117: =IF($B117="","",IF($P117<>"AED",0,IF($F117="Income",$O117,IF($F117="Expense",-$O117,0)))) -> -49 | S117: Yes | T117: CONFIRMED by owner — recurring monthly fee, continues until the card is closed after final payment. | U117: 2026-08-26
A118: =IF($B118="","","T"&TEXT(ROW()-6,"0000")) -> T112.00 | B118: 46259 | C118: =IF($B118="","",TEXT($B118,"YYYY-MM")) -> 2026-08 | D118: =IF($B118="","",YEAR($B118)) -> 2026 | E118: FAB 4001 Current | F118: Income | G118: Internal Transfer | H118: Vault transfer in | I118: From FAB 4002 | J118: Internal | K118: Variable | L118: Essential | M118: Transfer | N118: No | O118: 100 | P118: AED | Q118: =IF($B118="","",IF($P118<>"AED",0,IF($F118="Income",$O118,IF($F118="Expense",-$O118,0)))) -> 100 | S118: Yes | T118: CONFIRMED via SMS | U118: 2026-08-25 21:00
A119: =IF($B119="","","T"&TEXT(ROW()-6,"0000")) -> T113.00 | B119: 46259 | C119: =IF($B119="","",TEXT($B119,"YYYY-MM")) -> 2026-08 | D119: =IF($B119="","",YEAR($B119)) -> 2026 | E119: FAB 4001 Current | F119: Expense | G119: Food & Dining | H119: Cafe | I119: My Filli Cafe | J119: Personal | K119: Variable | L119: Non-Essential | M119: Card | N119: No | O119: 29 | P119: AED | Q119: =IF($B119="","",IF($P119<>"AED",0,IF($F119="Income",$O119,IF($F119="Expense",-$O119,0)))) -> -29 | S119: Yes | T119: CONFIRMED via SMS | U119: 2026-08-25 21:31
A120: =IF($B120="","","T"&TEXT(ROW()-6,"0000")) -> T114.00 | B120: 46259 | C120: =IF($B120="","",TEXT($B120,"YYYY-MM")) -> 2026-08 | D120: =IF($B120="","",YEAR($B120)) -> 2026 | E120: FAB 4001 Current | F120: Expense | G120: Food & Dining | H120: Restaurant | I120: Subway | J120: Personal | K120: Variable | L120: Non-Essential | M120: Card | N120: No | O120: 43 | P120: AED | Q120: =IF($B120="","",IF($P120<>"AED",0,IF($F120="Income",$O120,IF($F120="Expense",-$O120,0)))) -> -43 | S120: Yes | T120: CONFIRMED via SMS | U120: 2026-08-25 21:45
A121: =IF($B121="","","T"&TEXT(ROW()-6,"0000")) -> T115.00 | B121: 46259 | C121: =IF($B121="","",TEXT($B121,"YYYY-MM")) -> 2026-08 | D121: =IF($B121="","",YEAR($B121)) -> 2026 | E121: FAB 4001 Current | F121: Expense | G121: Lifestyle | H121: Ice cream | I121: Galadari Ice Cream Co | J121: Personal | K121: Variable | L121: Non-Essential | M121: Card | N121: No | O121: 10 | P121: AED | Q121: =IF($B121="","",IF($P121<>"AED",0,IF($F121="Income",$O121,IF($F121="Expense",-$O121,0)))) -> -10 | S121: Yes | T121: CONFIRMED via SMS | U121: 2026-08-25 22:02
...

Sheet Spending Breakdown
A1: Spending Breakdown
A2: Where every dirham has actually gone since 3 August. Reimbursable business outflows are excluded — this is your own money only.
A5: BY CATEGORY
A6: Category | B6: Amount | C6: % of total | D6: Essential? | E6: Recurring? | F6: What this is | H6: Category | I6: Amount
A7: Travel & Airfare | B7: 1430 | C7: =B7/$B$16 -> 0.40037293 | D7: Essential | E7: One-off | F7: Emirates ticket — fully refunded 12 Aug, so this nets to zero | H7: Travel & Airfare | I7: 1430
A8: Utilities | B8: 914.93 | C8: =B8/$B$16 -> 0.25616308 | D8: Essential | E8: Monthly | F8: du + Etisalat via DubaiPay, paid 3 Aug | H8: Utilities | I8: 914.93
A9: Lifestyle | B9: 577.25 | C9: =B9/$B$16 -> 0.16161907 | D9: Non-essential | E9: Variable | F9: Hotel AED 386.75, convenience stores, fuel — the biggest controllable line | H9: Lifestyle | I9: 549.75
A10: Food & Dining | B10: 316.52 | C10: =B10/$B$16 -> 0.088619609 | D10: Mixed | E10: Variable | F10: Restaurants, delivery, KFC — second biggest controllable | H10: Food & Dining | I10: 306.52
A11: Family Support | B11: 100 | C11: =B11/$B$16 -> 0.027998107 | D11: Essential | E11: Occasional | F11: e& Money medical support | H11: Family Support | I11: 100
A12: Groceries | B12: 120 | C12: =B12/$B$16 -> 0.033597729 | D12: Essential | E12: Variable | F12: Actual food shopping | H12: Groceries | I12: 77.75
A13: Transport | B13: 70 | C13: =B13/$B$16 -> 0.019598675 | D13: Essential | E13: Variable | F13: Fuel and Nol top-up | H13: Transport | I13: 70
A14: Household Other | B14: 22.97 | C14: =B14/$B$16 -> 0.0064311653 | D14: Essential | E14: Occasional | F14: Home supplies | H14: Household Other | I14: 22.97
A15: Entertainment | B15: 20 | C15: =B15/$B$16 -> 0.0055996215 | D15: Non-essential | E15: Occasional | F15: Cinema | H15: Entertainment | I15: 20
A16: TOTAL | B16: =SUM(B7:B15) -> 3571.67
A18: THE CONTROLLABLE PART · what you can actually change
A19: Line | B19: Amount | C19: Note
A20: Lifestyle | B20: =B9 -> 577.25 | C20: Hotel, convenience stores, fuel
A21: Food & Dining | B21: =B10 -> 316.52 | C21: Restaurants and delivery
A22: Entertainment | B22: =B15 -> 20 | C22: Cinema
A23: TOTAL DISCRETIONARY | B23: =B20+B21+B22 -> 913.77 | C23: This is the only pool that responds to willpower
A24: Fixed and essential | B24: =B16-B23 -> 2657.9 | C24: Utilities, groceries, transport, family, the refunded ticket
A25: Discretionary as % of all spending | B25: =B23/B16 -> 0.25583831 | C25: Everything else is committed
A27: Even cutting every discretionary dirham to zero saves about AED 876 — half the roughly AED 1,773 you need. The rest has to be earned. That is the honest arithmetic of your position.
A30: TOP MERCHANTS
A31: Merchant | B31: Amount | C31: Visits | F31: Note
A32: Emirates ticket | B32: 1430 | C32: 1 | F32: Refunded
A33: du + Etisalat | B33: 914.93 | C33: 1 | F33: Monthly utilities
A34: RTS Business Bay Hotel | B34: 386.75 | C34: 3 | F34: Three charges, one day — 08 Aug
A35: Asas Al Madina General | B35: 192 | C35: 8 | F35: Convenience store — most frequent stop
A36: Salkara / Team Taste | B36: 101.5 | C36: 1 | F36: Restaurant
A37: e& Money | B37: 100 | C37: 1 | F37: Family medical
A38: Zomato | B38: 66.52 | C38: 1 | F38: Delivery
A39: ENOC | B39: 50 | C39: 1 | F39: Fuel
A40: KFC | B40: 34.5 | C40: 2 | F40: 12 Aug

Sheet Bills & Commitments
A1: Bills & Commitments
A2: Everything owed and everything expected. The dashboard reads this sheet directly — if a bill is not here, it is invisible to the plan.
A4: BILLING RULES · DEWA: issued on the 20th, due by month-end. du + Etisalat: issued 2nd–3rd, due by the 15th. Tabby: statement due on the 3rd.
A5: COMMITMENT REGISTER
A6: Due Date | B6: Item | C6: Category | D6: Direction | E6: Expected | F6: Actual | G6: Amount Used | H6: Cur | I6: Settled? | J6: Settled Date | K6: Account | L6: Recurrence | M6: Mandatory? | N6: Priority | O6: Certainty | P6: Days Left | Q6: Status | R6: Notes | S6: Sort key | T6: Size key
A7: 46229 | B7: DEWA — July | C7: Utilities | D7: Outflow | E7: 793.42 | F7: 793.42 | G7: =IF($A7="","",IF($F7="",$E7,$F7)) -> 793.42 | H7: AED | I7: Yes | J7: 46229 | K7: FAB 4001 Current | L7: Monthly | M7: Yes | N7: Essential | O7: Actual | P7: =IF($A7="","",$A7-Settings!$B$9) -> -31 | Q7: =IF($A7="","",IF($I7="Yes","Settled",IF($P7<0,"OVERDUE",IF($P7<=3,"DUE ≤3 DAYS",IF($P7<=7,"DUE ≤7 DAYS","Scheduled"))))) -> Settled | R7: Paid — do not deduct again | S7: =IF(OR($A7="",$I7="Yes",$D7<>"Outflow",$H7<>"AED"),99999+ROW()/1000000,$P7+ROW()/1000000) -> 99999 | T7: =IF(OR($A7="",$I7="Yes",$D7<>"Outflow",$H7<>"AED",$A7>Settings!$B$21),-1-ROW()/1000000,$G7+ROW()/1000000) -> -1.000007
A8: 46237 | B8: du — August | C8: Telecom | D8: Outflow | E8: 590.98 | F8: 590.98 | G8: =IF($A8="","",IF($F8="",$E8,$F8)) -> 590.98 | H8: AED | I8: Yes | J8: 46237 | K8: FAB 4001 Current | L8: Monthly | M8: Yes | N8: Essential | O8: Actual | P8: =IF($A8="","",$A8-Settings!$B$9) -> -23 | Q8: =IF($A8="","",IF($I8="Yes","Settled",IF($P8<0,"OVERDUE",IF($P8<=3,"DUE ≤3 DAYS",IF($P8<=7,"DUE ≤7 DAYS","Scheduled"))))) -> Settled | R8: Paid via DubaiPay | S8: =IF(OR($A8="",$I8="Yes",$D8<>"Outflow",$H8<>"AED"),99999+ROW()/1000000,$P8+ROW()/1000000) -> 99999 | T8: =IF(OR($A8="",$I8="Yes",$D8<>"Outflow",$H8<>"AED",$A8>Settings!$B$21),-1-ROW()/1000000,$G8+ROW()/1000000) -> -1.000008
A9: 46237 | B9: Etisalat — August | C9: Telecom | D9: Outflow | E9: 323.95 | F9: 323.95 | G9: =IF($A9="","",IF($F9="",$E9,$F9)) -> 323.95 | H9: AED | I9: Yes | J9: 46237 | K9: FAB 4001 Current | L9: Monthly | M9: Yes | N9: Essential | O9: Actual | P9: =IF($A9="","",$A9-Settings!$B$9) -> -23 | Q9: =IF($A9="","",IF($I9="Yes","Settled",IF($P9<0,"OVERDUE",IF($P9<=3,"DUE ≤3 DAYS",IF($P9<=7,"DUE ≤7 DAYS","Scheduled"))))) -> Settled | R9: Paid via DubaiPay | S9: =IF(OR($A9="",$I9="Yes",$D9<>"Outflow",$H9<>"AED"),99999+ROW()/1000000,$P9+ROW()/1000000) -> 99999 | T9: =IF(OR($A9="",$I9="Yes",$D9<>"Outflow",$H9<>"AED",$A9>Settings!$B$21),-1-ROW()/1000000,$G9+ROW()/1000000) -> -1.000009
A10: 46244 | B10: Nippon SIP — August | C10: Investments | D10: Outflow | E10: 12000 | F10: 12000 | G10: =IF($A10="","",IF($F10="",$E10,$F10)) -> 12000 | H10: INR | I10: Yes | J10: 46244 | K10: ICICI (INR) | L10: Monthly | M10: Yes | N10: Core investment | O10: Actual | P10: =IF($A10="","",$A10-Settings!$B$9) -> -16 | Q10: =IF($A10="","",IF($I10="Yes","Settled",IF($P10<0,"OVERDUE",IF($P10<=3,"DUE ≤3 DAYS",IF($P10<=7,"DUE ≤7 DAYS","Scheduled"))))) -> Settled | R10: Four INR 3,000 SIPs completed | S10: =IF(OR($A10="",$I10="Yes",$D10<>"Outflow",$H10<>"AED"),99999+ROW()/1000000,$P10+ROW()/1000000) -> 99999 | T10: =IF(OR($A10="",$I10="Yes",$D10<>"Outflow",$H10<>"AED",$A10>Settings!$B$21),-1-ROW()/1000000,$G10+ROW()/1000000) -> -1.00001
A11: 46266 | B11: DEWA — August | C11: Utilities | D11: Outflow | E11: 813.28 | G11: =IF($A11="","",IF($F11="",$E11,$F11)) -> 813.28 | H11: AED | I11: Yes | J11: 46260 | K11: NBD Current | L11: Monthly | M11: Yes | N11: Essential | O11: Actual | P11: =IF($A11="","",$A11-Settings!$B$9) -> 6 | Q11: =IF($A11="","",IF($I11="Yes","Settled",IF($P11<0,"OVERDUE",IF($P11<=3,"DUE ≤3 DAYS",IF($P11<=7,"DUE ≤7 DAYS","Scheduled"))))) -> Settled | R11: CONFIRMED PAID 26 Aug — same day as salary, Tabby, and SIP. Not 1 Sep as first logged. | S11: =IF(OR($A11="",$I11="Yes",$D11<>"Outflow",$H11<>"AED"),99999+ROW()/1000000,$P11+ROW()/1000000) -> 99999 | T11: =IF(OR($A11="",$I11="Yes",$D11<>"Outflow",$H11<>"AED",$A11>Settings!$B$21),-1-ROW()/1000000,$G11+ROW()/1000000) -> -1.000011
A12: 46260 | B12: Remaining August payday (confirmed) | C12: Salary | D12: Inflow | E12: 2906 | G12: =IF($A12="","",IF($F12="",$E12,$F12)) -> 2906 | H12: AED | I12: Yes | J12: 46260 | K12: NBD Current | L12: Monthly | M12: – | N12: Critical | O12: Actual | P12: =IF($A12="","",$A12-Settings!$B$9) -> 0 | Q12: =IF($A12="","",IF($I12="Yes","Settled",IF($P12<0,"OVERDUE",IF($P12<=3,"DUE ≤3 DAYS",IF($P12<=7,"DUE ≤7 DAYS","Scheduled"))))) -> Settled | R12: CONFIRMED landed 26 Aug via SMS — into NBD, not FAB. Marked settled to avoid double-counting against current liquid cash. | S12: =IF(OR($A12="",$I12="Yes",$D12<>"Outflow",$H12<>"AED"),99999+ROW()/1000000,$P12+ROW()/1000000) -> 99999 | T12: =IF(OR($A12="",$I12="Yes",$D12<>"Outflow",$H12<>"AED",$A12>Settings!$B$21),-1-ROW()/1000000,$G12+ROW()/1000000) -> -1.000012
A13: 46246 | B13: Advance August salary (2nd portion) | C13: Salary | D13: Inflow | E13: 1540 | G13: =IF($A13="","",IF($F13="",$E13,$F13)) -> 1540 | H13: AED | I13: Yes | J13: 46246 | K13: FAB 4001 Current | L13: None | M13: – | N13: Critical | O13: Estimated | P13: =IF($A13="","",$A13-Settings!$B$9) -> -14 | Q13: =IF($A13="","",IF($I13="Yes","Settled",IF($P13<0,"OVERDUE",IF($P13<=3,"DUE ≤3 DAYS",IF($P13<=7,"DUE ≤7 DAYS","Scheduled"))))) -> Settled | R13: CONFIRMED 12 Aug — landed in FAB 4001 (not 4002 as planned), combined with the 1,430 refund as one AED 3,000 remittance. AED 30 surplus above the expected 2,970 remains unexplained. | S13: =IF(OR($A13="",$I13="Yes",$D13<>"Outflow",$H13<>"AED"),99999+ROW()/1000000,$P13+ROW()/1000000) -> 99999 | T13: =IF(OR($A13="",$I13="Yes",$D13<>"Outflow",$H13<>"AED",$A13>Settings!$B$21),-1-ROW()/1000000,$G13+ROW()/1000000) -> -1.000013
G14: =IF($A14="","",IF($F14="",$E14,$F14)) | P14: =IF($A14="","",$A14-Settings!$B$9) | Q14: =IF($A14="","",IF($I14="Yes","Settled",IF($P14<0,"OVERDUE",IF($P14<=3,"DUE ≤3 DAYS",IF($P14<=7,"DUE ≤7 DAYS","Scheduled"))))) | S14: =IF(OR($A14="",$I14="Yes",$D14<>"Outflow",$H14<>"AED"),99999+ROW()/1000000,$P14+ROW()/1000000) -> 99999 | T14: =IF(OR($A14="",$I14="Yes",$D14<>"Outflow",$H14<>"AED",$A14>Settings!$B$21),-1-ROW()/1000000,$G14+ROW()/1000000) -> -1.000014
A15: 46246 | B15: Rent refund — Emirates ticket | C15: Refund / Reimbursement | D15: Inflow | E15: 1430 | G15: =IF($A15="","",IF($F15="",$E15,$F15)) -> 1430 | H15: AED | I15: Yes | K15: FAB 4001 Current | L15: None | M15: – | N15: Critical | O15: Estimated | P15: =IF($A15="","",$A15-Settings!$B$9) -> -14 | Q15: =IF($A15="","",IF($I15="Yes","Settled",IF($P15<0,"OVERDUE",IF($P15<=3,"DUE ≤3 DAYS",IF($P15<=7,"DUE ≤7 DAYS","Scheduled"))))) -> Settled | R15: CONFIRMED 12 Aug — landed in FAB 4001, NOT the vault as originally planned. Move manually to FAB 4002 to protect it for rent. | S15: =IF(OR($A15="",$I15="Yes",$D15<>"Outflow",$H15<>"AED"),99999+ROW()/1000000,$P15+ROW()/1000000) -> 99999 | T15: =IF(OR($A15="",$I15="Yes",$D15<>"Outflow",$H15<>"AED",$A15>Settings!$B$21),-1-ROW()/1000000,$G15+ROW()/1000000) -> -1.000015
A16: 46268 | B16: Tabby — no-fee minimum | C16: BNPL | D16: Outflow | E16: 1314.5 | G16: =IF($A16="","",IF($F16="",$E16,$F16)) -> 1314.5 | H16: AED | I16: Yes | J16: 46260 | K16: NBD Current | L16: None | M16: Yes | N16: Essential | O16: Actual | P16: =IF($A16="","",$A16-Settings!$B$9) -> 8 | Q16: =IF($A16="","",IF($I16="Yes","Settled",IF($P16<0,"OVERDUE",IF($P16<=3,"DUE ≤3 DAYS",IF($P16<=7,"DUE ≤7 DAYS","Scheduled"))))) -> Settled | R16: CONFIRMED PAID via Tabby app screenshot — no-fee minimum fully settled, amount due AED 0.00. Paid via NBD (1,309.65 net of 4.85 cashback), not FAB as originally modeled. | S16: =IF(OR($A16="",$I16="Yes",$D16<>"Outflow",$H16<>"AED"),99999+ROW()/1000000,$P16+ROW()/1000000) -> 99999 | T16: =IF(OR($A16="",$I16="Yes",$D16<>"Outflow",$H16<>"AED",$A16>Settings!$B$21),-1-ROW()/1000000,$G16+ROW()/1000000) -> -1.000016
A17: 46280 | B17: du — September | C17: Telecom | D17: Outflow | E17: 590.98 | G17: =IF($A17="","",IF($F17="",$E17,$F17)) -> 590.98 | H17: AED | I17: No | K17: FAB 4001 Current | L17: Monthly | M17: Yes | N17: Essential | O17: Estimated | P17: =IF($A17="","",$A17-Settings!$B$9) -> 20 | Q17: =IF($A17="","",IF($I17="Yes","Settled",IF($P17<0,"OVERDUE",IF($P17<=3,"DUE ≤3 DAYS",IF($P17<=7,"DUE ≤7 DAYS","Scheduled"))))) -> Scheduled | R17: Bill issued 2–3 Sep · due by the 15th | S17: =IF(OR($A17="",$I17="Yes",$D17<>"Outflow",$H17<>"AED"),99999+ROW()/1000000,$P17+ROW()/1000000) -> 20.000017 | T17: =IF(OR($A17="",$I17="Yes",$D17<>"Outflow",$H17<>"AED",$A17>Settings!$B$21),-1-ROW()/1000000,$G17+ROW()/1000000) -> 590.98002
A18: 46280 | B18: Etisalat — September | C18: Telecom | D18: Outflow | E18: 323.95 | G18: =IF($A18="","",IF($F18="",$E18,$F18)) -> 323.95 | H18: AED | I18: No | K18: FAB 4001 Current | L18: Monthly | M18: Yes | N18: Essential | O18: Estimated | P18: =IF($A18="","",$A18-Settings!$B$9) -> 20 | Q18: =IF($A18="","",IF($I18="Yes","Settled",IF($P18<0,"OVERDUE",IF($P18<=3,"DUE ≤3 DAYS",IF($P18<=7,"DUE ≤7 DAYS","Scheduled"))))) -> Scheduled | R18: Bill issued 2–3 Sep · due by the 15th | S18: =IF(OR($A18="",$I18="Yes",$D18<>"Outflow",$H18<>"AED"),99999+ROW()/1000000,$P18+ROW()/1000000) -> 20.000018 | T18: =IF(OR($A18="",$I18="Yes",$D18<>"Outflow",$H18<>"AED",$A18>Settings!$B$21),-1-ROW()/1000000,$G18+ROW()/1000000) -> 323.95002
A19: 46275 | B19: Nippon SIP — September | C19: Investments | D19: Outflow | E19: 462.4 | G19: =IF($A19="","",IF($F19="",$E19,$F19)) -> 462.4 | H19: AED | I19: No | K19: ICICI (INR) | L19: Monthly | M19: Yes | N19: Core investment | O19: Estimated | P19: =IF($A19="","",$A19-Settings!$B$9) -> 15 | Q19: =IF($A19="","",IF($I19="Yes","Settled",IF($P19<0,"OVERDUE",IF($P19<=3,"DUE ≤3 DAYS",IF($P19<=7,"DUE ≤7 DAYS","Scheduled"))))) -> Scheduled | R19: INR 12,000 at the last confirmed rate | S19: =IF(OR($A19="",$I19="Yes",$D19<>"Outflow",$H19<>"AED"),99999+ROW()/1000000,$P19+ROW()/1000000) -> 15.000019 | T19: =IF(OR($A19="",$I19="Yes",$D19<>"Outflow",$H19<>"AED",$A19>Settings!$B$21),-1-ROW()/1000000,$G19+ROW()/1000000) -> 462.40002
A20: 46295 | B20: DEWA — September | C20: Utilities | D20: Outflow | E20: 793.42 | G20: =IF($A20="","",IF($F20="",$E20,$F20)) -> 793.42 | H20: AED | I20: No | K20: FAB 4001 Current | L20: Monthly | M20: Yes | N20: Essential | O20: Estimated | P20: =IF($A20="","",$A20-Settings!$B$9) -> 35 | Q20: =IF($A20="","",IF($I20="Yes","Settled",IF($P20<0,"OVERDUE",IF($P20<=3,"DUE ≤3 DAYS",IF($P20<=7,"DUE ≤7 DAYS","Scheduled"))))) -> Scheduled | R20: Bill issued 20 Sep · due by month-end | S20: =IF(OR($A20="",$I20="Yes",$D20<>"Outflow",$H20<>"AED"),99999+ROW()/1000000,$P20+ROW()/1000000) -> 35.00002 | T20: =IF(OR($A20="",$I20="Yes",$D20<>"Outflow",$H20<>"AED",$A20>Settings!$B$21),-1-ROW()/1000000,$G20+ROW()/1000000) -> 793.42002
A21: 46291 | B21: September salary | C21: Salary | D21: Inflow | E21: 7914.88 | G21: =IF($A21="","",IF($F21="",$E21,$F21)) -> 7914.88 | H21: AED | I21: No | K21: FAB 4001 Current | L21: Monthly | M21: – | N21: Critical | O21: Estimated | P21: =IF($A21="","",$A21-Settings!$B$9) -> 31 | Q21: =IF($A21="","",IF($I21="Yes","Settled",IF($P21<0,"OVERDUE",IF($P21<=3,"DUE ≤3 DAYS",IF($P21<=7,"DUE ≤7 DAYS","Scheduled"))))) -> Scheduled | R21: Lands before the rent cheque clears | S21: =IF(OR($A21="",$I21="Yes",$D21<>"Outflow",$H21<>"AED"),99999+ROW()/1000000,$P21+ROW()/1000000) -> 99999 | T21: =IF(OR($A21="",$I21="Yes",$D21<>"Outflow",$H21<>"AED",$A21>Settings!$B$21),-1-ROW()/1000000,$G21+ROW()/1000000) -> -1.000021
A22: 46310 | B22: du — October | C22: Telecom | D22: Outflow | E22: 590.98 | G22: =IF($A22="","",IF($F22="",$E22,$F22)) -> 590.98 | H22: AED | I22: No | K22: FAB 4001 Current | L22: Monthly | M22: Yes | N22: Essential | O22: Estimated | P22: =IF($A22="","",$A22-Settings!$B$9) -> 50 | Q22: =IF($A22="","",IF($I22="Yes","Settled",IF($P22<0,"OVERDUE",IF($P22<=3,"DUE ≤3 DAYS",IF($P22<=7,"DUE ≤7 DAYS","Scheduled"))))) -> Scheduled | R22: Bill issued 2–3 Oct · due by the 15th | S22: =IF(OR($A22="",$I22="Yes",$D22<>"Outflow",$H22<>"AED"),99999+ROW()/1000000,$P22+ROW()/1000000) -> 50.000022 | T22: =IF(OR($A22="",$I22="Yes",$D22<>"Outflow",$H22<>"AED",$A22>Settings!$B$21),-1-ROW()/1000000,$G22+ROW()/1000000) -> 590.98002
A23: 46310 | B23: Etisalat — October | C23: Telecom | D23: Outflow | E23: 323.95 | G23: =IF($A23="","",IF($F23="",$E23,$F23)) -> 323.95 | H23: AED | I23: No | K23: FAB 4001 Current | L23: Monthly | M23: Yes | N23: Essential | O23: Estimated | P23: =IF($A23="","",$A23-Settings!$B$9) -> 50 | Q23: =IF($A23="","",IF($I23="Yes","Settled",IF($P23<0,"OVERDUE",IF($P23<=3,"DUE ≤3 DAYS",IF($P23<=7,"DUE ≤7 DAYS","Scheduled"))))) -> Scheduled | R23: Bill issued 2–3 Oct · due by the 15th | S23: =IF(OR($A23="",$I23="Yes",$D23<>"Outflow",$H23<>"AED"),99999+ROW()/1000000,$P23+ROW()/1000000) -> 50.000023 | T23: =IF(OR($A23="",$I23="Yes",$D23<>"Outflow",$H23<>"AED",$A23>Settings!$B$21),-1-ROW()/1000000,$G23+ROW()/1000000) -> 323.95002
A24: 46305 | B24: Nippon SIP — October | C24: Investments | D24: Outflow | E24: 462.4 | G24: =IF($A24="","",IF($F24="",$E24,$F24)) -> 462.4 | H24: AED | I24: No | K24: ICICI (INR) | L24: Monthly | M24: Yes | N24: Core investment | O24: Estimated | P24: =IF($A24="","",$A24-Settings!$B$9) -> 45 | Q24: =IF($A24="","",IF($I24="Yes","Settled",IF($P24<0,"OVERDUE",IF($P24<=3,"DUE ≤3 DAYS",IF($P24<=7,"DUE ≤7 DAYS","Scheduled"))))) -> Scheduled | S24: =IF(OR($A24="",$I24="Yes",$D24<>"Outflow",$H24<>"AED"),99999+ROW()/1000000,$P24+ROW()/1000000) -> 45.000024 | T24: =IF(OR($A24="",$I24="Yes",$D24<>"Outflow",$H24<>"AED",$A24>Settings!$B$21),-1-ROW()/1000000,$G24+ROW()/1000000) -> 462.40002
A25: 46326 | B25: DEWA — October | C25: Utilities | D25: Outflow | E25: 793.42 | G25: =IF($A25="","",IF($F25="",$E25,$F25)) -> 793.42 | H25: AED | I25: No | K25: FAB 4001 Current | L25: Monthly | M25: Yes | N25: Essential | O25: Estimated | P25: =IF($A25="","",$A25-Settings!$B$9) -> 66 | Q25: =IF($A25="","",IF($I25="Yes","Settled",IF($P25<0,"OVERDUE",IF($P25<=3,"DUE ≤3 DAYS",IF($P25<=7,"DUE ≤7 DAYS","Scheduled"))))) -> Scheduled | R25: Bill issued 20 Oct · due by month-end — falls AFTER the rent cheque, funded by the 26 Oct salary | S25: =IF(OR($A25="",$I25="Yes",$D25<>"Outflow",$H25<>"AED"),99999+ROW()/1000000,$P25+ROW()/1000000) -> 66.000025 | T25: =IF(OR($A25="",$I25="Yes",$D25<>"Outflow",$H25<>"AED",$A25>Settings!$B$21),-1-ROW()/1000000,$G25+ROW()/1000000) -> -1.000025
A26: 46317 | B26: RENT CHEQUE | C26: Rent | D26: Outflow | E26: 11750 | G26: =IF($A26="","",IF($F26="",$E26,$F26)) -> 11750 | H26: AED | I26: No | K26: FAB 4002 Home Expenditure | L26: None | M26: Yes | N26: Critical | O26: Actual | P26: =IF($A26="","",$A26-Settings!$B$9) -> 57 | Q26: =IF($A26="","",IF($I26="Yes","Settled",IF($P26<0,"OVERDUE",IF($P26<=3,"DUE ≤3 DAYS",IF($P26<=7,"DUE ≤7 DAYS","Scheduled"))))) -> Scheduled | R26: Must be fully funded by 21 Oct — the 26 Oct salary is too late | S26: =IF(OR($A26="",$I26="Yes",$D26<>"Outflow",$H26<>"AED"),99999+ROW()/1000000,$P26+ROW()/1000000) -> 57.000026 | T26: =IF(OR($A26="",$I26="Yes",$D26<>"Outflow",$H26<>"AED",$A26>Settings!$B$21),-1-ROW()/1000000,$G26+ROW()/1000000) -> -1.000026
A27: 46298 | B27: Tabby — September statement | C27: BNPL | D27: Outflow | E27: 715.33 | G27: =IF($A27="","",IF($F27="",$E27,$F27)) -> 715.33 | H27: AED | I27: No | K27: FAB 4001 Current | L27: None | M27: Yes | N27: Essential | O27: Actual | P27: =IF($A27="","",$A27-Settings!$B$9) -> 38 | Q27: =IF($A27="","",IF($I27="Yes","Settled",IF($P27<0,"OVERDUE",IF($P27<=3,"DUE ≤3 DAYS",IF($P27<=7,"DUE ≤7 DAYS","Scheduled"))))) -> Scheduled | R27: CONFIRMED via Tabby chat, 15 Aug — real figure, not estimated. No-fee minimum for the September billing cycle. | S27: =IF(OR($A27="",$I27="Yes",$D27<>"Outflow",$H27<>"AED"),99999+ROW()/1000000,$P27+ROW()/1000000) -> 38.000027 | T27: =IF(OR($A27="",$I27="Yes",$D27<>"Outflow",$H27<>"AED",$A27>Settings!$B$21),-1-ROW()/1000000,$G27+ROW()/1000000) -> 715.33003
A28: 46321 | B28: October salary | C28: Salary | D28: Inflow | E28: 7914.88 | G28: =IF($A28="","",IF($F28="",$E28,$F28)) -> 7914.88 | H28: AED | I28: No | K28: FAB 4001 Current | L28: Monthly | M28: – | N28: Critical | O28: Estimated | P28: =IF($A28="","",$A28-Settings!$B$9) -> 61 | Q28: =IF($A28="","",IF($I28="Yes","Settled",IF($P28<0,"OVERDUE",IF($P28<=3,"DUE ≤3 DAYS",IF($P28<=7,"DUE ≤7 DAYS","Scheduled"))))) -> Scheduled | R28: Lands FOUR DAYS AFTER the rent cheque clears. Deliberately excluded from rent funding — it exists here so the cash calendar past 21 Oct is honest. | S28: =IF(OR($A28="",$I28="Yes",$D28<>"Outflow",$H28<>"AED"),99999+ROW()/1000000,$P28+ROW()/1000000) -> 99999 | T28: =IF(OR($A28="",$I28="Yes",$D28<>"Outflow",$H28<>"AED",$A28>Settings!$B$21),-1-ROW()/1000000,$G28+ROW()/1000000) -> -1.000028
A29: 46409 | B29: RENT CHEQUE — January renewal | C29: Rent | D29: Outflow | E29: 11750 | G29: =IF($A29="","",IF($F29="",$E29,$F29)) -> 11750 | H29: AED | I29: No | K29: FAB 4002 Home Expenditure | L29: Quarterly | M29: Yes | N29: Critical | O29: Estimated | P29: =IF($A29="","",$A29-Settings!$B$9) -> 149 | Q29: =IF($A29="","",IF($I29="Yes","Settled",IF($P29<0,"OVERDUE",IF($P29<=3,"DUE ≤3 DAYS",IF($P29<=7,"DUE ≤7 DAYS","Scheduled"))))) -> Scheduled | R29: Lease renewal falls here. Amount assumes flat rent per owner instruction — CONFIRMED date (22nd), flat-rent assumption also confirmed. | S29: =IF(OR($A29="",$I29="Yes",$D29<>"Outflow",$H29<>"AED"),99999+ROW()/1000000,$P29+ROW()/1000000) -> 149.00003 | T29: =IF(OR($A29="",$I29="Yes",$D29<>"Outflow",$H29<>"AED",$A29>Settings!$B$21),-1-ROW()/1000000,$G29+ROW()/1000000) -> -1.000029
A30: 46499 | B30: Rent cheque — April (quarterly) | C30: Rent | D30: Outflow | E30: 11750 | G30: =IF($A30="","",IF($F30="",$E30,$F30)) -> 11750 | H30: AED | I30: No | K30: FAB 4002 Home Expenditure | L30: Quarterly | M30: Yes | N30: Critical | O30: Estimated | P30: =IF($A30="","",$A30-Settings!$B$9) -> 239 | Q30: =IF($A30="","",IF($I30="Yes","Settled",IF($P30<0,"OVERDUE",IF($P30<=3,"DUE ≤3 DAYS",IF($P30<=7,"DUE ≤7 DAYS","Scheduled"))))) -> Scheduled | R30: Confirmed pattern — quarterly cheques, Jan date verified by owner | S30: =IF(OR($A30="",$I30="Yes",$D30<>"Outflow",$H30<>"AED"),99999+ROW()/1000000,$P30+ROW()/1000000) -> 239.00003 | T30: =IF(OR($A30="",$I30="Yes",$D30<>"Outflow",$H30<>"AED",$A30>Settings!$B$21),-1-ROW()/1000000,$G30+ROW()/1000000) -> -1.00003
A31: 46590 | B31: Rent cheque — July (quarterly) | C31: Rent | D31: Outflow | E31: 11750 | G31: =IF($A31="","",IF($F31="",$E31,$F31)) -> 11750 | H31: AED | I31: No | K31: FAB 4002 Home Expenditure | L31: Quarterly | M31: Yes | N31: Critical | O31: Estimated | P31: =IF($A31="","",$A31-Settings!$B$9) -> 330 | Q31: =IF($A31="","",IF($I31="Yes","Settled",IF($P31<0,"OVERDUE",IF($P31<=3,"DUE ≤3 DAYS",IF($P31<=7,"DUE ≤7 DAYS","Scheduled"))))) -> Scheduled | R31: Confirmed pattern — quarterly cheques, Jan date verified by owner | S31: =IF(OR($A31="",$I31="Yes",$D31<>"Outflow",$H31<>"AED"),99999+ROW()/1000000,$P31+ROW()/1000000) -> 330.00003 | T31: =IF(OR($A31="",$I31="Yes",$D31<>"Outflow",$H31<>"AED",$A31>Settings!$B$21),-1-ROW()/1000000,$G31+ROW()/1000000) -> -1.000031
A32: 46329 | B32: Tabby — October statement (est.) | C32: BNPL | D32: Outflow | E32: 657.53 | G32: =IF($A32="","",IF($F32="",$E32,$F32)) -> 657.53 | H32: AED | I32: No | K32: FAB 4001 Current | L32: None | M32: Yes | N32: Essential | O32: Actual | P32: =IF($A32="","",$A32-Settings!$B$9) -> 69 | Q32: =IF($A32="","",IF($I32="Yes","Settled",IF($P32<0,"OVERDUE",IF($P32<=3,"DUE ≤3 DAYS",IF($P32<=7,"DUE ≤7 DAYS","Scheduled"))))) -> Scheduled | R32: CONFIRMED via Tabby app screenshot — exact match to prior estimate. Statement balance AED 657.53, rolls to next month for free (no fee for the roll itself). | S32: =IF(OR($A32="",$I32="Yes",$D32<>"Outflow",$H32<>"AED"),99999+ROW()/1000000,$P32+ROW()/1000000) -> 69.000032 | T32: =IF(OR($A32="",$I32="Yes",$D32<>"Outflow",$H32<>"AED",$A32>Settings!$B$21),-1-ROW()/1000000,$G32+ROW()/1000000) -> -1.000032
G33: =IF($A33="","",IF($F33="",$E33,$F33)) | P33: =IF($A33="","",$A33-Settings!$B$9) | Q33: =IF($A33="","",IF($I33="Yes","Settled",IF($P33<0,"OVERDUE",IF($P33<=3,"DUE ≤3 DAYS",IF($P33<=7,"DUE ≤7 DAYS","Scheduled"))))) | S33: =IF(OR($A33="",$I33="Yes",$D33<>"Outflow",$H33<>"AED"),99999+ROW()/1000000,$P33+ROW()/1000000) -> 99999 | T33: =IF(OR($A33="",$I33="Yes",$D33<>"Outflow",$H33<>"AED",$A33>Settings!$B$21),-1-ROW()/1000000,$G33+ROW()/1000000) -> -1.000033
G34: =IF($A34="","",IF($F34="",$E34,$F34)) | P34: =IF($A34="","",$A34-Settings!$B$9) | Q34: =IF($A34="","",IF($I34="Yes","Settled",IF($P34<0,"OVERDUE",IF($P34<=3,"DUE ≤3 DAYS",IF($P34<=7,"DUE ≤7 DAYS","Scheduled"))))) | S34: =IF(OR($A34="",$I34="Yes",$D34<>"Outflow",$H34<>"AED"),99999+ROW()/1000000,$P34+ROW()/1000000) -> 99999 | T34: =IF(OR($A34="",$I34="Yes",$D34<>"Outflow",$H34<>"AED",$A34>Settings!$B$21),-1-ROW()/1000000,$G34+ROW()/1000000) -> -1.000034
G35: =IF($A35="","",IF($F35="",$E35,$F35)) | P35: =IF($A35="","",$A35-Settings!$B$9) | Q35: =IF($A35="","",IF($I35="Yes","Settled",IF($P35<0,"OVERDUE",IF($P35<=3,"DUE ≤3 DAYS",IF($P35<=7,"DUE ≤7 DAYS","Scheduled"))))) | S35: =IF(OR($A35="",$I35="Yes",$D35<>"Outflow",$H35<>"AED"),99999+ROW()/1000000,$P35+ROW()/1000000) -> 99999 | T35: =IF(OR($A35="",$I35="Yes",$D35<>"Outflow",$H35<>"AED",$A35>Settings!$B$21),-1-ROW()/1000000,$G35+ROW()/1000000) -> -1.000035
G36: =IF($A36="","",IF($F36="",$E36,$F36)) | P36: =IF($A36="","",$A36-Settings!$B$9) | Q36: =IF($A36="","",IF($I36="Yes","Settled",IF($P36<0,"OVERDUE",IF($P36<=3,"DUE ≤3 DAYS",IF($P36<=7,"DUE ≤7 DAYS","Scheduled"))))) | S36: =IF(OR($A36="",$I36="Yes",$D36<>"Outflow",$H36<>"AED"),99999+ROW()/1000000,$P36+ROW()/1000000) -> 99999 | T36: =IF(OR($A36="",$I36="Yes",$D36<>"Outflow",$H36<>"AED",$A36>Settings!$B$21),-1-ROW()/1000000,$G36+ROW()/1000000) -> -1.000036
G37: =IF($A37="","",IF($F37="",$E37,$F37)) | P37: =IF($A37="","",$A37-Settings!$B$9) | Q37: =IF($A37="","",IF($I37="Yes","Settled",IF($P37<0,"OVERDUE",IF($P37<=3,"DUE ≤3 DAYS",IF($P37<=7,"DUE ≤7 DAYS","Scheduled"))))) | S37: =IF(OR($A37="",$I37="Yes",$D37<>"Outflow",$H37<>"AED"),99999+ROW()/1000000,$P37+ROW()/1000000) -> 99999 | T37: =IF(OR($A37="",$I37="Yes",$D37<>"Outflow",$H37<>"AED",$A37>Settings!$B$21),-1-ROW()/1000000,$G37+ROW()/1000000) -> -1.000037
G38: =IF($A38="","",IF($F38="",$E38,$F38)) | P38: =IF($A38="","",$A38-Settings!$B$9) | Q38: =IF($A38="","",IF($I38="Yes","Settled",IF($P38<0,"OVERDUE",IF($P38<=3,"DUE ≤3 DAYS",IF($P38<=7,"DUE ≤7 DAYS","Scheduled"))))) | S38: =IF(OR($A38="",$I38="Yes",$D38<>"Outflow",$H38<>"AED"),99999+ROW()/1000000,$P38+ROW()/1000000) -> 99999 | T38: =IF(OR($A38="",$I38="Yes",$D38<>"Outflow",$H38<>"AED",$A38>Settings!$B$21),-1-ROW()/1000000,$G38+ROW()/1000000) -> -1.000038
G39: =IF($A39="","",IF($F39="",$E39,$F39)) | P39: =IF($A39="","",$A39-Settings!$B$9) | Q39: =IF($A39="","",IF($I39="Yes","Settled",IF($P39<0,"OVERDUE",IF($P39<=3,"DUE ≤3 DAYS",IF($P39<=7,"DUE ≤7 DAYS","Scheduled"))))) | S39: =IF(OR($A39="",$I39="Yes",$D39<>"Outflow",$H39<>"AED"),99999+ROW()/1000000,$P39+ROW()/1000000) -> 99999 | T39: =IF(OR($A39="",$I39="Yes",$D39<>"Outflow",$H39<>"AED",$A39>Settings!$B$21),-1-ROW()/1000000,$G39+ROW()/1000000) -> -1.000039
G40: =IF($A40="","",IF($F40="",$E40,$F40)) | P40: =IF($A40="","",$A40-Settings!$B$9) | Q40: =IF($A40="","",IF($I40="Yes","Settled",IF($P40<0,"OVERDUE",IF($P40<=3,"DUE ≤3 DAYS",IF($P40<=7,"DUE ≤7 DAYS","Scheduled"))))) | S40: =IF(OR($A40="",$I40="Yes",$D40<>"Outflow",$H40<>"AED"),99999+ROW()/1000000,$P40+ROW()/1000000) -> 99999 | T40: =IF(OR($A40="",$I40="Yes",$D40<>"Outflow",$H40<>"AED",$A40>Settings!$B$21),-1-ROW()/1000000,$G40+ROW()/1000000) -> -1.00004
G41: =IF($A41="","",IF($F41="",$E41,$F41)) | P41: =IF($A41="","",$A41-Settings!$B$9) | Q41: =IF($A41="","",IF($I41="Yes","Settled",IF($P41<0,"OVERDUE",IF($P41<=3,"DUE ≤3 DAYS",IF($P41<=7,"DUE ≤7 DAYS","Scheduled"))))) | S41: =IF(OR($A41="",$I41="Yes",$D41<>"Outflow",$H41<>"AED"),99999+ROW()/1000000,$P41+ROW()/1000000) -> 99999 | T41: =IF(OR($A41="",$I41="Yes",$D41<>"Outflow",$H41<>"AED",$A41>Settings!$B$21),-1-ROW()/1000000,$G41+ROW()/1000000) -> -1.000041
G42: =IF($A42="","",IF($F42="",$E42,$F42)) | P42: =IF($A42="","",$A42-Settings!$B$9) | Q42: =IF($A42="","",IF($I42="Yes","Settled",IF($P42<0,"OVERDUE",IF($P42<=3,"DUE ≤3 DAYS",IF($P42<=7,"DUE ≤7 DAYS","Scheduled"))))) | S42: =IF(OR($A42="",$I42="Yes",$D42<>"Outflow",$H42<>"AED"),99999+ROW()/1000000,$P42+ROW()/1000000) -> 99999 | T42: =IF(OR($A42="",$I42="Yes",$D42<>"Outflow",$H42<>"AED",$A42>Settings!$B$21),-1-ROW()/1000000,$G42+ROW()/1000000) -> -1.000042
G43: =IF($A43="","",IF($F43="",$E43,$F43)) | P43: =IF($A43="","",$A43-Settings!$B$9) | Q43: =IF($A43="","",IF($I43="Yes","Settled",IF($P43<0,"OVERDUE",IF($P43<=3,"DUE ≤3 DAYS",IF($P43<=7,"DUE ≤7 DAYS","Scheduled"))))) | S43: =IF(OR($A43="",$I43="Yes",$D43<>"Outflow",$H43<>"AED"),99999+ROW()/1000000,$P43+ROW()/1000000) -> 99999 | T43: =IF(OR($A43="",$I43="Yes",$D43<>"Outflow",$H43<>"AED",$A43>Settings!$B$21),-1-ROW()/1000000,$G43+ROW()/1000000) -> -1.000043
G44: =IF($A44="","",IF($F44="",$E44,$F44)) | P44: =IF($A44="","",$A44-Settings!$B$9) | Q44: =IF($A44="","",IF($I44="Yes","Settled",IF($P44<0,"OVERDUE",IF($P44<=3,"DUE ≤3 DAYS",IF($P44<=7,"DUE ≤7 DAYS","Scheduled"))))) | S44: =IF(OR($A44="",$I44="Yes",$D44<>"Outflow",$H44<>"AED"),99999+ROW()/1000000,$P44+ROW()/1000000) -> 99999 | T44: =IF(OR($A44="",$I44="Yes",$D44<>"Outflow",$H44<>"AED",$A44>Settings!$B$21),-1-ROW()/1000000,$G44+ROW()/1000000) -> -1.000044
... G80: =IF($A80="","",IF($F80="",$E80,$F80)) | P80: =IF($A80="","",$A80-Settings!$B$9) | Q80: =IF($A80="","",IF($I80="Yes","Settled",IF($P80<0,"OVERDUE",IF($P80<=3,"DUE ≤3 DAYS",IF($P80<=7,"DUE ≤7 DAYS","Scheduled"))))) | S80: =IF(OR($A80="",$I80="Yes",$D80<>"Outflow",$H80<>"AED"),99999+ROW()/1000000,$P80+ROW()/1000000) -> 99999 | T80: =IF(OR($A80="",$I80="Yes",$D80<>"Outflow",$H80<>"AED",$A80>Settings!$B$21),-1-ROW()/1000000,$G80+ROW()/1000000) -> -1.00008
A115: 46291 | B115: Tabby — monthly card fee | C115: BNPL | D115: Outflow | E115: 49 | G115: =IF($A115="","",IF($F115="",$E115,$F115)) -> 49 | H115: AED | I115: No | K115: NBD Current | L115: Monthly | M115: Yes | N115: Essential | O115: Confirmed | P115: =IF($A115="","",$A115-Settings!$B$9) -> 31 | Q115: =IF($A115="","",IF($I115="Yes","Settled",IF($P115<0,"OVERDUE",IF($P115<=3,"DUE ≤3 DAYS",IF($P115<=7,"DUE ≤7 DAYS","Scheduled"))))) -> Scheduled | R115: NEW — discovered 26 Aug. Continues monthly until the card is closed after the final Tabby payment (~3 Nov). Not previously in the plan.
A116: 46321 | B116: Tabby — monthly card fee | C116: BNPL | D116: Outflow | E116: 49 | G116: =IF($A116="","",IF($F116="",$E116,$F116)) -> 49 | H116: AED | I116: No | K116: NBD Current | L116: Monthly | M116: Yes | N116: Essential | O116: Confirmed | P116: =IF($A116="","",$A116-Settings!$B$9) -> 61 | Q116: =IF($A116="","",IF($I116="Yes","Settled",IF($P116<0,"OVERDUE",IF($P116<=3,"DUE ≤3 DAYS",IF($P116<=7,"DUE ≤7 DAYS","Scheduled"))))) -> Scheduled | R116: NEW — discovered 26 Aug. Continues monthly until the card is closed after the final Tabby payment (~3 Nov). Not previously in the plan.

Sheet Rent Vault
A1: Rent Protection System
A2: Rent money is not spending money. This sheet exists so the October cheque can never be quietly cannibalised.
A5: FUNDING POSITION
A6: Measure | B6: Value | C6: Unit | D6: Basis
A7: Rent cheque amount | B7: =Settings!$B$19 -> 11750 | C7: AED | D7: Control panel
A8: Cheque clears | B8: =Settings!$B$20 -> 46317 | C8: date | D8: Lease schedule
A9: Must be fully funded by | B9: =Settings!$B$21 -> 46316 | C9: date | D9: One day before clearing
A10: Days until funding deadline | B10: =Settings!$B$22 -> 56 | C10: days | D10: Live countdown
A11: Already vaulted (designated rent-vault account) | B11: =SUMIFS(Accounts!$E$7:$E$14,Accounts!$H$7:$H$14,"Rent vault") -> 5940.7 | C11: AED | D11: Reserved column, Accounts sheet
A12: Still to fund | B12: =MAX($B$7-$B$11,0) -> 5809.3 | C12: AED | D12: Cheque less vaulted
A13: Rent funding progress | B13: =IF($B$7=0,0,$B$11/$B$7) -> 0.50559149 | C13: % | D13: Vaulted / cheque
A14: Salary cycles before the deadline | B14: =COUNTIFS('Bills & Commitments'!$C$7:$C$80,"Salary",'Bills & Commitments'!$D$7:$D$80,"Inflow",'Bills & Commitments'!$I$7:$I$80,"No",'Bills & Commitments'!$A$7:$A$80,"<="&Settings!$B$21) -> 1 | C14: count | D14: Unsettled salary inflows on the Bills sheet
A15: Recommended contribution per remaining inflow | B15: =IF($B$14=0,0,$B$12/$B$14) -> 5809.3 | C15: AED | D15: Still to fund / cycles
A16: Projected cash available for rent by the deadline | B16: =Settings!$B$71 -> 8908.97 | C16: AED | D16: Engine E12 — spendable + inflows − commitments − minimum living + vault
A17: PROJECTED SHORTFALL | B17: =MAX($B$7-$B$16,0) -> 2841.03 | C17: AED | D17: Rent cheque less the cash projected to be available
A18: Funding on track? | B18: =IF($B$17<=0.009,"ON TRACK","NOT ON TRACK") -> NOT ON TRACK | C18: status | D18: Zero shortfall required
A21: ZERO-GAP CLOSURE PLAN · carried forward from the original workbook and re-verified
A22: Closure action | B22: Amount | C22: Deadline | D22: Evidence rule — only banked cash counts
A23: Projected shortfall before closure actions | B23: =$B$17 -> 2841.03 | C23: 46316 | D23: Live figure from the funding position above
A24: Lift August income to the AED 8,800 target | B24: =MAX(225.12,0) -> 225.12 | C24: 46265 | D24: Only confirmed receipts count
A25: Generate confirmed side income | B25: =600 -> 600 | C25: 46295 | D25: Only banked cash counts
A26: Hold living spend below the revised cap | B26: =MAX($B$23-$B$24-$B$25,0) -> 2015.91 | C26: 46316 | D26: Ledger spending must tie to the cap
A27: REMAINING GAP AFTER ALL ACTIONS | B27: =MAX($B$23-$B$24-$B$25-$B$26,0) -> 0 | C27: 46316 | D27: Must equal zero
A28: Revised living cap to the deadline | B28: =MAX(Settings!$B$22*Settings!$B$15-$B$26,0) -> 0 | C28: 46316 | D28: Minimum living need less the required reduction
A29: Revised cap expressed per day | B29: =IF(Settings!$B$22=0,0,$B$28/Settings!$B$22) -> 0 | C29: AED/day | D29: What you may actually spend per day if all three closure actions land
A30: Contingency: if the AED 1,430 refund fails the shortfall grows by AED 1,430. If the AED 1,540 pending salary cash fails it grows by AED 1,540. If both fail the plan needs AED 2,970 more than shown. Never release rent money against an unconfirmed inflow.
A35: How the cheque actually gets funded: money accumulates in FAB 4002 Home Expenditure, then moves across to FAB 4001 Current shortly before 22 October so the cheque clears. The vault balance below is the 4002 balance flagged as Reserved on the Accounts sheet.

Sheet Cash Calendar
A1: 90-Day Cash Calendar
A2: Week by week to the rent cheque. The monthly view hides the crunch weeks — this one does not.
A5: WEEKLY CASH PATH · blue cells are yours to plan and record
A6: Week start | B6: Week end | C6: Opening spendable | D6: Expected inflows | E6: Bills due | F6: Living | G6: Side-income target | H6: Side income BANKED (log here) | I6: Move to rent vault | J6: Closing spendable | K6: Rent vault balance | L6: Status | M6: Actual spent | N6: Spend status | O6: Earn status | P6: Cumulative earned | Q6: Cumulative target | R6: Overall earn status
A7: 46245 | B7: 46251 | C7: =Settings!$B$62 -> 156.8 | D7: =SUMIFS('Bills & Commitments'!$G$7:$G$80,'Bills & Commitments'!$D$7:$D$80,"Inflow",'Bills & Commitments'!$I$7:$I$80,"No",'Bills & Commitments'!$H$7:$H$80,"AED",'Bills & Commitments'!$A$7:$A$80,">="&$A7,'Bills & Commitments'!$A$7:$A$80,"<="&$B7) -> 0 | E7: =SUMIFS('Bills & Commitments'!$G$7:$G$80,'Bills & Commitments'!$D$7:$D$80,"Outflow",'Bills & Commitments'!$I$7:$I$80,"No",'Bills & Commitments'!$H$7:$H$80,"AED",'Bills & Commitments'!$C$7:$C$80,"<>Rent",'Bills & Commitments'!$A$7:$A$80,">="&$A7,'Bills & Commitments'!$A$7:$A$80,"<="&$B7) -> 0 | F7: =($B7-$A7+1)*Settings!$B$15 -> 105 | G7: =Settings!$B$83 -> 386.37875 | H7: 0 | I7: 0 | J7: =$C7+$D7+$H7-$E7-$F7-$I7 -> 51.8 | K7: =SUMIFS(Accounts!$E$7:$E$14,Accounts!$H$7:$H$14,"Rent vault")+$I7-SUMIFS('Bills & Commitments'!$G$7:$G$80,'Bills & Commitments'!$C$7:$C$80,"Rent",'Bills & Commitments'!$A$7:$A$80,">="&$A7,'Bills & Commitments'!$A$7:$A$80,"<="&$B7) -> 5940.7 | L7: =IF($J7<0,"NEGATIVE",IF($J7<Settings!$B$14,"BELOW BUFFER","OK")) -> BELOW BUFFER | M7: =SUMIFS(Transactions!$O$7:$O$520,Transactions!$F$7:$F$520,"Expense",Transactions!$P$7:$P$520,"AED",Transactions!$J$7:$J$520,"<>Business",Transactions!$B$7:$B$520,">="&$A7,Transactions!$B$7:$B$520,"<="&$B7) -> 616.33 | N7: =IF($M7>$F7,"OVER","On track") -> OVER | O7: =IF($H7>=$G7,"On track",IF($H7>=$G7*0.5,"Behind","Well behind")) -> Well behind | P7: =SUM($H$7:$H7) -> 0 | Q7: =SUM($G$7:$G7) -> 386.37875 | R7: =IF($P7>=$Q7,"ON PACE overall","SHORT by AED "&TEXT($Q7-$P7,"#,##0.00")) -> SHORT by AED 386.38
A8: 46252 | B8: 46258 | C8: =$J7 -> 51.8 | D8: =SUMIFS('Bills & Commitments'!$G$7:$G$80,'Bills & Commitments'!$D$7:$D$80,"Inflow",'Bills & Commitments'!$I$7:$I$80,"No",'Bills & Commitments'!$H$7:$H$80,"AED",'Bills & Commitments'!$A$7:$A$80,">="&$A8,'Bills & Commitments'!$A$7:$A$80,"<="&$B8) -> 0 | E8: =SUMIFS('Bills & Commitments'!$G$7:$G$80,'Bills & Commitments'!$D$7:$D$80,"Outflow",'Bills & Commitments'!$I$7:$I$80,"No",'Bills & Commitments'!$H$7:$H$80,"AED",'Bills & Commitments'!$C$7:$C$80,"<>Rent",'Bills & Commitments'!$A$7:$A$80,">="&$A8,'Bills & Commitments'!$A$7:$A$80,"<="&$B8) -> 0 | F8: =($B8-$A8+1)*Settings!$B$15 -> 105 | G8: =Settings!$B$83 -> 386.37875 | H8: 0 | I8: 0 | J8: =$C8+$D8+$H8-$E8-$F8-$I8 -> -53.2 | K8: =$K7+$I8-SUMIFS('Bills & Commitments'!$G$7:$G$80,'Bills & Commitments'!$C$7:$C$80,"Rent",'Bills & Commitments'!$A$7:$A$80,">="&$A8,'Bills & Commitments'!$A$7:$A$80,"<="&$B8) -> 5940.7 | L8: =IF($J8<0,"NEGATIVE",IF($J8<Settings!$B$14,"BELOW BUFFER","OK")) -> NEGATIVE | M8: =SUMIFS(Transactions!$O$7:$O$520,Transactions!$F$7:$F$520,"Expense",Transactions!$P$7:$P$520,"AED",Transactions!$J$7:$J$520,"<>Business",Transactions!$B$7:$B$520,">="&$A8,Transactions!$B$7:$B$520,"<="&$B8) -> 674.73 | N8: =IF($M8>$F8,"OVER","On track") -> OVER | O8: =IF($H8>=$G8,"On track",IF($H8>=$G8*0.5,"Behind","Well behind")) -> Well behind | P8: =SUM($H$7:$H8) -> 0 | Q8: =SUM($G$7:$G8) -> 772.7575 | R8: =IF($P8>=$Q8,"ON PACE overall","SHORT by AED "&TEXT($Q8-$P8,"#,##0.00")) -> SHORT by AED 772.76
A9: 46259 | B9: 46265 | C9: =$J8 -> -53.2 | D9: =SUMIFS('Bills & Commitments'!$G$7:$G$80,'Bills & Commitments'!$D$7:$D$80,"Inflow",'Bills & Commitments'!$I$7:$I$80,"No",'Bills & Commitments'!$H$7:$H$80,"AED",'Bills & Commitments'!$A$7:$A$80,">="&$A9,'Bills & Commitments'!$A$7:$A$80,"<="&$B9) -> 0 | E9: =SUMIFS('Bills & Commitments'!$G$7:$G$80,'Bills & Commitments'!$D$7:$D$80,"Outflow",'Bills & Commitments'!$I$7:$I$80,"No",'Bills & Commitments'!$H$7:$H$80,"AED",'Bills & Commitments'!$C$7:$C$80,"<>Rent",'Bills & Commitments'!$A$7:$A$80,">="&$A9,'Bills & Commitments'!$A$7:$A$80,"<="&$B9) -> 0 | F9: =($B9-$A9+1)*Settings!$B$15 -> 105 | G9: =Settings!$B$83 -> 386.37875 | H9: 0 | I9: 0 | J9: =$C9+$D9+$H9-$E9-$F9-$I9 -> -158.2 | K9: =$K8+$I9-SUMIFS('Bills & Commitments'!$G$7:$G$80,'Bills & Commitments'!$C$7:$C$80,"Rent",'Bills & Commitments'!$A$7:$A$80,">="&$A9,'Bills & Commitments'!$A$7:$A$80,"<="&$B9) -> 5940.7 | L9: =IF($J9<0,"NEGATIVE",IF($J9<Settings!$B$14,"BELOW BUFFER","OK")) -> NEGATIVE | M9: =SUMIFS(Transactions!$O$7:$O$520,Transactions!$F$7:$F$520,"Expense",Transactions!$P$7:$P$520,"AED",Transactions!$J$7:$J$520,"<>Business",Transactions!$B$7:$B$520,">="&$A9,Transactions!$B$7:$B$520,"<="&$B9) -> 2920.67 | N9: =IF($M9>$F9,"OVER","On track") -> OVER | O9: =IF($H9>=$G9,"On track",IF($H9>=$G9*0.5,"Behind","Well behind")) -> Well behind | P9: =SUM($H$7:$H9) -> 0 | Q9: =SUM($G$7:$G9) -> 1159.1363 | R9: =IF($P9>=$Q9,"ON PACE overall","SHORT by AED "&TEXT($Q9-$P9,"#,##0.00")) -> SHORT by AED 1,159.14
A10: 46266 | B10: 46272 | C10: =$J9 -> -158.2 | D10: =SUMIFS('Bills & Commitments'!$G$7:$G$80,'Bills & Commitments'!$D$7:$D$80,"Inflow",'Bills & Commitments'!$I$7:$I$80,"No",'Bills & Commitments'!$H$7:$H$80,"AED",'Bills & Commitments'!$A$7:$A$80,">="&$A10,'Bills & Commitments'!$A$7:$A$80,"<="&$B10) -> 0 | E10: =SUMIFS('Bills & Commitments'!$G$7:$G$80,'Bills & Commitments'!$D$7:$D$80,"Outflow",'Bills & Commitments'!$I$7:$I$80,"No",'Bills & Commitments'!$H$7:$H$80,"AED",'Bills & Commitments'!$C$7:$C$80,"<>Rent",'Bills & Commitments'!$A$7:$A$80,">="&$A10,'Bills & Commitments'!$A$7:$A$80,"<="&$B10) -> 0 | F10: =($B10-$A10+1)*Settings!$B$15 -> 105 | G10: =Settings!$B$83 -> 386.37875 | H10: 0 | I10: 0 | J10: =$C10+$D10+$H10-$E10-$F10-$I10 -> -263.2 | K10: =$K9+$I10-SUMIFS('Bills & Commitments'!$G$7:$G$80,'Bills & Commitments'!$C$7:$C$80,"Rent",'Bills & Commitments'!$A$7:$A$80,">="&$A10,'Bills & Commitments'!$A$7:$A$80,"<="&$B10) -> 5940.7 | L10: =IF($J10<0,"NEGATIVE",IF($J10<Settings!$B$14,"BELOW BUFFER","OK")) -> NEGATIVE | M10: =SUMIFS(Transactions!$O$7:$O$520,Transactions!$F$7:$F$520,"Expense",Transactions!$P$7:$P$520,"AED",Transactions!$J$7:$J$520,"<>Business",Transactions!$B$7:$B$520,">="&$A10,Transactions!$B$7:$B$520,"<="&$B10) -> 0 | N10: =IF($M10>$F10,"OVER","On track") -> On track | O10: =IF($H10>=$G10,"On track",IF($H10>=$G10*0.5,"Behind","Well behind")) -> Well behind | P10: =SUM($H$7:$H10) -> 0 | Q10: =SUM($G$7:$G10) -> 1545.515 | R10: =IF($P10>=$Q10,"ON PACE overall","SHORT by AED "&TEXT($Q10-$P10,"#,##0.00")) -> SHORT by AED 1,545.52
A11: 46273 | B11: 46279 | C11: =$J10 -> -263.2 | D11: =SUMIFS('Bills & Commitments'!$G$7:$G$80,'Bills & Commitments'!$D$7:$D$80,"Inflow",'Bills & Commitments'!$I$7:$I$80,"No",'Bills & Commitments'!$H$7:$H$80,"AED",'Bills & Commitments'!$A$7:$A$80,">="&$A11,'Bills & Commitments'!$A$7:$A$80,"<="&$B11) -> 0 | E11: =SUMIFS('Bills & Commitments'!$G$7:$G$80,'Bills & Commitments'!$D$7:$D$80,"Outflow",'Bills & Commitments'!$I$7:$I$80,"No",'Bills & Commitments'!$H$7:$H$80,"AED",'Bills & Commitments'!$C$7:$C$80,"<>Rent",'Bills & Commitments'!$A$7:$A$80,">="&$A11,'Bills & Commitments'!$A$7:$A$80,"<="&$B11) -> 462.4 | F11: =($B11-$A11+1)*Settings!$B$15 -> 105 | G11: =Settings!$B$83 -> 386.37875 | H11: 0 | I11: 0 | J11: =$C11+$D11+$H11-$E11-$F11-$I11 -> -830.6 | K11: =$K10+$I11-SUMIFS('Bills & Commitments'!$G$7:$G$80,'Bills & Commitments'!$C$7:$C$80,"Rent",'Bills & Commitments'!$A$7:$A$80,">="&$A11,'Bills & Commitments'!$A$7:$A$80,"<="&$B11) -> 5940.7 | L11: =IF($J11<0,"NEGATIVE",IF($J11<Settings!$B$14,"BELOW BUFFER","OK")) -> NEGATIVE | M11: =SUMIFS(Transactions!$O$7:$O$520,Transactions!$F$7:$F$520,"Expense",Transactions!$P$7:$P$520,"AED",Transactions!$J$7:$J$520,"<>Business",Transactions!$B$7:$B$520,">="&$A11,Transactions!$B$7:$B$520,"<="&$B11) -> 0 | N11: =IF($M11>$F11,"OVER","On track") -> On track | O11: =IF($H11>=$G11,"On track",IF($H11>=$G11*0.5,"Behind","Well behind")) -> Well behind | P11: =SUM($H$7:$H11) -> 0 | Q11: =SUM($G$7:$G11) -> 1931.8937 | R11: =IF($P11>=$Q11,"ON PACE overall","SHORT by AED "&TEXT($Q11-$P11,"#,##0.00")) -> SHORT by AED 1,931.89
A12: 46280 | B12: 46286 | C12: =$J11 -> -830.6 | D12: =SUMIFS('Bills & Commitments'!$G$7:$G$80,'Bills & Commitments'!$D$7:$D$80,"Inflow",'Bills & Commitments'!$I$7:$I$80,"No",'Bills & Commitments'!$H$7:$H$80,"AED",'Bills & Commitments'!$A$7:$A$80,">="&$A12,'Bills & Commitments'!$A$7:$A$80,"<="&$B12) -> 0 | E12: =SUMIFS('Bills & Commitments'!$G$7:$G$80,'Bills & Commitments'!$D$7:$D$80,"Outflow",'Bills & Commitments'!$I$7:$I$80,"No",'Bills & Commitments'!$H$7:$H$80,"AED",'Bills & Commitments'!$C$7:$C$80,"<>Rent",'Bills & Commitments'!$A$7:$A$80,">="&$A12,'Bills & Commitments'!$A$7:$A$80,"<="&$B12) -> 914.93 | F12: =($B12-$A12+1)*Settings!$B$15 -> 105 | G12: =Settings!$B$83 -> 386.37875 | H12: 0 | I12: 0 | J12: =$C12+$D12+$H12-$E12-$F12-$I12 -> -1850.53 | K12: =$K11+$I12-SUMIFS('Bills & Commitments'!$G$7:$G$80,'Bills & Commitments'!$C$7:$C$80,"Rent",'Bills & Commitments'!$A$7:$A$80,">="&$A12,'Bills & Commitments'!$A$7:$A$80,"<="&$B12) -> 5940.7 | L12: =IF($J12<0,"NEGATIVE",IF($J12<Settings!$B$14,"BELOW BUFFER","OK")) -> NEGATIVE | M12: =SUMIFS(Transactions!$O$7:$O$520,Transactions!$F$7:$F$520,"Expense",Transactions!$P$7:$P$520,"AED",Transactions!$J$7:$J$520,"<>Business",Transactions!$B$7:$B$520,">="&$A12,Transactions!$B$7:$B$520,"<="&$B12) -> 0 | N12: =IF($M12>$F12,"OVER","On track") -> On track | O12: =IF($H12>=$G12,"On track",IF($H12>=$G12*0.5,"Behind","Well behind")) -> Well behind | P12: =SUM($H$7:$H12) -> 0 | Q12: =SUM($G$7:$G12) -> 2318.2725 | R12: =IF($P12>=$Q12,"ON PACE overall","SHORT by AED "&TEXT($Q12-$P12,"#,##0.00")) -> SHORT by AED 2,318.27
A13: 46287 | B13: 46293 | C13: =$J12 -> -1850.53 | D13: =SUMIFS('Bills & Commitments'!$G$7:$G$80,'Bills & Commitments'!$D$7:$D$80,"Inflow",'Bills & Commitments'!$I$7:$I$80,"No",'Bills & Commitments'!$H$7:$H$80,"AED",'Bills & Commitments'!$A$7:$A$80,">="&$A13,'Bills & Commitments'!$A$7:$A$80,"<="&$B13) -> 7914.88 | E13: =SUMIFS('Bills & Commitments'!$G$7:$G$80,'Bills & Commitments'!$D$7:$D$80,"Outflow",'Bills & Commitments'!$I$7:$I$80,"No",'Bills & Commitments'!$H$7:$H$80,"AED",'Bills & Commitments'!$C$7:$C$80,"<>Rent",'Bills & Commitments'!$A$7:$A$80,">="&$A13,'Bills & Commitments'!$A$7:$A$80,"<="&$B13) -> 0 | F13: =($B13-$A13+1)*Settings!$B$15 -> 105 | G13: =Settings!$B$83 -> 386.37875 | H13: 0 | I13: 7750 | J13: =$C13+$D13+$H13-$E13-$F13-$I13 -> -1790.65 | K13: =$K12+$I13-SUMIFS('Bills & Commitments'!$G$7:$G$80,'Bills & Commitments'!$C$7:$C$80,"Rent",'Bills & Commitments'!$A$7:$A$80,">="&$A13,'Bills & Commitments'!$A$7:$A$80,"<="&$B13) -> 13690.7 | L13: =IF($J13<0,"NEGATIVE",IF($J13<Settings!$B$14,"BELOW BUFFER","OK")) -> NEGATIVE | M13: =SUMIFS(Transactions!$O$7:$O$520,Transactions!$F$7:$F$520,"Expense",Transactions!$P$7:$P$520,"AED",Transactions!$J$7:$J$520,"<>Business",Transactions!$B$7:$B$520,">="&$A13,Transactions!$B$7:$B$520,"<="&$B13) -> 0 | N13: =IF($M13>$F13,"OVER","On track") -> On track | O13: =IF($H13>=$G13,"On track",IF($H13>=$G13*0.5,"Behind","Well behind")) -> Well behind | P13: =SUM($H$7:$H13) -> 0 | Q13: =SUM($G$7:$G13) -> 2704.6512 | R13: =IF($P13>=$Q13,"ON PACE overall","SHORT by AED "&TEXT($Q13-$P13,"#,##0.00")) -> SHORT by AED 2,704.65
A14: 46294 | B14: 46300 | C14: =$J13 -> -1790.65 | D14: =SUMIFS('Bills & Commitments'!$G$7:$G$80,'Bills & Commitments'!$D$7:$D$80,"Inflow",'Bills & Commitments'!$I$7:$I$80,"No",'Bills & Commitments'!$H$7:$H$80,"AED",'Bills & Commitments'!$A$7:$A$80,">="&$A14,'Bills & Commitments'!$A$7:$A$80,"<="&$B14) -> 0 | E14: =SUMIFS('Bills & Commitments'!$G$7:$G$80,'Bills & Commitments'!$D$7:$D$80,"Outflow",'Bills & Commitments'!$I$7:$I$80,"No",'Bills & Commitments'!$H$7:$H$80,"AED",'Bills & Commitments'!$C$7:$C$80,"<>Rent",'Bills & Commitments'!$A$7:$A$80,">="&$A14,'Bills & Commitments'!$A$7:$A$80,"<="&$B14) -> 1508.75 | F14: =($B14-$A14+1)*Settings!$B$15 -> 105 | G14: =Settings!$B$83 -> 386.37875 | H14: 0 | I14: 0 | J14: =$C14+$D14+$H14-$E14-$F14-$I14 -> -3404.4 | K14: =$K13+$I14-SUMIFS('Bills & Commitments'!$G$7:$G$80,'Bills & Commitments'!$C$7:$C$80,"Rent",'Bills & Commitments'!$A$7:$A$80,">="&$A14,'Bills & Commitments'!$A$7:$A$80,"<="&$B14) -> 13690.7 | L14: =IF($J14<0,"NEGATIVE",IF($J14<Settings!$B$14,"BELOW BUFFER","OK")) -> NEGATIVE | M14: =SUMIFS(Transactions!$O$7:$O$520,Transactions!$F$7:$F$520,"Expense",Transactions!$P$7:$P$520,"AED",Transactions!$J$7:$J$520,"<>Business",Transactions!$B$7:$B$520,">="&$A14,Transactions!$B$7:$B$520,"<="&$B14) -> 0 | N14: =IF($M14>$F14,"OVER","On track") -> On track | O14: =IF($H14>=$G14,"On track",IF($H14>=$G14*0.5,"Behind","Well behind")) -> Well behind | P14: =SUM($H$7:$H14) -> 0 | Q14: =SUM($G$7:$G14) -> 3091.03 | R14: =IF($P14>=$Q14,"ON PACE overall","SHORT by AED "&TEXT($Q14-$P14,"#,##0.00")) -> SHORT by AED 3,091.03
A15: 46301 | B15: 46307 | C15: =$J14 -> -3404.4 | D15: =SUMIFS('Bills & Commitments'!$G$7:$G$80,'Bills & Commitments'!$D$7:$D$80,"Inflow",'Bills & Commitments'!$I$7:$I$80,"No",'Bills & Commitments'!$H$7:$H$80,"AED",'Bills & Commitments'!$A$7:$A$80,">="&$A15,'Bills & Commitments'!$A$7:$A$80,"<="&$B15) -> 0 | E15: =SUMIFS('Bills & Commitments'!$G$7:$G$80,'Bills & Commitments'!$D$7:$D$80,"Outflow",'Bills & Commitments'!$I$7:$I$80,"No",'Bills & Commitments'!$H$7:$H$80,"AED",'Bills & Commitments'!$C$7:$C$80,"<>Rent",'Bills & Commitments'!$A$7:$A$80,">="&$A15,'Bills & Commitments'!$A$7:$A$80,"<="&$B15) -> 462.4 | F15: =($B15-$A15+1)*Settings!$B$15 -> 105 | G15: =Settings!$B$83 -> 386.37875 | H15: 0 | I15: 0 | J15: =$C15+$D15+$H15-$E15-$F15-$I15 -> -3971.8 | K15: =$K14+$I15-SUMIFS('Bills & Commitments'!$G$7:$G$80,'Bills & Commitments'!$C$7:$C$80,"Rent",'Bills & Commitments'!$A$7:$A$80,">="&$A15,'Bills & Commitments'!$A$7:$A$80,"<="&$B15) -> 13690.7 | L15: =IF($J15<0,"NEGATIVE",IF($J15<Settings!$B$14,"BELOW BUFFER","OK")) -> NEGATIVE | M15: =SUMIFS(Transactions!$O$7:$O$520,Transactions!$F$7:$F$520,"Expense",Transactions!$P$7:$P$520,"AED",Transactions!$J$7:$J$520,"<>Business",Transactions!$B$7:$B$520,">="&$A15,Transactions!$B$7:$B$520,"<="&$B15) -> 0 | N15: =IF($M15>$F15,"OVER","On track") -> On track | O15: =IF($H15>=$G15,"On track",IF($H15>=$G15*0.5,"Behind","Well behind")) -> Well behind | P15: =SUM($H$7:$H15) -> 0 | Q15: =SUM($G$7:$G15) -> 3477.4088 | R15: =IF($P15>=$Q15,"ON PACE overall","SHORT by AED "&TEXT($Q15-$P15,"#,##0.00")) -> SHORT by AED 3,477.41
A16: 46308 | B16: 46314 | C16: =$J15 -> -3971.8 | D16: =SUMIFS('Bills & Commitments'!$G$7:$G$80,'Bills & Commitments'!$D$7:$D$80,"Inflow",'Bills & Commitments'!$I$7:$I$80,"No",'Bills & Commitments'!$H$7:$H$80,"AED",'Bills & Commitments'!$A$7:$A$80,">="&$A16,'Bills & Commitments'!$A$7:$A$80,"<="&$B16) -> 0 | E16: =SUMIFS('Bills & Commitments'!$G$7:$G$80,'Bills & Commitments'!$D$7:$D$80,"Outflow",'Bills & Commitments'!$I$7:$I$80,"No",'Bills & Commitments'!$H$7:$H$80,"AED",'Bills & Commitments'!$C$7:$C$80,"<>Rent",'Bills & Commitments'!$A$7:$A$80,">="&$A16,'Bills & Commitments'!$A$7:$A$80,"<="&$B16) -> 914.93 | F16: =($B16-$A16+1)*Settings!$B$15 -> 105 | G16: =Settings!$B$83 -> 386.37875 | H16: 0 | I16: 0 | J16: =$C16+$D16+$H16-$E16-$F16-$I16 -> -4991.73 | K16: =$K15+$I16-SUMIFS('Bills & Commitments'!$G$7:$G$80,'Bills & Commitments'!$C$7:$C$80,"Rent",'Bills & Commitments'!$A$7:$A$80,">="&$A16,'Bills & Commitments'!$A$7:$A$80,"<="&$B16) -> 13690.7 | L16: =IF($J16<0,"NEGATIVE",IF($J16<Settings!$B$14,"BELOW BUFFER","OK")) -> NEGATIVE | M16: =SUMIFS(Transactions!$O$7:$O$520,Transactions!$F$7:$F$520,"Expense",Transactions!$P$7:$P$520,"AED",Transactions!$J$7:$J$520,"<>Business",Transactions!$B$7:$B$520,">="&$A16,Transactions!$B$7:$B$520,"<="&$B16) -> 0 | N16: =IF($M16>$F16,"OVER","On track") -> On track | O16: =IF($H16>=$G16,"On track",IF($H16>=$G16*0.5,"Behind","Well behind")) -> Well behind | P16: =SUM($H$7:$H16) -> 0 | Q16: =SUM($G$7:$G16) -> 3863.7875 | R16: =IF($P16>=$Q16,"ON PACE overall","SHORT by AED "&TEXT($Q16-$P16,"#,##0.00")) -> SHORT by AED 3,863.79
A17: 46315 | B17: 46321 | C17: =$J16 -> -4991.73 | D17: =SUMIFS('Bills & Commitments'!$G$7:$G$80,'Bills & Commitments'!$D$7:$D$80,"Inflow",'Bills & Commitments'!$I$7:$I$80,"No",'Bills & Commitments'!$H$7:$H$80,"AED",'Bills & Commitments'!$A$7:$A$80,">="&$A17,'Bills & Commitments'!$A$7:$A$80,"<="&$B17) -> 7914.88 | E17: =SUMIFS('Bills & Commitments'!$G$7:$G$80,'Bills & Commitments'!$D$7:$D$80,"Outflow",'Bills & Commitments'!$I$7:$I$80,"No",'Bills & Commitments'!$H$7:$H$80,"AED",'Bills & Commitments'!$C$7:$C$80,"<>Rent",'Bills & Commitments'!$A$7:$A$80,">="&$A17,'Bills & Commitments'!$A$7:$A$80,"<="&$B17) -> 0 | F17: =($B17-$A17+1)*Settings!$B$15 -> 105 | G17: =Settings!$B$83 -> 386.37875 | H17: 0 | I17: 0 | J17: =$C17+$D17+$H17-$E17-$F17-$I17 -> 2818.15 | K17: =$K16+$I17-SUMIFS('Bills & Commitments'!$G$7:$G$80,'Bills & Commitments'!$C$7:$C$80,"Rent",'Bills & Commitments'!$A$7:$A$80,">="&$A17,'Bills & Commitments'!$A$7:$A$80,"<="&$B17) -> 1940.7 | L17: =IF($J17<0,"NEGATIVE",IF($J17<Settings!$B$14,"BELOW BUFFER","OK")) -> OK | M17: =SUMIFS(Transactions!$O$7:$O$520,Transactions!$F$7:$F$520,"Expense",Transactions!$P$7:$P$520,"AED",Transactions!$J$7:$J$520,"<>Business",Transactions!$B$7:$B$520,">="&$A17,Transactions!$B$7:$B$520,"<="&$B17) -> 0 | N17: =IF($M17>$F17,"OVER","On track") -> On track | O17: =IF($H17>=$G17,"On track",IF($H17>=$G17*0.5,"Behind","Well behind")) -> Well behind | P17: =SUM($H$7:$H17) -> 0 | Q17: =SUM($G$7:$G17) -> 4250.1663 | R17: =IF($P17>=$Q17,"ON PACE overall","SHORT by AED "&TEXT($Q17-$P17,"#,##0.00")) -> SHORT by AED 4,250.17
A18: 46322 | B18: 46328 | C18: =$J17 -> 2818.15 | D18: =SUMIFS('Bills & Commitments'!$G$7:$G$80,'Bills & Commitments'!$D$7:$D$80,"Inflow",'Bills & Commitments'!$I$7:$I$80,"No",'Bills & Commitments'!$H$7:$H$80,"AED",'Bills & Commitments'!$A$7:$A$80,">="&$A18,'Bills & Commitments'!$A$7:$A$80,"<="&$B18) -> 0 | E18: =SUMIFS('Bills & Commitments'!$G$7:$G$80,'Bills & Commitments'!$D$7:$D$80,"Outflow",'Bills & Commitments'!$I$7:$I$80,"No",'Bills & Commitments'!$H$7:$H$80,"AED",'Bills & Commitments'!$C$7:$C$80,"<>Rent",'Bills & Commitments'!$A$7:$A$80,">="&$A18,'Bills & Commitments'!$A$7:$A$80,"<="&$B18) -> 793.42 | F18: =($B18-$A18+1)*Settings!$B$15 -> 105 | G18: =Settings!$B$83 -> 386.37875 | H18: 0 | I18: 0 | J18: =$C18+$D18+$H18-$E18-$F18-$I18 -> 1919.73 | K18: =$K17+$I18-SUMIFS('Bills & Commitments'!$G$7:$G$80,'Bills & Commitments'!$C$7:$C$80,"Rent",'Bills & Commitments'!$A$7:$A$80,">="&$A18,'Bills & Commitments'!$A$7:$A$80,"<="&$B18) -> 1940.7 | L18: =IF($J18<0,"NEGATIVE",IF($J18<Settings!$B$14,"BELOW BUFFER","OK")) -> OK | M18: =SUMIFS(Transactions!$O$7:$O$520,Transactions!$F$7:$F$520,"Expense",Transactions!$P$7:$P$520,"AED",Transactions!$J$7:$J$520,"<>Business",Transactions!$B$7:$B$520,">="&$A18,Transactions!$B$7:$B$520,"<="&$B18) -> 0 | N18: =IF($M18>$F18,"OVER","On track") -> On track | O18: =IF($H18>=$G18,"On track",IF($H18>=$G18*0.5,"Behind","Well behind")) -> Well behind | P18: =SUM($H$7:$H18) -> 0 | Q18: =SUM($G$7:$G18) -> 4636.545 | R18: =IF($P18>=$Q18,"ON PACE overall","SHORT by AED "&TEXT($Q18-$P18,"#,##0.00")) -> SHORT by AED 4,636.55
A19: TOTAL | D19: =SUM(D7:D18) -> 15829.76 | E19: =SUM(E7:E18) -> 5056.83 | F19: =SUM(F7:F18) -> 1260 | G19: =SUM(G7:G18) -> 4636.545 | H19: =SUM(H7:H18) -> 0 | I19: =SUM(I7:I18) -> 7750 | J19: =J18 -> 1919.73 | K19: =K18 -> 1940.7
A21: READ THIS
A22: Lowest closing balance in the period | E22: =MIN(J7:J18) -> -4991.73
A23: Week it happens | E23: =INDEX($A$7:$A$18,MATCH(MIN(J7:J18),J7:J18,0)) -> 46308
A24: Weeks below the safety buffer | E24: =COUNTIFS(L7:L18,"BELOW BUFFER")+COUNTIFS(L7:L18,"NEGATIVE") -> 10
A25: Weeks that go negative | E25: =COUNTIFS(L7:L18,"NEGATIVE") -> 9
A26: Side income needed to clear every negative week | E26: =MAX(-MIN(J7:J18),0) -> 4991.73
A27: Rent vault at the cheque date | E27: =K16 -> 13690.7
A28: Vault surplus / shortfall vs the cheque | E28: =K16 -> 13690.7
A30: The vault plan in column I moves AED 1,430 tomorrow, AED 1,000 on the 26 Aug salary and AED 5,320 on the 26 Sep salary. Front-loading more in August breaks September. Change the blue figures and every downstream week re-rates.
A34: HOW TO USE THIS: every time you earn something, tell me the amount and I'll add it to the Side income BANKED column for that week. Column R shows whether you're on pace overall, not just this week — falling behind one week can be caught up later.

Sheet Planning Calendar
A1: Planning Calendar · every dated event to January 2027
A2: Bills, income, transfers and deadlines in one timeline. Running balance assumes you hold the living floor and bank the weekly target.
A5: THE TIMELINE
A6: Date | B6: Event | C6: Type | D6: Amount | E6: Account | F6: Running vault | G6: What to do
A7: 46247 | B7: Nothing due — hold the line | C7: Marker | D7: — | E7: — | F7: 7010.7 | G7: AED 156.32 must last 13 more days. About AED 11/day.
A8: 46260 | B8: August salary balance + profit | C8: Income | D8: 2934.88 | E8: FAB 4001 | F8: 7010.7 | G8: Lands in 4001. Do NOT move to vault — September bills need it.
A9: 46265 | B9: DEWA — August | C9: Bill | D9: -793.42 | E9: FAB 4001 | F9: 7010.7 | G9: Issued 20 Aug, due month-end.
A10: 46268 | B10: Tabby — September | C10: Bill | D10: -1314.5 | E10: FAB 4001 | F10: 7010.7 | G10: AUTOPAY — must be in 4001 that morning.
A11: 46275 | B11: Nippon SIP | C11: Bill | D11: -462.4 | E11: ICICI | F11: 7010.7 | G11: ₹12,000. Pausing this is the emergency lever, not the plan.
A12: 46280 | B12: du + Etisalat — September | C12: Bill | D12: -914.93 | E12: FAB 4001 | F12: 7010.7 | G12: Due by the 15th.
A13: 46291 | B13: September salary | C13: Income | D13: 7914.88 | E13: FAB 4001 | F13: 7010.7 | G13: The recovery month begins.
A14: 46295 | B14: DEWA — September | C14: Bill | D14: -793.42 | E14: FAB 4001 | F14: 7010.7
A15: 46298 | B15: Tabby — October | C15: Bill | D15: -1372.86 | E15: FAB 4001 | F15: 7010.7 | G15: Estimated — confirm from the app when the statement issues.
A16: 46305 | B16: Nippon SIP | C16: Bill | D16: -462.4 | E16: ICICI | F16: 7010.7
A17: 46310 | B17: du + Etisalat — October | C17: Bill | D17: -914.93 | E17: FAB 4001 | F17: 7010.7
A18: 46315 | B18: MOVE TO VAULT | C18: Transfer | D18: 3981.27 | E18: 4001 → 4002, | F18: =7010.7+3981.27 -> 10991.97 | G18: Everything spare goes across. This is the decisive action.
A19: 46316 | B19: VAULT DEADLINE | C19: Deadline | D19: — | E19: FAB 4002 | F19: =F18 -> 10991.97 | G19: Must hold AED 11,750. Shortfall closes only with earned income.
A20: 46317 | B20: RENT CHEQUE CLEARS | C20: Rent | D20: -11750 | E20: FAB 4002 | F20: — | G20: The cheque presents. Vault empties.
A21: 46321 | B21: October salary | C21: Income | D21: 7914.88 | E21: FAB 4001 | F21: — | G21: Lands 4 days AFTER the cheque — too late to fund it.
A22: 46326 | B22: DEWA — October | C22: Bill | D22: -793.42 | E22: FAB 4001 | F22: — | G22: First bill of the new quarter.
A23: 46331 | B23: UNTOLD Dubai | C23: Goal | D23: -350 | E23: FAB 4001 | F23: — | G23: 1 ticket. Only if Stage 1 closed cleanly.
A24: 46352 | B24: November salary | C24: Income | D24: 7914.88 | E24: FAB 4001 | F24: — | G24: Start building the January cheque here.
A25: 46382 | B25: December salary | C25: Income | D25: 7914.88 | E25: FAB 4001 | F25: — | G25: Second cheque-building month.
A26: 46409 | B26: RENT CHEQUE · January | C26: Rent | D26: -11750 | E26: FAB 4002 | F26: — | G26: Quarterly. Needs ~AED 3,900/month set aside from Nov.
A28: THE FOUR DATES THAT DECIDE EVERYTHING
A29: 26 August | B29: AED 2,934.88 lands. Keep it in 4001 — September's bills consume nearly all of it.
A30: 3 September | B30: Tabby autopays AED 1,314.50. The single largest debit before rent. Must be covered.
A31: 20 October | B31: Move everything spare into the vault. This one transfer decides whether the cheque clears.
A32: 21 October | B32: Vault must hold AED 11,750. No second chance — the 26 Oct salary arrives after the cheque.

Sheet Salary Cycles
A1: Salary Cycles · 26th to 25th
A2: Your money resets on the 26th, not the 1st. Every bill you have falls inside one cycle — this is the frame that matches how you actually get paid.
A5: CYCLE 1 · 26 AUG → 25 SEP · funded by the AED 2,934.88 pending payday
A6: Line | B6: Amount | C6: Date | F6: Note
A7: Income — August payday (confirmed) | B7: 2906 | C7: 46260 | F7: CONFIRMED 25 Aug — single consolidated payday figure, replaces old 2,634.88+300 split
C8: 46260 | F8: Confirmed
A9: TOTAL IN | B9: =B7 -> 2906
A10: DEWA — August (confirmed) | B10: -813.28 | C10: 46265 | F10: Issued 20th, due month-end
A11: Tabby — September | B11: -1314.5 | C11: 46268 | F11: Autopay, no-fee minimum
A12: Nippon SIP | B12: -462.4 | C12: 46275 | F12: ₹12,000
A13: du — September | B13: -590.98 | C13: 46280 | F13: Due by the 15th
A14: Etisalat — September | B14: -323.95 | C14: 46280 | F14: Due by the 15th
A15: TOTAL BILLS | B15: =SUM(B10:B14) -> -3505.11
A16: Living at the AED 15 floor × 31 days | B16: -465 | F16: Bare minimum
A17: CYCLE NET | B17: =B9+B15+B16 -> -1064.11 | F17: Before any rent-vault contribution
A18: Living at REAL spend (fuel/wife/parking/smokes/food) | B18: -1770 | F18: Groceries at nil — owner instruction until rent is funded
A19: CYCLE NET at real spend | B19: =B9+B15+B18 -> -2369.11 | F19: Gap vs the floor line above = your discretionary spending. It comes straight out of the rent vault.
A22: CYCLE 2 · 26 SEP → 22 OCT · the full salary lands, and the cheque clears
A23: Line | B23: Amount | C23: Date | F23: Note
A24: Income — September salary | B24: 7914.88 | C24: 46291 | F24: Full monthly salary
A25: DEWA — September (est., using confirmed Aug baseline) | B25: -813.28 | C25: 46295
A26: Tabby — September statement (REAL) | B26: -715.33 | C26: 46298 | F26: CONFIRMED via Tabby chat 15 Aug — was estimated 1,372.86, actual is 657.53 LESS
A27: Nippon SIP | B27: -462.4 | C27: 46305
A28: du — October | B28: -590.98 | C28: 46310
A29: Etisalat — October | B29: -323.95 | C29: 46310
A30: TOTAL BILLS | B30: =SUM(B25:B29) -> -2905.94
A31: Living at the floor × 26 days (aligned to the 22 Oct deadline) | B31: -390
A32: CYCLE NET before rent | B32: =B24+B30+B31 -> 4618.94 | F32: What's genuinely available
A33: Rent cheque clears | B33: -11750 | C33: 46317 | F33: Paid from the vault, not from this cycle
A34: Vault must hold by 21 Oct | B34: ='Rent Vault'!$B$12 -> 5809.3 | C34: 46316 | F34: Still to fund
A35: Living at REAL spend (26 days pro-rated) | B35: -1534
A36: CYCLE NET at real spend, before rent | B36: =B24+B30+B35 -> 3474.94
A39: WHY THIS FRAME MATTERS
A40: Every bill you have falls inside a single salary cycle — DEWA at month-end, Tabby on the 3rd, SIP on the 10th, du and Etisalat by the 15th. A calendar month splits that run across two views and hides it.
A42: Cycle 1 is the dangerous one. It is funded by a part-payday of AED 2,934.88 against AED 3,485.25 of bills. It was always going to be tight; the calendar view made it look like two ordinary half-months.
A44: Cycle 2 is where recovery happens — a full salary against similar bills. The surplus is real, but it lands after the vault deadline, which is why the AED 206.21 a week still has to come from somewhere else.
A49: THE TRUE SHORTAGE · floor vs. real spending
A51: Basis | B51: Cycle 1 net | C51: Cycle 2 net | D51: Vault at 21 Oct | E51: Shortage | F51: Per week (9 wks)
A52: Bare floor (15/day) | B52: =B17 -> -1064.11 | C52: =B32 -> 4618.94 | D52: =6090.7+B17+B32 -> 9645.53 | E52: =11750-D52 -> 2104.47 | F52: =E52/9 -> 233.83
A53: Real spending pattern | B53: =B19 -> -2369.11 | C53: =B36 -> 3474.94 | D53: =6090.7+B19+B36 -> 7196.53 | E53: =11750-D53 -> 4553.47 | F53: =E53/9 -> 505.94111
A55: The floor row is what the plan needs on paper. The real-spend row is what happens if spending keeps matching the last ten days. The gap between them is entirely within your control: it is smokes, dining out, and Asas Al Madina visits, nothing else.

Sheet Weekly Check-In
A1: Weekly & Monthly Check-In
A2: Spending shown by the week and the month — not by the day. A single day's number is too small to mean anything; a week is something you can actually feel.
A5: THIS WEEK
A6: Measure | B6: Value
A7: Week starts | B7: =Settings!$B$9-WEEKDAY(Settings!$B$9,2)+1 -> 46258
A8: Week ends | B8: =B7+6 -> 46264
A9: Safe spend for the week | B9: =Settings!$B$75*7 -> 0
A10: Spent so far this week | B10: =SUMIFS(Transactions!$O$7:$O$520,Transactions!$F$7:$F$520,"Expense",Transactions!$P$7:$P$520,"AED",Transactions!$B$7:$B$520,">="&B7,Transactions!$B$7:$B$520,"<="&B8) -> 2934.17
A11: Remaining this week | B11: =MAX(B9-B10,0) -> 0
A12: Days left in the week | B12: =B8-Settings!$B$9+1 -> 5
A13: STATUS | B13: =IF(B10>B9,"OVER FOR THE WEEK",IF(B10>B9*0.8,"WATCH — CLOSE TO THE LIMIT","ON TRACK")) -> OVER FOR THE WEEK
A15: =IF(Settings!$B$75<5,"In plain terms: this is the tightest stretch of the whole plan. Almost nothing is discretionary until the rent gap closes — every dirham beyond committed bills should stop.",IF(Settings!$B$75<20,"Room is thin but real — small, deliberate spending only.","Normal room to operate.")) -> In plain terms: this is the tightest stretch of the whole plan. Almost nothing is discretionary until the rent gap closes — every dirham beyond committed bills should stop.
A17: THIS MONTH
A18: Measure | B18: Value
A19: Month | B19: =Settings!$B$84 -> 2026-08
A20: Days elapsed / days in month | B20: =Settings!$B$89&" of "&DAY(EOMONTH(Settings!$B$9,0)) -> 26 of 31
A21: Spent so far this month | B21: =Settings!$B$86 -> 7587.65
A22: Average per day so far | B22: =Settings!$B$90 -> 119.99192
A23: Projected month-end cash | B23: =Settings!$B$94 -> -443.15962
A24: STATUS | B24: =IF(Settings!$B$94<0,"OVER — PROJECTED SHORTFALL",IF(Settings!$B$90>Settings!$B$75,"WATCH — RUNNING ABOVE THE SAFE PACE","ON TRACK")) -> OVER — PROJECTED SHORTFALL
A26: WEEK-BY-WEEK HISTORY · fills in automatically as weeks pass
A27: Week starting | B27: Safe budget | C27: Actual spent | D27: Variance | E27: Status
A28: =Settings!$B$9-WEEKDAY(Settings!$B$9,2)+1-7*0 -> 46258 | B28: =Settings!$B$75*7 -> 0 | C28: =SUMIFS(Transactions!$O$7:$O$520,Transactions!$F$7:$F$520,"Expense",Transactions!$P$7:$P$520,"AED",Transactions!$B$7:$B$520,">="&A28,Transactions!$B$7:$B$520,"<="&A28+6) -> 2934.17 | D28: =B28-C28 -> -2934.17 | E28: =IF(C28>B28,"Over","On track") -> Over
A29: =Settings!$B$9-WEEKDAY(Settings!$B$9,2)+1-7*1 -> 46251 | B29: =Settings!$B$75*7 -> 0 | C29: =SUMIFS(Transactions!$O$7:$O$520,Transactions!$F$7:$F$520,"Expense",Transactions!$P$7:$P$520,"AED",Transactions!$B$7:$B$520,">="&A29,Transactions!$B$7:$B$520,"<="&A29+6) -> 699.23 | D29: =B29-C29 -> -699.23 | E29: =IF(C29>B29,"Over","On track") -> Over
A30: =Settings!$B$9-WEEKDAY(Settings!$B$9,2)+1-7*2 -> 46244 | B30: =Settings!$B$75*7 -> 0 | C30: =SUMIFS(Transactions!$O$7:$O$520,Transactions!$F$7:$F$520,"Expense",Transactions!$P$7:$P$520,"AED",Transactions!$B$7:$B$520,">="&A30,Transactions!$B$7:$B$520,"<="&A30+6) -> 708.35 | D30: =B30-C30 -> -708.35 | E30: =IF(C30>B30,"Over","On track") -> Over
A31: =Settings!$B$9-WEEKDAY(Settings!$B$9,2)+1-7*3 -> 46237 | B31: =Settings!$B$75*7 -> 0 | C31: =SUMIFS(Transactions!$O$7:$O$520,Transactions!$F$7:$F$520,"Expense",Transactions!$P$7:$P$520,"AED",Transactions!$B$7:$B$520,">="&A31,Transactions!$B$7:$B$520,"<="&A31+6) -> 3245.9 | D31: =B31-C31 -> -3245.9 | E31: =IF(C31>B31,"Over","On track") -> Over
A32: =Settings!$B$9-WEEKDAY(Settings!$B$9,2)+1-7*4 -> 46230 | B32: =Settings!$B$75*7 -> 0 | C32: =SUMIFS(Transactions!$O$7:$O$520,Transactions!$F$7:$F$520,"Expense",Transactions!$P$7:$P$520,"AED",Transactions!$B$7:$B$520,">="&A32,Transactions!$B$7:$B$520,"<="&A32+6) -> 0 | D32: =B32-C32 -> 0 | E32: =IF(C32>B32,"Over","On track") -> On track
A33: =Settings!$B$9-WEEKDAY(Settings!$B$9,2)+1-7*5 -> 46223 | B33: =Settings!$B$75*7 -> 0 | C33: =SUMIFS(Transactions!$O$7:$O$520,Transactions!$F$7:$F$520,"Expense",Transactions!$P$7:$P$520,"AED",Transactions!$B$7:$B$520,">="&A33,Transactions!$B$7:$B$520,"<="&A33+6) -> 0 | D33: =B33-C33 -> 0 | E33: =IF(C33>B33,"Over","On track") -> On track
A34: =Settings!$B$9-WEEKDAY(Settings!$B$9,2)+1-7*6 -> 46216 | B34: =Settings!$B$75*7 -> 0 | C34: =SUMIFS(Transactions!$O$7:$O$520,Transactions!$F$7:$F$520,"Expense",Transactions!$P$7:$P$520,"AED",Transactions!$B$7:$B$520,">="&A34,Transactions!$B$7:$B$520,"<="&A34+6) -> 0 | D34: =B34-C34 -> 0 | E34: =IF(C34>B34,"Over","On track") -> On track
A35: =Settings!$B$9-WEEKDAY(Settings!$B$9,2)+1-7*7 -> 46209 | B35: =Settings!$B$75*7 -> 0 | C35: =SUMIFS(Transactions!$O$7:$O$520,Transactions!$F$7:$F$520,"Expense",Transactions!$P$7:$P$520,"AED",Transactions!$B$7:$B$520,">="&A35,Transactions!$B$7:$B$520,"<="&A35+6) -> 0 | D35: =B35-C35 -> 0 | E35: =IF(C35>B35,"Over","On track") -> On track
A36: =Settings!$B$9-WEEKDAY(Settings!$B$9,2)+1-7*8 -> 46202 | B36: =Settings!$B$75*7 -> 0 | C36: =SUMIFS(Transactions!$O$7:$O$520,Transactions!$F$7:$F$520,"Expense",Transactions!$P$7:$P$520,"AED",Transactions!$B$7:$B$520,">="&A36,Transactions!$B$7:$B$520,"<="&A36+6) -> 0 | D36: =B36-C36 -> 0 | E36: =IF(C36>B36,"Over","On track") -> On track
A37: =Settings!$B$9-WEEKDAY(Settings!$B$9,2)+1-7*9 -> 46195 | B37: =Settings!$B$75*7 -> 0 | C37: =SUMIFS(Transactions!$O$7:$O$520,Transactions!$F$7:$F$520,"Expense",Transactions!$P$7:$P$520,"AED",Transactions!$B$7:$B$520,">="&A37,Transactions!$B$7:$B$520,"<="&A37+6) -> 0 | D37: =B37-C37 -> 0 | E37: =IF(C37>B37,"Over","On track") -> On track
A38: =Settings!$B$9-WEEKDAY(Settings!$B$9,2)+1-7*10 -> 46188 | B38: =Settings!$B$75*7 -> 0 | C38: =SUMIFS(Transactions!$O$7:$O$520,Transactions!$F$7:$F$520,"Expense",Transactions!$P$7:$P$520,"AED",Transactions!$B$7:$B$520,">="&A38,Transactions!$B$7:$B$520,"<="&A38+6) -> 0 | D38: =B38-C38 -> 0 | E38: =IF(C38>B38,"Over","On track") -> On track
A39: =Settings!$B$9-WEEKDAY(Settings!$B$9,2)+1-7*11 -> 46181 | B39: =Settings!$B$75*7 -> 0 | C39: =SUMIFS(Transactions!$O$7:$O$520,Transactions!$F$7:$F$520,"Expense",Transactions!$P$7:$P$520,"AED",Transactions!$B$7:$B$520,">="&A39,Transactions!$B$7:$B$520,"<="&A39+6) -> 0 | D39: =B39-C39 -> 0 | E39: =IF(C39>B39,"Over","On track") -> On track

Sheet Goals & Future Planning
A1: Goals & Future Planning
A2: Everything beyond the next 90 days — UNTOLD, the trip, and the January rent renewal. These come after the rent gap, never before it.
A5: PRIORITY ORDER · read this before funding anything below
A6: 1. Close the current rent gap (AED —see Command Center) → 2. Rebuild the safety buffer → 3. Fund goals below, in the order you choose. Nothing here should be funded ahead of the rent cheque.
A9: UNTOLD DUBAI · 5–8 Nov 2026, Dubai Parks and Resorts
A10: Measure | B10: Value | C10: Note
A11: Event date | B11: =Settings!$B$133 -> 46331 | C11: Confirmed — Time Out Dubai
A12: Days from today | B12: =Settings!$B$133-Settings!$B$9 -> 71 | C12: Live countdown
A13: Tickets needed | B13: =Settings!$B$134 -> 1 | C13: Edit on Settings if solo, not a couple
A14: Price per ticket (early-bird) | B14: =Settings!$B$135 -> 350 | C14: Rises closer to the date — buy early-bird if you're going
A15: TOTAL COST | B15: =Settings!$B$134*Settings!$B$135 -> 350 | C15: Two 4-day GA passes at early-bird pricing
A16: Already saved toward this | B16: 0 | C16: Update as you set money aside
A17: Still needed | B17: =B15-B16 -> 350 | C17: Cost less what's already saved
A18: Weeks remaining | B18: =ROUNDUP(B12/7,0) -> 11
A19: REQUIRED PER WEEK | B19: =IF(B18=0,0,B17/B18) -> 31.818182 | C19: To have it fully funded by the event
A21: COUPLE'S TRIP · 4–5 days, destination and date not yet chosen
A22: Measure | B22: Value | C22: Note
A23: Budget (both of you) | B23: =Settings!$B$136 -> 4000 | C23: Midpoint of your AED 3,000–5,000 range
A24: Target month | B24: =Settings!$B$137 -> TBD | C24: Set a real month on Settings to activate the countdown below
A25: Already saved toward this | B25: 0 | C25: Update as you set money aside
A26: Still needed | B26: =B23-B25 -> 4000
A27: Weeks to save (once a date is set) | B27: =IF(Settings!$B$137="TBD","Set a target month first",MAX(ROUNDUP((DATEVALUE("01 "&Settings!$B$137)-Settings!$B$9)/7,0),1)) -> Set a target month first
A28: REQUIRED PER WEEK | B28: =IF(Settings!$B$137="TBD",0,IF(B27=0,0,B26/B27)) -> 0 | C28: Blank until a target month exists
A29: To activate the weekly target: change Settings!B137 from "TBD" to a month like "Dec 2026" — the countdown and weekly figure fill in automatically.
A32: JANUARY 2027 RENT RENEWAL · paid quarterly, 4 cheques a year
A33: Measure | B33: Value | C33: Note
A34: Renewal / next cheque date | B34: =Settings!$B$130 -> 46409 | C34: Assumed same day-of-month as October — confirm the exact date
A35: Days from today | B35: =Settings!$B$130-Settings!$B$9 -> 149
A36: Rent assumption | B36: =Settings!$B$131 -> Flat — no increase | C36: Your instruction, 11 Aug 2026 — revisit once the landlord confirms
A37: Amount to fund (flat-rent case) | B37: =Settings!$B$128 -> 11750 | C37: Same as the October cheque
A38: Full 2027 quarterly pattern (Jan+Apr+Jul+Oct) | B38: =Settings!$B$128*4 -> 47000 | C38: Assumed — confirm against the real schedule once known
A39: SENSITIVITY — if rent rises | B39: =Settings!$B$132 -> 0.07 | C39: What-if only, not the working plan
A40: Extra per cheque if the increase happens | B40: =Settings!$B$128*Settings!$B$132 -> 822.5
A41: Extra across the 2027 year if it happens | B41: =B40*4 -> 3290 | C41: Worth keeping in mind even though the base plan assumes flat
A42: The January, April and July 2027 cheques are already on the Bills & Commitments sheet at the assumed AED 11,750 rate, so they'll show up in any forecast that runs that far — clearly marked Estimated, never Actual.
A45: COMBINED SAVINGS TARGET · everything above, side by side
A46: Goal | B46: Target date | C46: Still needed | D46: Per week | E46: Status
A47: UNTOLD Dubai | B47: =B11 -> 46331 | C47: =B17 -> 350 | D47: =B19 -> 31.818182 | E47: =IF(D47=0,"—",IF(D47>Settings!$B$82,"COMPETES WITH THE RENT GAP","Fits alongside it")) -> Fits alongside it
A48: Couple's trip | B48: =IF(Settings!$B$137="TBD","No date set",Settings!$B$137) -> No date set | C48: =B26 -> 4000 | D48: =B28 -> 0 | E48: =IF(D48=0,"—",IF(D48>Settings!$B$82,"COMPETES WITH THE RENT GAP","Fits alongside it")) -> —
A49: TOTAL PER WEEK (both goals) | D49: =SUM(D47:D48) -> 31.818182
A51: =CONCATENATE("For comparison: closing the current rent gap needs AED ",TEXT(Settings!$B$82,"#,##0.00")," a week. These two goals together need AED ",TEXT(D49,"#,##0.00")," a week on top of that once you start funding them.") -> For comparison: closing the current rent gap needs AED 55.20 a week. These two goals together need AED 31.82 a week on top of that once you start funding them.

Sheet Family & Future Security
A1: Family & Future Security
A2: A staged plan for a possible pregnancy, an emergency fund built for a family, and a home — starting from where you actually are today, not where you'd like to be.
A5: WHERE THIS STARTS · the honest baseline
A6: Today you have AED 250.91 of genuinely free cash and a rent gap still open. None of the goals below can be funded ahead of that. This sheet exists so the path from here to there is visible, not so it happens overnight.
A9: STAGE 1 — STABILISE · now through the 26 September salary
A10: Milestone | B10: Target | C10: By when | D10: Status
A11: Close the current rent gap | B11: =Settings!$B$81 -> 3091.03 | C11: 46316 | D11: =IF(Settings!$B$81<=0,"Done","In progress") -> In progress
A12: Rebuild the safety buffer to its full level | B12: =Settings!$B$14 -> 250 | D12: =IF(Accounts!$D$15-Accounts!$E$15>=Settings!$B$14,"Done","Not yet") -> Not yet
A14: STAGE 2 — EMERGENCY FUND · sized for a family, not a single person
A15: Measure | B15: Value | C15: Note
A16: Target — months of essential expenses | B16: =Settings!$B$141 -> 6
A17: Average essential monthly spend | B17: =Settings!$B$142 -> 3661
A18: FULL TARGET | B18: =Settings!$B$141*Settings!$B$142 -> 21966 | C18: Six months covers job loss, a health scare, or a slow quarter without touching the rent vault or investments
A19: Current emergency fund | B19: =Accounts!$D$9 -> 7.67 | C19: FAB 4003
A20: Progress | B20: =IF(B18=0,0,B19/B18) -> 0.000349176
A21: Still needed | B21: =MAX(B18-B19,0) -> 21958.33
A23: STAGE 3 — IF YOUR WIFE BECOMES PREGNANT · her EBP insurance changes this materially
A24: Measure | B24: Value | C24: Note
A25: Her insurance | B25: =Settings!$B$158 -> Basic / Essential Benefits Plan | C25: Confirmed active, no waiting period
A26: EBP covers — normal delivery, up to | B26: =Settings!$B$160 -> 7000 | C26: Minus a 10% co-payment on the covered portion
A27: EBP covers — C-section, up to | B27: =Settings!$B$161 -> 10000 | C27: Minus a 10% co-payment on the covered portion
A28: OUT-OF-POCKET — government route | B28: =Settings!$B$162*MIN(Settings!$B$143,Settings!$B$160)+MAX(Settings!$B$143-Settings!$B$160,0) -> 600 | C28: =Settings!$B$162*MIN(Settings!$B$144,Settings!$B$160)+MAX(Settings!$B$144-Settings!$B$160,0) -> 8700 | D28: Low–high, AED 6,000–15,000 total cost — B is low end, C is high end
A29: OUT-OF-POCKET — private route | B29: =Settings!$B$162*MIN(Settings!$B$145,Settings!$B$160)+MAX(Settings!$B$145-Settings!$B$160,0) -> 5700 | C29: =Settings!$B$162*MIN(Settings!$B$146,Settings!$B$160)+MAX(Settings!$B$146-Settings!$B$160,0) -> 23700 | D29: Low–high, AED 12,000–30,000 total cost — exceeds the sub-limit either way
A30: SUGGESTED CONTINGENCY (edit freely — you said 'a little') | B30: 3000 | C30: A working buffer for scans, tests, or extras — not the full private-route exposure
A31: Newborn first-year essentials | B31: =Settings!$B$149 -> 8000 | C31: Not covered by health insurance — car seat, crib, clothing, paediatrician
A32: TOTAL TO PREPARE FOR | B32: =B30+B31 -> 11000
A33: Already saved toward this | B33: 0
A34: Still needed | B34: =B32-B33 -> 11000
A35: STAGE 4 — A HOME · Dubai reality check first, then a savings target
A36: Confirm one thing with HR: some Basic plans exclude maternity even when general coverage is immediate. A five-minute call now is cheaper than a surprise later.
A38: Typical UAE bank minimum for a mortgage | B38: =Settings!$B$150 -> 15000 | C38: Most lenders
A39: Lowest seen (smaller loans only) | B39: =Settings!$B$151 -> 10000
A40: MORTGAGE-ELIGIBLE TODAY? | B40: =IF(B37>=B38,"Yes",IF(B37>=B39,"Possibly, small loan only","Not yet on this income alone")) -> Not yet on this income alone | C40: Your income alone is below most banks' floor. Joint income with your wife, or income growth, changes this
A41: Expat down payment, first home under AED 5M | B41: =Settings!$B$152 -> 20% | C41: Central Bank minimum
A42: Total cash needed at closing (incl. fees) | B42: =Settings!$B$153 -> ~27–28% of price | C42: Deposit plus DLD, registration, broker, valuation
A43: Example — AED 1,000,000 apartment: cash needed | B43: ~AED 270,000–280,000 | C43: 27–28% of price, all-in
A44: India option | B44: =Settings!$B$154 -> NOT SET
A46: Home ownership on your current income is realistically a multi-year goal, not a near-term one — and that's the honest picture, not a discouragement. Joint income once your wife's situation is clearer, salary growth, or India (where price points can be far more accessible) all change this materially. Tell me a city in India and I'll research real numbers instead of guessing.
A49: STAGE 5 — THE ROADMAP · realistic sequencing, not everything at once
A50: Stage | B50: What | C50: Realistic timing
A51: 1 | B51: Close the rent gap, rebuild the buffer | D51: Now → Oct 2026
A52: 2 | B52: Emergency fund to 6 months of essentials | D52: Late 2026 → mid 2027
A53: 3 | B53: Maternity fund + insurance upgrade (start NOW if trying this year) | D53: Immediate — insurance timing is the constraint
A54: 4 | B54: UNTOLD + the couple's trip | D54: Once Stage 1 is done — see Goals & Future Planning
A55: 5 | B55: Income growth — the real unlock for everything below | D55: Ongoing
A56: 6 | B56: Home down payment fund | D56: Once mortgage-eligible — likely 2+ years out on current income
A58: HOUSEHOLD INCOME CHANGE · wife stops working 15 September
A59: This is real and confirmed, but two numbers are still unknown — her past contribution (owner said "under AED 2,000/month") and her ongoing allowance (still being figured out). Nothing below should be treated as final.
A62: Item | B62: Value | C62: Date | D62: Note
A63: Her last working day | B63: =Settings!$B$167 -> 46280 | D63: Confirmed
A64: Past contribution (placeholder estimate) | B64: =Settings!$B$168 -> 1500 | D64: Midpoint of the range given — not exact
A65: Ongoing allowance needed | B65: =Settings!$B$169 -> Already 100% Johnny this year | D65: Not yet determined — update once known
A66: Falls inside Cycle 1 (26 Aug–25 Sep) | B66: Yes | D66: Already a deficit cycle — this makes it tighter, not easier
A67: THE REAL POST-TABBY PICTURE · now including groceries
A68: Item | B68: Monthly AED | C68: Note
A69: Salary | B69: =Settings!$B$10 -> 7914.88
A70: DEWA + du + Etisalat + SIP | B70: =-(793.42+590.98+323.95+462.4) -> -2170.75
A71: Groceries (transferring from wife) | B71: =-Settings!$B$168 -> -1500 | C71: Estimate — get the real figure
A72: Quarterly rent set-aside (÷ 3) | B72: =-11750/3 -> -3916.6667 | C72: Protects the January cheque
A73: TRUE SPENDABLE, POST-TABBY | B73: =B69+B70+B71+B72 -> 327.46333
A74: Per week | B74: =B73/4.33 -> 75.626636
A75: Per day | B75: =B73/30 -> 10.915444
A76: This drops from the earlier AED 1,827/month estimate to roughly AED 327/month once groceries genuinely transfer. The relief from Tabby closing is largely absorbed by this new cost — real, not a setback, just a correction to an earlier estimate that did not know about it yet.

Sheet BNPL & Debt
A1: BNPL, Cards & Debt
A2: Tabby Card is frozen. Tabby Cash is a funded wallet and is never borrowing — the two must never be merged.
A5: INSTALMENT & BNPL PLANS
A6: Provider | B6: Plan / purchase | C6: Original amount | D6: Instalment # | E6: Total instalments | F6: Next due date | G6: Next payment | H6: Remaining balance | I6: Months left | J6: Final payment month | K6: Payment account | L6: Status / note
A7: Tabby | B7: Consolidated instalment plan | C7: 2687.36 | D7: Cycle 1 of 2–3 | E7: 2–3 est. | F7: 46268 | G7: =Settings!$B$30 -> 1314.5 | H7: =$C$7-$G$7 -> 1372.86 | I7: 2–3 est. | J7: Oct–Nov 2026 est. | K7: FAB 4001 Current | L7: AUTOPAY IS ON for the no-fee minimum — AED 1,314.50 debits automatically on 3 Sep. Instalments due this cycle are AED 985.77, so the AED 1,372.86 balance is likely ~1 further full cycle plus a small tail. Open Payments due in the app to confirm the exact tail month.
A9: EXPOSURE SUMMARY
A10: Measure | B10: Value | C10: Note
A11: Total limit | B11: =$B$20 -> 8000 | C11: Tabby Card 3620
A12: Outstanding exposure | B12: =Settings!$B$32 -> 2687.36 | C12: Limit less available — ties exactly to the app
A13: Available limit | B13: =$B$20-Settings!$B$32 -> 5312.64 | C13: App shows AED 5,312.64 — self-validating
A14: Utilisation | B14: =Settings!$B$32/$B$20 -> 0.33592 | C14: Below 40% is comfortable; this is not your problem
A15: Due 3 Sep — no-fee minimum | B15: =Settings!$B$30 -> 1314.5 | C15: Autopay. Instalments 985.77 + previous-month transactions 328.73
A16: Balance after the 3 Sep payment | B16: =Settings!$B$32-Settings!$B$30 -> 1372.86 | C16: Modelled conservatively as due 3 Oct, entirely inside the rent window
A17: Monthly cash released once Tabby clears | B17: =Settings!$B$30 -> 1314.5 | C17: From roughly November — the single biggest structural improvement to 2027
A18: CREDIT CARDS
A19: Card / lender | B19: Credit limit | C19: Outstanding | D19: Available limit | E19: Statement date | F19: Due date | G19: Minimum due | H19: Full payment | I19: Utilisation | J19: Status | K19: Payment account | L19: Note
A20: Tabby Card 3620 | B20: 8000 | C20: =Settings!$B$32 -> 2687.36 | D20: =$B$20-$C$20 -> 5312.64 | E20: 3rd of month | F20: 46268 | G20: =Settings!$B$30 -> 1314.5 | H20: =Settings!$B$31 -> 1972.03 | I20: =$C$20/$B$20 -> 0.33592 | J20: FROZEN | K20: FAB 4001 Current | L20: Frozen by choice — no new spending. 5% August cashback on pharmacies, taxis and health is unusable while frozen. Keep it frozen.
A22: SEPTEMBER STATEMENT · what the AED 1,314.50 is actually made of
A23: Component | B23: Amount | C23: Note
A24: Instalments due this cycle | B24: 985.77 | C24: Scheduled BNPL repayments
A25: Previous-month card transactions | B25: 328.73 | C25: Partner stores 14.00 + non-partner stores 314.73
A26: NO-FEE MINIMUM | B26: =$B$24+$B$25 -> 1314.5 | C26: Autopay debits this on 3 Sep — no fees
A27: Full statement amount | B27: =Settings!$B$31 -> 1972.03 | C27: Optional. Costs AED 657.53 more now and saves nothing inside the rent window
A28: Difference | B28: =$B$27-$B$26 -> 657.53 | C28: Pay the minimum, not the statement — keep the cash later while rent is unfunded
A30: There is a third payment option in the app that was cut off in the screenshot — it appears to carry fees. Ignore it. The no-fee minimum is already on autopay and is the correct choice.

Sheet Investments
A1: Investments & Savings
A2: MF Central snapshot dated 10 Aug 2026, after the four INR 3,000 Nippon SIPs. No market values are estimated or invented.
A5: Fund | B5: Fund house | C5: Units | D5: Cost (INR) | E5: Current NAV | F5: Value (INR) | G5: Gain / Loss | H5: Return % | I5: Monthly SIP (INR) | J5: SIP status | K5: Last priced | L5: Note
A6: Nippon Large Cap | B6: Nippon | C6: 758.192 | D6: 75000 | E6: 101.97 | F6: =C6*E6 -> 77312.838 | G6: =F6-D6 -> 2312.8382 | H6: =IF(D6=0,0,G6/D6) -> 0.030837843 | I6: 3000 | J6: Active | K6: 46259 | L6: =IF((TODAY()-K6)>Settings!$B$123,"⚠ REPRICE — "&(TODAY()-K6)&"d old","Current") -> Current
A7: Nippon Multi Cap | B7: Nippon | C7: 226.127 | D7: 73936.89 | E7: 338.55 | F7: =C7*E7 -> 76555.296 | G7: =F7-D7 -> 2618.4059 | H7: =IF(D7=0,0,G7/D7) -> 0.035414065 | I7: 3000 | J7: Active | K7: 46259 | L7: =IF((TODAY()-K7)>Settings!$B$123,"⚠ REPRICE — "&(TODAY()-K7)&"d old","Current") -> Current
A8: Nippon Growth Mid Cap | B8: Nippon | C8: 6.993 | D8: 33000 | E8: 5077.57 | F8: =C8*E8 -> 35507.447 | G8: =F8-D8 -> 2507.447 | H8: =IF(D8=0,0,G8/D8) -> 0.075983243 | I8: 3000 | J8: Active | K8: 46259 | L8: =IF((TODAY()-K8)>Settings!$B$123,"⚠ REPRICE — "&(TODAY()-K8)&"d old","Current") -> Current
A9: Nippon Small Cap | B9: Nippon | C9: 189.636 | D9: 35968 | E9: 209.8 | F9: =C9*E9 -> 39785.633 | G9: =F9-D9 -> 3817.6328 | H9: =IF(D9=0,0,G9/D9) -> 0.1061397 | I9: 3000 | J9: Active | K9: 46259 | L9: =IF((TODAY()-K9)>Settings!$B$123,"⚠ REPRICE — "&(TODAY()-K9)&"d old","Current") -> Current
A10: Nippon Silver ETF FoF | B10: Nippon | C10: 115.191 | D10: 2971.14 | E10: 36.49 | F10: =C10*E10 -> 4203.3196 | G10: =F10-D10 -> 1232.1796 | H10: =IF(D10=0,0,G10/D10) -> 0.4147161 | I10: 0 | J10: Cancelled | K10: 46259 | L10: =IF((TODAY()-K10)>Settings!$B$123,"⚠ REPRICE — "&(TODAY()-K10)&"d old","Current") -> Current
A11: Motilal Oswal Midcap | B11: Motilal Oswal | C11: 93.721 | D11: 11000 | E11: 123.27 | F11: =C11*E11 -> 11552.988 | G11: =F11-D11 -> 552.98767 | H11: =IF(D11=0,0,G11/D11) -> 0.050271606 | I11: 0 | J11: Active | K11: 46259 | L11: =IF((TODAY()-K11)>Settings!$B$123,"⚠ REPRICE — "&(TODAY()-K11)&"d old","Current") -> Current
A12: TOTAL | D12: =SUM(D6:D11) -> 231876.03 | F12: =SUM(F6:F11) -> 244917.52 | G12: =SUM(G6:G11) -> 13041.491 | H12: =IF(D12=0,0,G12/D12) -> 0.056243378 | I12: =SUM(I6:I11) -> 12000 | L12: =IF(COUNTIF(L6:L11,"Current")=6,"All current","Some stale — see above") -> All current
A15: How to update: type the fund's current NAV into the yellow cell each time you check MF Central — value, gain/loss, return and the stale-flag all recompute instantly.
A16: Control | B16: Value | C16: Status | D16: Note
A17: Portfolio value (AED equivalent) | B17: =F12*Settings!$B$28 -> 9437.4803 | C17: – | D17: At the Settings INR→AED rate
A18: Nippon concentration | B18: =SUM(F6:F10)/F12 -> 0.95282907 | C18: =IF($B18>Settings!$B$121,"HIGH","OK") -> HIGH | D18: Nippon value / total MF value — MUTUAL FUNDS ONLY, does not yet include Amana or Binance
A19: Motilal concentration | B19: =F11/F12 -> 0.047170932 | C19: Low
A20: Monthly SIP commitment (AED) | B20: =Settings!$B$29 -> 462.4 | C20: Active | D20: Due the 10th of each month
A21: Emergency fund balance | B21: =Accounts!$D$9 -> 7.67 | C21: – | D21: FAB Emergency
A22: Emergency fund target | B22: =Settings!$B$23 -> 1000 | C22: – | D22: Control panel
A23: Emergency fund progress | B23: =IF(Settings!$B$23=0,0,Accounts!$D$9/Settings!$B$23) -> 0.00767 | C23: CRITICALLY LOW | D23: Effectively no emergency cover
A24: Savings rate this month | B24: =IF(Settings!$B$85=0,0,(Settings!$B$85-Settings!$B$86)/Settings!$B$85) -> 0.33828826 | C24: – | D24: (Income − spending) / income, month to date
A26: THE SIP DECISION · AED 462.40 a month, during a rent crunch
A27: Measure | B27: Value | C27: What it means
A28: Cost of the Sep + Oct SIPs | B28: =Settings!$B$29*2 -> 924.8 | C28: Cash that leaves before the rent cheque clears
A29: Remaining rent gap | B29: =Settings!$B$81 -> 3091.03 | C29: What you are short by, buffer intact
A30: Gap if both SIPs are paused | B30: =MAX(Settings!$B$81-Settings!$B$29*2,0) -> 2166.23 | C30: Pausing two months closes the gap outright, with room to spare
A31: Side income needed if you keep investing | B31: =Settings!$B$83 -> 386.37875 | C31: Per week, for ten weeks
A32: Portfolio value if you pause two months | B32: =Investments!$F$12 -> 244917.52 | C32: Unchanged — you keep every unit you already own
A33: What pausing actually costs | B33: =Settings!$B$27*2 -> 24000 | C33: INR of contributions deferred, plus the compounding on them and your SIP streak
A35: This is the single largest discretionary lever you hold. It is not a recommendation — the numbers are here so the decision is yours and made with your eyes open. Pausing is reversible; missing the rent cheque is not.
A38: Statement date | B38: 46244 | D38: =IF((TODAY()-B38)>Settings!$B$123,"⚠ Get a fresh statement — "&(TODAY()-B38)&"d old","Current") -> ⚠ Get a fresh statement — 16d old
A39: AMANA — MULTI-ASSET BROKERAGE · statement 21 Jul 2023 to 10 Aug 2026
A40: Measure | B40: USD | C40: AED equivalent | D40: Note
A41: Beginning account value | B41: 0 | C41: =$B41*Settings!$B$34 -> 0 | D41: Statement opening, Jul 2023
A42: Money in | B42: 1723.04 | C42: =$B42*Settings!$B$34 -> 6327.8644 | D42: Total deposits over the account's life
A43: Money out | B43: -870.93 | C43: =$B43*Settings!$B$34 -> -3198.4904 | D43: Total withdrawals
A44: Net money in/out | B44: =$B42+$B43 -> 852.11 | C44: =$B44*Settings!$B$34 -> 3129.374 | D44: Deposits less withdrawals
A45: Amana Earn interest | B45: 3.72 | C45: =$B45*Settings!$B$34 -> 13.6617 | D45: Cash-sweep interest
A46: Realized profit | B46: 162.13 | C46: =$B46*Settings!$B$34 -> 595.42242 | D46: Closed-trade gains, life of account
A47: Floating profit/loss | B47: -130.69 | C47: =$B47*Settings!$B$34 -> -479.95902 | D47: Unrealized, on the 41 open positions
A48: Floating fees | B48: -8.45 | C48: =$B48*Settings!$B$34 -> -31.032625 | D48: Accrued on open positions
A49: Overnight fees | B49: -12.02 | C49: =$B49*Settings!$B$34 -> -44.14345 | D49: Financing/swap charges, life of account
A50: ENDING ACCOUNT VALUE | B50: =Settings!$B$35 -> 864.82 | C50: =$B50*Settings!$B$34 -> 3176.0514 | D50: Statement figure, 10 Aug 2026 — this is what you actually have
A51: Open positions | B51: 41 | D51: Count, not a currency figure — no AED conversion applies
A52: Realized profit as % of net deposits | B52: =IFERROR($B46/$B44,0) -> 0.19026886 | C52: =$B52*Settings!$B$34 -> 0.6987624 | D52: Lifetime realized return on capital actually put in
A54: AMANA POSITIONS · 41 open positions by asset class — statement PDF, 10 Aug 2026
A55: Asset class | B55: Count | C55: Tickers | D55: Note
A56: US equities | B56: 16 | C56: AAPL, AMZN, AVGO, AXP, BAC, CB, CVX, DVA, GOOGL, KHC, KO, MCO, META, MSFT, NVDA, OXY | D56: Mega-cap concentrated — META, MSFT, NVDA, AAPL, GOOGL, AMZN together are the single largest style bet in the whole portfolio
A57: UAE-listed equities | B57: 9 | C57: ADNOCDIST, ADNOCDRILL, AIRA, DEWAA, EMAARDEV, EMAR, FAB, PARKIN, SALIK | D57: DEWAA is a DFM-listed stock ticker — do not confuse with the DEWA utility bill elsewhere in this workbook
A58: ETFs | B58: 4 | C58: SPYD, VEU, VTI, VWO | D58: Broad-market and dividend trackers — the only genuinely diversified sleeve
A59: Crypto (CFD) | B59: 12 | C59: ADAUSD, AVAXUSD, BTCUSD, DOGEUSD, DOTUSD, ETHUSD, HBARUSD, LINKUSD, SOLUSD, SUIUSD, UNIUSD, XRPUSD | D59: 29% of position count. These are CFDs inside Amana, not spot coins — separate from any Binance holding
A60: TOTAL | B60: 41 | D60: Ties to the statement's stated position count
A62: REQUIRES VERIFICATION: the statement's position table uses a multi-column layout that does not extract reliably as text — I can confirm every symbol above but not the per-position dollar value or entry date without risking a misattributed figure. If you want position-level detail in this workbook, export a CSV from Amana rather than the PDF.
A65: COMBINED NET WORTH · every account, both currencies, one number
A66: Sleeve | B66: Value (AED) | C66: Share of investments | D66: Note
A67: Mutual funds (Nippon + Motilal Oswal) | B67: =Settings!$B$96 -> 9437.4803 | C67: =Settings!$B$96/Settings!$B$114 -> 0.73699616 | D67: INR 245,087.15 at the fixed conversion rate
A68: Amana (multi-asset brokerage) | B68: =Settings!$B$110 -> 3176.0514 | C68: =Settings!$B$110/Settings!$B$114 -> 0.24802571 | D68: 41 positions — US/UAE equities, ETFs, crypto CFDs
A69: Binance (spot crypto) | B69: =Settings!$B$113 -> 191.8 | C69: =Settings!$B$113/Settings!$B$114 -> 0.014978136 | D69: 10 coins, TRX and BTC largest — a starter allocation, not concentrated
A70: TOTAL INVESTMENTS | B70: =B67+B68+B69 -> 12805.332 | C70: 1 | D70: Excludes liquid cash
A71: Liquid cash (from Accounts) | B71: =Settings!$B$60 -> 6105.17
A72: TOTAL NET WORTH TRACKED HERE | B72: =B70+B71 -> 18910.502 | D72: Understated until Binance is added
A74: BINANCE STILL MISSING — send the screenshot and this section, the dashboard, and the concentration analysis all update in one pass. Nothing below is estimated to fill the gap.
A78: BINANCE — SPOT HOLDINGS · app snapshot, 11 Aug 2026
A79: Coin | B79: Name | C79: Quantity | D79: Value (AED) | E79: Implied price (AED) | F79: Today's PNL (AED) | G79: Today's PNL % | H79: Last updated | I79: Status
A80: TRX | B80: Tron | C80: 33.981504 | D80: 41.94 | E80: =IF(C80=0,0,D80/C80) -> 1.2342008 | F80: 0.42 | G80: +1.45% | H80: 46245 | I80: =IF((TODAY()-H80)>Settings!$B$123,"⚠ STALE — "&(TODAY()-H80)&"d","Current") -> ⚠ STALE — 15d
A81: BTC | B81: Bitcoin | C81: 8.934e-05 | D81: 21.09 | E81: =IF(C81=0,0,D81/C81) -> 236064.47 | F81: -0.24 | G81: -1.14% | H81: 46245 | I81: =IF((TODAY()-H81)>Settings!$B$123,"⚠ STALE — "&(TODAY()-H81)&"d","Current") -> ⚠ STALE — 15d
A82: BNB | B82: BNB | C82: 0.00897213 | D82: 20.01 | E82: =IF(C82=0,0,D82/C82) -> 2230.2396 | F82: 0.09 | G82: +0.45% | H82: 46245 | I82: =IF((TODAY()-H82)>Settings!$B$123,"⚠ STALE — "&(TODAY()-H82)&"d","Current") -> ⚠ STALE — 15d
A83: XLM | B83: Stellar Lumens | C83: 32.397293 | D83: 19.11 | E83: =IF(C83=0,0,D83/C83) -> 0.58986411 | F83: -0.34 | G83: -1.77% | H83: 46245 | I83: =IF((TODAY()-H83)>Settings!$B$123,"⚠ STALE — "&(TODAY()-H83)&"d","Current") -> ⚠ STALE — 15d
A84: LINK | B84: Chainlink | C84: 0.57117658 | D84: 18.2 | E84: =IF(C84=0,0,D84/C84) -> 31.864052 | F84: 0.79 | G84: +4.54% | H84: 46245 | I84: =IF((TODAY()-H84)>Settings!$B$123,"⚠ STALE — "&(TODAY()-H84)&"d","Current") -> ⚠ STALE — 15d
A85: ETH | B85: Ethereum | C85: 0.00256822 | D85: 17.83 | E85: =IF(C85=0,0,D85/C85) -> 6942.5517 | F85: -0.26 | G85: -1.43% | H85: 46245 | I85: =IF((TODAY()-H85)>Settings!$B$123,"⚠ STALE — "&(TODAY()-H85)&"d","Current") -> ⚠ STALE — 15d
A86: SOL | B86: Solana | C86: 0.05376033 | D86: 15.02 | E86: =IF(C86=0,0,D86/C86) -> 279.38817 | F86: -0.14 | G86: -0.94% | H86: 46245 | I86: =IF((TODAY()-H86)>Settings!$B$123,"⚠ STALE — "&(TODAY()-H86)&"d","Current") -> ⚠ STALE — 15d
A87: XRP | B87: XRP | C87: 3.9531955 | D87: 14.63 | E87: =IF(C87=0,0,D87/C87) -> 3.7008036 | F87: -0.37 | G87: -2.47% | H87: 46245 | I87: =IF((TODAY()-H87)>Settings!$B$123,"⚠ STALE — "&(TODAY()-H87)&"d","Current") -> ⚠ STALE — 15d
A88: AVAX | B88: Avalanche | C88: 0.52959503 | D88: 12.64 | E88: =IF(C88=0,0,D88/C88) -> 23.867293 | F88: -0.07 | G88: -0.52% | H88: 46245 | I88: =IF((TODAY()-H88)>Settings!$B$123,"⚠ STALE — "&(TODAY()-H88)&"d","Current") -> ⚠ STALE — 15d
A89: ADA | B89: Cardano | C89: 16.017267 | D89: 11.06 | E89: =IF(C89=0,0,D89/C89) -> 0.69050481 | F89: -0.45 | G89: -3.93% | H89: 46245 | I89: =IF((TODAY()-H89)>Settings!$B$123,"⚠ STALE — "&(TODAY()-H89)&"d","Current") -> ⚠ STALE — 15d
A90: TOTAL | D90: =SUM(D80:D89) -> 191.53 | F90: =SUM(F80:F89) -> -0.57 | I90: =IF(COUNTIF(I80:I89,"Current")=10,"All current","Some stale") -> Some stale
A92: App-reported "Est. Total Value" | D92: =Settings!$B$57 -> 191.8 | F92: This is the figure used everywhere else in the workbook | I92: This is the figure used everywhere else in the workbook
A93: How to update: each time you check the Binance app, overwrite Value (AED) and Today's PNL for any coin that moved — quantity, implied price and staleness recompute automatically.
A95: Largest holdings: TRX and BTC together are 33% of the Binance balance. The rest is spread across eight coins in roughly equal, small amounts — a starter/exploratory allocation, not a concentrated position.
A99: PORTFOLIO HEALTH CHECK · objective, rules-based flags — not predictions
A100: These are risk-management triggers computed from your own thresholds on the Settings sheet. They flag concentration and staleness. They do not predict prices, and they are not buy or sell signals.
